Workbook
Name E: 'INPUT2 - Veh Sub-Syst Mass'!$B$262

Sheet Updates
C3: Date | D3: Updates | E3: Who
B4: V1.0 | C4: 44201 | D4: Initial release | E4: Hervé URVOY DE PORTZAMPARC
B5: V2.0 | C5: 44785 | D5: Excel document global review : - Inputs updated. - CoG formula updated. - Z CoG compared to groung new calculation. - Unsprung mass calculation added. - Check ased on P64 Bev done. | E5: Gilles PAPET
B6: V3.0 | C6: 44854 | D6: ? | E6: Gilles PAPET
B7: V4.0 | C7: 44854 | D7: ? | E7: Gilles PAPET
B8: V5.0 | C8: 44880 | D8: Formula correction : - Unsprung Twist beam calculation - CoG calculation (INPUT2 - Veh Sub-Syst Mass) | E8: Gilles PAPET
B9: V6.0 | C9: 44886 | D9: Update of engines generic CoG position. | E9: Gilles PAPET
B10: V7.0 | C10: 46106 | D10: Deleted : - Condenseur de clim (line 23) beacause doubling - Front engine : M4+RGM (line 88) beacause doubling Modified : - Formulas of CdG Durites (line 15), Liquide de refroidissement (line 16), FACADE (line 22), LIQUIDE REFROIDISSEMENT (line 24), MEAP/Ventilateur/Radiateur/Condenseur (X only, line 141) | E10: Laurent BOLIVAL

Sheet INPUT1 - Veh Geometry
B2: INPUTS SHEET :
B3: Yellow cells : A remplir avec le 5ème de ref ou données remontage véhicue remplacé / Fill with information from GAP or previous vehicule
B4: Orange cells : Pour info (ne pas toucher !!) / For Your Information (don't modify!!)
B5: Grey cells : Info non utile, ne pas remplir / Not used, do not fill
M6: Source Input : Qui? | N6: Quand? | O6: Commentaire
B7: Vehicle :
B8: Program / Project / Version : | H8: STLA-S | I8: J1X MHEV P2 FWD | J8: L2
B10: Inputs for GVW load case estimation : | H10: X(mm) | I10: Y (mm) | J10: Z(mm)
C11: Options : FRONT mass | G11: 1.3159445
C12: Options : REAR mass | G12: 54.688055
C13: Options : TOTAL mass | G13: =G11+G12 -> 56.004 | H13: =G12/G13*H33+H61 -> 2535.467 | I13: 0 | J13: 250
C14: Number of passengers | G14: 5
C15: Passenger mass : | G15: 75
G16: Total : | H16: X CoG : | I16: Mass Front : | J16: Mass Rear :
C17: - Row1 passengers repartition : | G17: =(IF('INPUT1 - Veh Geometry'!G14=0,0,IF('INPUT1 - Veh Geometry'!G14=1,1,IF('INPUT1 - Veh Geometry'!G14=2,2,2))))*'INPUT1 - Veh Geometry'!G15 -> 150 | H17: =H42 -> 1334 | I17: =G17-J17 -> 71.789773 | J17: =G17*(H17-$H$61)/$H$33 -> 78.210227
C18: - Row2 passengers repartition : | G18: =(IF(OR('INPUT1 - Veh Geometry'!G14=0,'INPUT1 - Veh Geometry'!G14=1,'INPUT1 - Veh Geometry'!G14=2),0,IF('INPUT1 - Veh Geometry'!G14=3,1,IF('INPUT1 - Veh Geometry'!G14=4,2,IF('INPUT1 - Veh Geometry'!G14=5,3,3)))))*'INPUT1 - Veh Geometry'!G15 -> 225 | H18: =H49 -> 2130 | I18: =G18-J18 -> 39.84375 | J18: =G18*(H18-$H$61)/$H$33 -> 185.15625
C19: - Row3 passengers repartition : | G19: =(IF(AND('INPUT1 - Veh Geometry'!G14>=0,'INPUT1 - Veh Geometry'!G14<=5),0,IF('INPUT1 - Veh Geometry'!G14=6,1,IF('INPUT1 - Veh Geometry'!G14=7,2,2))))*'INPUT1 - Veh Geometry'!G15 -> 0 | H19: =H52 -> 0 | I19: =G19-J19 -> 0 | J19: =G19*(H19-$H$61)/$H$33 -> 0
C20: - Global passengers : | I20: =SUM(I17:I19) -> 111.63352 | J20: =SUM(J17:J19) -> 263.36648
C21: EMC / After sale payload | G21: 40
G22: Total : | H22: X CoG : | I22: Mass Front : | J22: Mass Rear :
C23: - EMC repartition | G23: =G21 -> 40 | H23: =H57 -> 2750 | I23: =G23-J23 -> -2.3106061 | J23: =G23*(H23-$H$61)/$H$33 -> 42.310606
B25: Inputs for MREF load case estimation :
C26: Number of row1 passengers | G26: 2
C27: Mass of row1 passenger : | G27: 68
C28: Number of row2 passengers + Mass | G28: 2
C29: Mass of row1 passenger : ADULT / CHILDREN | G29: 68
C30: Luggage per passenger : | G30: 7
B32: Platform : | H32: X(mm) | I32: Y (mm) | J32: Z(mm)
C33: Empattement (mm) / wheelbase | H33: 2640 | L33: Données issues du 1/5e de ref / Inputs from the GAP (1/5e de ref) | M33: CHRISTOPHE KOTTMANN | N33: 46108
C34: Hauteur Vh en ODM / Vehicule Height in ODM | J34: 1650 | L34: Données issues du 1/5e de ref / Inputs from the GAP (1/5e de ref)
C35: PàF Av (mm) / Front OverHang | H35: 820 | L35: Données issues du 1/5e de ref / Inputs from the GAP (1/5e de ref)
C36: PàF Ar (mm) / Rear OverHang | H36: 700 | L36: Données issues du 1/5e de ref / Inputs from the GAP (1/5e de ref)
C37: Voies / Wheel track | H37: Front : | I37: Rear :
C38: Voies / Wheel track | H38: 1584 | I38: 1574 | L38: Données issues du 1/5e de ref / Inputs from the GAP (1/5e de ref)
C39: Largeur / Body width | I39: 1846 | L39: Données issues du 1/5e de ref / Inputs from the GAP (1/5e de ref)
B41: Rang 1 / Row1 : | H41: X(mm) | I41: Y (mm) | J41: Z(mm)
C42: Point Hx Rang 1 / Hx Point row 1 | H42: 1334 | I42: -355 | J42: 390.3 | L42: Données issues du 1/5e de ref / Inputs from the GAP (1/5e de ref)
C43: Talon / Acc heel Point | J43: 90 | L43: Données issues du 1/5e de ref / Inputs from the GAP (1/5e de ref)
C44: Cote essieu pédale / Axle Pedal dist. | H44: 437 | L44: Données issues du 1/5e de ref / Inputs from the GAP (1/5e de ref)
C45: Point V1 / V1 point | H45: 946 | J45: 750 | L45: Données issues du 1/5e de ref / Inputs from the GAP (1/5e de ref)
C46: Point V2 / V2 point | H46: 475.2 | J46: 531.8 | L46: Données issues du 1/5e de ref / Inputs from the GAP (1/5e de ref)
B48: Rang 2 / row 2 : | H48: X(mm) | I48: Y (mm) | J48: Z(mm)
C49: Point R Rang 2 / R point row 2 | H49: 2130 | I49: 355 | J49: 389 | L49: Données issues du 1/5e de ref / Inputs from the GAP (1/5e de ref)
B51: Rang 3 / Row 3 : | H51: X(mm) | I51: Y (mm) | J51: Z(mm)
C52: Point Hx Rang 3 / Hx Point row 3 | L52: Données issues du 1/5e de ref / Inputs from the GAP (1/5e de ref)
C53: Hauteur d'assise | L53: Données issues du 1/5e de ref / Inputs from the GAP (1/5e de ref)
B55: Positions of elements : | H55: X(mm) | I55: Y (mm) | J55: Z(mm)
C56: Réservoir / fuel tank | H56: 1960 | I56: 38 | J56: 33 | L56: Données issues du 1/5e de ref / Inputs from the GAP (1/5e de ref)
C57: Coffre bagage / trunk | H57: 2750 | I57: 0 | J57: 625 | L57: Données issues du 1/5e de ref / Inputs from the GAP (1/5e de ref)
B59: Axles :
C60: Essieu Avant / Front axle | H60: X(mm) | I60: Y (mm) | J60: Z(mm)
C61: - CdR Av Réf / FWC (ref) | H61: -42.5 | J61: 67 | L61: Données issues du 1/5e de ref / Inputs from the GAP (1/5e de ref)
C62: - Z0 sol M-REF / Ground Z0 position for REF load case | J62: -270 | L62: Données issues du 1/5e de ref / Inputs from the GAP (1/5e de ref) | M62: CHRISTOPHE KOTTMANN | N62: 46108
C63: - Z0 sol MAV / Groud Z0 for Kerb load case | J63: -292 | K63: =J63-J62 -> -22 | L63: Données issues du 1/5e de ref / Inputs from the GAP (1/5e de ref) | M63: CHRISTOPHE KOTTMANN | N63: 46108
C64: - Z0 sol MTAC / Groud Z0 for GVW load case | J64: -266 | K64: =J64-J62 -> 4 | M64: CHRISTOPHE KOTTMANN | N64: 46108
G65: Total : | H65: X CoG : | I65: Mass Front : | J65: Mass Rear :
C66: - REF load case : Front passengers | G66: =G26*G27 -> 136 | H66: =H42 -> 1334 | I66: =G66-J66 -> 65.089394 | J66: =G66*(H66-$H$61)/$H$33 -> 70.910606
C67: - REF load case : Rear passengers | G67: =G28*G29 -> 136 | H67: =H49 -> 2130 | I67: =G67-J67 -> 24.083333 | J67: =G67*(H67-$H$61)/$H$33 -> 111.91667
C68: - REF load case : Luggage | G68: =(G26+G28)*G30 -> 28 | H68: =H57 -> 2750 | I68: =G68-J68 -> -1.6174242 | J68: =G68*(H68-$H$61)/$H$33 -> 29.617424
C69: - Global : (MAV versus M_Ref) | I69: =SUM(I66:I68) -> 87.555303 | J69: =SUM(J66:J68) -> 212.4447
C71: Essieu Arrière / Rear axle | H71: X(mm) | I71: Y (mm) | J71: Z(mm)
C72: - CdR Ar Réf / RWC (ref) | H72: 2597.5 | J72: 76 | L72: Données issues du 1/5e de ref / Inputs from the GAP (1/5e de ref)
C73: - Z0 sol M-REF / Ground Z0 position for REF load case | J73: -266 | L73: Données issues du 1/5e de ref / Inputs from the GAP (1/5e de ref) | M73: CHRISTOPHE KOTTMANN | N73: 46108
C74: - Z0 sol MAV / Groud Z0 for Kerb load case | J74: -317 | K74: =J74-J73 -> -51 | L74: Données issues du 1/5e de ref / Inputs from the GAP (1/5e de ref) | M74: CHRISTOPHE KOTTMANN | N74: 46108
C75: - Z0 sol MTAC / Groud Z0 for GVW load case | J75: -235 | K75: =J75-J73 -> 31 | M75: CHRISTOPHE KOTTMANN | N75: 46108
C77: Rear axle type (TwistedBeam or MultiLink) | G77: Twisted Beam
C79: Wheels | Q79: u_
C80: Pneu / Tyre | H80: 235/60R17
C81: Wheel Outer Diameter | H81: =RIGHT(H80,2)*25.4+LEFT(H80,3)*LEFT(RIGHT(H80,5),2)/50 -> 713.8
H82: Front (mm) : | I82: Rear (mm) :
C83: R sous charge / Laden Radius | H83: 333 | I83: 337 | M83: CHRISTOPHE KOTTMANN | N83: 46108
B85: Engines :
C86: Front Engine | H86: X(mm) | I86: Y (mm) | J86: Z(mm)
C87: M4 + RGM | G87: 122.4 | H87: -241.5 | I87: -48 | J87: 144.4 | M87: CHRISTOPHE KOTTMANN | N87: 46108
C89: Rear engine : | H89: X(mm) | I89: Y (mm) | J89: Z(mm)
C90: eRAD Gen2 | G90: 58.1
B92: Positions of sub systems | G92: Lot A | H92: X(mm) | I92: Y (mm) | J92: Z(mm)
C93: Batterie traction / HV Battery *(BEV/PHEV/MHEV) | G93: 510.4 | H93: 1331 | I93: 26 | J93: -9.5 | L93: Données issues d'un véhicule remplacé sur même PF / Inputs from a previous vehicle on same plateform | M93: CHRISTOPHE KOTTMANN | N93: 46108
C94: OBC / On Board Charger *(BEV / PHEV) | G94: 13.5 | L94: Données issues d'un véhicule remplacé sur même PF / Inputs from a previous vehicle on same plateform
C95: DCDC * (MHEV) | G95: inclus | H95: 1313 | I95: 324 | J95: -36 | L95: Données issues d'un véhicule remplacé sur même PF / Inputs from a previous vehicle on same plateform | M95: CHRISTOPHE KOTTMANN | N95: 46108
C96: Assistance de direction / Power Steering | G96: 15.2 | H96: 171 | I96: -133 | J96: 78 | L96: Données issues d'un véhicule remplacé sur même PF / Inputs from a previous vehicle on same plateform | M96: CHRISTOPHE KOTTMANN | N96: 46108
C97: Batterie 12v / 12V Battery | G97: 17.3 | H97: 2661 | I97: 143 | J97: 130 | L97: Données issues d'un véhicule remplacé sur même PF / Inputs from a previous vehicle on same plateform | M97: CHRISTOPHE KOTTMANN | N97: 46108
C98: Reservoir liquide refroidissement / Coolant liquid tank | G98: ? | H98: -204 | I98: 604 | J98: 536 | L98: Données issues d'un véhicule remplacé sur même PF / Inputs from a previous vehicle on same plateform | M98: CHRISTOPHE KOTTMANN | N98: 46108
C99: Bocal lave vitre / Washer tank | G99: 2.6 | H99: -493 | I99: 619 | J99: 175 | L99: Données issues d'un véhicule remplacé sur même PF / Inputs from a previous vehicle on same plateform
C100: Colonne direction / Direction | G100: 4.8 | H100: 577 | I100: -326 | J100: 583 | L100: Données issues d'un véhicule remplacé sur même PF / Inputs from a previous vehicle on same plateform
C101: Echappement / Exhaust Line | G101: NA | H101: 1265 | I101: -290 | J101: -32 | L101: Données issues d'un véhicule remplacé sur même PF / Inputs from a previous vehicle on same plateform | M101: CHRISTOPHE KOTTMANN | N101: 46108
C102: Groupe clim / HVAC | G102: 15.9 | H102: 267 | I102: 35 | J102: 338 | L102: Données issues d'un véhicule remplacé sur même PF / Inputs from a previous vehicle on same plateform
C103: ISOVAC (AMCT) / Brake Booster | G103: 5.9 | H103: 194 | I103: -254 | J103: 462 | L103: Données issues d'un véhicule remplacé sur même PF / Inputs from a previous vehicle on same plateform
C104: Pédalier / Pedals | G104: 1.9 | H104: 305 | I104: -201 | J104: 316 | L104: Données issues d'un véhicule remplacé sur même PF / Inputs from a previous vehicle on same plateform
C105: Roue de secours - KDPP / Spare Wheel - Tools | G105: 1.9 | H105: 2600 | I105: 0 | J105: 252 | L105: Données issues d'un véhicule remplacé sur même PF / Inputs from a previous vehicle on same plateform
C106: Réservoir SCR / SCR tank *(Diesel) | G106: NA | H106: 1944 | I106: 42 | J106: 33 | L106: Données issues d'un véhicule remplacé sur même PF / Inputs from a previous vehicle on same plateform
C107: ABS/ESP | G107: 2.8 | H107: 92 | I107: -388 | J107: 477 | L107: Données issues d'un véhicule remplacé sur même PF / Inputs from a previous vehicle on same plateform
C108: Berceau Av / Front Cradle | G108: 28.4 | H108: 112 | I108: 5 | J108: -44 | L108: Données issues d'un véhicule remplacé sur même PF / Inputs from a previous vehicle on same plateform | M108: CHRISTOPHE KOTTMANN | N108: 46108
C109: Faisceau 'Global' / 'Global' harness | G109: =SUM(G111:G114) -> 42.1 | H109: 956 | I109: -280 | J109: 430
C110: - Faisceau Principal / Vehicle main Harness | G110: 15 | H110: 243 | I110: -101 | J110: 369 | L110: Données issues d'un véhicule remplacé sur même PF / Inputs from a previous vehicle on same plateform
C111: - Faisceau Habitacle / Cockpit Harness | G111: 13.4 | H111: 1239 | I111: -179 | J111: 303 | L111: Données issues d'un véhicule remplacé sur même PF / Inputs from a previous vehicle on same plateform
C112: - Faisceau Planche de bod / Dashboard harness | G112: 2.1 | H112: 479 | I112: -242 | J112: 486 | L112: Données issues d'un véhicule remplacé sur même PF / Inputs from a previous vehicle on same plateform
C113: - Faisceau Ouvrant AR / Tailgaite-Trunk harness | G113: 1.8 | H113: 2672 | I113: -208 | J113: 1050 | L113: Données issues d'un véhicule remplacé sur même PF / Inputs from a previous vehicle on same plateform
C114: - Faisceau 'divers' / Others harness | G114: 24.8 | H114: 1043 | I114: -267 | J114: 327 | L114: Données issues d'un véhicule remplacé sur même PF / Inputs from a previous vehicle on same plateform
C115: Façade AV : MEAP/Ventilateur/Radiateur/Condenseur | G115: 15.1 | H115: -634.6 | I115: -188 | J115: 191 | L115: Données issues d'un véhicule remplacé sur même PF / Inputs from a previous vehicle on same plateform
...

Sheet INPUT2 - Veh Sub-Syst Mass
D2: PROGRAM : | E2: ='INPUT1 - Veh Geometry'!H8 -> STLA-S | H2: PROJECT : | I2: ='INPUT1 - Veh Geometry'!I8 -> J1X MHEV P2 FWD | L2: MODEL : | O2: ='INPUT1 - Veh Geometry'!J8 -> L2
B4: Evaluation AdP du MCI / CdG Evaluation at early stage | L4: Curb Mass | O4: X | P4: Y | Q4: Z (REF ground) | R4: Z (Curb ground) | S4: Z (GVW ground) | T4: Mfront | U4: Mrear
K5: Nb | L5: =SUMPRODUCT(L6:L252,K6:K252) -> 1456.289 | M5: Unsprung Coef | O5: =SUMPRODUCT(O6:O252,K6:K252,L6:L252)/$L$5 -> 998.48486 | P5: =SUMPRODUCT(P6:P252,K6:K252,L6:L252)/$L$5 -> -21.573203 | Q5: =SUMPRODUCT(Q6:Q252,$K6:$K252,$L6:$L252)/$L$5 -> 261.01732 | R5: =SUMPRODUCT(R6:R252,$K6:$K252,$L6:$L252)/$L$5 -> 256.80369 | S5: =SUMPRODUCT(S6:S252,$K6:$K252,$L6:$L252)/$L$5 -> 262.96106 | T5: =SUMIF($K6:$K252,">0",T6:T252) -> 882.05612 | U5: =SUMIF($K6:$K252,">0",U6:U252) -> 574.23288 | V5: =T5/L5 -> 0.60568755 | Z5: Perimeter | AA5: Module | AB5: A2MAC1 Level1 | AC5: A2MAC1 Level2 | AD5: A2MAC1 Level3 | AE5: A2MAC1 Structure | AF5: Découpages DEC5 | AJ5: commentaire | AN5: comment
B6: ADAPTATION | F6: POWERTRAIN ADAPTATION | L6: =SUMPRODUCT($K7:$K30,$L7:$L30) -> 124.6 | O6: =SUMPRODUCT($K7:$K30,$L7:$L30,O7:O30)/$L6 -> 923.00462 | P6: =SUMPRODUCT($K7:$K30,$L7:$L30,P7:P30)/$L6 -> -60.187961 | Q6: =SUMPRODUCT($K7:$K30,$L7:$L30,Q7:Q30)/$L6 -> 80.768186 | R6: =SUMPRODUCT($K7:$K30,$L7:$L30,R7:R30)/$L6 -> 80.768186 | S6: =SUMPRODUCT($K7:$K30,$L7:$L30,S7:S30)/$L6 -> 80.768186 | T6: =SUM(T7:T30) -> 79.031108 | U6: =SUMIF($K7:$K30,">0",$U7:$U30) -> 45.568892 | Y6: =IF(ISNUMBER(K6),L6*K6,0) -> 0 | Z6: CMAG | AB6: =IF(B6<>0,B6,AB5) -> ADAPTATION | AD6: =IF(D6<>"",D6,"") | AE6: =CONCATENATE(AB6," / ",AC6," / ",AD6) -> ADAPTATION / /
C7: ADDBLUE (+ reservoir) | F7: Addblue tank + liquid | O7: ='INPUT1 - Veh Geometry'!$H$106 -> 1944 | P7: ='INPUT1 - Veh Geometry'!$I$106 -> 42 | Q7: ='INPUT1 - Veh Geometry'!$J$106 -> 33 | R7: =$Q7 -> 33 | S7: =$Q7 -> 33 | T7: =L7*K7-U7 -> 0 | U7: =IF(ISNUMBER(K7),L7*K7*(O7-$D$262)/E,) -> 0 | Y7: =IF(ISNUMBER(K7),L7*K7,0) -> 0 | Z7: CMAG | AB7: =IF(B7<>0,B7,AB6) -> ADAPTATION | AC7: =IF(C7<>0,C7,AC6) -> ADDBLUE (+ reservoir) | AD7: =IF(D7<>"",D7,"") | AE7: =CONCATENATE(AB7," / ",AC7," / ",AD7) -> ADAPTATION / ADDBLUE (+ reservoir) /
C8: CIRCUIT CARBURANT | Y8: =IF(ISNUMBER(K8),L8*K8,0) -> 0 | Z8: CMAG | AB8: =IF(B8<>0,B8,AB7) -> ADAPTATION | AC8: =IF(C8<>0,C8,AC7) -> CIRCUIT CARBURANT | AD8: =IF(D8<>"",D8,"") | AE8: =CONCATENATE(AB8," / ",AC8," / ",AD8) -> ADAPTATION / CIRCUIT CARBURANT /
C9: CIRCUIT AIR | F9: Air intake loop | Y9: =IF(ISNUMBER(K9),L9*K9,0) -> 0 | Z9: CMAG | AB9: =IF(B9<>0,B9,AB8) -> ADAPTATION | AC9: =IF(C9<>0,C9,AC8) -> CIRCUIT AIR | AD9: =IF(D9<>"",D9,"") | AE9: =CONCATENATE(AB9," / ",AC9," / ",AD9) -> ADAPTATION / CIRCUIT AIR /
D10: Filtre | G10: Air filter | O10: ='INPUT1 - Veh Geometry'!H$87 -> -241.5 | P10: ='INPUT1 - Veh Geometry'!I$87 -> -48 | Q10: ='INPUT1 - Veh Geometry'!J$87 -> 144.4 | R10: =$Q10 -> 144.4 | S10: =$Q10 -> 144.4 | T10: =L10*K10-U10 -> 0 | U10: =IF(ISNUMBER(K10),L10*K10*(O10-$D$262)/E,) -> 0 | Y10: =IF(ISNUMBER(K10),L10*K10,0) -> 0 | Z10: CMAG | AA10: ACT02 | AB10: =IF(B10<>0,B10,AB9) -> ADAPTATION | AC10: =IF(C10<>0,C10,AC9) -> CIRCUIT AIR | AD10: =IF(D10<>"",D10,"") -> Filtre | AE10: =CONCATENATE(AB10," / ",AC10," / ",AD10) -> ADAPTATION / CIRCUIT AIR / Filtre | AH10: Sauf pour moteur EP6 (déjà compté dans le bilan moteur) | AL10: Except for EP6 (already counted in the mass of GMP)
D11: Durites | G11: Air pipes | K11: 1 | L11: 6.8 | O11: ='INPUT1 - Veh Geometry'!H$87 -> -241.5 | P11: ='INPUT1 - Veh Geometry'!I$87 -> -48 | Q11: ='INPUT1 - Veh Geometry'!J$87 -> 144.4 | R11: =$Q11 -> 144.4 | S11: =$Q11 -> 144.4 | T11: =L11*K11-U11 -> 7.3125758 | U11: =IF(ISNUMBER(K11),L11*K11*(O11-$D$262)/E,) -> -0.51257576 | Y11: =IF(ISNUMBER(K11),L11*K11,0) -> 6.8 | Z11: CMAG | AA11: ACT02 | AB11: =IF(B11<>0,B11,AB10) -> ADAPTATION | AC11: =IF(C11<>0,C11,AC10) -> CIRCUIT AIR | AD11: =IF(D11<>"",D11,"") -> Durites | AE11: =CONCATENATE(AB11," / ",AC11," / ",AD11) -> ADAPTATION / CIRCUIT AIR / Durites
D12: RAS | G12: CAC | O12: ='INPUT1 - Veh Geometry'!$H$115 -> -634.6 | P12: ='INPUT1 - Veh Geometry'!$I$115 -> -188 | Q12: ='INPUT1 - Veh Geometry'!$J$115 -> 191 | R12: =$Q12 -> 191 | S12: =$Q12 -> 191 | T12: =L12*K12-U12 -> 0 | U12: =IF(ISNUMBER(K12),L12*K12*(O12-$D$262)/E,) -> 0 | Y12: =IF(ISNUMBER(K12),L12*K12,0) -> 0 | Z12: CMAG | AA12: ACT01 | AB12: =IF(B12<>0,B12,AB11) -> ADAPTATION | AC12: =IF(C12<>0,C12,AC11) -> CIRCUIT AIR | AD12: =IF(D12<>"",D12,"") -> RAS | AE12: =CONCATENATE(AB12," / ",AC12," / ",AD12) -> ADAPTATION / CIRCUIT AIR / RAS | AH12: En cas de RAS déporté (type IRIS), mettre à jour la valeur du Y CDG | AL12: In case of a CAC in the wheel arch (IRIS Type), adjust the Y position
C13: CIRCUIT EAU | F13: Water cooling loop | Y13: =IF(ISNUMBER(K13),L13*K13,0) -> 0 | Z13: CMAG | AB13: =IF(B13<>0,B13,AB12) -> ADAPTATION | AC13: =IF(C13<>0,C13,AC12) -> CIRCUIT EAU | AD13: =IF(D13<>"",D13,"") | AE13: =CONCATENATE(AB13," / ",AC13," / ",AD13) -> ADAPTATION / CIRCUIT EAU /
D14: Système radiateur | G14: Radiator | O14: ='INPUT1 - Veh Geometry'!$H$115 -> -634.6 | P14: ='INPUT1 - Veh Geometry'!$I$115 -> -188 | Q14: ='INPUT1 - Veh Geometry'!$J$115 -> 191 | R14: =$Q14 -> 191 | S14: =$Q14 -> 191 | T14: =L14*K14-U14 -> 0 | U14: =IF(ISNUMBER(K14),L14*K14*(O14-$D$262)/E,) -> 0 | Y14: =IF(ISNUMBER(K14),L14*K14,0) -> 0 | Z14: CMAG | AA14: ACT01 | AB14: =IF(B14<>0,B14,AB13) -> ADAPTATION | AC14: =IF(C14<>0,C14,AC13) -> CIRCUIT EAU | AD14: =IF(D14<>"",D14,"") -> Système radiateur | AE14: =CONCATENATE(AB14," / ",AC14," / ",AD14) -> ADAPTATION / CIRCUIT EAU / Système radiateur | AH14: Valeurs entre 3 et 4kg suivant la taille et la classe de radia | AL14: Value between 3 and 4kg depending on size or class of radiator
D15: Durites | G15: Water pipes | O15: =('INPUT1 - Veh Geometry'!$H$116+'INPUT1 - Veh Geometry'!$H$93+'INPUT1 - Veh Geometry'!$H$87+'INPUT1 - Veh Geometry'!$H$90+'INPUT1 - Veh Geometry'!$H$98)/5 -> 105.18 | P15: =('INPUT1 - Veh Geometry'!$I$116+'INPUT1 - Veh Geometry'!$I$93+'INPUT1 - Veh Geometry'!$I$87+'INPUT1 - Veh Geometry'!$I$90+'INPUT1 - Veh Geometry'!$I$98)/5 -> 70.4 | Q15: =('INPUT1 - Veh Geometry'!$J$116+'INPUT1 - Veh Geometry'!$J$93+'INPUT1 - Veh Geometry'!$J$87+'INPUT1 - Veh Geometry'!$J$90+'INPUT1 - Veh Geometry'!$J$98)/5 -> 158.18 | R15: =$Q15 -> 158.18 | S15: =$Q15 -> 158.18 | T15: =L15*K15-U15 -> 0 | U15: =IF(ISNUMBER(K15),L15*K15*(O15-$D$262)/E,) -> 0 | Y15: =IF(ISNUMBER(K15),L15*K15,0) -> 0 | Z15: CMAG | AA15: ACT01 | AB15: =IF(B15<>0,B15,AB14) -> ADAPTATION | AC15: =IF(C15<>0,C15,AC14) -> CIRCUIT EAU | AD15: =IF(D15<>"",D15,"") -> Durites | AE15: =CONCATENATE(AB15," / ",AC15," / ",AD15) -> ADAPTATION / CIRCUIT EAU / Durites | AH15: Valeurs entre 4kg (tuyaux + boite dégazage) et 12kg (PHEV/BEV 4x4) | AL15: Value between 4kg (classic ICE) and 12kg (BEV/PHEV 4x4)
D16: Liquide de refroidissement | G16: Cooling liquid | K16: 1 | L16: 20.7 | O16: =('INPUT1 - Veh Geometry'!$H$116+'INPUT1 - Veh Geometry'!$H$93+'INPUT1 - Veh Geometry'!$H$87+'INPUT1 - Veh Geometry'!$H$90+'INPUT1 - Veh Geometry'!$H$98)/5 -> 105.18 | P16: =('INPUT1 - Veh Geometry'!$I$116+'INPUT1 - Veh Geometry'!$I$93+'INPUT1 - Veh Geometry'!$I$87+'INPUT1 - Veh Geometry'!$I$90+'INPUT1 - Veh Geometry'!$I$98)/5 -> 70.4 | Q16: =('INPUT1 - Veh Geometry'!$J$116+'INPUT1 - Veh Geometry'!$J$93+'INPUT1 - Veh Geometry'!$J$87+'INPUT1 - Veh Geometry'!$J$90+'INPUT1 - Veh Geometry'!$J$98)/5 -> 158.18 | R16: =$Q16 -> 158.18 | S16: =$Q16 -> 158.18 | T16: =L16*K16-U16 -> 19.542055 | U16: =IF(ISNUMBER(K16),L16*K16*(O16-$D$262)/E,) -> 1.1579455 | Y16: =IF(ISNUMBER(K16),L16*K16,0) -> 20.7 | Z16: CMAG | AA16: ACT03 | AB16: =IF(B16<>0,B16,AB15) -> ADAPTATION | AC16: =IF(C16<>0,C16,AC15) -> CIRCUIT EAU | AD16: =IF(D16<>"",D16,"") -> Liquide de refroidissement | AE16: =CONCATENATE(AB16," / ",AC16," / ",AD16) -> ADAPTATION / CIRCUIT EAU / Liquide de refroidissement | AH16: Valeurs entre 5kg (ICE) et 15kg (BEV) | AL16: value between 5kg (ICE) and 15kg (PHEV/BEV 4x4)
D17: Système motoventilateur | G17: Fan system | O17: ='INPUT1 - Veh Geometry'!$H$115+100 -> -534.6 | P17: ='INPUT1 - Veh Geometry'!$I$115 -> -188 | Q17: ='INPUT1 - Veh Geometry'!$J$115 -> 191 | R17: =$Q17 -> 191 | S17: =$Q17 -> 191 | T17: =L17*K17-U17 -> 0 | U17: =IF(ISNUMBER(K17),L17*K17*(O17-$D$262)/E,) -> 0 | Y17: =IF(ISNUMBER(K17),L17*K17,0) -> 0 | Z17: CMAG | AA17: ACT01 | AB17: =IF(B17<>0,B17,AB16) -> ADAPTATION | AC17: =IF(C17<>0,C17,AC16) -> CIRCUIT EAU | AD17: =IF(D17<>"",D17,"") -> Système motoventilateur | AE17: =CONCATENATE(AB17," / ",AC17," / ",AD17) -> ADAPTATION / CIRCUIT EAU / Système motoventilateur | AH17: Prendre l'ensemble ventilateur + cadre, entre 3 et 4kg en général | AL17: value of entire module with air dam, usually from 3 to 4kg
D18: Système pompe auxiliaire | G18: Auxiliary water pumps | O18: ='INPUT1 - Veh Geometry'!$H$87 -> -241.5 | P18: ='INPUT1 - Veh Geometry'!$I$87 -> -48 | Q18: ='INPUT1 - Veh Geometry'!$J$87-100 -> 44.4 | R18: =$Q18 -> 44.4 | S18: =$Q18 -> 44.4 | T18: =L18*K18-U18 -> 0 | U18: =IF(ISNUMBER(K18),L18*K18*(O18-$D$262)/E,) -> 0 | Y18: =IF(ISNUMBER(K18),L18*K18,0) -> 0 | Z18: DSEE | AB18: =IF(B18<>0,B18,AB17) -> ADAPTATION | AC18: =IF(C18<>0,C18,AC17) -> CIRCUIT EAU | AD18: =IF(D18<>"",D18,"") -> Système pompe auxiliaire | AE18: =CONCATENATE(AB18," / ",AC18," / ",AD18) -> ADAPTATION / CIRCUIT EAU / Système pompe auxiliaire | AH18: en général, 1 pompe pour ICE, 2 ou 3 pompes pour les BEV/ MHEV / BEV; 0,3 à 0,6kg pour chaque pompe | AL18: 1 pump fpr ICE, 2 to 3 pumps for MHEV / BEV / PHEV; value of 0,3 to 0,6kg each
C19: COMMANDE VITESSE | F19: Gear shift command | K19: 1 | L19: 1.3 | O19: ='INPUT1 - Veh Geometry'!$H$42-300 -> 1034 | P19: ='INPUT1 - Veh Geometry'!$I$42 -> -355 | Q19: ='INPUT1 - Veh Geometry'!$J$42-100 -> 290.3 | R19: =$Q19 -> 290.3 | S19: =$Q19 -> 290.3 | T19: =L19*K19-U19 -> 0.7699053 | U19: =IF(ISNUMBER(K19),L19*K19*(O19-$D$262)/E,) -> 0.5300947 | Y19: =IF(ISNUMBER(K19),L19*K19,0) -> 1.3 | Z19: CMAG | AA19: ACT11 | AB19: =IF(B19<>0,B19,AB18) -> ADAPTATION | AC19: =IF(C19<>0,C19,AC18) -> COMMANDE VITESSE | AD19: =IF(D19<>"",D19,"") | AE19: =CONCATENATE(AB19," / ",AC19," / ",AD19) -> ADAPTATION / COMMANDE VITESSE / | AH19: levier de vitesse | AL19: gear lever
C20: ECHAPPEMENT | F20: Exhaust line | K20: 1 | L20: 22.9 | O20: ='INPUT1 - Veh Geometry'!$H$101 -> 1265 | P20: ='INPUT1 - Veh Geometry'!$I$101 -> -290 | Q20: ='INPUT1 - Veh Geometry'!$J$101 -> -32 | R20: =$Q20 -> -32 | S20: =$Q20 -> -32 | T20: =L20*K20-U20 -> 11.558428 | U20: =IF(ISNUMBER(K20),L20*K20*(O20-$D$262)/E,) -> 11.341572 | Y20: =IF(ISNUMBER(K20),L20*K20,0) -> 22.9 | Z20: CMAG | AA20: ACT08+09 | AB20: =IF(B20<>0,B20,AB19) -> ADAPTATION | AC20: =IF(C20<>0,C20,AC19) -> ECHAPPEMENT | AD20: =IF(D20<>"",D20,"") | AE20: =CONCATENATE(AB20," / ",AC20," / ",AD20) -> ADAPTATION / ECHAPPEMENT / | AH20: ligne complète: catalyseur et ligne froide | AL20: full exhasut line with catalyser and cold line
C21: ECRANS THERMIQUE | F21: Thermal shields | L21: 0 | O21: ='INPUT1 - Veh Geometry'!$H$101 -> 1265 | P21: ='INPUT1 - Veh Geometry'!$I$101 -> -290 | Q21: ='INPUT1 - Veh Geometry'!$J$101 -> -32 | R21: =$Q21 -> -32 | S21: =$Q21 -> -32 | T21: =L21*K21-U21 -> 0 | U21: =IF(ISNUMBER(K21),L21*K21*(O21-$D$262)/E,) -> 0 | Y21: =IF(ISNUMBER(K21),L21*K21,0) -> 0 | Z21: CMAG | AA21: Hors module | AB21: =IF(B21<>0,B21,AB20) -> ADAPTATION | AC21: =IF(C21<>0,C21,AC20) -> ECRANS THERMIQUE | AD21: =IF(D21<>"",D21,"") | AE21: =CONCATENATE(AB21," / ",AC21," / ",AD21) -> ADAPTATION / ECRANS THERMIQUE / | AH21: Entre 2 et 2,8kg | AL21: from 2 to 3kg
C22: FACADE | K22: 1 | L22: 13 | O22: ='INPUT1 - Veh Geometry'!$H$115 -> -634.6 | P22: ='INPUT1 - Veh Geometry'!$I$115 -> -188 | Q22: ='INPUT1 - Veh Geometry'!$J$115 -> 191 | R22: =$Q22 -> 191 | S22: =$Q22 -> 191 | T22: =L22*K22-U22 -> 15.915644 | U22: =IF(ISNUMBER(K22),L22*K22*(O22-$D$262)/E,) -> -2.9156439 | Y22: =IF(ISNUMBER(K22),L22*K22,0) -> 13 | Z22: ADTH | AB22: =IF(B22<>0,B22,AB21) -> ADAPTATION | AC22: =IF(C22<>0,C22,AC21) -> FACADE | AD22: =IF(D22<>"",D22,"") | AE22: =CONCATENATE(AB22," / ",AC22," / ",AD22) -> ADAPTATION / FACADE /
C23: LIQUIDE ADDITIF | L23: 0 | O23: ='INPUT1 - Veh Geometry'!$H$101 -> 1265 | P23: ='INPUT1 - Veh Geometry'!$I$101 -> -290 | Q23: ='INPUT1 - Veh Geometry'!$J$101 -> -32 | R23: =$Q23 -> -32 | S23: =$Q23 -> -32 | T23: =L23*K23-U23 -> 0 | U23: =IF(ISNUMBER(K23),L23*K23*(O23-$D$262)/E,) -> 0 | Y23: =IF(ISNUMBER(K23),L23*K23,0) -> 0 | Z23: CMAG | AB23: =IF(B23<>0,B23,AB22) -> ADAPTATION | AC23: =IF(C23<>0,C23,#REF!) -> LIQUIDE ADDITIF | AD23: =IF(D23<>"",D23,"") | AE23: =CONCATENATE(AB23," / ",AC23," / ",AD23) -> ADAPTATION / LIQUIDE ADDITIF /
B24: Déjà en ligne 16 | C24: LIQUIDE REFROIDISSEMENT | G24: Cooling liquid | O24: =('INPUT1 - Veh Geometry'!$H$116+'INPUT1 - Veh Geometry'!$H$93+'INPUT1 - Veh Geometry'!$H$87+'INPUT1 - Veh Geometry'!$H$90+'INPUT1 - Veh Geometry'!$H$98)/5 -> 105.18 | P24: =('INPUT1 - Veh Geometry'!$I$116+'INPUT1 - Veh Geometry'!$I$93+'INPUT1 - Veh Geometry'!$I$87+'INPUT1 - Veh Geometry'!$I$90+'INPUT1 - Veh Geometry'!$I$98)/5 -> 70.4 | Q24: =('INPUT1 - Veh Geometry'!$J$116+'INPUT1 - Veh Geometry'!$J$93+'INPUT1 - Veh Geometry'!$J$87+'INPUT1 - Veh Geometry'!$J$90+'INPUT1 - Veh Geometry'!$J$98)/5 -> 158.18 | R24: =$Q24 -> 158.18 | S24: =$Q24 -> 158.18 | T24: =L24*K24-U24 -> 0 | U24: =IF(ISNUMBER(K24),L24*K24*(O24-$D$262)/E,) -> 0 | Y24: =IF(ISNUMBER(K24),L24*K24,0) -> 0 | Z24: CMAG | AA24: ACT03 | AB24: =IF(B24<>0,B24,AB23) -> Déjà en ligne 16 | AC24: =IF(C24<>0,C24,AC23) -> LIQUIDE REFROIDISSEMENT | AD24: =IF(D24<>"",D24,"") | AE24: =CONCATENATE(AB24," / ",AC24," / ",AD24) -> Déjà en ligne 16 / LIQUIDE REFROIDISSEMENT / | AH24: Valeurs entre 5kg (ICE) et 15kg (BEV) | AL24: value between 5kg (ICE) and 15kg (PHEV/BEV 4x4)
C25: PEDALIER | F25: Pedals | K25: 1 | L25: 2.2 | O25: ='INPUT1 - Veh Geometry'!$H$104 -> 305 | P25: ='INPUT1 - Veh Geometry'!$I$104 -> -201 | Q25: ='INPUT1 - Veh Geometry'!$J$104 -> 316 | R25: =$Q25 -> 316 | S25: =$Q25 -> 316 | T25: =L25*K25-U25 -> 1.9104167 | U25: =IF(ISNUMBER(K25),L25*K25*(O25-$D$262)/E,) -> 0.28958333 | Y25: =IF(ISNUMBER(K25),L25*K25,0) -> 2.2 | Z25: CMAG | AA25: ACT07 | AB25: =IF(B25<>0,B25,AB24) -> Déjà en ligne 16 | AC25: =IF(C25<>0,C25,AC24) -> PEDALIER | AD25: =IF(D25<>"",D25,"") | AE25: =CONCATENATE(AB25," / ",AC25," / ",AD25) -> Déjà en ligne 16 / PEDALIER / | AH25: Valeur moyenne, 1,5 à 2kg | AL25: mean value from 1,5 to 2kg
C26: RESERVOIR CARBURANT | F26: Fuel tank | K26: 1 | L26: 48 | O26: ='INPUT1 - Veh Geometry'!$H$56 -> 1960 | P26: ='INPUT1 - Veh Geometry'!$I$56 -> 38 | Q26: ='INPUT1 - Veh Geometry'!$J$56 -> 33 | R26: =$Q26 -> 33 | S26: =$Q26 -> 33 | T26: =L26*K26-U26 -> 11.590909 | U26: =IF(ISNUMBER(K26),L26*K26*(O26-$D$262)/E,) -> 36.409091 | Y26: =IF(ISNUMBER(K26),L26*K26,0) -> 48 | Z26: CMAG | AA26: ACT06 | AB26: =IF(B26<>0,B26,AB25) -> Déjà en ligne 16 | AC26: =IF(C26<>0,C26,AC25) -> RESERVOIR CARBURANT | AD26: =IF(D26<>"",D26,"") | AE26: =CONCATENATE(AB26," / ",AC26," / ",AD26) -> Déjà en ligne 16 / RESERVOIR CARBURANT / | AH26: Entre 9kg (réservoir simple 45L) et 15kg (réservoir pressurisé 60L) | AL26: From 9kg (simple tank, 45L) to 16kg (pressurised tank, 60L)
C27: Canister | F27: Canister | L27: 0 | O27: ='INPUT1 - Veh Geometry'!$H$56 -> 1960 | P27: ='INPUT1 - Veh Geometry'!$I$56 -> 38 | Q27: ='INPUT1 - Veh Geometry'!$J$56 -> 33 | R27: =$Q27 -> 33 | S27: =$Q27 -> 33 | T27: =L27*K27-U27 -> 0 | U27: =IF(ISNUMBER(K27),L27*K27*(O27-$D$262)/E,) -> 0 | Y27: =IF(ISNUMBER(K27),L27*K27,0) -> 0 | Z27: CMAG | AA27: ACT06 | AB27: =IF(B27<>0,B27,AB26) -> Déjà en ligne 16 | AC27: =IF(C27<>0,C27,AC26) -> Canister | AD27: =IF(D27<>"",D27,"") | AE27: =CONCATENATE(AB27," / ",AC27," / ",AD27) -> Déjà en ligne 16 / Canister / | AH27: Entre 0,5kg (€6 Europe) et 3kg (dépol €7 et Chine) | AL27: From 0,5kg (€6) to 3kg (€7 and China)
C28: Masse carburant | F28: Fuel mass | L28: 0 | O28: ='INPUT1 - Veh Geometry'!$H$56 -> 1960 | P28: ='INPUT1 - Veh Geometry'!I56 -> 38 | Q28: ='INPUT1 - Veh Geometry'!$J$56 -> 33 | R28: =$Q28 -> 33 | S28: =$Q28 -> 33 | T28: =L28*K28-U28 -> 0 | U28: =IF(ISNUMBER(K28),L28*K28*(O28-$D$262)/E,) -> 0 | Y28: =IF(ISNUMBER(K28),L28*K28,0) -> 0 | Z28: CMAG | AA28: ACT06 | AB28: =IF(B28<>0,B28,AB27) -> Déjà en ligne 16 | AC28: =IF(C28<>0,C28,AC27) -> Masse carburant | AD28: =IF(D28<>"",D28,"") | AE28: =CONCATENATE(AB28," / ",AC28," / ",AD28) -> Déjà en ligne 16 / Masse carburant / | AH28: Faire le calcul nbre de litres x0,75 (essence) ou 0,8 (diesel) | AL28: Liters * 0,75 (gasoline) or 0,8 (diesel)
C29: SUPPORT GMP AV | F29: Front Electric engine brackets | K29: 1 | L29: 9.7 | O29: ='INPUT1 - Veh Geometry'!H87 -> -241.5 | P29: ='INPUT1 - Veh Geometry'!I87 -> -48 | Q29: ='INPUT1 - Veh Geometry'!J87 -> 144.4 | R29: =$Q29 -> 144.4 | S29: =$Q29 -> 144.4 | T29: =L29*K29-U29 -> 10.431174 | U29: =IF(ISNUMBER(K29),L29*K29*(O29-$D$262)/E,) -> -0.73117424 | Y29: =IF(ISNUMBER(K29),L29*K29,0) -> 9.7 | Z29: CMAG | AA29: ACT12 | AB29: =IF(B29<>0,B29,AB28) -> Déjà en ligne 16 | AC29: =IF(C29<>0,C29,AC28) -> SUPPORT GMP AV | AD29: =IF(D29<>"",D29,"") | AE29: =CONCATENATE(AB29," / ",AC29," / ",AD29) -> Déjà en ligne 16 / SUPPORT GMP AV /
C30: Supports MEL AR | F30: Rear Electric engine brackets | O30: ='INPUT1 - Veh Geometry'!H90 -> 0 | P30: ='INPUT1 - Veh Geometry'!I90 -> 0 | Q30: ='INPUT1 - Veh Geometry'!J90 -> 0 | R30: =$Q30 -> 0 | S30: =$Q30 -> 0 | T30: =L30*K30-U30 -> 0 | U30: =IF(ISNUMBER(K30),L30*K30*(O30-$D$262)/E,) -> 0 | Y30: =IF(ISNUMBER(K30),L30*K30,0) -> 0 | Z30: CMAG | AA30: ACT12 | AB30: =IF(B30<>0,B30,AB29) -> Déjà en ligne 16 | AC30: =IF(C30<>0,C30,AC29) -> Supports MEL AR | AD30: =IF(D30<>"",D30,"") | AE30: =CONCATENATE(AB30," / ",AC30," / ",AD30) -> Déjà en ligne 16 / Supports MEL AR / | AH30: Pour PHEV/BEV 4x4 | AL30: For PHEV / BEV 4x4
B31: ADTH | F31: ADTH | L31: =SUMPRODUCT(K32:K37,L32:L37) -> 17.4 | O31: =SUMPRODUCT($K32:$K37,$L32:$L37,O32:O37)/$L31 -> -37.214751 | P31: =SUMPRODUCT($K32:$K37,$L32:$L37,P32:P37)/$L31 -> -22.791188 | Q31: =SUMPRODUCT($K32:$K37,$L32:$L37,Q32:Q37)/$L31 -> 243.23218 | R31: =SUMPRODUCT($K32:$K37,$L32:$L37,R32:R37)/$L31 -> 243.23218 | S31: =SUMPRODUCT($K32:$K37,$L32:$L37,S32:S37)/$L31 -> 243.23218 | T31: =SUM(T32:T37) -> 17.365165 | U31: =SUMIF($K32:$K37,">0",$U32:$U37) -> 0.034834596 | Y31: =IF(ISNUMBER(K31),L31*K31,0) -> 0 | Z31: ADTH | AB31: =IF(B31<>0,B31,AB30) -> ADTH | AC31: =IF(C31<>0,C31,AC30) -> Supports MEL AR | AD31: =IF(D31<>"",D31,"") | AE31: =CONCATENATE(AB31," / ",AC31," / ",AD31) -> ADTH / Supports MEL AR /
C32: Gaz de climatisation | F32: Air conditioning gas | O32: ='INPUT1 - Veh Geometry'!$H$115 -> -634.6 | P32: ='INPUT1 - Veh Geometry'!$I$115 -> -188 | Q32: ='INPUT1 - Veh Geometry'!$J$115 -> 191 | R32: =$Q32 -> 191 | S32: =$Q32 -> 191 | T32: =L32*K32-U32 -> 0 | U32: =IF(ISNUMBER(K32),L32*K32*(O32-$D$262)/E,) -> 0 | Y32: =IF(ISNUMBER(K32),L32*K32,0) -> 0 | Z32: ADTH | AB32: =IF(B32<>0,B32,AB31) -> ADTH | AC32: =IF(C32<>0,C32,AC31) -> Gaz de climatisation | AD32: =IF(D32<>"",D32,"") | AE32: =CONCATENATE(AB32," / ",AC32," / ",AD32) -> ADTH / Gaz de climatisation / | AH32: valeur usuelle, entre 0,8 et 1kg | AL32: mean value from 0,8 to 1kg
C33: Conduits de clim | F33: Air conditioning ducts | K33: 1 | L33: 2.8 | O33: =('INPUT1 - Veh Geometry'!$H$115*2+'INPUT1 - Veh Geometry'!$H$102)/3 -> -334.06667 | P33: =('INPUT1 - Veh Geometry'!$I$115*2+'INPUT1 - Veh Geometry'!$I$102)/3 -> -113.66667 | Q33: =('INPUT1 - Veh Geometry'!$J$115*2+'INPUT1 - Veh Geometry'!$J$102)/3 -> 240 | R33: =$Q33 -> 240 | S33: =$Q33 -> 240 | T33: =L33*K33-U33 -> 3.1092374 | U33: =IF(ISNUMBER(K33),L33*K33*(O33-$D$262)/E,) -> -0.30923737 | Y33: =IF(ISNUMBER(K33),L33*K33,0) -> 2.8 | Z33: ADTH | AB33: =IF(B33<>0,B33,AB32) -> ADTH | AC33: =IF(C33<>0,C33,AC32) -> Conduits de clim | AD33: =IF(D33<>"",D33,"") | AE33: =CONCATENATE(AB33," / ",AC33," / ",AD33) -> ADTH / Conduits de clim / | AH33: valeur mpyenne, 2kg | AL33: mean value, 2kg
C34: Groupe de clim | F34: HVAC | K34: 1 | L34: 7.5 | O34: ='INPUT1 - Veh Geometry'!$H$102 -> 267 | P34: ='INPUT1 - Veh Geometry'!$I$102 -> 35 | Q34: ='INPUT1 - Veh Geometry'!$J$102 -> 338 | R34: =$Q34 -> 338 | S34: =$Q34 -> 338 | T34: =L34*K34-U34 -> 6.6207386 | U34: =IF(ISNUMBER(K34),L34*K34*(O34-$D$262)/E,) -> 0.87926136 | Y34: =IF(ISNUMBER(K34),L34*K34,0) -> 7.5 | Z34: ADTH | AB34: =IF(B34<>0,B34,AB33) -> ADTH | AC34: =IF(C34<>0,C34,AC33) -> Groupe de clim | AD34: =IF(D34<>"",D34,"") | AE34: =CONCATENATE(AB34," / ",AC34," / ",AD34) -> ADTH / Groupe de clim / | AH34: valeur entre 8 et 10kg | AL34: mean value from 8 to 10kg
C35: Compresseur de clim + support | F35: Compressor + bracket | K35: 1 | L35: 7.1 | O35: ='INPUT1 - Veh Geometry'!H87 -> -241.5 | P35: ='INPUT1 - Veh Geometry'!I87 -> -48 | Q35: ='INPUT1 - Veh Geometry'!$J$87 -> 144.4 | R35: =$Q35 -> 144.4 | S35: =$Q35 -> 144.4 | T35: =L35*K35-U35 -> 7.6351894 | U35: =IF(ISNUMBER(K35),L35*K35*(O35-$D$262)/E,) -> -0.53518939 | Y35: =IF(ISNUMBER(K35),L35*K35,0) -> 7.1 | Z35: ADTH | AB35: =IF(B35<>0,B35,AB34) -> ADTH | AC35: =IF(C35<>0,C35,AC34) -> Compresseur de clim + support | AD35: =IF(D35<>"",D35,"") | AE35: =CONCATENATE(AB35," / ",AC35," / ",AD35) -> ADTH / Compresseur de clim + support / | AH35: valeur entre 4 et 6kg | AL35: mean value from 4 to 6kg
C36: Chiller + support | F36: Chiller + bracket | O36: ='INPUT1 - Veh Geometry'!$H$115 -> -634.6 | P36: ='INPUT1 - Veh Geometry'!$I$115 -> -188 | Q36: ='INPUT1 - Veh Geometry'!$J$115 -> 191 | R36: =$Q36 -> 191 | S36: =$Q36 -> 191 | T36: =L36*K36-U36 -> 0 | U36: =IF(ISNUMBER(K36),L36*K36*(O36-$D$262)/E,) -> 0 | Y36: =IF(ISNUMBER(K36),L36*K36,0) -> 0 | Z36: ADTH | AB36: =IF(B36<>0,B36,AB35) -> ADTH | AC36: =IF(C36<>0,C36,AC35) -> Chiller + support | AD36: =IF(D36<>"",D36,"") | AE36: =CONCATENATE(AB36," / ",AC36," / ",AD36) -> ADTH / Chiller + support / | AH36: chiller, entre 0,5 et 1kg | AL36: mean value for the chiller, from 0,5 to 1kg
C37: CTP (Water heater) + support | F37: CTP (Water heater) + bracket | O37: ='INPUT1 - Veh Geometry'!$H$46 -> 475.2 | P37: ='INPUT1 - Veh Geometry'!$I$46 -> 0 | Q37: ='INPUT1 - Veh Geometry'!$J$46 -> 531.8 | R37: =$Q37 -> 531.8 | S37: =$Q37 -> 531.8 | T37: =L37*K37-U37 -> 0 | U37: =IF(ISNUMBER(K37),L37*K37*(O37-$D$262)/E,) -> 0 | Y37: =IF(ISNUMBER(K37),L37*K37,0) -> 0 | Z37: ADTH | AB37: =IF(B37<>0,B37,AB36) -> ADTH | AC37: =IF(C37<>0,C37,AC36) -> CTP (Water heater) + support | AD37: =IF(D37<>"",D37,"") | AE37: =CONCATENATE(AB37," / ",AC37," / ",AD37) -> ADTH / CTP (Water heater) + support / | AH37: valeur entre 1,5 et 2,5k pour la CTP, ajouter la meme masse pour le support | AL37: mean value from 1,5 to 2,5kg for the WH, add the same mass for its bracket
B38: AILES | F38: Wings | L38: =SUMPRODUCT(K39:K40,L39:L40) -> 4.4 | O38: =SUMPRODUCT($K39:$K40,$L39:$L40,O39:O40)/$L38 -> 72.5 | P38: =SUMPRODUCT($K39:$K40,$L39:$L40,P39:P40)/$L38 -> 0 | Q38: =SUMPRODUCT($K39:$K40,$L39:$L40,Q39:Q40)/$L38 -> 523.9 | R38: =SUMPRODUCT($K39:$K40,$L39:$L40,R39:R40)/$L38 -> 523.9 | S38: =SUMPRODUCT($K39:$K40,$L39:$L40,S39:S40)/$L38 -> 523.9 | T38: =SUM(T39:T40) -> 4.2083333 | U38: =SUMIF($K39:$K40,">0",$U39:$U40) -> 0.19166667 | Y38: =IF(ISNUMBER(K38),L38*K38,0) -> 0 | Z38: SOEE | AB38: =IF(B38<>0,B38,AB37) -> AILES | AC38: =IF(C38<>0,C38,AC37) -> CTP (Water heater) + support | AD38: =IF(D38<>"",D38,"") | AE38: =CONCATENATE(AB38," / ",AC38," / ",AD38) -> AILES / CTP (Water heater) + support /
C39: Ailes avant | F39: Front wing | K39: 1 | L39: 4.4 | O39: ='INPUT1 - Veh Geometry'!$H$61+115 -> 72.5 | P39: 0 | Q39: ='INPUT1 - Veh Geometry'!$J$61+'INPUT1 - Veh Geometry'!$H$81/2+100 -> 523.9 | R39: =$Q39 -> 523.9 | S39: =$Q39 -> 523.9 | T39: =L39*K39-U39 -> 4.2083333 | U39: =IF(ISNUMBER(K39),L39*K39*(O39-$D$262)/E,) -> 0.19166667 | Y39: =IF(ISNUMBER(K39),L39*K39,0) -> 4.4 | Z39: SOEE | AB39: =IF(B39<>0,B39,AB38) -> AILES | AC39: =IF(C39<>0,C39,AC38) -> Ailes avant | AD39: =IF(D39<>"",D39,"") | AE39: =CONCATENATE(AB39," / ",AC39," / ",AD39) -> AILES / Ailes avant / | AH39: valeur usuelle autours de 4kg | AL39: mean value around 4kg
C40: Ailes arrière | F40: Rear wing | O40: ='INPUT1 - Veh Geometry'!$H$33+'INPUT1 - Veh Geometry'!$H$61+300 -> 2897.5 | P40: 0 | Q40: ='INPUT1 - Veh Geometry'!$J$72+'INPUT1 - Veh Geometry'!$H$81 -> 789.8 | R40: =$Q40 -> 789.8 | S40: =$Q40 -> 789.8 | T40: =L40*K40-U40 -> 0 | U40: =IF(ISNUMBER(K40),L40*K40*(O40-$D$262)/E,) -> 0 | Y40: =IF(ISNUMBER(K40),L40*K40,0) -> 0 | Z40: SOEE | AB40: =IF(B40<>0,B40,AB39) -> AILES | AC40: =IF(C40<>0,C40,AC39) -> Ailes arrière | AD40: =IF(D40<>"",D40,"") | AE40: =CONCATENATE(AB40," / ",AC40," / ",AD40) -> AILES / Ailes arrière / | AH40: 0 en général, inclus dans coté de caisse | AL40: 0 in general, included in the side panel
B41: ASSISES | F41: Seats | L41: =SUMPRODUCT(L42:L46,K42:K46) -> 58.8 | O41: =SUMPRODUCT($K42:$K46,$L42:$L46,O42:O46)/$L41 -> 1676.4966 | P41: =SUMPRODUCT($K42:$K46,$L42:$L46,P42:P46)/$L41 -> 0 | Q41: =SUMPRODUCT($K42:$K46,$L42:$L46,Q42:Q46)/$L41 -> 486.55187 | R41: =SUMPRODUCT($K42:$K46,$L42:$L46,R42:R46)/$L41 -> 486.55187 | S41: =SUMPRODUCT($K42:$K46,$L42:$L46,S42:S46)/$L41 -> 486.55187 | T41: =SUM(T42:T46) -> #VALUE! | U41: =SUMIF($K42:$K46,">0",$U42:$U46) -> 38.286742 | Y41: =IF(ISNUMBER(K41),L41*K41,0) -> 0 | Z41: SPCS | AB41: =IF(B41<>0,B41,AB40) -> ASSISES | AC41: =IF(C41<>0,C41,AC40) -> Ailes arrière | AD41: =IF(D41<>"",D41,"") | AE41: =CONCATENATE(AB41," / ",AC41," / ",AD41) -> ASSISES / Ailes arrière /
C42: ASSISE AR RG2 | F42: Row 2 seats | K42: 1 | L42: 25.3 | O42: ='INPUT1 - Veh Geometry'!$H$49 -> 2130 | P42: 0 | Q42: ='INPUT1 - Veh Geometry'!$J$49+225 -> 614 | R42: =$Q42 -> 614 | S42: =$Q42 -> 614 | T42: =L42*K42-U42 -> 4.4802083 | U42: =IF(ISNUMBER(K42),L42*K42*(O42-$D$262)/E,) -> 20.819792 | Y42: =IF(ISNUMBER(K42),L42*K42,0) -> 25.3 | Z42: SPCS | AB42: =IF(B42<>0,B42,AB41) -> ASSISES | AC42: =IF(C42<>0,C42,AC41) -> ASSISE AR RG2 | AD42: =IF(D42<>"",D42,"") | AE42: =CONCATENATE(AB42," / ",AC42," / ",AD42) -> ASSISES / ASSISE AR RG2 / | AH42: Dépend du concept: banquette fixe/coulissante, siège amovible | AL42: very large variations, depending on the concept
C43: ASSISE AR RG3 | F43: Row 3 seats | O43: ='INPUT1 - Veh Geometry'!$H$52 -> 0 | P43: 0 | Q43: ='INPUT1 - Veh Geometry'!$J$53-30 -> -30 | R43: =$Q43 -> -30 | S43: =$Q43 -> -30 | T43: =L43*K43-U43 -> 0 | U43: =IF(ISNUMBER(K43),L43*K43*(O43-$D$262)/E,) -> 0 | Y43: =IF(ISNUMBER(K43),L43*K43,0) -> 0 | Z43: SPCS | AB43: =IF(B43<>0,B43,AB42) -> ASSISES | AC43: =IF(C43<>0,C43,AC42) -> ASSISE AR RG3 | AD43: =IF(D43<>"",D43,"") | AE43: =CONCATENATE(AB43," / ",AC43," / ",AD43) -> ASSISES / ASSISE AR RG3 /
C44: ASSISE AV | F44: Front seats | K44: x | L44: 33.5 | O44: =SUMPRODUCT($K45:$K46,$L45:$L46,O45:O46)/$L44 -> 1334 | P44: =SUMPRODUCT($K45:$K46,$L45:$L46,P45:P46)/$L44 -> 0 | Q44: =SUMPRODUCT($K45:$K46,$L45:$L46,Q45:Q46)/$L44 -> 390.3 | R44: =$Q44 -> 390.3 | S44: =$Q44 -> 390.3 | T44: =L44*K44-U44 -> #VALUE! | U44: =IF(ISNUMBER(K44),L44*K44*(O44-$D$262)/E,) -> 0 | Y44: =IF(ISNUMBER(K44),L44*K44,0) -> 0 | Z44: SPCS | AB44: =IF(B44<>0,B44,AB43) -> ASSISES | AC44: =IF(C44<>0,C44,AC43) -> ASSISE AV | AD44: =IF(D44<>"",D44,"") | AE44: =CONCATENATE(AB44," / ",AC44," / ",AD44) -> ASSISES / ASSISE AV /
D45: Avant conducteur | F45: Driver's seat | K45: 1 | L45: =L44/2 -> 16.75 | O45: ='INPUT1 - Veh Geometry'!$H$42 -> 1334 | P45: ='INPUT1 - Veh Geometry'!I42 -> -355 | Q45: ='INPUT1 - Veh Geometry'!$J$42 -> 390.3 | R45: =$Q45 -> 390.3 | S45: =$Q45 -> 390.3 | T45: =L45*K45-U45 -> 8.0165246 | U45: =IF(ISNUMBER(K45),L45*K45*(O45-$D$262)/E,) -> 8.7334754 | Y45: =IF(ISNUMBER(K45),L45*K45,0) -> 16.75 | Z45: SPCS | AB45: =IF(B45<>0,B45,AB44) -> ASSISES | AC45: =IF(C45<>0,C45,AC44) -> ASSISE AV | AD45: =IF(D45<>"",D45,"") -> Avant conducteur | AE45: =CONCATENATE(AB45," / ",AC45," / ",AD45) -> ASSISES / ASSISE AV / Avant conducteur | AH45: Dépend du niveau de gamme, 15 à 30kg | AL45: related to the trim level, can vary from 15 to 30kg
D46: Avant passager | F46: Front passenger seat | K46: 1 | L46: =L44/2 -> 16.75 | O46: ='INPUT1 - Veh Geometry'!$H$42 -> 1334 | P46: =-'INPUT1 - Veh Geometry'!I42 -> 355 | Q46: ='INPUT1 - Veh Geometry'!$J$42 -> 390.3 | R46: =$Q46 -> 390.3 | S46: =$Q46 -> 390.3 | T46: =L46*K46-U46 -> 8.0165246 | U46: =IF(ISNUMBER(K46),L46*K46*(O46-$D$262)/E,) -> 8.7334754 | Y46: =IF(ISNUMBER(K46),L46*K46,0) -> 16.75 | Z46: SPCS | AB46: =IF(B46<>0,B46,AB45) -> ASSISES | AC46: =IF(C46<>0,C46,AC45) -> ASSISE AV | AD46: =IF(D46<>"",D46,"") -> Avant passager | AE46: =CONCATENATE(AB46," / ",AC46," / ",AD46) -> ASSISES / ASSISE AV / Avant passager | AH46: Dépend du niveau de gamme, 15 à 30kg; égal ou inférieur au siège conducteur | AL46: related to the trim level, can vary from 15 to 30kg; sould be equal or below the mass of driver's seat
B47: BATTERIE 12V | F47: 12V battery | L47: =SUMPRODUCT(K48:K49,L48:L49) -> 12 | O47: =SUMPRODUCT($K48:$K49,$L48:$L49,O48:O49)/$L47 -> 2661 | P47: =SUMPRODUCT($K48:$K49,$L48:$L49,P48:P49)/$L47 -> 143 | Q47: =SUMPRODUCT($K48:$K49,$L48:$L49,Q48:Q49)/$L47 -> 130 | R47: =SUMPRODUCT($K48:$K49,$L48:$L49,R48:R49)/$L47 -> 130 | S47: =R47 -> 130 | T47: =SUM(T48:T49) -> -0.28863636 | U47: =SUMIF($K48:$K49,">0",$U48:$U49) -> 12.288636 | Y47: =IF(ISNUMBER(K47),L47*K47,0) -> 0 | Z47: DSEE-sil | AB47: =IF(B47<>0,B47,AB46) -> BATTERIE 12V | AC47: =IF(C47<>0,C47,AC46) -> ASSISE AV | AD47: =IF(D47<>"",D47,"") | AE47: =CONCATENATE(AB47," / ",AC47," / ",AD47) -> BATTERIE 12V / ASSISE AV /
C48: Batterie démarrage | F48: 12v battery | K48: 1 | L48: 12 | O48: ='INPUT1 - Veh Geometry'!$H$97 -> 2661 | P48: ='INPUT1 - Veh Geometry'!$I$97 -> 143 | Q48: ='INPUT1 - Veh Geometry'!$J$97 -> 130 | R48: =$Q48 -> 130 | S48: =$Q48 -> 130 | T48: =L48*K48-U48 -> -0.28863636 | U48: =IF(ISNUMBER(K48),L48*K48*(O48-$D$262)/E,) -> 12.288636 | Y48: =IF(ISNUMBER(K48),L48*K48,0) -> 12 | Z48: DCTC | AB48: =IF(B48<>0,B48,AB47) -> BATTERIE 12V | AC48: =IF(C48<>0,C48,AC47) -> Batterie démarrage | AD48: =IF(D48<>"",D48,"") | AE48: =CONCATENATE(AB48," / ",AC48," / ",AD48) -> BATTERIE 12V / Batterie démarrage / | AH48: Dépend de la motorisation; batterie L2: 17kg; batterie L3: 21kg | AL48: L2 battery: 17kg; L3 battery: 21kg
C49: Batterie additionnelle | F49: additional battery | O49: ='INPUT1 - Veh Geometry'!$H$57 -> 2750 | P49: ='INPUT1 - Veh Geometry'!$I$57 -> 0 | Q49: ='INPUT1 - Veh Geometry'!$J$57 -> 625 | R49: =$Q49 -> 625 | S49: =$Q49 -> 625 | T49: =L49*K49-U49 -> 0 | U49: =IF(ISNUMBER(K49),L49*K49*(O49-$D$262)/E,) -> 0 | Y49: =IF(ISNUMBER(K49),L49*K49,0) -> 0 | Z49: DSEE-sil | AB49: =IF(B49<>0,B49,AB48) -> BATTERIE 12V | AC49: =IF(C49<>0,C49,AC48) -> Batterie additionnelle | AD49: =IF(D49<>"",D49,"") | AE49: =CONCATENATE(AB49," / ",AC49," / ",AD49) -> BATTERIE 12V / Batterie additionnelle / | AH49: Pour PHEV V1/V2 ou pour TJC (6kg) | AL49: use case PHEV V1/V2 or TJC (6kg)
B50: BATTERIE DE TRACTION | F50: ENGINE BATTERY | L50: =SUMPRODUCT(K51:K61,L51:L61) -> 14.4 | O50: =SUMPRODUCT($K51:$K61,$L51:$L61,O51:O61)/$L50 -> 1328 | P50: =SUMPRODUCT($K51:$K61,$L51:$L61,P51:P61)/$L50 -> 75.666667 | Q50: =SUMPRODUCT($K51:$K61,$L51:$L61,Q51:Q61)/$L50 -> -13.916667 | R50: =SUMPRODUCT($K51:$K61,$L51:$L61,R51:R61)/$L50 -> -13.916667 | S50: =SUMPRODUCT($K51:$K61,$L51:$L61,S51:S61)/$L50 -> -13.916667 | T50: =SUM(T51:T61) -> 6.9245455 | U50: =SUMIF($K51:$K61,">0",$U51:$U61) -> 7.4754545 | Y50: =IF(ISNUMBER(K50),L50*K50,0) -> 0 | Z50: DSEE-sil | AB50: =IF(B50<>0,B50,AB49) -> BATTERIE DE TRACTION | AC50: =IF(C50<>0,C50,AC49) -> Batterie additionnelle | AD50: =IF(D50<>"",D50,"") | AE50: =CONCATENATE(AB50," / ",AC50," / ",AD50) -> BATTERIE DE TRACTION / Batterie additionnelle /
C51: Système batterie traction | F51: Système batterie traction | K51: 1 | L51: 12 | O51: ='INPUT1 - Veh Geometry'!H$93 -> 1331 | P51: ='INPUT1 - Veh Geometry'!I$93 -> 26 | Q51: ='INPUT1 - Veh Geometry'!J$93 -> -9.5 | R51: =$Q51 -> -9.5 | S51: =$Q51 -> -9.5 | T51: =L51*K51-U51 -> 5.7568182 | U51: =IF(ISNUMBER(K51),L51*K51*(O51-$D$262)/E,) -> 6.2431818 | Y51: =IF(ISNUMBER(K51),L51*K51,0) -> 12 | Z51: DCTC | AB51: =IF(B51<>0,B51,AB50) -> BATTERIE DE TRACTION | AC51: =IF(C51<>0,C51,AC50) -> Système batterie traction | AD51: =IF(D51<>"",D51,"") | AE51: =CONCATENATE(AB51," / ",AC51," / ",AD51) -> BATTERIE DE TRACTION / Système batterie traction / | AH51: Dépend de la motorisation; batterie L2: 17kg; batterie L3: 21kg | AL51: L2 battery: 17kg; L3 battery: 21kg
D52: Bac batterie | G52: housing | O52: ='INPUT1 - Veh Geometry'!H$93 -> 1331 | P52: ='INPUT1 - Veh Geometry'!I$93 -> 26 | Q52: ='INPUT1 - Veh Geometry'!J$93 -> -9.5 | R52: =$Q52 -> -9.5 | S52: =$Q52 -> -9.5 | T52: =L52*K52-U52 -> 0 | U52: =IF(ISNUMBER(K52),L52*K52*(O52-$D$262)/E,) -> 0 | Y52: =IF(ISNUMBER(K52),L52*K52,0) -> 0 | Z52: SCEG-Batt | AB52: =IF(B52<>0,B52,AB51) -> BATTERIE DE TRACTION | AC52: =IF(C52<>0,C52,AC51) -> Système batterie traction | AD52: =IF(D52<>"",D52,"") -> Bac batterie | AE52: =CONCATENATE(AB52," / ",AC52," / ",AD52) -> BATTERIE DE TRACTION / Système batterie traction / Bac batterie | AH52: masse: env. 0,75kg par L de batterie (acier) ou 0,6kg par L (alu) | AL52: mass: 0,75kg per L useful of modules (steel housing) or 0,6kg (alloy housing)
D53: modules | G53: modules | O53: ='INPUT1 - Veh Geometry'!H$93 -> 1331 | P53: ='INPUT1 - Veh Geometry'!I$93 -> 26 | Q53: ='INPUT1 - Veh Geometry'!J$93 -> -9.5 | R53: =$Q53 -> -9.5 | S53: =$Q53 -> -9.5 | T53: =L53*K53-U53 -> 0 | U53: =IF(ISNUMBER(K53),L53*K53*(O53-$D$262)/E,) -> 0 | Y53: =IF(ISNUMBER(K53),L53*K53,0) -> 0 | Z53: DSEE-Batt | AB53: =IF(B53<>0,B53,AB52) -> BATTERIE DE TRACTION | AC53: =IF(C53<>0,C53,AC52) -> Système batterie traction | AD53: =IF(D53<>"",D53,"") -> modules | AE53: =CONCATENATE(AB53," / ",AC53," / ",AD53) -> BATTERIE DE TRACTION / Système batterie traction / modules | AH53: masse de la chimie: 2,2kg par L utile de module | AL53: chemistry mass: 2,2kg par L useful of modules
D54: autres: bus bar, refri, BMS… | G54: cooling+ wires, BMS… | O54: ='INPUT1 - Veh Geometry'!H$93 -> 1331 | P54: ='INPUT1 - Veh Geometry'!I$93 -> 26 | Q54: ='INPUT1 - Veh Geometry'!J$93 -> -9.5 | R54: =$Q54 -> -9.5 | S54: =$Q54 -> -9.5 | T54: =L54*K54-U54 -> 0 | U54: =IF(ISNUMBER(K54),L54*K54*(O54-$D$262)/E,) -> 0 | Y54: =IF(ISNUMBER(K54),L54*K54,0) -> 0 | Z54: DSEE-Batt | AB54: =IF(B54<>0,B54,AB53) -> BATTERIE DE TRACTION | AC54: =IF(C54<>0,C54,AC53) -> Système batterie traction | AD54: =IF(D54<>"",D54,"") -> autres: bus bar, refri, BMS… | AE54: =CONCATENATE(AB54," / ",AC54," / ",AD54) -> BATTERIE DE TRACTION / Système batterie traction / autres: bus bar, refri, BMS… | AH54: masse des autres éléments: env. 40kg | AL54: others: around 40kg
D55: Convertisseur DC-DC | F55: DCDC converter | K55: 1 | L55: 2.4 | O55: ='INPUT1 - Veh Geometry'!H$95 -> 1313 | P55: ='INPUT1 - Veh Geometry'!I$95 -> 324 | Q55: ='INPUT1 - Veh Geometry'!J$95 -> -36 | R55: =$Q55 -> -36 | S55: =$Q55 -> -36 | T55: =L55*K55-U55 -> 1.1677273 | U55: =IF(ISNUMBER(K55),L55*K55*(O55-$D$262)/E,) -> 1.2322727 | Y55: =IF(ISNUMBER(K55),L55*K55,0) -> 2.4 | Z55: DCTC | AB55: =IF(B55<>0,B55,AB54) -> BATTERIE DE TRACTION | AC55: =IF(C55<>0,C55,AC54) -> Système batterie traction | AD55: =IF(D55<>"",D55,"") -> Convertisseur DC-DC | AE55: =CONCATENATE(AB55," / ",AC55," / ",AD55) -> BATTERIE DE TRACTION / Système batterie traction / Convertisseur DC-DC | AH55: pour MHEV, PHEV, BEV | AL55: in case of a MHEV, PHEV, BEV
C56: Système module de charge HT | F56: OBC | O56: ='INPUT1 - Veh Geometry'!H$94 -> 0 | P56: ='INPUT1 - Veh Geometry'!I$94 -> 0 | Q56: ='INPUT1 - Veh Geometry'!J$94 -> 0 | R56: =$Q56 -> 0 | S56: =$Q56 -> 0 | T56: =L56*K56-U56 -> 0 | U56: =IF(ISNUMBER(K56),L56*K56*(O56-$D$262)/E,) -> 0 | Y56: =IF(ISNUMBER(K56),L56*K56,0) -> 0 | Z56: DCTC | AB56: =IF(B56<>0,B56,AB55) -> BATTERIE DE TRACTION | AC56: =IF(C56<>0,C56,AC55) -> Système module de charge HT | AD56: =IF(D56<>"",D56,"") | AE56: =CONCATENATE(AB56," / ",AC56," / ",AD56) -> BATTERIE DE TRACTION / Système module de charge HT / | AH56: Dépend de la motorisation; batterie L2: 17kg; batterie L3: 21kg | AL56: L2 battery: 17kg; L3 battery: 21kg
C57: Durite de ventilation module charge HT | F57: Durite de ventilation module charge HT | O57: ='INPUT1 - Veh Geometry'!$H$97 -> 2661 | P57: ='INPUT1 - Veh Geometry'!$I$109 -> -280 | Q57: ='INPUT1 - Veh Geometry'!$J$97 -> 130 | R57: =$Q57 -> 130 | S57: =$Q57 -> 130 | T57: =L57*K57-U57 -> 0 | U57: =IF(ISNUMBER(K57),L57*K57*(O57-$D$262)/E,) -> 0 | Y57: =IF(ISNUMBER(K57),L57*K57,0) -> 0 | Z57: DCTC | AB57: =IF(B57<>0,B57,AB56) -> BATTERIE DE TRACTION | AC57: =IF(C57<>0,C57,AC56) -> Durite de ventilation module charge HT | AD57: =IF(D57<>"",D57,"") | AE57: =CONCATENATE(AB57," / ",AC57," / ",AD57) -> BATTERIE DE TRACTION / Durite de ventilation module charge HT / | AH57: Dépend de la motorisation; batterie L2: 17kg; batterie L3: 21kg | AL57: L2 battery: 17kg; L3 battery: 21kg
C58: Calculateur gestion batterie HT | F58: Calculateur gestion batterie HT | O58: ='INPUT1 - Veh Geometry'!$H$97 -> 2661 | P58: ='INPUT1 - Veh Geometry'!$I$109 -> -280 | Q58: ='INPUT1 - Veh Geometry'!$J$97 -> 130 | R58: =$Q58 -> 130 | S58: =$Q58 -> 130 | T58: =L58*K58-U58 -> 0 | U58: =IF(ISNUMBER(K58),L58*K58*(O58-$D$262)/E,) -> 0 | Y58: =IF(ISNUMBER(K58),L58*K58,0) -> 0 | Z58: DCTC | AB58: =IF(B58<>0,B58,AB57) -> BATTERIE DE TRACTION | AC58: =IF(C58<>0,C58,AC57) -> Calculateur gestion batterie HT | AD58: =IF(D58<>"",D58,"") | AE58: =CONCATENATE(AB58," / ",AC58," / ",AD58) -> BATTERIE DE TRACTION / Calculateur gestion batterie HT / | AH58: Dépend de la motorisation; batterie L2: 17kg; batterie L3: 21kg | AL58: L2 battery: 17kg; L3 battery: 21kg
C59: Second support module charge HT | F59: Second support module charge HT | O59: ='INPUT1 - Veh Geometry'!$H$97 -> 2661 | P59: ='INPUT1 - Veh Geometry'!$I$109 -> -280 | Q59: ='INPUT1 - Veh Geometry'!$J$97 -> 130 | R59: =$Q59 -> 130 | S59: =$Q59 -> 130 | T59: =L59*K59-U59 -> 0 | U59: =IF(ISNUMBER(K59),L59*K59*(O59-$D$262)/E,) -> 0 | Y59: =IF(ISNUMBER(K59),L59*K59,0) -> 0 | Z59: DCTC | AB59: =IF(B59<>0,B59,AB58) -> BATTERIE DE TRACTION | AC59: =IF(C59<>0,C59,AC58) -> Second support module charge HT | AD59: =IF(D59<>"",D59,"") | AE59: =CONCATENATE(AB59," / ",AC59," / ",AD59) -> BATTERIE DE TRACTION / Second support module charge HT / | AH59: Dépend de la motorisation; batterie L2: 17kg; batterie L3: 21kg | AL59: L2 battery: 17kg; L3 battery: 21kg
C60: Support calculateur gestion batterie HT | F60: Support calculateur gestion batterie HT | O60: ='INPUT1 - Veh Geometry'!$H$97 -> 2661 | P60: ='INPUT1 - Veh Geometry'!$I$109 -> -280 | Q60: ='INPUT1 - Veh Geometry'!$J$97 -> 130 | R60: =$Q60 -> 130 | S60: =$Q60 -> 130 | T60: =L60*K60-U60 -> 0 | U60: =IF(ISNUMBER(K60),L60*K60*(O60-$D$262)/E,) -> 0 | Y60: =IF(ISNUMBER(K60),L60*K60,0) -> 0 | Z60: DCTC | AB60: =IF(B60<>0,B60,AB59) -> BATTERIE DE TRACTION | AC60: =IF(C60<>0,C60,AC59) -> Support calculateur gestion batterie HT | AD60: =IF(D60<>"",D60,"") | AE60: =CONCATENATE(AB60," / ",AC60," / ",AD60) -> BATTERIE DE TRACTION / Support calculateur gestion batterie HT / | AH60: Dépend de la motorisation; batterie L2: 17kg; batterie L3: 21kg | AL60: L2 battery: 17kg; L3 battery: 21kg
C61: Deuxiéme support calculateur gestion batterie HT | F61: Deuxiéme support calculateur gestion batterie HT | O61: ='INPUT1 - Veh Geometry'!$H$57 -> 2750 | P61: ='INPUT1 - Veh Geometry'!$I$57 -> 0 | Q61: ='INPUT1 - Veh Geometry'!$J$57 -> 625 | R61: =$Q61 -> 625 | S61: =$Q61 -> 625 | T61: =L61*K61-U61 -> 0 | U61: =IF(ISNUMBER(K61),L61*K61*(O61-$D$262)/E,) -> 0 | Y61: =IF(ISNUMBER(K61),L61*K61,0) -> 0 | Z61: DSEE-sil | AB61: =IF(B61<>0,B61,AB60) -> BATTERIE DE TRACTION | AC61: =IF(C61<>0,C61,AC60) -> Deuxiéme support calculateur gestion batterie HT | AD61: =IF(D61<>"",D61,"") | AE61: =CONCATENATE(AB61," / ",AC61," / ",AD61) -> BATTERIE DE TRACTION / Deuxiéme support calculateur gestion batterie HT / | AH61: Pour PHEV V1/V2 ou pour TJC (6kg) | AL61: use case PHEV V1/V2 or TJC (6kg)
B62: BOUCLIER AR | F62: Rear bumper | L62: =SUMPRODUCT(K63:K64,L63:L64) -> 6.6 | O62: =SUMPRODUCT($K63:$K64,$L63:$L64,O63:O64)/$L62 -> 3147.5 | P62: =SUMPRODUCT($K63:$K64,$L63:$L64,P63:P64)/$L62 -> 0 | Q62: =SUMPRODUCT($K63:$K64,$L63:$L64,Q63:Q64)/$L62 -> 240.3 | R62: =SUMPRODUCT($K63:$K64,$L63:$L64,R63:R64)/$L62 -> 240.3 | S62: =SUMPRODUCT($K63:$K64,$L63:$L64,S63:S64)/$L62 -> 240.3 | T62: =SUM(T63:T64) -> -1.375 | U62: =SUMIF($K63:$K64,">0",$U63:$U64) -> 7.975 | Y62: =IF(ISNUMBER(K62),L62*K62,0) -> 0 | Z62: SOEE | AB62: =IF(B62<>0,B62,AB61) -> BOUCLIER AR | AC62: =IF(C62<>0,C62,AC61) -> Deuxiéme support calculateur gestion batterie HT | AD62: =IF(D62<>"",D62,"") | AE62: =CONCATENATE(AB62," / ",AC62," / ",AD62) -> BOUCLIER AR / Deuxiéme support calculateur gestion batterie HT /
C63: Pare Choc AR | F63: Rear bumper | K63: 1 | L63: 6.6 | O63: ='INPUT1 - Veh Geometry'!$H$72+'INPUT1 - Veh Geometry'!$H$36-150 -> 3147.5 | P63: 0 | Q63: ='INPUT1 - Veh Geometry'!$J$42-150 -> 240.3 | R63: =$Q63 -> 240.3 | S63: =$Q63 -> 240.3 | T63: =L63*K63-U63 -> -1.375 | U63: =IF(ISNUMBER(K63),L63*K63*(O63-$D$262)/E,) -> 7.975 | Y63: =IF(ISNUMBER(K63),L63*K63,0) -> 6.6 | Z63: =IF(K63=0,"","SOEE") -> SOEE | AB63: =IF(B63<>0,B63,AB62) -> BOUCLIER AR | AC63: =IF(C63<>0,C63,AC62) -> Pare Choc AR | AD63: =IF(D63<>"",D63,"") | AE63: =CONCATENATE(AB63," / ",AC63," / ",AD63) -> BOUCLIER AR / Pare Choc AR /
C64: Pare boue AR | F64: Rear mudguard | O64: ='INPUT1 - Veh Geometry'!$H$72-150 -> 2447.5 | P64: 0 | Q64: ='INPUT1 - Veh Geometry'!$J$72+'INPUT1 - Veh Geometry'!$H$81/2-100 -> 332.9 | R64: =$Q64 -> 332.9 | S64: =$Q64 -> 332.9 | T64: =L64*K64-U64 -> 0 | U64: =IF(ISNUMBER(K64),L64*K64*(O64-$D$262)/E,) -> 0 | Y64: =IF(ISNUMBER(K64),L64*K64,0) -> 0 | Z64: =IF(K64=0,"","SOEE") | AB64: =IF(B64<>0,B64,AB63) -> BOUCLIER AR | AC64: =IF(C64<>0,C64,AC63) -> Pare boue AR | AD64: =IF(D64<>"",D64,"") | AE64: =CONCATENATE(AB64," / ",AC64," / ",AD64) -> BOUCLIER AR / Pare boue AR / | AH64: Si présent, env. 2kg
B65: BOUCLIER AV | F65: Front bumper | L65: =SUMPRODUCT(K66:K67,L66:L67) -> 12.6 | O65: =SUMPRODUCT($K66:$K67,$L66:$L67,O66:O67)/$L65 -> -662.5 | P65: =SUMPRODUCT($K66:$K67,$L66:$L67,P66:P67)/$L65 -> 0 | Q65: =SUMPRODUCT($K66:$K67,$L66:$L67,Q66:Q67)/$L65 -> 290.3 | R65: =SUMPRODUCT($K66:$K67,$L66:$L67,R66:R67)/$L65 -> 290.3 | S65: =SUMPRODUCT($K66:$K67,$L66:$L67,S66:S67)/$L65 -> 290.3 | T65: =SUM(T66:T67) -> 15.559091 | U65: =SUMIF($K66:$K67,">0",$U66:$U67) -> -2.9590909 | Y65: =IF(ISNUMBER(K65),L65*K65,0) -> 0 | Z65: =IF(K65=0,"","SOEE") | AB65: =IF(B65<>0,B65,AB64) -> BOUCLIER AV | AC65: =IF(C65<>0,C65,AC64) -> Pare boue AR | AD65: =IF(D65<>"",D65,"") | AE65: =CONCATENATE(AB65," / ",AC65," / ",AD65) -> BOUCLIER AV / Pare boue AR /
C66: Pare Choc AV | F66: Front bumper | K66: 1 | L66: 12.6 | O66: ='INPUT1 - Veh Geometry'!$H$61-'INPUT1 - Veh Geometry'!$H$35+200 -> -662.5 | P66: 0 | Q66: ='INPUT1 - Veh Geometry'!$J$42-100 -> 290.3 | R66: =$Q66 -> 290.3 | S66: =$Q66 -> 290.3 | T66: =L66*K66-U66 -> 15.559091 | U66: =IF(ISNUMBER(K66),L66*K66*(O66-$D$262)/E,) -> -2.9590909 | Y66: =IF(ISNUMBER(K66),L66*K66,0) -> 12.6 | Z66: =IF(K66=0,"","SOEE") -> SOEE | AB66: =IF(B66<>0,B66,AB65) -> BOUCLIER AV | AC66: =IF(C66<>0,C66,AC65) -> Pare Choc AV | AD66: =IF(D66<>"",D66,"") | AE66: =CONCATENATE(AB66," / ",AC66," / ",AD66) -> BOUCLIER AV / Pare Choc AV /
C67: Pare boue AV | F67: Front mudguard | O67: ='INPUT1 - Veh Geometry'!$H$61 -> -42.5 | P67: 0 | Q67: ='INPUT1 - Veh Geometry'!$J$61+'INPUT1 - Veh Geometry'!$H$81/2-100 -> 323.9 | R67: =$Q67 -> 323.9 | S67: =$Q67 -> 323.9 | T67: =L67*K67-U67 -> 0 | U67: =IF(ISNUMBER(K67),L67*K67*(O67-$D$262)/E,) -> 0 | Y67: =IF(ISNUMBER(K67),L67*K67,0) -> 0 | Z67: =IF(K67=0,"","SOEE") | AB67: =IF(B67<>0,B67,AB66) -> BOUCLIER AV | AC67: =IF(C67<>0,C67,AC66) -> Pare boue AV | AD67: =IF(D67<>"",D67,"") | AE67: =CONCATENATE(AB67," / ",AC67," / ",AD67) -> BOUCLIER AV / Pare boue AV / | AH67: valeur moyenne, env. 3kg (inclu une bavette aérodynamique de roue av) | AL67: Mean value 3kg (including front wheel spoiler)
B68: BV / Réducteur | F68: Gearbox / reducer | L68: =SUMPRODUCT(L69:L74,K69:K74) -> 107.1 | O68: =SUMPRODUCT($L69:$L74,O69:O74,$K69:$K74)/$L68 -> -241.5 | P68: =SUMPRODUCT($L69:$L74,P69:P74,$K69:$K74)/$L68 -> -48 | Q68: =SUMPRODUCT($L69:$L74,Q69:Q74,$K69:$K74)/$L68 -> 144.4 | R68: =SUMPRODUCT($L69:$L74,R69:R74,$K69:$K74)/$L68 -> 144.4 | S68: =SUMPRODUCT($L69:$L74,S69:S74,$K69:$K74)/$L68 -> 144.4 | T68: =SUM(T69:T74) -> 115.17307 | U68: =SUMIF($K69:$K74,">0",$U69:$U74) -> -8.0730682 | Y68: =IF(ISNUMBER(K68),L68*K68,0) -> 0 | Z68: DCTC | AB68: =IF(B68<>0,B68,AB67) -> BV / Réducteur | AC68: =IF(C68<>0,C68,AC67) -> Pare boue AV | AD68: =IF(D68<>"",D68,"") | AE68: =CONCATENATE(AB68," / ",AC68," / ",AD68) -> BV / Réducteur / Pare boue AV /
C69: 4x4 | F69: 4x4 transmission | R69: =$Q69 -> 0 | S69: =$Q69 -> 0 | T69: =L69*K69-U69 -> 0 | U69: =IF(ISNUMBER(K69),L69*K69*(O69-$D$262)/E,) -> 0 | Y69: =IF(ISNUMBER(K69),L69*K69,0) -> 0 | Z69: DCTC | AB69: =IF(B69<>0,B69,AB68) -> BV / Réducteur | AC69: =IF(C69<>0,C69,AC68) -> 4x4 | AD69: =IF(D69<>"",D69,"") | AE69: =CONCATENATE(AB69," / ",AC69," / ",AD69) -> BV / Réducteur / 4x4 / | AH69: masse de la transmission longi dans le cas d'un 4x4 | AL69: mass of longitudinal transmission in case of a 4WD
C70: BVA | F70: Automatic gearbox | K70: 1 | L70: 107.1 | O70: ='INPUT1 - Veh Geometry'!$H$87 -> -241.5 | P70: ='INPUT1 - Veh Geometry'!$I$87 -> -48 | Q70: ='INPUT1 - Veh Geometry'!$J$87 -> 144.4 | R70: =$Q70 -> 144.4 | S70: =$Q70 -> 144.4 | T70: =L70*K70-U70 -> 115.17307 | U70: =IF(ISNUMBER(K70),L70*K70*(O70-$D$262)/E,) -> -8.0730682 | Y70: =IF(ISNUMBER(K70),L70*K70,0) -> 107.1 | Z70: DCTC | AB70: =IF(B70<>0,B70,AB69) -> BV / Réducteur | AC70: =IF(C70<>0,C70,AC69) -> BVA | AD70: =IF(D70<>"",D70,"") | AE70: =CONCATENATE(AB70," / ",AC70," / ",AD70) -> BV / Réducteur / BVA / | AH70: masse du réducteur AV (si BEV) | AL70: mass of front reducer
C71: BVM | F71: Manual gearbox | O71: ='INPUT1 - Veh Geometry'!$H$87 -> -241.5 | P71: ='INPUT1 - Veh Geometry'!$I$87 -> -48 | Q71: ='INPUT1 - Veh Geometry'!$J$87 -> 144.4 | R71: =$Q71 -> 144.4 | S71: =$Q71 -> 144.4 | T71: =L71*K71-U71 -> 0 | U71: =IF(ISNUMBER(K71),L71*K71*(O71-$D$262)/E,) -> 0 | Y71: =IF(ISNUMBER(K71),L71*K71,0) -> 0 | Z71: DCTC | AB71: =IF(B71<>0,B71,AB70) -> BV / Réducteur | AC71: =IF(C71<>0,C71,AC70) -> BVM | AD71: =IF(D71<>"",D71,"") | AE71: =CONCATENATE(AB71," / ",AC71," / ",AD71) -> BV / Réducteur / BVM / | AH71: masse du réducteur AR (si BEV) | AL71: mass of rear reducer
C72: COUPLAGE | F72: Coupling | O72: ='INPUT1 - Veh Geometry'!$H$87 -> -241.5 | P72: ='INPUT1 - Veh Geometry'!$I$87 -> -48 | Q72: ='INPUT1 - Veh Geometry'!$J$87 -> 144.4 | R72: =$Q72 -> 144.4 | S72: =$Q72 -> 144.4 | T72: =L72*K72-U72 -> 0 | U72: =IF(ISNUMBER(K72),L72*K72*(O72-$D$262)/E,) -> 0 | Y72: =IF(ISNUMBER(K72),L72*K72,0) -> 0 | Z72: DCTC | AB72: =IF(B72<>0,B72,AB71) -> BV / Réducteur | AC72: =IF(C72<>0,C72,AC71) -> COUPLAGE | AD72: =IF(D72<>"",D72,"") | AE72: =CONCATENATE(AB72," / ",AC72," / ",AD72) -> BV / Réducteur / COUPLAGE / | AH72: masse du réducteur AR (si BEV) | AL72: mass of rear reducer
C73: REDUCTEUR AR | F73: Rear reducer | O73: ='INPUT1 - Veh Geometry'!$H$90 -> 0 | P73: ='INPUT1 - Veh Geometry'!$I$90 -> 0 | Q73: ='INPUT1 - Veh Geometry'!$J$90 -> 0 | R73: =$Q73 -> 0 | S73: =$Q73 -> 0 | T73: =L73*K73-U73 -> 0 | U73: =IF(ISNUMBER(K73),L73*K73*(O73-$D$262)/E,) -> 0 | Y73: =IF(ISNUMBER(K73),L73*K73,0) -> 0 | Z73: DCTC | AB73: =IF(B73<>0,B73,AB72) -> BV / Réducteur | AC73: =IF(C73<>0,C73,AC72) -> REDUCTEUR AR | AD73: =IF(D73<>"",D73,"") | AE73: =CONCATENATE(AB73," / ",AC73," / ",AD73) -> BV / Réducteur / REDUCTEUR AR / | AH73: masse de la boite de vitesse | AL73: mass of gearbox
C74: REDUCTEUR AV | F74: Front reducer | O74: ='INPUT1 - Veh Geometry'!$H$87 -> -241.5 | P74: ='INPUT1 - Veh Geometry'!$I$87 -> -48 | Q74: ='INPUT1 - Veh Geometry'!$J$87 -> 144.4 | R74: =$Q74 -> 144.4 | S74: =$Q74 -> 144.4 | T74: =L74*K74-U74 -> 0 | U74: =IF(ISNUMBER(K74),L74*K74*(O74-$D$262)/E,) -> 0 | Y74: =IF(ISNUMBER(K74),L74*K74,0) -> 0 | Z74: DCTC | AB74: =IF(B74<>0,B74,AB73) -> BV / Réducteur | AC74: =IF(C74<>0,C74,AC73) -> REDUCTEUR AV | AD74: =IF(D74<>"",D74,"") | AE74: =CONCATENATE(AB74," / ",AC74," / ",AD74) -> BV / Réducteur / REDUCTEUR AV / | AH74: valeur du couplage / DVA si non compté dans la boite de vitesse | AL74: mass of coupling device (if not included in the mass of the gearbox)
B75: CAISSE EN BLANC | F75: Body in white | L75: =SUMPRODUCT(K76:K80,L76:L80) -> 321.9 | O75: =SUMPRODUCT($K76:$K80,$L76:$L80,O76:O80)/$L75 -> 1394 | P75: =SUMPRODUCT($K76:$K80,$L76:$L80,P76:P80)/$L75 -> -1.9 | Q75: =SUMPRODUCT($K76:$K80,$L76:$L80,Q76:Q80)/$L75 -> 200 | R75: =SUMPRODUCT($K76:$K80,$L76:$L80,R76:R80)/$L75 -> 200 | S75: =SUMPRODUCT($K76:$K80,$L76:$L80,S76:S80)/$L75 -> 200 | T75: =SUM(T76:T80) -> 146.74494 | U75: =SUMIF($K76:$K80,">0",$U76:$U80) -> 175.15506 | Y75: =IF(ISNUMBER(K75),L75*K75,0) -> 0 | Z75: SCEG | AB75: =IF(B75<>0,B75,AB74) -> CAISSE EN BLANC | AC75: =IF(C75<>0,C75,AC74) -> REDUCTEUR AV | AD75: =IF(D75<>"",D75,"") | AE75: =CONCATENATE(AB75," / ",AC75," / ",AD75) -> CAISSE EN BLANC / REDUCTEUR AV /
C76: RENFORT DE CAISSE | O76: ='INPUT1 - Veh Geometry'!H$119 -> 1394 | P76: ='INPUT1 - Veh Geometry'!I$119 -> -1.9 | Q76: ='INPUT1 - Veh Geometry'!J$119 -> 200 | R76: =$Q76 -> 200 | S76: =$Q76 -> 200 | T76: =L76*K76-U76 -> 0 | U76: =IF(ISNUMBER(K76),L76*K76*(O76-$D$262)/E,) -> 0 | Y76: =IF(ISNUMBER(K76),L76*K76,0) -> 0 | Z76: SCEG-base | AB76: =IF(B76<>0,B76,AB75) -> CAISSE EN BLANC | AC76: =IF(C76<>0,C76,AC75) -> RENFORT DE CAISSE | AD76: =IF(D76<>"",D76,"") | AE76: =CONCATENATE(AB76," / ",AC76," / ",AD76) -> CAISSE EN BLANC / RENFORT DE CAISSE / | AH76: si non connu, mettre 60% de l'estimation caisse en blanc totale | AL76: if unknown, around 2/3 of the total BIW
C77: TABLIER COTE CONDUCTEUR / UNIQUE | O77: ='INPUT1 - Veh Geometry'!H$119 -> 1394 | P77: ='INPUT1 - Veh Geometry'!I$119 -> -1.9 | Q77: ='INPUT1 - Veh Geometry'!J$119 -> 200 | R77: =$Q77 -> 200 | S77: =$Q77 -> 200 | T77: =L77*K77-U77 -> 0 | U77: =IF(ISNUMBER(K77),L77*K77*(O77-$D$262)/E,) -> 0 | Y77: =IF(ISNUMBER(K77),L77*K77,0) -> 0 | Z77: SCEG | AB77: =IF(B77<>0,B77,AB76) -> CAISSE EN BLANC | AC77: =IF(C77<>0,C77,AC76) -> TABLIER COTE CONDUCTEUR / UNIQUE | AD77: =IF(D77<>"",D77,"") | AE77: =CONCATENATE(AB77," / ",AC77," / ",AD77) -> CAISSE EN BLANC / TABLIER COTE CONDUCTEUR / UNIQUE / | AH77: valeur du véhicule remplacé avec ratio d'échelle | AL77: value from previous vehicule with rato for scaling
C78: TABLIER COTE PASSAGER | O78: ='INPUT1 - Veh Geometry'!H$119 -> 1394 | P78: ='INPUT1 - Veh Geometry'!I$119 -> -1.9 | Q78: ='INPUT1 - Veh Geometry'!J$119 -> 200 | R78: =$Q78 -> 200 | S78: =$Q78 -> 200 | T78: =L78*K78-U78 -> 0 | U78: =IF(ISNUMBER(K78),L78*K78*(O78-$D$262)/E,) -> 0 | Y78: =IF(ISNUMBER(K78),L78*K78,0) -> 0 | Z78: SCEG | AB78: =IF(B78<>0,B78,AB77) -> CAISSE EN BLANC | AC78: =IF(C78<>0,C78,AC77) -> TABLIER COTE PASSAGER | AD78: =IF(D78<>"",D78,"") | AE78: =CONCATENATE(AB78," / ",AC78," / ",AD78) -> CAISSE EN BLANC / TABLIER COTE PASSAGER / | AH78: valeur du véhicule remplacé avec ratio d'échelle | AL78: value from previous vehicule with rato for scaling
C79: BAC DE RANGEMENT ARRIERE 1 | O79: ='INPUT1 - Veh Geometry'!H$119 -> 1394 | P79: ='INPUT1 - Veh Geometry'!I$119 -> -1.9 | Q79: ='INPUT1 - Veh Geometry'!J$119 -> 200 | R79: =$Q79 -> 200 | S79: =$Q79 -> 200 | T79: =L79*K79-U79 -> 0 | U79: =IF(ISNUMBER(K79),L79*K79*(O79-$D$262)/E,) -> 0 | Y79: =IF(ISNUMBER(K79),L79*K79,0) -> 0 | Z79: SCEG | AB79: =IF(B79<>0,B79,AB78) -> CAISSE EN BLANC | AC79: =IF(C79<>0,C79,AC78) -> BAC DE RANGEMENT ARRIERE 1 | AD79: =IF(D79<>"",D79,"") | AE79: =CONCATENATE(AB79," / ",AC79," / ",AD79) -> CAISSE EN BLANC / BAC DE RANGEMENT ARRIERE 1 / | AH79: valeur usuelle, 10kg | AL79: mean value, 10kg
C80: CAISSE EN BLANC (AVEC PEINTURE) | K80: 1 | L80: 321.9 | O80: ='INPUT1 - Veh Geometry'!H$119 -> 1394 | P80: ='INPUT1 - Veh Geometry'!I$119 -> -1.9 | Q80: ='INPUT1 - Veh Geometry'!J$119 -> 200 | R80: =$Q80 -> 200 | S80: =$Q80 -> 200 | T80: =L80*K80-U80 -> 146.74494 | U80: =IF(ISNUMBER(K80),L80*K80*(O80-$D$262)/E,) -> 175.15506 | Y80: =IF(ISNUMBER(K80),L80*K80,0) -> 321.9 | Z80: SCEG | AB80: =IF(B80<>0,B80,AB79) -> CAISSE EN BLANC | AC80: =IF(C80<>0,C80,AC79) -> CAISSE EN BLANC (AVEC PEINTURE) | AD80: =IF(D80<>"",D80,"") | AE80: =CONCATENATE(AB80," / ",AC80," / ",AD80) -> CAISSE EN BLANC / CAISSE EN BLANC (AVEC PEINTURE) / | AH80: valeur usuelle, 10kg | AL80: mean value, 10kg
B81: CAPOT | F81: Hood | L81: =SUMPRODUCT(K82:K83,L82:L83) -> 12.7 | O81: =SUMPRODUCT($K82:$K83,$L82:$L83,O82:O83)/$L81 -> -129 | P81: =SUMPRODUCT($K82:$K83,$L82:$L83,P82:P83)/$L81 -> 0 | Q81: =SUMPRODUCT($K82:$K83,$L82:$L83,Q82:Q83)/$L81 -> 720 | R81: =SUMPRODUCT($K82:$K83,$L82:$L83,R82:R83)/$L81 -> 720 | S81: =SUMPRODUCT($K82:$K83,$L82:$L83,S82:S83)/$L81 -> 720 | T81: =SUM(T82:T83) -> 13.116117 | U81: =SUMIF($K82:$K83,">0",$U82:$U83) -> -0.41611742 | Y81: =IF(ISNUMBER(K81),L81*K81,0) -> 0 | Z81: SCEG | AB81: =IF(B81<>0,B81,AB80) -> CAPOT | AC81: =IF(C81<>0,C81,AC80) -> CAISSE EN BLANC (AVEC PEINTURE) | AD81: =IF(D81<>"",D81,"") | AE81: =CONCATENATE(AB81," / ",AC81," / ",AD81) -> CAPOT / CAISSE EN BLANC (AVEC PEINTURE) /
C82: Tôlerie capot | F82: Metal sheet | K82: 1 | L82: 10.9 | O82: ='INPUT1 - Veh Geometry'!$H$127 -> -129 | P82: 0 | Q82: ='INPUT1 - Veh Geometry'!$J$127 -> 720 | R82: =$Q82 -> 720 | S82: =$Q82 -> 720 | T82: =L82*K82-U82 -> 11.25714 | U82: =IF(ISNUMBER(K82),L82*K82*(O82-$D$262)/E,) -> -0.35714015 | Y82: =IF(ISNUMBER(K82),L82*K82,0) -> 10.9 | Z82: SCEG | AB82: =IF(B82<>0,B82,AB81) -> CAPOT | AC82: =IF(C82<>0,C82,AC81) -> Tôlerie capot | AD82: =IF(D82<>"",D82,"") | AE82: =CONCATENATE(AB82," / ",AC82," / ",AD82) -> CAPOT / Tôlerie capot / | AH82: Valeur usuelle, 5 à 9kg | AL82: value from previous vehicule with rato for scaling
C83: Equipement capot | F83: Equipment | K83: 1 | L83: 1.8 | O83: ='INPUT1 - Veh Geometry'!$H$127 -> -129 | P83: 0 | Q83: ='INPUT1 - Veh Geometry'!$J$127 -> 720 | R83: =$Q83 -> 720 | S83: =$Q83 -> 720 | T83: =L83*K83-U83 -> 1.8589773 | U83: =IF(ISNUMBER(K83),L83*K83*(O83-$D$262)/E,) -> -0.058977273 | Y83: =IF(ISNUMBER(K83),L83*K83,0) -> 1.8 | Z83: SCEG | AB83: =IF(B83<>0,B83,AB82) -> CAPOT | AC83: =IF(C83<>0,C83,AC82) -> Equipement capot | AD83: =IF(D83<>"",D83,"") | AE83: =CONCATENATE(AB83," / ",AC83," / ",AD83) -> CAPOT / Equipement capot / | AH83: Valeur moyenne 3kg (béquille, serrure, charnieres) | AL83: mean value, 3kg (hinges, lock, arm)
B84: CIELO / TO | F84: Cielo / Open Sunroof | L84: =K85*L85 -> 0 | O84: =IF($L84=0,"0",SUMPRODUCT($K85:$K85,$L85:$L85,O85:O85)/$L84) -> 0 | P84: =IF($L84=0,"0",SUMPRODUCT($K85:$K85,$L85:$L85,P85:P85)/$L84) -> 0 | Q84: =IF($L84=0,"0",SUMPRODUCT($K85:$K85,$L85:$L85,Q85:Q85)/$L84) -> 0 | R84: =IF($L84=0,"0",SUMPRODUCT($K85:$K85,$L85:$L85,R85:R85)/$L84) -> 0 | S84: =IF($L84=0,"0",SUMPRODUCT($K85:$K85,$L85:$L85,S85:S85)/$L84) -> 0 | T84: =SUM(T85:T85) -> 0 | U84: =SUMIF($K85:$K85,">0",$U85:$U85) -> 0 | Y84: =IF(ISNUMBER(K84),L84*K84,0) -> 0 | Z84: SCEG | AB84: =IF(B84<>0,B84,AB83) -> CIELO / TO | AC84: =IF(C84<>0,C84,AC83) -> Equipement capot | AD84: =IF(D84<>"",D84,"") | AE84: =CONCATENATE(AB84," / ",AC84," / ",AD84) -> CIELO / TO / Equipement capot /
C85: Cielo/TO | F85: Cielo / Open Sunroof | O85: =('INPUT1 - Veh Geometry'!$H$42+'INPUT1 - Veh Geometry'!$H$49)/2 -> 1732 | P85: 0 | Q85: ='INPUT1 - Veh Geometry'!$J$34-'INPUT1 - Veh Geometry'!$H$81/2+'INPUT1 - Veh Geometry'!$J$61-150 -> 1210.1 | R85: =$Q85 -> 1210.1 | S85: =$Q85 -> 1210.1 | T85: =L85*K85-U85 -> 0 | U85: =IF(ISNUMBER(K85),L85*K85*(O85-$D$262)/E,) -> 0 | Y85: =IF(ISNUMBER(K85),L85*K85,0) -> 0 | Z85: SCEG | AB85: =IF(B85<>0,B85,AB84) -> CIELO / TO | AC85: =IF(C85<>0,C85,AC84) -> Cielo/TO | AD85: =IF(D85<>"",D85,"") | AE85: =CONCATENATE(AB85," / ",AC85," / ",AD85) -> CIELO / TO / Cielo/TO / | AH85: Si présent, valeur moyenne 25kg TO et 10kg Cielo | AL85: if present, mean value 25kg for open sunroof and 10kg for a Cielo
B86: COLONNE de direction | F86: Direction | L86: =SUMPRODUCT(L87:L89,K87:K89) -> 4.7 | O86: =SUMPRODUCT($K87:$K89,$L87:$L89,O87:O89)/$L86 -> 577 | P86: =SUMPRODUCT($K87:$K89,$L87:$L89,P87:P89)/$L86 -> -326 | Q86: =SUMPRODUCT($K87:$K89,$L87:$L89,Q87:Q89)/$L86 -> 583 | R86: =SUMPRODUCT($K87:$K89,$L87:$L89,R87:R89)/$L86 -> 583 | S86: =SUMPRODUCT($K87:$K89,$L87:$L89,S87:S89)/$L86 -> 583 | T86: =SUM(T87:T89) -> 3.5971023 | U86: =SUMIF($K87:$K89,">0",$U87:$U89) -> 1.1028977 | Y86: =IF(ISNUMBER(K86),L86*K86,0) -> 0 | Z86: ICDV | AB86: =IF(B86<>0,B86,AB85) -> COLONNE de direction | AC86: =IF(C86<>0,C86,AC85) -> Cielo/TO | AD86: =IF(D86<>"",D86,"") | AE86: =CONCATENATE(AB86," / ",AC86," / ",AD86) -> COLONNE de direction / Cielo/TO /
C87: Colonne de direction | F87: Steering column | K87: 1 | L87: 4.7 | O87: ='INPUT1 - Veh Geometry'!$H$100 -> 577 | P87: ='INPUT1 - Veh Geometry'!$I$100 -> -326 | Q87: ='INPUT1 - Veh Geometry'!$J$100 -> 583 | R87: =$Q87 -> 583 | S87: =$Q87 -> 583 | T87: =L87*K87-U87 -> 3.5971023 | U87: =IF(ISNUMBER(K87),L87*K87*(O87-$D$262)/E,) -> 1.1028977 | Y87: =IF(ISNUMBER(K87),L87*K87,0) -> 4.7 | Z87: ICDV | AB87: =IF(B87<>0,B87,AB86) -> COLONNE de direction | AC87: =IF(C87<>0,C87,AC86) -> Colonne de direction | AD87: =IF(D87<>"",D87,"") | AE87: =CONCATENATE(AB87," / ",AC87," / ",AD87) -> COLONNE de direction / Colonne de direction / | AH87: valeur PF | AL87: value from chassis database
C88: Neman, joints, fixations | F88: Neman, fasteners | O88: ='INPUT1 - Veh Geometry'!$H$100 -> 577 | P88: ='INPUT1 - Veh Geometry'!$I$100 -> -326 | Q88: ='INPUT1 - Veh Geometry'!$J$100 -> 583 | R88: =$Q88 -> 583 | S88: =$Q88 -> 583 | T88: =L88*K88-U88 -> 0 | U88: =IF(ISNUMBER(K88),L88*K88*(O88-$D$262)/E,) -> 0 | Y88: =IF(ISNUMBER(K88),L88*K88,0) -> 0 | Z88: ICDV | AB88: =IF(B88<>0,B88,AB87) -> COLONNE de direction | AC88: =IF(C88<>0,C88,AC87) -> Neman, joints, fixations | AD88: =IF(D88<>"",D88,"") | AE88: =CONCATENATE(AB88," / ",AC88," / ",AD88) -> COLONNE de direction / Neman, joints, fixations / | AH88: valeur usuelle, 1,2kg | AL88: mean value, 1,2kg
C89: colonne avec motorisations | F89: Electric steering column | O89: ='INPUT1 - Veh Geometry'!$H$100 -> 577 | P89: ='INPUT1 - Veh Geometry'!$I$100 -> -326 | Q89: ='INPUT1 - Veh Geometry'!$J$100 -> 583 | R89: =$Q89 -> 583 | S89: =$Q89 -> 583 | T89: =L89*K89-U89 -> 0 | U89: =IF(ISNUMBER(K89),L89*K89*(O89-$D$262)/E,) -> 0 | Y89: =IF(ISNUMBER(K89),L89*K89,0) -> 0 | Z89: ICDV | AB89: =IF(B89<>0,B89,AB88) -> COLONNE de direction | AC89: =IF(C89<>0,C89,AC88) -> colonne avec motorisations | AD89: =IF(D89<>"",D89,"") | AE89: =CONCATENATE(AB89," / ",AC89," / ",AD89) -> COLONNE de direction / colonne avec motorisations /
B90: CONSOLE | F90: Console | L90: =SUMPRODUCT(K91:K92,L91:L92) -> 9.6 | O90: =SUMPRODUCT($K91:$K92,$L91:$L92,O91:O92)/$L90 -> 1004 | P90: =SUMPRODUCT($K91:$K92,$L91:$L92,P91:P92)/$L90 -> 0 | Q90: =SUMPRODUCT($K91:$K92,$L91:$L92,Q91:Q92)/$L90 -> 390.3 | R90: =SUMPRODUCT($K91:$K92,$L91:$L92,R91:R92)/$L90 -> 390.3 | S90: =SUMPRODUCT($K91:$K92,$L91:$L92,S91:S92)/$L90 -> 390.3 | T90: =SUM(T91:T92) -> 5.7945455 | U90: =SUMIF($K91:$K92,">0",$U91:$U92) -> 3.8054545 | Y90: =IF(ISNUMBER(K90),L90*K90,0) -> 0 | Z90: SPCS | AB90: =IF(B90<>0,B90,AB89) -> CONSOLE | AC90: =IF(C90<>0,C90,AC89) -> colonne avec motorisations | AD90: =IF(D90<>"",D90,"") | AE90: =CONCATENATE(AB90," / ",AC90," / ",AD90) -> CONSOLE / colonne avec motorisations /
C91: Console centrale | F91: Central console | K91: 1 | L91: 9.6 | O91: ='INPUT1 - Veh Geometry'!$H$42-'INPUT1 - Veh Geometry'!H33/8 -> 1004 | P91: 0 | Q91: ='INPUT1 - Veh Geometry'!$J$42 -> 390.3 | R91: =$Q91 -> 390.3 | S91: =$Q91 -> 390.3 | T91: =L91*K91-U91 -> 5.7945455 | U91: =IF(ISNUMBER(K91),L91*K91*(O91-$D$262)/E,) -> 3.8054545 | Y91: =IF(ISNUMBER(K91),L91*K91,0) -> 9.6 | Z91: SPCS | AB91: =IF(B91<>0,B91,AB90) -> CONSOLE | AC91: =IF(C91<>0,C91,AC90) -> Console centrale | AD91: =IF(D91<>"",D91,"") | AE91: =CONCATENATE(AB91," / ",AC91," / ",AD91) -> CONSOLE / Console centrale / | AH91: Valeur moyenne 3kg | AL91: mean value, 3kg
C92: Garnitures / rangements | F92: Garnish/storing devices | O92: ='INPUT1 - Veh Geometry'!$H$42-200 -> 1134 | P92: 0 | Q92: ='INPUT1 - Veh Geometry'!$J$42 -> 390.3 | R92: =$Q92 -> 390.3 | S92: =$Q92 -> 390.3 | T92: =L92*K92-U92 -> 0 | U92: =IF(ISNUMBER(K92),L92*K92*(O92-$D$262)/E,) -> 0 | Y92: =IF(ISNUMBER(K92),L92*K92,0) -> 0 | Z92: SPCS | AB92: =IF(B92<>0,B92,AB91) -> CONSOLE | AC92: =IF(C92<>0,C92,AC91) -> Garnitures / rangements | AD92: =IF(D92<>"",D92,"") | AE92: =CONCATENATE(AB92," / ",AC92," / ",AD92) -> CONSOLE / Garnitures / rangements / | AH92: Valeur moyenne 3kg | AL92: mean value, 3kg
B93: DAE | F93: Power Steering | L93: =SUMPRODUCT(K94:K95,L94:L95) -> 12.7 | O93: =SUMPRODUCT($K94:$K95,$L94:$L95,O94:O95)/$L93 -> 171 | P93: =SUMPRODUCT($K94:$K95,$L94:$L95,P94:P95)/$L93 -> -133 | Q93: =SUMPRODUCT($K94:$K95,$L94:$L95,Q94:Q95)/$L93 -> 78 | R93: =SUMPRODUCT($K94:$K95,$L94:$L95,R94:R95)/$L93 -> 78 | S93: =SUMPRODUCT($K94:$K95,$L94:$L95,S94:S95)/$L93 -> 78 | T93: =SUM(T94:T95) -> 11.672936 | U93: =SUMIF($K94:$K95,">0",$U94:$U95) -> 1.0270644 | Y93: =IF(ISNUMBER(K93),L93*K93,0) -> 0 | Z93: ICDV | AB93: =IF(B93<>0,B93,AB92) -> DAE | AC93: =IF(C93<>0,C93,AC92) -> Garnitures / rangements | AD93: =IF(D93<>"",D93,"") | AE93: =CONCATENATE(AB93," / ",AC93," / ",AD93) -> DAE / Garnitures / rangements /
C94: DAE | F94: Power Steering | K94: 1 | L94: 12.7 | O94: ='INPUT1 - Veh Geometry'!H$96 -> 171 | P94: ='INPUT1 - Veh Geometry'!I$96 -> -133 | Q94: ='INPUT1 - Veh Geometry'!J$96 -> 78 | R94: =$Q94 -> 78 | S94: =$Q94 -> 78 | T94: =L94*K94-U94 -> 11.672936 | U94: =IF(ISNUMBER(K94),L94*K94*(O94-$D$262)/E,) -> 1.0270644 | Y94: =IF(ISNUMBER(K94),L94*K94,0) -> 12.7 | Z94: ICDV | AB94: =IF(B94<>0,B94,AB93) -> DAE | AC94: =IF(C94<>0,C94,AC93) -> DAE | AD94: =IF(D94<>"",D94,"") | AE94: =CONCATENATE(AB94," / ",AC94," / ",AD94) -> DAE / DAE / | AH94: valeur PF | AL94: value from chassis database
C95: Fixations et protections | F95: fasteners / protections | O95: ='INPUT1 - Veh Geometry'!H$96 -> 171 | P95: ='INPUT1 - Veh Geometry'!I$96 -> -133 | Q95: ='INPUT1 - Veh Geometry'!J$96 -> 78 | R95: =$Q95 -> 78 | S95: =$Q95 -> 78 | T95: =L95*K95-U95 -> 0 | U95: =IF(ISNUMBER(K95),L95*K95*(O95-$D$262)/E,) -> 0 | Y95: =IF(ISNUMBER(K95),L95*K95,0) -> 0 | Z95: ICDV | AB95: =IF(B95<>0,B95,AB94) -> DAE | AC95: =IF(C95<>0,C95,AC94) -> Fixations et protections | AD95: =IF(D95<>"",D95,"") | AE95: =CONCATENATE(AB95," / ",AC95," / ",AD95) -> DAE / Fixations et protections / | AH95: Valeur usuelle 0,5kg; si écran thermique: +0,3kg | AL95: mean value 0,5kg; add 0,3kg in case of a thermal screen
B96: DEMARREUR | F96: Power Steering | L96: =SUMPRODUCT(K97:K98,L97:L98) -> 0 | O96: =IF($L96=0,"0",SUMPRODUCT($K97:$K98,$L97:$L98,O97:O98)/$L96) -> 0 | P96: =IF($L96=0,"0",SUMPRODUCT($K97:$K98,$L97:$L98,P97:P98)/$L96) -> 0 | Q96: =IF($L96=0,"0",SUMPRODUCT($K97:$K98,$L97:$L98,Q97:Q98)/$L96) -> 0 | R96: =IF($L96=0,"0",SUMPRODUCT($K97:$K98,$L97:$L98,R97:R98)/$L96) -> 0 | S96: =IF($L96=0,"0",SUMPRODUCT($K97:$K98,$L97:$L98,S97:S98)/$L96) -> 0 | T96: =SUM(T97:T98) -> 0 | U96: =SUMIF($K97:$K98,">0",$U97:$U98) -> 0 | Y96: =IF(ISNUMBER(K96),L96*K96,0) -> 0 | Z96: ICDV | AB96: =IF(B96<>0,B96,AB95) -> DEMARREUR | AC96: =IF(C96<>0,C96,AC95) -> Fixations et protections | AD96: =IF(D96<>"",D96,"") | AE96: =CONCATENATE(AB96," / ",AC96," / ",AD96) -> DEMARREUR / Fixations et protections /
C97: DEMARREUR | O97: ='INPUT1 - Veh Geometry'!$H$87 -> -241.5 | P97: ='INPUT1 - Veh Geometry'!$I$87 -> -48 | Q97: ='INPUT1 - Veh Geometry'!$J$87 -> 144.4 | R97: =$Q97 -> 144.4 | S97: =$Q97 -> 144.4 | T97: =L97*K97-U97 -> 0 | U97: =IF(ISNUMBER(K97),L97*K97*(O97-$D$262)/E,) -> 0 | Y97: =IF(ISNUMBER(K97),L97*K97,0) -> 0 | Z97: ICDV | AB97: =IF(B97<>0,B97,AB96) -> DEMARREUR | AC97: =IF(C97<>0,C97,AC96) -> DEMARREUR | AD97: =IF(D97<>"",D97,"") | AE97: =CONCATENATE(AB97," / ",AC97," / ",AD97) -> DEMARREUR / DEMARREUR / | AH97: valeur PF | AL97: value from chassis database
C98: PROTECTION DEMARREUR | O98: ='INPUT1 - Veh Geometry'!$H$87 -> -241.5 | P98: ='INPUT1 - Veh Geometry'!$I$87 -> -48 | Q98: ='INPUT1 - Veh Geometry'!$J$87 -> 144.4 | R98: =$Q98 -> 144.4 | S98: =$Q98 -> 144.4 | T98: =L98*K98-U98 -> 0 | U98: =IF(ISNUMBER(K98),L98*K98*(O98-$D$262)/E,) -> 0 | Y98: =IF(ISNUMBER(K98),L98*K98,0) -> 0 | Z98: ICDV | AB98: =IF(B98<>0,B98,AB97) -> DEMARREUR | AC98: =IF(C98<>0,C98,AC97) -> PROTECTION DEMARREUR | AD98: =IF(D98<>"",D98,"") | AE98: =CONCATENATE(AB98," / ",AC98," / ",AD98) -> DEMARREUR / PROTECTION DEMARREUR / | AH98: Valeur usuelle 0,5kg; si écran thermique: +0,3kg | AL98: mean value 0,5kg; add 0,3kg in case of a thermal screen
B99: DIVERS CAISSE | F99: outer trims | L99: =SUMPRODUCT(L100:L108,K100:K108) -> 10.8 | O99: =SUMPRODUCT($K100:$K108,$L100:$L108,O100:O108)/$L99 -> 867.13981 | P99: =SUMPRODUCT($K100:$K108,$L100:$L108,P100:P108)/$L99 -> -113.39815 | Q99: =SUMPRODUCT($K100:$K108,$L100:$L108,Q100:Q108)/$L99 -> 946.48333 | R99: =SUMPRODUCT($K100:$K108,$L100:$L108,R100:R108)/$L99 -> 946.48333 | S99: =SUMPRODUCT($K100:$K108,$L100:$L108,S100:S108)/$L99 -> 946.48333 | T99: =SUM(T100:T108) -> 7.0787462 | U99: =SUMIF($K100:$K108,">0",$U100:$U108) -> 3.7212538 | Y99: =IF(ISNUMBER(K99),L99*K99,0) -> 0 | Z99: SCEG | AB99: =IF(B99<>0,B99,AB98) -> DIVERS CAISSE | AC99: =IF(C99<>0,C99,AC98) -> PROTECTION DEMARREUR | AD99: =IF(D99<>"",D99,"") | AE99: =CONCATENATE(AB99," / ",AC99," / ",AD99) -> DIVERS CAISSE / PROTECTION DEMARREUR /
C100: AVERTISSEUR SONORE + bruiteur | F100: horn / pedestrian adviser | K100: 1 | L100: 1 | O100: ='INPUT1 - Veh Geometry'!$H$117 -> -495 | P100: ='INPUT1 - Veh Geometry'!$I$117 -> -574 | Q100: ='INPUT1 - Veh Geometry'!$J$117 -> 240 | R100: =$Q100 -> 240 | S100: =$Q100 -> 240 | T100: =L100*K100-U100 -> 1.1714015 | U100: =IF(ISNUMBER(K100),L100*K100*(O100-$D$262)/E,) -> -0.17140152 | Y100: =IF(ISNUMBER(K100),L100*K100,0) -> 1 | Z100: DSEE | AB100: =IF(B100<>0,B100,AB99) -> DIVERS CAISSE | AC100: =IF(C100<>0,C100,AC99) -> AVERTISSEUR SONORE + bruiteur | AD100: =IF(D100<>"",D100,"") | AE100: =CONCATENATE(AB100," / ",AC100," / ",AD100) -> DIVERS CAISSE / AVERTISSEUR SONORE + bruiteur / | AH100: Valeur moyenne 0,3kg pour klaxon, 1kg pour AVAS (avec support) | AL100: mean value 0,3kg for the horn; for ZEV: add the 'AVAS', 1kg including bracket
C101: Bas de caisse rapportés | F101: skid plates | O101: =('INPUT1 - Veh Geometry'!$H$61+'INPUT1 - Veh Geometry'!$H$72)/2 -> 1277.5 | P101: 0 | Q101: ='INPUT1 - Veh Geometry'!$J$42-200 -> 190.3 | R101: =$Q101 -> 190.3 | S101: =$Q101 -> 190.3 | T101: =L101*K101-U101 -> 0 | U101: =IF(ISNUMBER(K101),L101*K101*(O101-$D$262)/E,) -> 0 | Y101: =IF(ISNUMBER(K101),L101*K101,0) -> 0 | Z101: SCEG | AB101: =IF(B101<>0,B101,AB100) -> DIVERS CAISSE | AC101: =IF(C101<>0,C101,AC100) -> Bas de caisse rapportés | AD101: =IF(D101<>"",D101,"") | AE101: =CONCATENATE(AB101," / ",AC101," / ",AD101) -> DIVERS CAISSE / Bas de caisse rapportés / | AH101: si présents, valeur moyenne 5kg (bas de caisse + enjo d'aile) | AL101: if available, mean value 5kg
C102: Enjoliveur Sup côté de caisse | F102: Body upper trim | K102: 1 | L102: 5.1 | O102: ='INPUT1 - Veh Geometry'!H42 -> 1334 | P102: 0 | Q102: ='INPUT1 - Veh Geometry'!J34-('INPUT1 - Veh Geometry'!H81/2)+'INPUT1 - Veh Geometry'!J72-100 -> 1269.1 | R102: =$Q102 -> 1269.1 | S102: =$Q102 -> 1269.1 | T102: =L102*K102-U102 -> 2.4408523 | U102: =IF(ISNUMBER(K102),L102*K102*(O102-$D$262)/E,) -> 2.6591477 | Y102: =IF(ISNUMBER(K102),L102*K102,0) -> 5.1 | Z102: DSEE | AB102: =IF(B102<>0,B102,AB101) -> DIVERS CAISSE | AC102: =IF(C102<>0,C102,AC101) -> Enjoliveur Sup côté de caisse | AD102: =IF(D102<>"",D102,"") | AE102: =CONCATENATE(AB102," / ",AC102," / ",AD102) -> DIVERS CAISSE / Enjoliveur Sup côté de caisse / | AH102: Valeur moyenne 0,3kg pour klaxon, 1kg pour AVAS (avec support) | AL102: mean value 0,3kg for the horn; for ZEV: add the 'AVAS', 1kg including bracket
...

Sheet UNSPRUNG Mass estimation
B2: UNSPRUNG MASS ESTIMATION | L2: COMPARISON WITH A REFERENCE VEHICLE
I4: Estimated with figures from sheet 'Evaluations mass+CoG' | M4: Copy here the unsprung mass of a refrence vehicle | O4: If delta between Estimation versus Reference < 3% : Green
O5: If delta between Estimation versus Reference > 3% : Red
C7: ='INPUT1 - Veh Geometry'!H8 -> STLA-S | D7: Plaque de conception
C8: ='INPUT1 - Veh Geometry'!I8 -> J1X MHEV P2 FWD | D8: Finition | I8: ='INPUT1 - Veh Geometry'!J8 -> L2
D9: Sièges
D10: Hybridation
D11: Pack technique
D12: Spécificité technique
D13: Charge utile
D14: Roues
D15: Pôle
D16: Moteur
D17: Boite
C18: Màj du :
C19: Précédente diffusion :
C20: LES MASSES CI-DESSOUS NE SONT PAS DES VALEURS HOMOLOGUEES. POUR CES DERNIERES CONTACTER LE SERVICE HOMOLOGATION
E21: MASSE A VIDE
E22: EQUIPEMENTS OPTIONNELS
E25: MOTEUR NU
E26: HABILLAGE MOTEUR
E27: BOITE DE VITESSE (avec couplage)
E28: ADAPTATION (avec fluides)
C30: DETAIL MASSES NON SUSPENDUES (MNS) | H30: components mass without coefficient | I30: MNS with coefficient applied : | O30: Delta (%) between Estimation and Refrence
C31: Masses non suspendues AV | E31: Coeff | I31: =SUM(I32:I47) -> 109.94 | M31: 160 | O31: =IF(ISBLANK(M31),"/",1/M31*(I31-M31)) -> -0.312875
C32: FRN | D32: TRANSMISSION AV | E32: C61 | F32: 0.7 | I32: =H32*F32 -> 0 | O32: =IF(ISBLANK(M32),"/",1/M32*(I32-M32)) -> /
C33: FRN | D33: TRANSMISSION A JOINTS AV | E33: C71 | F33: 0.7 | H33: ='INPUT2 - Veh Sub-Syst Mass'!L233*'INPUT2 - Veh Sub-Syst Mass'!K233+'INPUT2 - Veh Sub-Syst Mass'!L234*'INPUT2 - Veh Sub-Syst Mass'!K234 -> 11.6 | I33: =H33*F33 -> 8.12 | M33: 11 | O33: =IF(ISBLANK(M33),"/",1/M33*(I33-M33)) -> -0.26181818
C34: FRN | D34: ELEMENTS COMMUNS 1C7 | E34: C7Z | F34: 0.7 | I34: =H34*F34 -> 0 | O34: =IF(ISBLANK(M34),"/",1/M34*(I34-M34)) -> /
C35: FRN | D35: MOYEU – ROULEMENT ROUE AV | E35: E13 | F35: 1 | H35: ='INPUT2 - Veh Sub-Syst Mass'!L204*'INPUT2 - Veh Sub-Syst Mass'!K204 -> 5.7 | I35: =H35*F35 -> 5.7 | O35: =IF(ISBLANK(M35),"/",1/M35*(I35-M35)) -> /
C36: FRN | D36: ROUE PRINCIPALE | E36: E31 | F36: 0.5 | H36: ='INPUT2 - Veh Sub-Syst Mass'!K189*'INPUT2 - Veh Sub-Syst Mass'!L189+'INPUT2 - Veh Sub-Syst Mass'!K188*'INPUT2 - Veh Sub-Syst Mass'!L188 -> 88.6 | I36: =H36*F36 -> 44.3 | O36: =IF(ISBLANK(M36),"/",1/M36*(I36-M36)) -> /
C37: FRN | D37: ENJOLIVEUR ROUE | E37: E33 | F37: 0.5 | I37: =H37*F37 -> 0 | O37: =IF(ISBLANK(M37),"/",1/M37*(I37-M37)) -> /
C38: FRN | D38: INDICATEUR PERTE PRESSION | E38: E34 | F38: 0.5 | I38: =H38*F38 -> 0 | O38: =IF(ISBLANK(M38),"/",1/M38*(I38-M38)) -> /
C39: FRN | D39: DISQUE – TAMBOUR AV | E39: F11 | F39: 1 | H39: ='INPUT2 - Veh Sub-Syst Mass'!L157*'INPUT2 - Veh Sub-Syst Mass'!K157 -> 15.8 | I39: =H39*F39 -> 15.8 | O39: =IF(ISBLANK(M39),"/",1/M39*(I39-M39)) -> /
C40: FRN | D40: ETRIER – PLATEAU AV (SANS CABLE) | E40: F21 | F40: 1 | H40: ='INPUT2 - Veh Sub-Syst Mass'!L158*'INPUT2 - Veh Sub-Syst Mass'!K158+'INPUT2 - Veh Sub-Syst Mass'!L159*'INPUT2 - Veh Sub-Syst Mass'!K159 -> 13.62 | I40: =H40*F40 -> 13.62 | O40: =IF(ISBLANK(M40),"/",1/M40*(I40-M40)) -> /
C41: HYD | D41: ELEMENT SUSPENSION AV HYDROPNEUMATIQUE | E41: E16 | F41: 0.7 | I41: =H41*F41 -> 0 | O41: =IF(ISBLANK(M41),"/",1/M41*(I41-M41)) -> /
C42: LAS | D42: BERCEAU – TRAVERSE TRAIN AV | E42: E11 | F42: 0 | H42: ='INPUT2 - Veh Sub-Syst Mass'!L200*'INPUT2 - Veh Sub-Syst Mass'!K200 -> 22.9 | I42: =H42*F42 -> 0 | O42: =IF(ISBLANK(M42),"/",1/M42*(I42-M42)) -> /
C43: LAS | D43: TRIANGLE BRAS ESSIEU RIGIDE | E43: E12 | F43: 0.4 | H43: ='INPUT2 - Veh Sub-Syst Mass'!L202*'INPUT2 - Veh Sub-Syst Mass'!K202 -> 8.1 | I43: =H43*F43 -> 3.24 | O43: =IF(ISBLANK(M43),"/",1/M43*(I43-M43)) -> /
C44: LAS | D44: ELEMENT SUSPENSION AV METALLIQUE | E44: E14 | F44: 0.8 | H44: ='INPUT2 - Veh Sub-Syst Mass'!L198*'INPUT2 - Veh Sub-Syst Mass'!K198 -> 22.7 | I44: =H44*F44 -> 18.16 | O44: =IF(ISBLANK(M44),"/",1/M44*(I44-M44)) -> /
C45: LAS | D45: ANTIDEVERS AV | E45: E15 | F45: 0.2 | H45: ='INPUT2 - Veh Sub-Syst Mass'!L203*'INPUT2 - Veh Sub-Syst Mass'!K203 -> 5 | I45: =H45*F45 -> 1 | O45: =IF(ISBLANK(M45),"/",1/M45*(I45-M45)) -> /
I46: =H46*F46 -> 0 | O46: =IF(ISBLANK(M46),"/",1/M46*(I46-M46)) -> /
I47: =H47*F47 -> 0 | O47: =IF(ISBLANK(M47),"/",1/M47*(I47-M47)) -> /
C49: Masses non suspendues AR | E49: Coeff | F49: TD | G49: MB | I49: =SUM(I50:I66) -> 101.344 | M49: 141 | O49: =IF(ISBLANK(M49),"/",1/M49*(I49-M49)) -> -0.28124823
C50: FRN | D50: TRANSMISSION AR ROUES INDEPENDANTES | E50: C62 | F50: 0.7 | G50: 0.7 | I50: =IF('INPUT1 - Veh Geometry'!$G$77="Twisted beam",'UNSPRUNG Mass estimation'!H50*'UNSPRUNG Mass estimation'!F50,'UNSPRUNG Mass estimation'!H50*'UNSPRUNG Mass estimation'!G50) -> 0 | O50: =IF(ISBLANK(M50),"/",1/M50*(I50-M50)) -> /
C51: FRN | D51: TRANSMISSION AR TRAIN RIGIDE | E51: C63 | F51: 1 | G51: 1 | I51: =IF('INPUT1 - Veh Geometry'!$G$77="Twisted beam",'UNSPRUNG Mass estimation'!H51*'UNSPRUNG Mass estimation'!F51,'UNSPRUNG Mass estimation'!H51*'UNSPRUNG Mass estimation'!G51) -> 0 | O51: =IF(ISBLANK(M51),"/",1/M51*(I51-M51)) -> /
C52: FRN | D52: TRANSMISSION A JOINTS AR | E52: C73 | F52: 0.7 | G52: 0.7 | H52: ='INPUT2 - Veh Sub-Syst Mass'!L238*'INPUT2 - Veh Sub-Syst Mass'!K238+'INPUT2 - Veh Sub-Syst Mass'!L239*'INPUT2 - Veh Sub-Syst Mass'!K239 -> 0.2 | I52: =IF('INPUT1 - Veh Geometry'!$G$77="Twisted beam",'UNSPRUNG Mass estimation'!H52*'UNSPRUNG Mass estimation'!F52,'UNSPRUNG Mass estimation'!H52*'UNSPRUNG Mass estimation'!G52) -> 0.14 | O52: =IF(ISBLANK(M52),"/",1/M52*(I52-M52)) -> /
C53: FRN | D53: MOYEU – ROULEMENT ROUE AR | E53: E24 | F53: 1 | G53: 1 | H53: ='INPUT2 - Veh Sub-Syst Mass'!L196*'INPUT2 - Veh Sub-Syst Mass'!K196 -> 7.6 | I53: =IF('INPUT1 - Veh Geometry'!$G$77="Twisted beam",'UNSPRUNG Mass estimation'!H53*'UNSPRUNG Mass estimation'!F53,'UNSPRUNG Mass estimation'!H53*'UNSPRUNG Mass estimation'!G53) -> 7.6 | O53: =IF(ISBLANK(M53),"/",1/M53*(I53-M53)) -> /
C54: FRN | D54: ROUE PRINCIPALE | E54: E31 | F54: 0.5 | G54: 0.5 | H54: ='INPUT2 - Veh Sub-Syst Mass'!L187 -> 88.6 | I54: =IF('INPUT1 - Veh Geometry'!$G$77="Twisted beam",'UNSPRUNG Mass estimation'!H54*'UNSPRUNG Mass estimation'!F54,'UNSPRUNG Mass estimation'!H54*'UNSPRUNG Mass estimation'!G54) -> 44.3 | O54: =IF(ISBLANK(M54),"/",1/M54*(I54-M54)) -> /
C55: FRN | D55: ENJOLIVEUR ROUE | E55: E33 | F55: 0.5 | G55: 0.5 | I55: =IF('INPUT1 - Veh Geometry'!$G$77="Twisted beam",'UNSPRUNG Mass estimation'!H55*'UNSPRUNG Mass estimation'!F55,'UNSPRUNG Mass estimation'!H55*'UNSPRUNG Mass estimation'!G55) -> 0 | O55: =IF(ISBLANK(M55),"/",1/M55*(I55-M55)) -> /
C56: FRN | D56: INDICATEUR PERTE PRESSION | E56: E34 | F56: 0.5 | G56: 0.5 | I56: =IF('INPUT1 - Veh Geometry'!$G$77="Twisted beam",'UNSPRUNG Mass estimation'!H56*'UNSPRUNG Mass estimation'!F56,'UNSPRUNG Mass estimation'!H56*'UNSPRUNG Mass estimation'!G56) -> 0 | O56: =IF(ISBLANK(M56),"/",1/M56*(I56-M56)) -> /
C57: FRN | D57: DISQUE – TAMBOUR AR | E57: F31 | F57: 1 | G57: 1 | H57: ='INPUT2 - Veh Sub-Syst Mass'!L153*'INPUT2 - Veh Sub-Syst Mass'!K153 -> 24.206 | I57: =IF('INPUT1 - Veh Geometry'!$G$77="Twisted beam",'UNSPRUNG Mass estimation'!H57*'UNSPRUNG Mass estimation'!F57,'UNSPRUNG Mass estimation'!H57*'UNSPRUNG Mass estimation'!G57) -> 24.206 | O57: =IF(ISBLANK(M57),"/",1/M57*(I57-M57)) -> /
C58: FRN | D58: ETRIER – PLATEAU AR (SANS CABLE) | E58: F41 | F58: 1 | G58: 1 | H58: ='INPUT2 - Veh Sub-Syst Mass'!L154*'INPUT2 - Veh Sub-Syst Mass'!K154+'INPUT2 - Veh Sub-Syst Mass'!L155*'INPUT2 - Veh Sub-Syst Mass'!K155 -> 0 | I58: =IF('INPUT1 - Veh Geometry'!$G$77="Twisted beam",'UNSPRUNG Mass estimation'!H58*'UNSPRUNG Mass estimation'!F58,'UNSPRUNG Mass estimation'!H58*'UNSPRUNG Mass estimation'!G58) -> 0 | O58: =IF(ISBLANK(M58),"/",1/M58*(I58-M58)) -> /
C59: HYD | D59: ELEMENT SUSPENSION AR HYDROPNEUMATIQUE | E59: E28 | F59: 0.35 | G59: 0.35 | I59: =IF('INPUT1 - Veh Geometry'!$G$77="Twisted beam",'UNSPRUNG Mass estimation'!H59*'UNSPRUNG Mass estimation'!F59,'UNSPRUNG Mass estimation'!H59*'UNSPRUNG Mass estimation'!G59) -> 0 | O59: =IF(ISBLANK(M59),"/",1/M59*(I59-M59)) -> /
C60: LAS | D60: BERCEAU – TRAVERSE TRAIN AR | E60: E21 | F60: 0.64 | G60: 0 | H60: ='INPUT2 - Veh Sub-Syst Mass'!L193*'INPUT2 - Veh Sub-Syst Mass'!K193 -> 30.7 | I60: =IF('INPUT1 - Veh Geometry'!$G$77="Twisted beam",'UNSPRUNG Mass estimation'!H60*'UNSPRUNG Mass estimation'!F60,'UNSPRUNG Mass estimation'!H60*'UNSPRUNG Mass estimation'!G60) -> 19.648 | O60: =IF(ISBLANK(M60),"/",1/M60*(I60-M60)) -> /
C61: LAS | D61: BRAS SUSPENSION AR – ENS. BRAS – FUSEE | E61: E22 | F61: 0.55 | G61: 0.55 | H61: ='INPUT2 - Veh Sub-Syst Mass'!L194*'INPUT2 - Veh Sub-Syst Mass'!K194 -> 0 | I61: =IF('INPUT1 - Veh Geometry'!$G$77="Twisted beam",'UNSPRUNG Mass estimation'!H61*'UNSPRUNG Mass estimation'!F61,'UNSPRUNG Mass estimation'!H61*'UNSPRUNG Mass estimation'!G61) -> 0 | O61: =IF(ISBLANK(M61),"/",1/M61*(I61-M61)) -> /
C62: LAS | D62: ESSIEU RIGIDE – GUIDAGE | E62: E23 | F62: 0.5 | G62: 0.5 | I62: =IF('INPUT1 - Veh Geometry'!$G$77="Twisted beam",'UNSPRUNG Mass estimation'!H62*'UNSPRUNG Mass estimation'!F62,'UNSPRUNG Mass estimation'!H62*'UNSPRUNG Mass estimation'!G62) -> 0 | O62: =IF(ISBLANK(M62),"/",1/M62*(I62-M62)) -> /
C63: LAS | D63: ELEMENT SUSPENSION AR METALLIQUE | E63: E25 | F63: 0.5 | G63: 0.75 | H63: ='INPUT2 - Veh Sub-Syst Mass'!L191*'INPUT2 - Veh Sub-Syst Mass'!K191 -> 10.9 | I63: =IF('INPUT1 - Veh Geometry'!$G$77="Twisted beam",'UNSPRUNG Mass estimation'!H63*'UNSPRUNG Mass estimation'!F63,'UNSPRUNG Mass estimation'!H63*'UNSPRUNG Mass estimation'!G63) -> 5.45 | O63: =IF(ISBLANK(M63),"/",1/M63*(I63-M63)) -> /
C64: LAS | D64: ANTIDEVERS AR | E64: E26 | F64: 0.2 | G64: 0.2 | H64: ='INPUT2 - Veh Sub-Syst Mass'!L195*'INPUT2 - Veh Sub-Syst Mass'!K195 -> 0 | I64: =IF('INPUT1 - Veh Geometry'!$G$77="Twisted beam",'UNSPRUNG Mass estimation'!H64*'UNSPRUNG Mass estimation'!F64,'UNSPRUNG Mass estimation'!H64*'UNSPRUNG Mass estimation'!G64) -> 0 | O64: =IF(ISBLANK(M64),"/",1/M64*(I64-M64)) -> /
I65: =IF('INPUT1 - Veh Geometry'!$G$77="Twisted beam",'UNSPRUNG Mass estimation'!H65*'UNSPRUNG Mass estimation'!F65,'UNSPRUNG Mass estimation'!H65*'UNSPRUNG Mass estimation'!G65) -> 0 | O65: =IF(ISBLANK(M65),"/",1/M65*(I65-M65)) -> /
I66: =IF('INPUT1 - Veh Geometry'!$G$77="Twisted beam",'UNSPRUNG Mass estimation'!H66*'UNSPRUNG Mass estimation'!F66,'UNSPRUNG Mass estimation'!H66*'UNSPRUNG Mass estimation'!G66) -> 0 | O66: =IF(ISBLANK(M66),"/",1/M66*(I66-M66)) -> /

Sheet OUTPUT - Mass & CoG
D2: PROGRAM : | E2: ='INPUT1 - Veh Geometry'!H8 -> STLA-S | H2: PROJECT : | I2: ='INPUT1 - Veh Geometry'!I8 -> J1X MHEV P2 FWD | L2: MODEL : | O2: ='INPUT1 - Veh Geometry'!J8 -> L2
B4: Mass & CoG Synthesis :
C6: A) CURB WEIGHT LOAD CASE
H8: MASS : | L8: COG POSITION
O9: Wheels at 'REF load case' position | Q9: Wheels at 'CURB load case' position
D10: Curb weight : | H10: Total Veh | I10: Front | J10: Rear | L10: X | M10: Y | O10: Z / veh referential | Q10: Z / veh referential | S10: Z / ground
D11: Masses Suspendues / Sprung mass : | H11: ='INPUT2 - Veh Sub-Syst Mass'!D276 -> 1245.005 | I11: ='INPUT2 - Veh Sub-Syst Mass'!F276 -> 774.56829 | J11: ='INPUT2 - Veh Sub-Syst Mass'!H276 -> 470.43671 | L11: ='INPUT2 - Veh Sub-Syst Mass'!O276 -> 955.04854 | M11: ='INPUT2 - Veh Sub-Syst Mass'!Q276 -> -25.234291 | O11: ='INPUT2 - Veh Sub-Syst Mass'!S276 -> 289.2012 | Q11: =+'INPUT2 - Veh Sub-Syst Mass'!T276 -> 289.14878
D13: Masses Non Suspendues / Unsprung mass : | F13: Front axle | H13: ='INPUT2 - Veh Sub-Syst Mass'!D268 -> 109.94 | I13: ='INPUT2 - Veh Sub-Syst Mass'!F268 -> 110.55152 | J13: ='INPUT2 - Veh Sub-Syst Mass'!H268 -> -0.61151515 | L13: ='INPUT2 - Veh Sub-Syst Mass'!O268 -> -57.184373 | M13: ='INPUT2 - Veh Sub-Syst Mass'!Q268 -> 0 | O13: ='INPUT2 - Veh Sub-Syst Mass'!S268 -> 110.34131 | Q13: ='INPUT2 - Veh Sub-Syst Mass'!T268 -> 92.163398
F14: Rear axle | H14: ='INPUT2 - Veh Sub-Syst Mass'!D269 -> 101.344 | I14: ='INPUT2 - Veh Sub-Syst Mass'!F269 -> -3.0636837 | J14: ='INPUT2 - Veh Sub-Syst Mass'!H269 -> 104.40768 | L14: ='INPUT2 - Veh Sub-Syst Mass'!O269 -> 2677.3086 | M14: ='INPUT2 - Veh Sub-Syst Mass'!Q269 -> 0 | O14: ='INPUT2 - Veh Sub-Syst Mass'!S269 -> 78.236442 | Q14: ='INPUT2 - Veh Sub-Syst Mass'!T269 -> 38.051246
F15: Total | H15: =H13+H14 -> 211.284 | I15: =I13+I14 -> 107.48783 | J15: =J13+J14 -> 103.79617 | L15: =($H13*L13+$H14*L14)/$H15 -> 1254.4363 | M15: =($H13*M13+$H14*M14)/$H15 -> 0 | O15: =($H13*O13+$H14*O14)/$H15 -> 94.941964 | Q15: =($H13*Q13+$H14*Q14)/$H15 -> 66.208087
D17: Total Veh / Sprung + Unsprung : | H17: =H11+H13+H14 -> 1456.289 | I17: =I11+I13+I14 -> 882.05612 | J17: =J11+J13+J14 -> 574.23288 | L17: ='INPUT2 - Veh Sub-Syst Mass'!O274 -> 998.48486 | M17: ='INPUT2 - Veh Sub-Syst Mass'!Q274 -> -21.573203 | O17: ='INPUT2 - Veh Sub-Syst Mass'!S274 -> 261.01732 | Q17: =SUMPRODUCT(H11:H14,Q11:Q14)/SUM(H11:H14) -> 256.80369 | S17: =Q17-H26+((L17-'INPUT1 - Veh Geometry'!H61)/'INPUT1 - Veh Geometry'!H33)*(H26-I26) -> 558.6615
H19: Ft repartition : | I19: =I17/H17 -> 0.60568755
D21: Output for 'Lot A' :
H23: Front (ZA1) | I23: Rear (ZA2)
D24: Position centre Roue - ZA theo (Curb mass load case) | H24: ='INPUT1 - Veh Geometry'!J61-'INPUT1 - Veh Geometry'!J62+'INPUT1 - Veh Geometry'!J63 -> 45 | I24: ='INPUT1 - Veh Geometry'!J72-'INPUT1 - Veh Geometry'!J73+'INPUT1 - Veh Geometry'!J74 -> 25
D25: Rayon du pneu sous charge (Curb mass load case) | H25: ='INPUT1 - Veh Geometry'!H83+6 -> 339 | I25: ='INPUT1 - Veh Geometry'!I83+6 -> 343
D26: Z sol dans rep véh. (Curb mass load case) | H26: ='INPUT1 - Veh Geometry'!J63 -> -292 | I26: ='INPUT1 - Veh Geometry'!J74 -> -317
C30: B) GROSS VEHICLE WEIGHT LOAD CASE
H32: MASS : | L32: COG POSITION
O33: Wheels at 'REF load case' position | Q33: Related to GVW load case ground
D34: GVW : | H34: Total Veh | I34: Front | J34: Rear | L34: X | M34: Y | O34: Z / veh referential | Q34: Z / veh referential | S34: Z / ground
D35: Masses Suspendues / Sprung mass : | H35: ='INPUT2 - Veh Sub-Syst Mass'!D276+SUM('INPUT2 - Veh Sub-Syst Mass'!D279:D283) -> 1716.009 | I35: ='INPUT2 - Veh Sub-Syst Mass'!F276+SUM('INPUT2 - Veh Sub-Syst Mass'!F279:F283) -> 885.20715 | J35: ='INPUT2 - Veh Sub-Syst Mass'!H276+SUM('INPUT2 - Veh Sub-Syst Mass'!H279:H283) -> 830.80185 | L35: =($H41*L41-$H37*L37-$H38*L38)/$H35 -> 1235.65 | M35: =($H41*M41-$H37*M37-$H38*M38)/$H35 -> -18.308073 | O35: =($H41*O41-$H37*O37-$H38*O38)/$H35 -> 317.67196 | Q35: =($H41*Q41-$H37*Q37-$H38*Q38)/$H35 -> 317.66719
D37: Masses Non Suspendues / Unsprung mass : | F37: Front axle | H37: =H13 -> 109.94 | I37: =I13 -> 110.55152 | J37: =J13 -> -0.61151515 | L37: =L13 -> -57.184373 | M37: =M13 -> 0 | O37: =O13 -> 110.34131 | Q37: ='INPUT2 - Veh Sub-Syst Mass'!U268 -> 113.64639
F38: Rear axle | H38: =H14 -> 101.344 | I38: =I14 -> -3.0636837 | J38: =J14 -> 104.40768 | L38: =L14 -> 2677.3086 | M38: =M14 -> 0 | O38: =O14 -> 78.236442 | Q38: ='INPUT2 - Veh Sub-Syst Mass'!U269 -> 102.66274
F39: Total | H39: =H37+H38 -> 211.284 | I39: =I37+I38 -> 107.48783 | J39: =J37+J38 -> 103.79617 | L39: =($H37*L37+$H38*L38)/$H39 -> 1254.4363 | M39: =($H37*M37+$H38*M38)/$H39 -> 0 | O39: =($H37*O37+$H38*O38)/$H39 -> 94.941964 | Q39: =($H37*Q37+$H38*Q38)/$H39 -> 108.378
D41: Total Veh / Sprung + Unsprung : | H41: ='INPUT2 - Veh Sub-Syst Mass'!D284 -> 1927.293 | I41: ='INPUT2 - Veh Sub-Syst Mass'!F284 -> 992.69498 | J41: ='INPUT2 - Veh Sub-Syst Mass'!H284 -> 934.59802 | L41: ='INPUT2 - Veh Sub-Syst Mass'!O284 -> 1237.7095 | M41: ='INPUT2 - Veh Sub-Syst Mass'!Q284 -> -16.301008 | O41: ='INPUT2 - Veh Sub-Syst Mass'!S284 -> 293.25466 | Q41: ='INPUT2 - Veh Sub-Syst Mass'!U284 -> 294.72338 | S41: =Q41-H45+((L41-'INPUT1 - Veh Geometry'!H61)/'INPUT1 - Veh Geometry'!H33)*(H45-I45) -> 545.69061
H43: Ft repartition : | I43: =I41/H41 -> 0.51507217
D45: Z sol dans rep véh. (GVW load case) | H45: ='INPUT1 - Veh Geometry'!J64 -> -266 | I45: ='INPUT1 - Veh Geometry'!J75 -> -235
C49: C) 1P5L LOAD CASE
H51: MASS : | L51: COG POSITION
O52: Wheels at 'REF load case' position | Q52: Wheels at 'CURB load case' position
D53: 1P5L : | H53: Total Veh | I53: Front | J53: Rear | L53: X | M53: Y | O53: Z / veh referential | Q53: Z / veh referential | S53: Z / ground
D54: Curb mass (total vehicle) : | H54: =H17 -> 1456.289 | I54: =I17 -> 882.05612 | J54: =J17 -> 574.23288 | L54: =L17 -> 998.48486 | M54: =M17 -> -21.573203 | O54: =O17 -> 261.01732 | Q54: =Q17 -> 256.80369
D55: - 1 passenger | H55: ='INPUT1 - Veh Geometry'!G15 -> 75 | I55: =H55-J55 -> 35.894886 | J55: =H55*(L55-'INPUT1 - Veh Geometry'!$H$61)/'INPUT1 - Veh Geometry'!$H$33 -> 39.105114 | L55: ='INPUT1 - Veh Geometry'!H42 -> 1334 | M55: ='INPUT1 - Veh Geometry'!I42 -> -355 | O55: ='INPUT1 - Veh Geometry'!J42 -> 390.3 | Q55: =O55 -> 390.3
D56: - 5 liter of fuel only | H56: =-('INPUT2 - Veh Sub-Syst Mass'!L28-5*0.75) -> 3.75 | I56: =H56-J56 -> 0.90553977 | J56: =H56*(L56-'INPUT1 - Veh Geometry'!$H$61)/'INPUT1 - Veh Geometry'!$H$33 -> 2.8444602 | L56: ='INPUT1 - Veh Geometry'!H56 -> 1960 | M56: ='INPUT1 - Veh Geometry'!I56 -> 38 | O56: ='INPUT1 - Veh Geometry'!J56 -> 33 | Q56: =O56 -> 33
D58: Total Veh (1P5L) : | H58: =H54+H55+H56 -> 1535.039 | I58: =I54+I55+I56 -> 918.85655 | J58: =J54+J55+J56 -> 616.18245 | L58: =($H54*L54+$H55*L55+$H56*L56)/$H58 -> 1017.2266 | M58: =($H54*M54+$H55*M55+$H56*M56)/$H58 -> -37.718467 | O58: =($H54*O54+$H55*O55+$H56*O56)/$H58 -> 266.77687 | Q58: =($H54*Q54+$H55*Q55+$H56*Q56)/$H58 -> 262.77941
H60: Ft repartition : | I60: =I58/H58 -> 0.5985884
B67: Bilan par périmètre (estimé, pour info) / Assesment per perimeter, for information
D69: Top Hat : | H69: SOEE | I69: =SUMIF('INPUT2 - Veh Sub-Syst Mass'!$Z$6:$Z$252,"SOEE",'INPUT2 - Veh Sub-Syst Mass'!$Y$6:$Y$252) -> 220.362
H70: SCEG | I70: =SUMIF('INPUT2 - Veh Sub-Syst Mass'!$Z$6:$Z$252,"SCEG",'INPUT2 - Veh Sub-Syst Mass'!$Y$6:$Y$252) -> 398.501
H71: SCEG-sil | I71: =SUMIF('INPUT2 - Veh Sub-Syst Mass'!$Z$6:$Z$252,"SCEG-sil",'INPUT2 - Veh Sub-Syst Mass'!$Y$6:$Y$252) -> 0
H72: SPCS | I72: =SUMIF('INPUT2 - Veh Sub-Syst Mass'!$Z$6:$Z$252,"SPCS",'INPUT2 - Veh Sub-Syst Mass'!$Y$6:$Y$252) -> 105.8
H73: ICDV-Wheels | I73: =SUMIF('INPUT2 - Veh Sub-Syst Mass'!$Z$6:$Z$252,"ICDV-roue",'INPUT2 - Veh Sub-Syst Mass'!$Y$6:$Y$252) -> 88.6
H74: DSEE-sil | I74: =SUMIF('INPUT2 - Veh Sub-Syst Mass'!$Z$6:$Z$252,"DSEE-sil",'INPUT2 - Veh Sub-Syst Mass'!$Y$6:$Y$252) -> 0
H75: DSEE | I75: =SUMIF('INPUT2 - Veh Sub-Syst Mass'!$Z$6:$Z$252,"DSEE",'INPUT2 - Veh Sub-Syst Mass'!$Y$6:$Y$252) -> 54.6
H76: Sub-total : | I76: =SUM(I69:I75) -> 867.863
D78: Platform : | H78: SCEG-Base | I78: =SUMIF('INPUT2 - Veh Sub-Syst Mass'!$Z$6:$Z$252,"SCEG-base",'INPUT2 - Veh Sub-Syst Mass'!$Y$6:$Y$252) -> 0
H79: DCTC | I79: =SUMIF('INPUT2 - Veh Sub-Syst Mass'!$Z$6:$Z$252,"DCTC",'INPUT2 - Veh Sub-Syst Mass'!$Y$6:$Y$252) -> 251.9
H80: ICDV | I80: =SUMIF('INPUT2 - Veh Sub-Syst Mass'!$Z$6:$Z$252,"ICDV",'INPUT2 - Veh Sub-Syst Mass'!$Y$6:$Y$252) -> 194.526
H81: ADTH | I81: =SUMIF('INPUT2 - Veh Sub-Syst Mass'!$Z$6:$Z$252,"ADTH",'INPUT2 - Veh Sub-Syst Mass'!$Y$6:$Y$252) -> 30.4
H82: CMAG | I82: =SUMIF('INPUT2 - Veh Sub-Syst Mass'!$Z$6:$Z$252,"CMAG",'INPUT2 - Veh Sub-Syst Mass'!$Y$6:$Y$252) -> 111.6
H83: DSEE-Batt | I83: =SUMIF('INPUT2 - Veh Sub-Syst Mass'!$Z$6:$Z$252,"DSEE-Batt",'INPUT2 - Veh Sub-Syst Mass'!$Y$6:$Y$252) -> 0
H84: SCEG-Batt | I84: =SUMIF('INPUT2 - Veh Sub-Syst Mass'!$Z$6:$Z$252,"SCEG-Batt",'INPUT2 - Veh Sub-Syst Mass'!$Y$6:$Y$252) -> 0
H86: Sub-total : | I86: =SUM(I78:I85) -> 588.426
H88: ??? Or Empty | I88: =SUMIF('INPUT2 - Veh Sub-Syst Mass'!$Z$6:$Z$252,"???",'INPUT2 - Veh Sub-Syst Mass'!$Y$6:$Y$252)+SUMIF('INPUT2 - Veh Sub-Syst Mass'!$Z$6:$Z$252,"",'INPUT2 - Veh Sub-Syst Mass'!$Y$6:$Y$252) -> 0
H89: Total : | I89: =I76+I86+I88 -> 1456.289
B94: Rappel INPUTS, for information :
D96: Rappel inputs :
D97: - Opt : | F97: ='INPUT1 - Veh Geometry'!G13 -> 56.004
D98: - Passenger : | F98: ='INPUT1 - Veh Geometry'!G14 -> 5
D99: - EMC : | F99: ='INPUT1 - Veh Geometry'!G21 -> 40
D100: ='INPUT1 - Veh Geometry'!C61 -> - CdR Av Réf / FWC (ref) | F100: ='INPUT1 - Veh Geometry'!J61 -> 67
D101: ='INPUT1 - Veh Geometry'!C72 -> - CdR Ar Réf / RWC (ref) | F101: ='INPUT1 - Veh Geometry'!J72 -> 76
D107: X cdg total X Massse Totale = Xcdg unspung AV X Masse Unsprung AV + Xcdg unspung AR X Masse Unsprung AR + Xcdg Sprung X Masse Sprung | E107: X cdg total X Massse Totale = Xcdg unspung AV X Masse Unsprung AV + Xcdg unspung AR X Masse Unsprung AR + Xcdg Sprung X Masse Sprung
D109: Xcdg Sprung = (X cdg total X Massse Totale - Xcdg unspung AV X Masse Unsprung AV - Xcdg unspung AR X Masse Unsprung AR) / Masse Srung | E109: Xcdg Sprung = (X cdg total X Massse Totale - Xcdg unspung AV X Masse Unsprung AV - Xcdg unspung AR X Masse Unsprung AR) / Masse Srung

Sheet Vide

Sheet DEC5 <--> A2MAC1 Dictionary
A2: IMPORTANT : Last update of DEC5 <--> A2MAC1 Dictionary is stored into document : 00987_22_00053
A4: Lot | B4: Pièce | C4: Découpage | D4: Check | E4: Lot + Dec | F4: Niv 1 | G4: Niv 2
A5: --- | B5: AFFECTATION LOT/DECOUPAGE NON PREVUE | C5: 0_Total | E5: --- 0_Total
A6: ABA | B6: CONDITIONNEMENT | C6: 83G | D6: ok | E6: ABA 83G | F6: NON AFFECTE
A7: ABA | B7: PIECES VEHICULE REPETITIVES (OU A CARACTERE REPETITIF) | C7: 73R | D7: ok | E7: ABA 73R | F7: BV | G7: BVA
A8: ABA | B8: CONVERTISSEUR | C8: C12 | D8: ok | E8: ABA C12 | F8: BV | G8: BVA
A9: ABA | B9: COUPLEUR | C9: C13 | D9: ok | E9: ABA C13 | F9: BV | G9: BVA
A10: ABA | B10: BOITE VITESSES AUTOMATIQUE | C10: C24 | D10: ok | E10: ABA C24 | F10: BV | G10: BVA
A11: ABA | B11: PILOTAGE ELECTRONIQUE TRANSMISSION AUTOMATIQUE | C11: C26 | D11: ok | E11: ABA C26 | F11: BV | G11: BVA
A12: ABA | B12: CARTER BOITE VITESSES AUTOMATIQUE | C12: C27 | D12: ok | E12: ABA C27 | F12: BV | G12: BVA
A13: ABA | B13: VARIATEUR TRANSMISSION CONTINU | C13: C28 | D13: ok | E13: ABA C28 | F13: BV | G13: BVA
A14: ABA | B14: EQUIPEMENT ELECTRIQUE BOITE VITESSES | C14: C29 | D14: ok | E14: ABA C29 | F14: BV | G14: BVA
A15: ABA | B15: MARQUAGE TRANSMISSION | C15: C91 | D15: ok | E15: ABA C91 | F15: BV | G15: BVA
A16: ABA | B16: MONTAGE BOITE VITESSES AUTOMATIQUE | C16: CZC | D16: ok | E16: ABA CZC | F16: BV | G16: BVA
A17: ABA | B17: NON REPARTI | C17: NR- | D17: ok | E17: ABA NR- | F17: BV | G17: BVA
A18: AEE | B18: COMPOSANTS FAISCEAUX | C18: 73F | D18: ok | E18: AEE 73F | F18: NON AFFECTE
A19: AEE | C19: 0_Total
A20: AEE | B20: CONDITIONNEMENT | C20: 83G | D20: ok | E20: AEE 83G | F20: NON AFFECTE
A21: AEE | B21: STG ARCHITECTURE ELECTRICITE ELECTRONIQUE | C21: 98B | D21: ok | E21: AEE 98B | F21: NON AFFECTE
A22: AEE | B22: PIECES VEHICULE REPETITIVES (OU A CARACTERE REPETITIF) | C22: 73R | D22: ok | E22: AEE 73R | F22: FAISCEAUX | G22: Faisceau
A23: AEE | B23: ALLUMAGE | C23: A33 | D23: ok | E23: AEE A33 | F23: GMP
A24: AEE | B24: EQUIPEMENT DIESEL | C24: A34 | D24: ok | E24: AEE A34 | F24: GMP
A25: AEE | B25: BOITIER PILOTAGE ELECTRONIQUE MULTIFONCTIONNEL (MECANIQUE) | C25: A36 | D25: ok | E25: AEE A36 | F25: GMP
A26: AEE | B26: PILOTAGE ELECTRONIQUE TRANSMISSION AUTOMATIQUE | C26: C26 | D26: ok | E26: AEE C26 | F26: DIVERS EE
A27: AEE | B27: NON REPARTI | C27: NR- | D27: ok | E27: AEE NR- | F27: DIVERS EE
A28: AEE | B28: EQUIPEMENT ELECTRIQUE ASSISE AV | C28: Y1L | D28: ok | E28: AEE Y1L | F28: ASSISES | G28: ASSISE AV
A29: AEE | B29: EQUIPEMENT ELECTRIQUE ASSISE AR | C29: Y2K | D29: ok | E29: AEE Y2K | F29: ASSISES | G29: ASSISE AR RG2
A30: AEE | B30: FIXATION – REFROIDISSEMENT BATTERIE | C30: Z1B | D30: ok | E30: AEE Z1B | F30: BATTERIE
A31: AEE | B31: ELEMENTS COMMUNS 3Z1 | C31: Z1Z | E31: AEE Z1Z | F31: NON AFFECTE
A32: AEE | B32: SUPPORT BATTERIE (SI AMOVIBLE) | C32: Z1C | D32: ok | E32: AEE Z1C | F32: BATTERIE
A33: AEE | B33: EQUIPEMENT ELECTRIQUE PROTECTION – DERIVATION | C33: Z5U | D33: ok | E33: AEE Z5U | F33: DIVERS EE | G33: Système porte fusibles/relais
A34: AEE | B34: CABLAGE BATTERIE SERVITUDE – TRACTION | C34: Z9A | D34: ok | E34: AEE Z9A | F34: FAISCEAUX | G34: Câblage de puissance
A35: AEE | B35: RANGEMENT ELECTRICITE – ELECTRONIQUE (BOITE, SUPPORT) | C35: Z9F | D35: ok | E35: AEE Z9F | F35: DIVERS EE
A36: AEE | B36: ELEMENT CONNEXION ET RELAIS MULTIFONCTIONNEL | C36: Z9G | D36: ok | E36: AEE Z9G | F36: DIVERS EE
A37: AEE | B37: FAISCEAU MOTEUR | C37: Z9J | D37: ok | E37: AEE Z9J | F37: FAISCEAUX | G37: Faisceau
A38: AEE | B38: FAISCEAU EQUIPEMENT MECANIQUE – MOTEUR | C38: Z9K | D38: ok | E38: AEE Z9K | F38: FAISCEAUX | G38: Faisceau
A39: AEE | B39: FAISCEAU PRINCIPAL | C39: Z9L | D39: ok | E39: AEE Z9L | F39: FAISCEAUX | G39: Faisceau
A40: AEE | B40: FAISCEAU FACADE AV | C40: Z9M | D40: ok | E40: AEE Z9M | F40: FAISCEAUX | G40: Faisceau
A41: AEE | B41: FAISCEAU PLANCHE BORD | C41: Z9N | D41: ok | E41: AEE Z9N | F41: FAISCEAUX | G41: Faisceau
A42: AEE | B42: FAISCEAU ACCES AR | C42: Z9P | D42: ok | E42: AEE Z9P | F42: FAISCEAUX | G42: Faisceau
A43: AEE | B43: FAISCEAU PORTE | C43: Z9R | D43: ok | E43: AEE Z9R | F43: FAISCEAUX | G43: Faisceau
A44: AEE | B44: FAISCEAU HABITACLE | C44: Z9S | D44: ok | E44: AEE Z9S | F44: FAISCEAUX | G44: Faisceau
A45: AEE | B45: ELEMENTS COMMUNS 3Z9 | C45: Z9Z | D45: ok | E45: AEE Z9Z | F45: NON AFFECTE
A46: AEE | B46: FAISCEAU COMPLEMENTAIRE HABITACLE | C46: Z9T | D46: ok | E46: AEE Z9T | F46: FAISCEAUX | G46: Faisceau
A47: AEE | B47: FIXATION CABLAGE BATTERIE SERVITUDE – TRACTION | C47: ZAA | D47: ok | E47: AEE ZAA | F47: FAISCEAUX | G47: Systeme support faisceaux
A48: AEE | B48: FIXATION FAISCEAU MOTEUR | C48: ZAJ | D48: ok | E48: AEE ZAJ | F48: FAISCEAUX | G48: Systeme support faisceaux
A49: AEE | B49: FIXATION FAISCEAU EQUIPEMENT MECANIQUE – MOTEUR | C49: ZAK | D49: ok | E49: AEE ZAK | F49: FAISCEAUX | G49: Systeme support faisceaux
A50: AEE | B50: FIXATION FAISCEAU PRINCIPAL | C50: ZAL | D50: ok | E50: AEE ZAL | F50: FAISCEAUX | G50: Systeme support faisceaux
A51: AEE | B51: FIXATION FAISCEAU FACADE AV | C51: ZAM | D51: ok | E51: AEE ZAM | F51: FAISCEAUX | G51: Systeme support faisceaux
A52: AEE | B52: FIXATION FAISCEAU PLANCHE BORD | C52: ZAN | D52: ok | E52: AEE ZAN | F52: FAISCEAUX | G52: Systeme support faisceaux
A53: AEE | B53: FIXATION FAISCEAU ACCES AR | C53: ZAP | D53: ok | E53: AEE ZAP | F53: FAISCEAUX | G53: Systeme support faisceaux
A54: AEE | B54: FIXATION FAISCEAU PORTE | C54: ZAR | D54: ok | E54: AEE ZAR | F54: FAISCEAUX | G54: Systeme support faisceaux
A55: AEE | B55: FIXATION FAISCEAU HABITACLE | C55: ZAS | D55: ok | E55: AEE ZAS | F55: FAISCEAUX | G55: Systeme support faisceaux
A56: AEE | B56: ELEMENTS COMMUNS 3ZA | C56: ZAZ | D56: ok | E56: AEE ZAZ | F56: NON AFFECTE
A57: AEE | B57: FIXATION FAISCEAU COMPLEMENTAIRE HABITACLE | C57: ZAT | D57: ok | E57: AEE ZAT | F57: FAISCEAUX | G57: Systeme support faisceaux
A58: AEE | B58: SCHEMA PRINCIPE ELECTRIQUE MOTEUR | C58: ZBA | E58: AEE ZBA | F58: NON AFFECTE
A59: AEE | B59: SCHEMA PRINCIPE ELECTRIQUE MECANIQUE | C59: ZBB | E59: AEE ZBB | F59: NON AFFECTE
A60: AEE | B60: SCHEMA PRINCIPE ELECTRIQUE CARROSSERIE | C60: ZBC | E60: AEE ZBC | F60: NON AFFECTE
A61: AEE | B61: SCHEMA PRINCIPE ELECTRIQUE ENSEMBLE VEHICULE | C61: ZBD | E61: AEE ZBD | F61: NON AFFECTE
A62: AEE | B62: MULTIPLEXAGE – RESEAUX INTERSYSTEMES | C62: ZBE | E62: AEE ZBE | F62: NON AFFECTE
A63: AEE | B63: MULTIPLEXAGE – RESEAUX CONFORT | C63: ZBF | E63: AEE ZBF | F63: NON AFFECTE
A64: AEE | B64: MULTIPLEXAGE – RESEAUX CARROSSERIE | C64: ZBG | E64: AEE ZBG | F64: NON AFFECTE
A65: AEE | B65: ELEMENTS COMMUNS 3ZB | C65: ZBZ | E65: AEE ZBZ | F65: NON AFFECTE
A66: AEE | B66: MULTIPLEXAGE - RESEAUX LIN BSI | C66: ZBJ | E66: AEE ZBJ | F66: NON AFFECTE
A67: AEE | B67: MONTAGE – FINITION | C67: ZZA | E67: AEE ZZA | F67: NON AFFECTE
A68: AMO | C68: 0_Total | E68: AMO 0_Total
A69: AMO | B69: CONDITIONNEMENT | C69: 83G | E69: AMO 83G | F69: NON AFFECTE
A70: AMO | B70: PIECES VEHICULE REPETITIVES (OU A CARACTERE REPETITIF) | C70: 73R | E70: AMO 73R | F70: ADAPTATION
A71: AMO | B71: ALIMENTATION CARBURANT | C71: A25 | D71: ok | E71: AMO A25 | F71: ADAPTATION | G71: RESERVOIR CARBURANT
A72: AMO | B72: ALIMENTATION AIR | C72: A26 | D72: ok | E72: AMO A26 | F72: ADAPTATION | G72: CIRCUIT AIR
A73: AMO | B73: BOITIER PILOTAGE ELECTRONIQUE MULTIFONCTIONNEL (MECANIQUE) | C73: A36 | E73: AMO A36 | F73: GMP
A74: AMO | B74: CAPTEUR PILOTAGE ELECTRONIQUE | C74: A37 | E74: AMO A37 | F74: GMP
A75: AMO | B75: ACTIONNEUR – PILOTAGE DEPOLLUTION | C75: A39 | E75: AMO A39 | F75: GMP
A76: AMO | B76: VENTILATEUR – BUSE | C76: B11 | D76: ok | E76: AMO B11 | F76: ADAPTATION | G76: CIRCUIT EAU
A77: AMO | B77: RADIATEUR EAU – CIRCUIT PRECHAUFFAGE | C77: B12 | D77: ok | E77: AMO B12 | F77: ADAPTATION | G77: CIRCUIT EAU
A78: AMO | B78: ECHANGEUR HUILE MOTEUR – CIRCUIT PRECHAUFFAGE | C78: B13 | D78: ok | E78: AMO B13 | F78: ADAPTATION | G78: CIRCUIT EAU
A79: AMO | B79: ELEMENTS COMMUNS 1B1 | C79: B1Z | D79: ok | E79: AMO B1Z | F79: NON AFFECTE
A80: AMO | B80: EQUIPEMENT ELECTRIQUE ECHANGE THERMIQUE | C80: B14 | D80: ok | E80: AMO B14 | F80: ADAPTATION | G80: CIRCUIT EAU
A81: AMO | B81: LIGNE ECHAPPEMENT – CATALYSEUR | C81: B21 | D81: ok | E81: AMO B21 | F81: ADAPTATION | G81: ECHAPPEMENT
A82: AMO | B82: DISPOSITIF PILOTAGE ECHAPPEMENT | C82: B23 | D82: ok | E82: AMO B23 | F82: ADAPTATION | G82: ECHAPPEMENT
A83: AMO | B83: PILOTAGE - CONTROLE RECUPERATEUR THERMIQUE ECHAPPEMENT | C83: B24 | D83: ok | E83: AMO B24 | F83: ADAPTATION | G83: ECHAPPEMENT
A84: AMO | B84: DISPOSITIF DEPOLLUTION ECHAPPEMENT | C84: B25 | D84: ok | E84: AMO B25 | F84: ADAPTATION | G84: ADDBLUE
A85: AMO | B85: RESERVOIR – REMPLISSAGE | C85: B31 | D85: ok | E85: AMO B31 | F85: ADAPTATION | G85: RESERVOIR CARBURANT
A86: AMO | B86: CANALISATION CARBURANT | C86: B32 | D86: ok | E86: AMO B32 | F86: ADAPTATION | G86: RESERVOIR CARBURANT
A87: AMO | B87: EQUIPEMENT ELECTRIQUE RESERVOIR CARBURANT | C87: B33 | D87: ok | E87: AMO B33 | F87: ADAPTATION | G87: RESERVOIR CARBURANT
A88: AMO | B88: ABSORPTION VAPEURS CARBURANT | C88: B34 | D88: ok | E88: AMO B34 | F88: ADAPTATION | G88: RESERVOIR CARBURANT
A89: AMO | B89: ELEMENTS COMMUNS 1B3 | C89: B3Z | D89: ok | E89: AMO B3Z | F89: NON AFFECTE
A90: AMO | B90: RESERVOIR – REMPLISSAGE BICARBURATION | C90: B35 | D90: ok | E90: AMO B35 | F90: ADAPTATION | G90: RESERVOIR CARBURANT
A91: AMO | B91: RESERVOIR ADDITIF – REMPLISSAGE | C91: B41 | D91: ok | E91: AMO B41 | F91: ADAPTATION | G91: RESERVOIR ADDITIF
A92: AMO | B92: CANALISATION ADDITIF | C92: B42 | D92: ok | E92: AMO B42 | F92: ADAPTATION | G92: RESERVOIR ADDITIF
A93: AMO | B93: ELEMENTS COMMUNS 1B4 | C93: B4Z | D93: ok | E93: AMO B4Z | F93: NON AFFECTE
A94: AMO | B94: EQUIPEMENT ELECTRIQUE RESERVOIR ADDITIF | C94: B43 | D94: ok | E94: AMO B43 | F94: ADAPTATION | G94: RESERVOIR ADDITIF
A95: AMO | B95: MARQUAGE ELEMENTS LIES AU MOTEUR | C95: B91 | E95: AMO B91 | F95: NON AFFECTE
A96: AMO | B96: ASSEMBLAGE – PREPARATION CONDITIONNEMENT | C96: BZA | E96: AMO BZA | F96: NON AFFECTE
A97: AMO | B97: PILOTAGE SUSPENSION GMP | C97: D12 | E97: AMO D12 | F97: ADAPTATION | G97: SUPPORT GMP
A98: AMO | B98: SUPPORT – PEDALES – COIFFES | C98: G11 | E98: AMO G11 | F98: ADAPTATION | G98: PEDALIER
A99: AMO | B99: LIAISON SYSTEME ALIMENTATION | C99: G41 | E99: AMO G41 | F99: ADAPTATION
A100: AMO | B100: ELEMENTS COMMUNS 1G4 | C100: G4Z | E100: AMO G4Z | F100: NON AFFECTE
A101: AMO | B101: INTERRUPTEUR COMMANDE MISE EN ACTION – ACCELERATION | C101: G44 | E101: AMO G44 | F101: ADAPTATION
A102: AMO | B102: NON REPARTI | C102: NR- | D102: ok | E102: AMO NR- | F102: NON AFFECTE
...

Sheet A2MAC1 MICV Std bookmark
B2: -1 | C2: ADAPTATION
B3: -1 | C3: =D3 -> ADDBLUE | D3: ADDBLUE
B4: -1 | C4: =D4 -> CARBURANT | D4: CARBURANT
B5: -1 | C5: =D5 -> CIRCUIT AIR | D5: CIRCUIT AIR
B6: -1 | C6: =D6 -> CIRCUIT EAU | D6: CIRCUIT EAU
B7: -1 | C7: =D7 -> COMMANDE VITESSE | D7: COMMANDE VITESSE
B8: -1 | C8: =D8 -> ECHAPPEMENT | D8: ECHAPPEMENT
B9: -1 | C9: =D9 -> ECRANS THERMIQUE | D9: ECRANS THERMIQUE
B10: -1 | C10: =D10 -> FACADE | D10: FACADE
B11: -1 | C11: =D11 -> LIQUIDE ADDITIF | D11: LIQUIDE ADDITIF
B12: -1 | C12: =D12 -> LIQUIDE REFROIDISSEMENT | D12: LIQUIDE REFROIDISSEMENT
B13: -1 | C13: =D13 -> PEDALIER | D13: PEDALIER
B14: -1 | C14: =D14 -> RESERVOIR ADDITIF | D14: RESERVOIR ADDITIF
... B17: 3123 | C17: =D17 -> Système de refroidissement par huile | D17: Système de refroidissement par huile
B18: -1 | C18: ADTH
B19: -1 | C19: =D19 -> DIVERS ADTH | D19: DIVERS ADTH
B20: -1 | C20: =D20 -> GROUP CLIM | D20: GROUP CLIM
B21: -1 | C21: =D21 -> COMPRESSEUR CLIM | D21: COMPRESSEUR CLIM
B22: -1 | C22: =D22 -> GROUPE ADDITIONNEL | D22: GROUPE ADDITIONNEL
B23: -1 | C23: AILES
B24: 13885 | C24: =D24 -> Ailes avant | D24: Ailes avant
B25: 14859 | C25: =D25 -> Ailes arrière | D25: Ailes arrière
B26: 2432 | C26: =D26 -> Avant gauche (ancien process) | D26: Avant gauche (ancien process)
B27: 2431 | C27: =D27 -> Avant droite (ancien process) | D27: Avant droite (ancien process)
B28: -1 | C28: ALTERNATEUR
B29: 6208 | C29: =D29 -> Système alternateur | D29: Système alternateur
B30: -1 | C30: ASSISES
B31: -1 | C31: =D31 -> ASSISE AR RG2 | D31: ASSISE AR RG2
B32: -1 | C32: =D32 -> ASSISE AR RG3 | D32: ASSISE AR RG3
B33: -1 | C33: =D33 -> ASSISE AV | D33: ASSISE AV
B34: 9573 | C34: =D34 -> Fixations ISOFIX | D34: Fixations ISOFIX
B35: -1 | C35: ATTELAGE
B36: 5541 | C36: =D36 -> Système crochet d attelage / Porte vélo | D36: Système crochet d attelage / Porte vélo
B37: -1 | C37: BATTERIE
B38: 2131 | C38: =D38 -> Système batterie 12V | D38: Système batterie 12V
B39: -1 | C39: BATTERIE TRACTION
B40: 11460 | C40: =D40 -> Système batterie traction | D40: Système batterie traction
B41: 30155 | C41: =D41 -> Système module de charge HT | D41: Système module de charge HT
B42: 18975 | C42: =D42 -> Durite de ventilation module charge HT | D42: Durite de ventilation module charge HT
B43: 30029 | C43: =D43 -> Calculateur gestion batterie HT | D43: Calculateur gestion batterie HT
B44: 26718 | C44: =D44 -> Second support module charge HT | D44: Second support module charge HT
B45: 31711 | C45: =D45 -> Support calculateur gestion batterie HT | D45: Support calculateur gestion batterie HT
B46: 31712 | C46: =D46 -> Deuxiéme support calculateur gestion batterie HT | D46: Deuxiéme support calculateur gestion batterie HT
B47: -1 | C47: BOUCLIER AR
B48: 93 | C48: =D48 -> Arrière | D48: Arrière
B49: -1 | C49: BOUCLIER AV
B50: 92 | C50: =D50 -> Avant | D50: Avant
B51: 5732 | C51: =D51 -> Calandre | D51: Calandre
B52: -1 | C52: BV
B53: -1 | C53: =D53 -> 4x4 | D53: 4x4
B54: -1 | C54: =D54 -> BVA | D54: BVA
B55: -1 | C55: =D55 -> BVM | D55: BVM
B56: -1 | C56: =D56 -> COUPLAGE | D56: COUPLAGE
B57: -1 | C57: =D57 -> HUILE BOITE | D57: HUILE BOITE
B58: -1 | C58: =D58 -> REDUCTEUR AR | D58: REDUCTEUR AR
B59: -1 | C59: =D59 -> REDUCTEUR AV | D59: REDUCTEUR AV
B60: -1 | C60: CAISSE EN BLANC
B61: 6830 | C61: =D61 -> Renfort de caisse | D61: Renfort de caisse
B62: 1375 | C62: =D62 -> Tablier coté conducteur / unique | D62: Tablier coté conducteur / unique
B63: 13167 | C63: =D63 -> Tablier coté passager | D63: Tablier coté passager
B64: 5665 | C64: =D64 -> Bac de rangement arrière 1 | D64: Bac de rangement arrière 1
B65: 2523 | C65: =D65 -> Caisse en blanc (avec peinture) | D65: Caisse en blanc (avec peinture)
B66: -1 | C66: CAPOT
B67: -1 | C67: =D67 -> EQUIPEMENT CAPOT | D67: EQUIPEMENT CAPOT
B68: -1 | C68: =D68 -> TOLERIE CAPOT | D68: TOLERIE CAPOT
B69: -1 | C69: CIELO / TO
B70: 4151 | C70: =D70 -> Système toit ouvrant | D70: Système toit ouvrant
B71: 7726 | C71: =D71 -> Toit panoramique | D71: Toit panoramique
B72: 34257 | C72: =D72 -> Vitre de toit | D72: Vitre de toit
B73: -1 | C73: COLONNE
B74: 128 | C74: =D74 -> Colonne de direction | D74: Colonne de direction
B75: -1 | C75: CONSOLE
B76: 3097 | C76: =D76 -> Garnitures latérales | D76: Garnitures latérales
B77: 3760 | C77: =D77 -> Partie supérieure | D77: Partie supérieure
B78: 12320 | C78: =D78 -> Console centrale | D78: Console centrale
B79: 2991 | C79: =D79 -> Garniture arrière 1 | D79: Garniture arrière 1
B80: 1371 | C80: =D80 -> Supports | D80: Supports
B81: 1758 | C81: =D81 -> Instrumentation | D81: Instrumentation
B82: 1757 | C82: =D82 -> Cendrier | D82: Cendrier
B83: 12540 | C83: =D83 -> Rangement avant | D83: Rangement avant
B84: 12536 | C84: =D84 -> Rangement central | D84: Rangement central
B85: 2588 | C85: =D85 -> Rangement arrière (accoudoir) | D85: Rangement arrière (accoudoir)
B86: 12004 | C86: =D86 -> Rangement rang 2 | D86: Rangement rang 2
B87: 12317 | C87: =D87 -> Garniture avant | D87: Garniture avant
... B140: 39240 | C140: =D140 -> Eclairage factice | D140: Eclairage factice
B141: -1 | C141: DAE
B142: 4976 | C142: =D142 -> Système barre de direction | D142: Système barre de direction
B143: 2470 | C143: =D143 -> Réservoir de liquide de direction assistée | D143: Réservoir de liquide de direction assistée
B144: 873 | C144: =D144 -> Conduit de retour assistance | D144: Conduit de retour assistance
B145: 872 | C145: =D145 -> Conduit de pression assistance | D145: Conduit de pression assistance
B146: 2499 | C146: =D146 -> Système groupe électro-pompe | D146: Système groupe électro-pompe
B147: 1268 | C147: =D147 -> Système assistance électrique | D147: Système assistance électrique
B148: 2730 | C148: =D148 -> Pompe de direction assistée | D148: Pompe de direction assistée
B149: 6345 | C149: =D149 -> Système radiateur | D149: Système radiateur
B150: 11423 | C150: =D150 -> Support de faisceau | D150: Support de faisceau
B151: 9270 | C151: =D151 -> Conduit d alimentation | D151: Conduit d alimentation
B152: 12560 | C152: =D152 -> Cache trou conduite inversée | D152: Cache trou conduite inversée
B153: 5329 | C153: =D153 -> Liquide de direction assistée | D153: Liquide de direction assistée
B154: -1 | C154: DEMARREUR
B155: 77 | C155: =D155 -> Démarreur | D155: Démarreur
...

Sheet V2.0 update follow-up
B3: Outil de référence WGHT : Outil_eval_CdG_V1.0.xlsx (00987_19_00164)
B4: Problème à traiter : | C4: Qui a rencontré / Quand : | D4: Action de progrès : | E4: Pilote / Quand : | F4: Avancement :
A5: 1 | B5: Problème : Importantes variations de x/z cdg (de l’ordre de 20mm en Z) entre les estimations AVP au JAP, les remontages RdfnU, puis TKO sur les silhouettes P64 (Bev principalement). | C5: Grégory / Yvan / Thierry | D5: Quoi : Robustifier les hypothèses de positionnement des masses des sous-système : | E5: Gilles / août-22 | F5: 10/08/2022 : - Revue globale de l'outil réalisée (correction erreurs formules, réaffectation de sous-systèmes, adaptation des facteurs de positionnement des Cdg). - Test réalisé pour un P64 BEV AWD Level3 à partir du fichier de remontage numérique MCI_SS_ENS_P64_TKO_BEV_AWD_LEVEL3_V3.xlsm (docinfo : 00987_22_00103). --> Résultats obtenus : - MAV : 2262,3kg (2263,2mm au remontage num) - X CdG : 1238mm (1221mm au remontage num) --> Attention Cdg à 1330mm dans Cas deCahrge P64. - Y Cdg : -3,5mm (-3,7mm au remontagenum ) - Z cdg : 246,7mm (245,6mm dau remontage num)
B6: Causes identifiées : | D6: Comment :
B7: 1) Trop d’écarts entre le véhicule à estimer (P64 Bev) et le véhicule de référence (P84 ICE). Manque de retex/connaissance pour correctement estimer les briques du cascading en AVP. | D7: - Tester l’outil avec un P64 BEV AWD à Injecter les valeurs du 1/5ième + DEC5 + positions issues des remontages numériques TKO.
B8: 2) Les hypothèses utilisées par l’outil (positionnement par lot) ne sont pas nécessairement ‘juste’. | D8: - Analyser les écarts et corriger les positionnements des CDG
D9: - Compléter la liste des inputs si nécessaire.
A10: 2 | B10: Problème : Le contenu de chaque découpage utilisé dans l’outil n’est pas toujours explicite et trivial à interpréter à Risque d’erreur d’interprétation. | C10: Grégory / Yvan / Thierry | D10: Quoi : Clarifier le contenu de chaque sous-système A2MAC1 utilisé dans l’outils AVP. | E10: Gilles / août-22 | F10: 12/08/2022 : - Copie du dictionnaire DEC5 <--> A2MAC1 intégré dans l'outil. Avec rappel lien vers version officielle. - Reste à faire : 1) Reprendre la table de l'onglet 'INPUTS 2' afin qu'elle soit strictement identique au Bookmark MICV A2MAC1. --> Voir nécessité. 2) Ajouter liste des DEC5 en face de chaque sous-système.
D11: Comment :
D12: - Mettre à disposition dans l’outil la table d’équivalence construite pour l’outil Benchmark à Clairement notifier le lien vers la table de référence à jour dans l’outil Bench.
D13: - Etudier faisabilité / Utilité de lister les codes découpage xPSA en face de chaque ligne de l’onglet ‘Evaluation’
A14: 3 | B14: Problème : Il est nécessaire re remplir manuellement toutes les masses des sous-systèmes lorsque le veh de réf n’a pas été démonté par A2MAC1. | D14: Quoi : Permettre d’injecter directement dans l’onglet Evaluation les masses converties d’un DEC5 vers un découpage A2MAC1. | E14: Olivier + Laurent
D15: Comment : | E15: 44805
D16: - Compléter la matrice d’équivalence DEC5 à A2MAC1 pour intégrer les niveaux 3 et 4 (quand nécessaire).
D17: - Gérer dans l’outil Bench deux tableaux de sortie DEC5 à A2MAC1 (1 avec les niveaux 1 et 2, l’autre avec les niveaux 1 à 4).
A18: 4 | B18: Problème : Le calcul des MNS est ‘caché’, nécessite de rigoureusement détailler les masses des sous-systèmes. | D18: Quoi : Mettre en évidence les inputs utilisées pour calculer les MNS et visualiser les écarts avec le véhicule de référence. | E18: Gilles / août-22 | F18: 10/08/2022 : - Traité. - Intégré dans fichier version docinfo à partir de v2.0.
B19: Problèmes : Le contrôle de la justesse des MNS sorties par l’outil n’est pas ‘instantané’. | D19: Comment : - Remettre en forme et rendre visible le calcul des MNS.
D20: - Reprendre le formalisme d’un DEC5.
D21: - Afficher une comparaison des MNS estimées avec celles du véhicule de ref (format DEC5).
A22: 5 | B22: Problème : Les données relatives aux moteurs (masses et cdg) référencées dans l’onglet ‘Input Data’ ne sont pas nécessairement à jour et leur prise en compte (position) reste macro. | D22: Quoi : Assurer l’utilisation de données ‘moteur’ à jour. Assurer une correcte répartition dans le véhicule. | E22: Gilles Sept-Oct-22 | F22: 12/08/2022 : - Reste à faire = Mettre à jour les CdG des différentes motorisations à partir de la BDD : 00987_15_00582 21/11/2022 : - Mise à jour à partir de la BDD moteur effectuée.
D23: Comment :
D24: - Mise à jour des inputs et des formules de prise en compte.
D25: - Intégration plus précise des différents motorisations électriques.
A26: 6 | B26: Problème : L’estimation du Zcdg par rapport au sol doit être consommée avec précaution car elle fait appel à des données d’entrée non nécessairement vérifiées. | D26: Quoi : Mettre en place un warning sur les données d’entrée du Zcdg (centre d eroue…). | E26: Gilles Sept-Oct-22 | F26: 12/08/2022 : - Changement de la méthode d'estimation du CdG par rapport au sol --> Utilisation de la position des MNS recalée pour chaque sol.
A28: 7 | B28: Problème : L’outil ne génère que des estimations en masse à vide. | D28: Quoi : Intégrer des estimations en MTAC. | E28: Gilles / Nov-22 | F28: 12/08/2022 : - Modification du fichier afin d'estimer la position du CdG en configuration MTAC. - Méthode utilisée = repositionnement de chaque masse non suspendue à partir de l'écart entre le sol de REF et le sol MTAC (calculté en calculant la raideur des suspensions à partir des positions des sols MAV et REF du 1/5ième).
D29: Comment :
D30: - Ajouter une prise en compte des options, passager et EMC.
