Workbook
Name PROBABILITE: '[4]tri eco'!$M$2:$M$8
Name PROBABILITE: '[4]tri eco'!$M$2:$M$8
Name PROBABILITE: '[4]tri eco'!$M$2:$M$8
Name PROBABILITE: '[4]tri eco'!$M$2:$M$8
Name PROBABILITE: 'tri eco'!$M$2:$M$8

Sheet Lien 
B4: SP1 portefolio | C4: http://docinfogroupe.inetpsa.com/ead/doc/ref.00987_24_00014/v.vc/fiche

Sheet Portefeuille SP2
D1: BCI_BODY | E1: TH | Q1: IN PROGRESS | S1: 0
D2: BCI_DOORS | E2: PTF | Q2: DECIDED | S2: 0.25
D3: BCI_FRSD | E3: PRS | Q3: CANCELED | S3: 0.5
D4: BCI_EMC | Q4: IN STATUS | S4: 0.75
D5: BCI_SEATS/TRIMS | S5: 1
D6: BCI_PDB/CONSOLE
D7: BCI_DOORS_INT
D8: BCI_CHASSIS
D9: SWX_EHE
D10: PRS_PHES
D11: PRS_PPM
D12: PRS_EDM
D13: PRS_BATT
A14: Topic Nr | B14: Creation Date | C14: Responsible | D14: Functions | E14: BVH / PWT / Tophat | F14: RESp | G14: Désignation : Ensemble / Piéces FR | H14: Désignation : Ensemble / Piéces ENG | I14: Description | J14: Comments BCI SPC_1 | K14: Date | L14: Mass comments (changes, dates, …) | M14: Invest impact | N14: TPC Impact (€) | O14: Next steps | P14: Decision expected for ? | Q14: COTATION (*) | R14: Priorization | S14: Confidence % | T14: Mass kg (*) | U14: Ponderated mass / Ratio (kg*%) | V14: O3H HR 63 FWD€ | W14: O3H XR 80 FWD€ | X14: O3H XR 80 AWD perfo € | Y14: O3H MHEV FWD€ | Z14: O3H HEV FWD€ | AA14: O3W 63 kWhu LFP FWD€ | AB14: O3W 80 kWhu NMx FWD€ | AC14: O3W MHEV FWD€ | AD14: O3W HEV FWD€ | AE14: P3S HR 63 FWD€ | AF14: P3S XR 80 FWD€ | AG14: P3S XR 80 AWD perfo € | AH14: P3S MHEV FWD€ | AI14: P3S HEV FWD€ | AJ14: P3W 63 kWhu LFP FWD€ | AK14: P3W 80 kWhu NMx FWD€ | AL14: P3W MHEV FWD€ | AM14: P3W HEV FWD€ | AN14: P3U HR 63 FWD€ | AO14: P3U XR 80 FWD€ | AP14: P3U XR 80 AWD perfo € | AQ14: P3U MHEV FWD€ | AR14: P3U HEV FWD€ | AS14: J1X SR FWD€ | AT14: J1X MHEV FWD€ | AU14: J1X MHEV AWD€ | AV14: J1X HEV FWD€ | AW14: J2U HR 63 FWD€ | AX14: J2U XR 80 FWD€ | AY14: J2U MHEV FWD | AZ14: J2U HEV FWD | BA14: J2U HEV AWD
B15: 45632 | C15: SPC_1 | D15: BIW | E15: TH | F15: MICHAEL BORE | G15: activ spoiler | H15: activ spoiler | J15: 06/10/2025 sujet à supprimer car pas d'active Spoiler sur le projet SPC_1 | P15: o | Q15: CANCELED | R15: TBD | S15: 0.8 | T15: 4 | U15: =T15*S15 -> 3.2 | V15: 1 | W15: 1 | X15: 1 | Y15: 1 | Z15: 1 | AA15: 1 | AB15: 1 | AC15: 1 | AD15: 1 | AE15: 1 | AF15: 1 | AG15: 1 | AH15: 1 | AI15: 1 | AJ15: 1 | AK15: 1 | AL15: 1 | AM15: 1 | AN15: 1 | AO15: 1 | AP15: 1 | AQ15: 1 | AR15: 1 | AS15: 1 | AV15: 1 | AW15: 1 | AX15: 1 | AY15: 1 | AZ15: 1 | BA15: 1
A16: 301a | B16: 20/06/2025 | C16: SP1 | D16: FRSD | E16: TH | F16: Sébastien Bonnefoi (P1H)/ Jean Michel Gabus P1X | G16: PC Av / Proj - MS | H16: style/brand | I16: P1HX : Nouvelle face_Av MS | J16: Stratégie projet | L16: 20/06/2025 Retour frns : Proj MS+1,2kg / PC MS+1kg 28/05/2025 à 50% suite 1er retour frns du Proj / En attente info du PC 06/05/2025 passe à 75% 22/04/2025 RD _S16 : Choix Concept Proj (3 parts)_01353_25_00247 24/03/2025 Impact nvo Style_Feu déporté | P16: o | Q16: CANCELED | S16: 1 | T16: 2.2 | U16: =T16*S16 -> 2.2 | V16: 1 | W16: 1 | X16: 1 | Y16: 1 | Z16: 1 | AA16: 1 | AB16: 1 | AC16: 1 | AD16: 1 | AE16: 1 | AF16: 1 | AG16: 1 | AH16: 1 | AI16: 1 | AJ16: 1 | AK16: 1 | AL16: 1 | AM16: 1 | AN16: 1 | AO16: 1 | AP16: 1 | AQ16: 1 | AR16: 1 | AS16: 1 | AV16: 1 | AW16: 1 | AX16: 1 | AY16: 1 | AZ16: 1 | BA16: 1
A17: 220 | B17: 45536 | C17: SPC_1 | D17: BIW | E17: TH | F17: MICHAEL BORE | G17: Pantographe capot | H17: hood Pantographe | I17: imposé par le style | J17: 10/10/2025 référence projet col de cygne, mais demande PEDPRO de Pantographe 11/10/2024 QCTP Pantograh hood hinge =>https://docinfogroupe.stellantis.com/ead/doc/ref.21007_24_00151/v.vc/fiche | K17: PM | M17: =150+200 -> 350 | N17: 8.5 | P17: o | Q17: DECIDED | R17: TBD | S17: 1 | T17: 1 | U17: =T17*S17 -> 1 | V17: 1 | W17: 1 | X17: 1 | Y17: 1 | Z17: 1 | AA17: 1 | AB17: 1 | AC17: 1 | AD17: 1 | AE17: 1 | AF17: 1 | AG17: 1 | AH17: 1 | AI17: 1 | AJ17: 1 | AK17: 1 | AL17: 1 | AM17: 1 | AN17: 1 | AO17: 1 | AP17: 1 | AQ17: 1 | AR17: 1 | AS17: 1 | AV17: 1 | AW17: 1 | AX17: 1 | AY17: 1 | AZ17: 1 | BA17: 1
B18: 45536 | C18: SPC_1 | D18: BIW | E18: TH | F18: MICHAEL BORE | G18: Pare choc | H18: front & rear bumper | I18: nouvelle politique GPC | J18: 06/10/2025 Pas de PORO | M18: 0 | N18: (-6) | P18: o | Q18: DECIDED | R18: TBD | S18: 1 | T18: 0.82 | U18: =T18*S18 -> 0.82 | V18: 1 | W18: 1 | X18: 1 | Y18: 1 | Z18: 1 | AA18: 1 | AB18: 1 | AC18: 1 | AD18: 1 | AE18: 1 | AF18: 1 | AG18: 1 | AH18: 1 | AI18: 1 | AJ18: 1 | AK18: 1 | AL18: 1 | AM18: 1 | AN18: 1 | AO18: 1 | AP18: 1 | AQ18: 1 | AR18: 1 | AS18: 1 | AT18: 1 | AU18: 1 | AV18: 1 | AW18: 1 | AX18: 1 | AY18: 1 | AZ18: 1 | BA18: 1
A19: 322 | B19: 45813 | C19: SP1 | D19: INT - PDB/CONSOLE | E19: TH | F19: FREDERIC BRUNIER | G19: PdB/Console UPPER | H19: Dashboard/Upper console | I19: Chgt de matière (passage du TD 12 vierge au TD12 recyclé / passage du MD20 au TD28 green) | J19: CP P1H Sébastien Dupuis 24/06/2025 à confirmer avec Sébastien car attente panneau SYNC5 et MAJ de la masse | L19: 05/06/2025  Planche de Bord : +0.280 kg / Console UPPER : +0.147 kg et +0.260 kg | P19: o | Q19: CANCELED | S19: 0.75 | T19: 1 | U19: =T19*S19 -> 0.75 | V19: 1 | W19: 1 | X19: 1 | Y19: 1 | Z19: 1 | AA19: 1 | AB19: 1 | AC19: 1 | AD19: 1 | AE19: 1 | AF19: 1 | AG19: 1 | AH19: 1 | AI19: 1 | AJ19: 1 | AK19: 1 | AL19: 1 | AM19: 1 | AN19: 1 | AO19: 1 | AP19: 1 | AQ19: 1 | AR19: 1 | AS19: 1 | AV19: 1 | AW19: 1 | AX19: 1 | AY19: 1 | AZ19: 1 | BA19: 1
A20: 131 | B20: 01/04/2025 | C20: SP1 | D20: Door panel | E20: TH | F20: FREDERIC BRUNIER | G20: Panneau de porte | H20: style/brand | I20: Suppression Textile Fabric | J20: CP P1H Sébastien Dupuis 23/06/25 LM : Vu avec Frédéric refusé par SP1 - A confirmer pour SPC | L20: 01/04/2025 FOAM nécessaire pour process/frn. Et Risque d'ajout d'un tissu embossé sur Portes AV - Demande STYLE, TT niveau -(PTM/VSM) 15/11/2024 Suppression FOAM 14/03/2024 Line-up V9 | P20: o | Q20: CANCELED | S20: 0.25 | T20: 0.1 | U20: =T20*S20 -> 0.025 | V20: 1 | W20: 1 | X20: 1 | Y20: 1 | Z20: 1 | AA20: 1 | AB20: 1 | AC20: 1 | AD20: 1 | AE20: 1 | AF20: 1 | AG20: 1 | AH20: 1 | AI20: 1 | AJ20: 1 | AK20: 1 | AL20: 1 | AM20: 1 | AN20: 1 | AO20: 1 | AP20: 1 | AQ20: 1 | AR20: 1 | AS20: 1 | AV20: 1 | AW20: 1 | AX20: 1 | AY20: 1 | AZ20: 1 | BA20: 1
A21: 132 | B21: 01/04/2025 | C21: SP1 | D21: INT - PDB/CONSOLE | E21: TH | F21: FREDERIC BRUNIER | G21: Pdb_suppression du foam sur les décors textiles | H21: style/brand | I21: suppression du foam sur les décors textiles | J21: CP P1H Sébastien Dupuis 23/06/25 LM : Vu avec Frédéric refusé par SP1 - A confirmer pour SPC | L21: 01/04/2025 Idem Pano Porte 20/09/2024 Passage en PT/VSM CW40 05/09/2024 A revoir avec Guillaume 14/03/2024 Line-up V9 | P21: o | Q21: CANCELED | S21: 0.25 | T21: 0.1 | U21: =T21*S21 -> 0.025 | V21: 1 | W21: 1 | X21: 1 | Y21: 1 | Z21: 1 | AA21: 1 | AB21: 1 | AC21: 1 | AD21: 1 | AE21: 1 | AF21: 1 | AG21: 1 | AH21: 1 | AI21: 1 | AJ21: 1 | AK21: 1 | AL21: 1 | AM21: 1 | AN21: 1 | AO21: 1 | AP21: 1 | AQ21: 1 | AR21: 1 | AS21: 1 | AV21: 1 | AW21: 1 | AX21: 1 | AY21: 1 | AZ21: 1 | BA21: 1
B22: 45546 | C22: SPC_1 | D22: BIW | E22: TH | F22: FRANK BAILLON | G22: Doublure pied central | H22: B pillar inner | I22: stratégie embout Mise en panoplie avec Seatbelt return fix reinforcer | J22: 06/10/2025 a reboucler avec l'embout - Mickael Ludovic DASNOIS | K22: DTM PM-CM | L22: 26/06/2025 a reboucler après hypothèse projet | M22: -350K€ | N22: 2 | P22: x | Q22: DECIDED | R22: TBD | S22: 0.5 | T22: 1.5 | U22: =T22*S22 -> 0.75 | V22: 1 | W22: 1 | X22: 1 | Y22: 1 | Z22: 1 | AA22: 1 | AB22: 1 | AC22: 1 | AD22: 1 | AE22: 1 | AF22: 1 | AG22: 1 | AH22: 1 | AI22: 1 | AJ22: 1 | AK22: 1 | AL22: 1 | AM22: 1 | AN22: 1 | AO22: 1 | AP22: 1 | AQ22: 1 | AR22: 1 | AS22: 1 | AT22: 1 | AU22: 1 | AV22: 1 | AW22: 1 | AX22: 1 | AY22: 1 | AZ22: 1 | BA22: 1
A23: 181 | B23: 46058 | C23: SP1 | D23: BCI_CHASSIS | E23: PTF | G23: Train ar ML : écran aero | H23: Rr axle ML | I23: Demande ajout écran aero sur bras train ML | L23: 27/11/2025 : Présentation en VSM/PTM. Gain important en Aero, mais cout important (+3,5€). Besoin à confirmer après essai, pas en ref en ce moment. Nouvelle estimation à 0,5 kg 03/10/2025 : Aero demande des écrans sur les bras du ML. Demande à confirmer. | P23: o | Q23: IN PROGRESS | S23: 0.75 | T23: 0 | U23: =T23*S23 -> 0 | V23: 1 | W23: 1 | X23: 1 | Y23: 1 | Z23: 1 | AA23: 1 | AB23: 1 | AC23: 1 | AD23: 1 | AE23: 1 | AF23: 1 | AG23: 1 | AH23: 1 | AI23: 1 | AJ23: 1 | AK23: 1 | AL23: 1 | AM23: 1 | AN23: 1 | AO23: 1 | AP23: 1 | AQ23: 1 | AR23: 1 | AS23: 1 | AT23: 1 | AU23: 1 | AV23: 1 | AW23: 1 | AX23: 1 | AY23: 1 | AZ23: 1 | BA23: 1
A24: 202 | B24: 11/06/2025 | C24: SP1 | D24: DIW | E24: TH | F24: Filipe Goncalves (P1H)/ Cyrille P1X | G24: Rft Choc LAT Porte AV | H24: BIW/ DIW process | I24: Embout à chaud PHS950 YS1500T => PHS1400-Y1800T et réduction épaisseur | J24: déjà intégré dans la BDD SP2 - ligne à supprimer | L24: 02/07/2025 CANCELLED : Ep.mini déjà atteinte (chgt de matière possible mais aurait nécessité une dimintution d'épasisseur) 11/06/2025 A ré-évaluer 04/11/2024 Idem post Go-Calcul SYNC3 08/07/2024 Retour calcul SYNC3 (Go calcul Nov => 2025?) Pièce en Embout à chaud | P24: o | Q24: CANCELED | S24: 0.5 | T24: -0.1 | U24: =T24*S24 -> -0.05 | V24: 1 | W24: 1 | X24: 1 | Y24: 1 | Z24: 1 | AA24: 1 | AB24: 1 | AC24: 1 | AD24: 1 | AE24: 1 | AF24: 1 | AG24: 1 | AH24: 1 | AI24: 1 | AJ24: 1 | AK24: 1 | AL24: 1 | AM24: 1 | AN24: 1 | AO24: 1 | AP24: 1 | AQ24: 1 | AR24: 1 | AS24: 1 | AV24: 1 | AW24: 1 | AX24: 1 | AY24: 1 | AZ24: 1 | BA24: 1
B25: 45536 | C25: SPC_1 | D25: BIW | E25: TH | F25: MICHAEL BORE | G25: Rear quarter GLASS | H25: Rear quarter GLASS | I25: Part addition for style | J25: 06/10/2025 OK pour P3U et J2U | K25: PM-CM | L25: 26/06/2025 a reboucler après hypothèse projet | M25: 690K€ | N25: 27.1 | P25: o | Q25: DECIDED | R25: TBD | S25: 0.75 | T25: 1 | U25: =T25*S25 -> 0.75 | V25: 1 | W25: 1 | X25: 1 | Y25: 1 | Z25: 1 | AA25: 1 | AB25: 1 | AC25: 1 | AD25: 1 | AE25: 1 | AF25: 1 | AG25: 1 | AH25: 1 | AI25: 1 | AJ25: 1 | AK25: 1 | AL25: 1 | AM25: 1 | AN25: 1 | AO25: 1 | AP25: 1 | AQ25: 1 | AR25: 1 | AS25: 1 | AT25: 1 | AU25: 1 | AV25: 1 | AW25: 1 | AX25: 1 | AY25: 1 | AZ25: 1 | BA25: 1
A26: 215 | B26: 46058 | C26: SP1 | D26: SWX/EE | E26: PTF | G26: Goulotte faisceaux moteur | H26: ENGINE CABLE DUCT | I26: Optimisation | L26: 25/09/2024 : Compté dans le périmètre TH. 18/07/2024 : issu GT EE scope du 15/07/2024 | P26: o | Q26: IN PROGRESS | S26: 0.5 | T26: 0.02 | U26: =T26*S26 -> 0.01 | V26: 1 | W26: 1 | X26: 1 | Y26: 1 | Z26: 1 | AA26: 1 | AB26: 1 | AC26: 1 | AD26: 1 | AE26: 1 | AF26: 1 | AG26: 1 | AH26: 1 | AI26: 1 | AJ26: 1 | AK26: 1 | AL26: 1 | AM26: 1 | AN26: 1 | AO26: 1 | AP26: 1 | AQ26: 1 | AR26: 1 | AS26: 1 | AT26: 1 | AU26: 1 | AV26: 1 | AW26: 1 | AX26: 1 | AY26: 1 | AZ26: 1 | BA26: 1
A27: 224 | B27: 25/09/2024 | C27: SP1 | D27: ICDV | E27: TH | G27: Pneu | I27: Optim de masse 17" et 18" | L27: 25/09/2024 reporté S40 02/09/2024 besoin anayse VDYN 12/06/2024 New / attente retour frns | P27: o | Q27: CANCELED | S27: 0.5 | T27: -1.2 | U27: =T27*S27 -> -0.6 | V27: 1 | W27: 1 | X27: 1 | Y27: 1 | Z27: 1 | AA27: 1 | AB27: 1 | AC27: 1 | AD27: 1 | AE27: 1 | AF27: 1 | AG27: 1 | AH27: 1 | AI27: 1 | AJ27: 1 | AK27: 1 | AL27: 1 | AM27: 1 | AN27: 1 | AO27: 1 | AP27: 1 | AQ27: 1 | AR27: 1 | AS27: 1 | AV27: 1 | AW27: 1 | AX27: 1 | AY27: 1 | AZ27: 1 | BA27: 1
A28: 271 | B28: 08/04/2025 | C28: SP1 | D28: BIW | E28: TH | F28: Franck Baillon (SP1)/ Cyrille P1X | G28: Zone Auvent | H28: new part | I28: Ajout pièces | J28: ???? Déjà sur SP2 | L28: 08/04/2025 Détail : Finition LAT D/G Grille Entrée Air / Grille Entrée Air / Deflect Eau / Etanchéité D/G Grille / Conduit Entrée Air 22/11/2024 Complétude de BOM | P28: o | Q28: DECIDED | S28: 1 | T28: 0.54 | U28: =T28*S28 -> 0.54 | V28: 1 | W28: 1 | X28: 1 | Y28: 1 | Z28: 1 | AA28: 1 | AB28: 1 | AC28: 1 | AD28: 1 | AE28: 1 | AF28: 1 | AG28: 1 | AH28: 1 | AI28: 1 | AJ28: 1 | AK28: 1 | AL28: 1 | AM28: 1 | AN28: 1 | AO28: 1 | AP28: 1 | AQ28: 1 | AR28: 1 | AS28: 1 | AT28: 1 | AU28: 1 | AV28: 1 | AW28: 1 | AX28: 1 | AY28: 1 | AZ28: 1 | BA28: 1
A29: 323 | B29: 06/06/2025 | C29: SP1 | D29: FRSD | E29: TH | F29: Sébastien Bonnefoi (P1H)/ Jean Michel Gabus P1X | G29: PC Av/Ar | H29: Front/Rear bumper | I29: P1X | J29: traité en PORO dépend du style | L29: 06/06/2025 PC P1X avec Air-Curtain | P29: o | Q29: CANCELED | S29: 0.25 | T29: 2 | U29: =T29*S29 -> 0.5 | V29: 1 | W29: 1 | X29: 1 | Y29: 1 | Z29: 1 | AA29: 1 | AB29: 1 | AC29: 1 | AD29: 1 | AE29: 1 | AF29: 1 | AG29: 1 | AH29: 1 | AI29: 1 | AJ29: 1 | AK29: 1 | AL29: 1 | AM29: 1 | AN29: 1 | AO29: 1 | AP29: 1 | AQ29: 1 | AR29: 1 | AS29: 1 | AV29: 1 | AW29: 1 | AX29: 1 | AY29: 1 | AZ29: 1 | BA29: 1
A30: 238 | B30: 46058 | C30: SP1 | D30: SWX/EE | E30: PTF | G30: Batterie 12V | H30: 12V battery | I30: Retour fournisseur en fonction de niv equipement | L30: 25/09/2024 : batterie EFR L2 sur niv1. La masse absolue dépend du fournisseur. 24/06/2024 : Retour fournisseur | P30: o | Q30: CANCELED | S30: 1 | T30: -0.4 | U30: =T30*S30 -> -0.4 | V30: 1 | W30: 1 | X30: 1 | Y30: 1 | Z30: 1 | AA30: 1 | AB30: 1 | AC30: 1 | AD30: 1 | AE30: 1 | AF30: 1 | AG30: 1 | AH30: 1 | AI30: 1 | AJ30: 1 | AK30: 1 | AL30: 1 | AM30: 1 | AN30: 1 | AO30: 1 | AP30: 1 | AS30: 1 | AW30: 1 | AX30: 1 | AY30: 1
A31: 245 | B31: 09/07/2024 | C31: SP1 | D31: PRS | E31: PWT | F31: ANTOINE SAINT MARCOUX | G31: Batterie RR/SR/HR | H31: HR battery | I31: 2 topics : Remove Fuse FO -0,3kg + Volume increase +1kg | L31: 09/07/2024 New | P31: o | Q31: IN PROGRESS | S31: 0.5 | T31: 0.7 | U31: =T31*S31 -> 0.35 | V31: 1 | W31: 1 | X31: 1 | Y31: 1 | Z31: 1 | AA31: 1 | AB31: 1 | AC31: 1 | AD31: 1 | AE31: 1 | AF31: 1 | AG31: 1 | AH31: 1 | AI31: 1 | AJ31: 1 | AK31: 1 | AL31: 1 | AM31: 1 | AN31: 1 | AS31: 1 | AW31: 1
A32: 248 | B32: 09/07/2024 | C32: SP1 | D32: PRS | E32: PWT | F32: ANTOINE SAINT MARCOUX | G32: Batterie HR | H32: HR battery | L32: 26/09/2025 Brackets : inc ds le STATUS 24/07/2025 2 sujets new : Bracket reinforct -2kg / Alu Busbar-3 (50%) 09/07/2024 New | P32: o | Q32: IN PROGRESS | S32: 0.5 | T32: -3 | U32: =T32*S32 -> -1.5 | V32: 1 | W32: 1 | X32: 1 | Y32: 1 | Z32: 1 | AA32: 1 | AB32: 1 | AC32: 1 | AD32: 1 | AE32: 1 | AF32: 1 | AG32: 1 | AH32: 1 | AI32: 1 | AJ32: 1 | AK32: 1 | AL32: 1 | AM32: 1 | AN32: 1 | AW32: 1
A33: 270 | B33: 08/04/2025 | C33: SP1 | D33: INT - SEATS/TRIMS | E33: TH | F33: HALIM | G33: Isolant Tapis | H33: Carpet insulation | I33: Insono Tapis pour le ThermalRunaway | J33: 24/06/2025 à vérifier plus tard | K33: SFM | L33: 08/04/2025 GT_calcul : Risque levé pour P1H-SR / Reste pour HR et XR 18/03/2025 Coord_STLAS : Pour P1h=7pièces => +1,5kg ; +4€ // Pour P1X +2pièces 19/11/2024 Risque SYNC3 (Estim 1,2*1,9 / 650gr/m²:GlassMAT™HTX isolation thermique et phonique des compartiments moteur) | P33: o | Q33: CANCELED | S33: 0.25 | T33: 1.482 | U33: =T33*S33 -> 0.3705 | V33: 1 | W33: 1 | X33: 1 | Y33: 1 | Z33: 1 | AA33: 1 | AB33: 1 | AC33: 1 | AD33: 1 | AE33: 1 | AF33: 1 | AG33: 1 | AH33: 1 | AI33: 1 | AJ33: 1 | AK33: 1 | AL33: 1 | AM33: 1 | AN33: 1 | AO33: 1 | AP33: 1 | AQ33: 1 | AR33: 1 | AS33: 1 | AV33: 1 | AW33: 1 | AX33: 1 | AY33: 1 | AZ33: 1 | BA33: 1
A34: 107b | B34: 08/10/2024 | C34: SP1 | D34: SWX/EE | E34: PTF | G34: Cable mode3 (7kW) | I34: Passage en option/APV | L34: 08/10/2024 : Proposition de mettre le cable en option lors de l'achat (forcée par défaut dans le cnfigurateur avec possibilité de le supprimer). 25/09/2024 : Interdit par la politique tech pour le passage APV (Julien Grand clerc / Alain Lefevre sollicités pour offi). 19/06/2024 : en cours sur SP1 et sur SP2 13/03/2024 ECMP > APV | P34: o | Q34: CANCELED | S34: 0.5 | T34: -2.6 | U34: =T34*S34 -> -1.3 | V34: 1 | W34: 1 | X34: 1 | Y34: 1 | Z34: 1 | AA34: 1 | AB34: 1 | AC34: 1 | AD34: 1 | AE34: 1 | AF34: 1 | AG34: 1 | AH34: 1 | AI34: 1 | AJ34: 1 | AK34: 1 | AL34: 1 | AM34: 1 | AN34: 1 | AO34: 1 | AP34: 1 | AQ34: 1 | AR34: 1 | AS34: 1 | AV34: 1 | AW34: 1 | AX34: 1 | AY34: 1 | AZ34: 1 | BA34: 1
A35: 188a | B35: 28/05/2025 | C35: SP1 | D35: FRSD | E35: TH | F35: Sébastien Bonnefoi (P1H)/ Jean Michel Gabus P1X | G35: Aile/Capot P1X | H35: style/brand | I35: Nvo STYLE | L35: 28/05/2025 CHANTIER MASSE : Nvo Styl, en attente design 25/04/2024 : pas de modif style => A annuler pour P1H. 27/03/2024 New WS S14 | P35: o | Q35: CANCELED | S35: 0.25 | T35: 0.5 | U35: =T35*S35 -> 0.125 | V35: 1 | W35: 1 | X35: 1 | Y35: 1 | Z35: 1 | AA35: 1 | AB35: 1 | AC35: 1 | AD35: 1 | AE35: 1 | AF35: 1 | AG35: 1 | AH35: 1 | AI35: 1 | AJ35: 1 | AK35: 1 | AL35: 1 | AM35: 1 | AN35: 1 | AO35: 1 | AP35: 1 | AQ35: 1 | AR35: 1 | AS35: 1 | AV35: 1 | AW35: 1 | AX35: 1 | AY35: 1 | AZ35: 1 | BA35: 1
A36: 45b | B36: 46058 | C36: SP1 | D36: PHES | E36: PTF | G36: Optimisation des supports PHES | H36: support optim | I36: STEP2 : Optimize thickness | L36: 11/09/2024 : Travaux en cours | P36: o | Q36: IN PROGRESS | S36: 0.25 | T36: -0.5 | U36: =T36*S36 -> -0.125 | V36: 1 | W36: 1 | X36: 1 | Y36: 1 | Z36: 1 | AA36: 1 | AB36: 1 | AC36: 1 | AD36: 1 | AE36: 1 | AF36: 1 | AG36: 1 | AH36: 1 | AI36: 1 | AJ36: 1 | AK36: 1 | AL36: 1 | AM36: 1 | AN36: 1 | AO36: 1 | AP36: 1 | AQ36: 1 | AR36: 1 | AS36: 1 | AT36: 1 | AU36: 1 | AV36: 1 | AW36: 1 | AX36: 1 | AY36: 1 | AZ36: 1 | BA36: 1
A37: 45c | B37: 46058 | C37: SP1 | D37: SWX/EE | E37: PTF | G37: SUPPORT MULTIFONCTION AR G BATTERIE TRACTION | H37: support optim | I37: STEP2 : Optimize thickness valeur initiale : 0,847 kg | L37: 09/12/2025 : Proposition de créer une diversité entre les versions AWD et FWD pour tous les HR | P37: o | Q37: IN PROGRESS | S37: 1 | T37: -0.45 | U37: =T37*S37 -> -0.45 | V37: 1 | W37: 1 | X37: 1 | Y37: 1 | Z37: 1 | AA37: 1 | AB37: 1 | AC37: 1 | AD37: 1 | AE37: 1 | AF37: 1 | AG37: 1 | AH37: 1 | AI37: 1 | AJ37: 1 | AK37: 1 | AL37: 1 | AM37: 1 | AN37: 1 | AO37: 1 | AP37: 1 | AS37: 1 | AW37: 1 | AX37: 1
A38: 92 | B38: 06/06/2025 | C38: SP1 | D38: DIW | E38: TH | F38: Filipe Goncalves (P1H)/ Cyrille P1X | G38: Portes | H38: BIW/ DIW process | I38: Impact masse demande DIR pour diminuer la diversité (ép. : dizaine supérieure) | J38: 06/02/2026LM Pas concerné | L38: 06/06/2025 Niveau de risk diminué à 25%, Final step : fin de SYNC3 04/11/2024 Décalage planning > Post Go_Calcul 12/07/2024 En attente des résultats SYNC3 21/03/2024 A valoriser suite aux résultats SYNC2 (voir avec RM) 14/03/2024 New / A décider avant engagement SYNC3 | P38: o | Q38: CANCELED | S38: 0.25 | T38: 1.2 | U38: =T38*S38 -> 0.3 | V38: 1 | W38: 1 | X38: 1 | Y38: 1 | Z38: 1 | AA38: 1 | AB38: 1 | AC38: 1 | AD38: 1 | AE38: 1 | AF38: 1 | AG38: 1 | AH38: 1 | AI38: 1 | AJ38: 1 | AK38: 1 | AL38: 1 | AM38: 1 | AN38: 1 | AO38: 1 | AP38: 1 | AQ38: 1 | AR38: 1 | AS38: 1 | AV38: 1 | AW38: 1 | AX38: 1 | AY38: 1 | AZ38: 1 | BA38: 1
A39: 93B | B39: 08/04/2025 | C39: SP1 | D39: BIW | E39: TH | F39: Franck Baillon (SP1)/ Cyrille P1X | G39: BIW : CHOC | H39: risk perfo | I39: Rft 3é voie | J39: Bilan Choc dira si on peut appliquer aussi | L39: 08/04/2025 Scénario choc tt SP1 : Dbl Aile AV & Rft Abv Cote HAB (+0,888kg) 03/09/2024 En attente travaux Base sur la 3ée voie … Synthèse idem P1H ! (0,5kg à 50%) 25/04/2024 : Suite choc frontal SYNC1 .Risque ajout raidisseu 13/03/2024 maj 01/02/2024 Ptf | P39: x | Q39: DECIDED | S39: 0.5 | T39: 0.888 | U39: =T39*S39 -> 0.444 | V39: 1 | W39: 1 | X39: 1 | Y39: 1 | Z39: 1 | AA39: 1 | AB39: 1 | AC39: 1 | AD39: 1 | AE39: 1 | AF39: 1 | AG39: 1 | AH39: 1 | AI39: 1 | AJ39: 1 | AK39: 1 | AL39: 1 | AM39: 1 | AN39: 1 | AO39: 1 | AP39: 1 | AQ39: 1 | AR39: 1 | AS39: 1 | AV39: 1 | AW39: 1 | AX39: 1 | AY39: 1 | AZ39: 1 | BA39: 1
B40: 45536 | C40: SPC_1 | D40: BIW | E40: TH | F40: FRANK BAILLON | G40: Doublure custode | H40: Lower quarter inner | I40: stratégie embout Mise en panoplie avec Upper rear inner quarter | J40: 06/10/2025 a reboucler avec l'embout - Mickael Ludovic DASNOIS | K40: DTM PM-CM | L40: 26/06/2025 a reboucler après hypothèse projet | M40: -400K€ | N40: 0.7 | P40: o | Q40: CANCELED | R40: TBD | S40: 0.5 | T40: 0.43 | U40: =T40*S40 -> 0.215 | V40: 1 | W40: 1 | X40: 1 | Y40: 1 | Z40: 1 | AA40: 1 | AB40: 1 | AC40: 1 | AD40: 1 | AE40: 1 | AF40: 1 | AG40: 1 | AH40: 1 | AI40: 1 | AJ40: 1 | AK40: 1 | AL40: 1 | AM40: 1 | AN40: 1 | AO40: 1 | AP40: 1 | AQ40: 1 | AR40: 1 | AS40: 1 | AT40: 1 | AU40: 1 | AV40: 1 | AW40: 1 | AX40: 1 | AY40: 1 | AZ40: 1 | BA40: 1
B41: 45536 | C41: SPC_1 | D41: BIW | E41: TH | F41: FRANK BAILLON | G41: Doublure panneau AR | H41: Rear Inner pannel | I41: stratégie embout Mise en panoplie avec Closing | J41: 06/10/2025 a reboucler avec l'embout - Mickael Ludovic DASNOIS | K41: DTM PM-CM | L41: 26/06/2025 a reboucler après hypothèse projet | M41: -500K€ | N41: 0.6 | P41: o | Q41: CANCELED | R41: TBD | S41: 0.5 | T41: 0.4 | U41: =T41*S41 -> 0.2 | V41: 1 | W41: 1 | X41: 1 | Y41: 1 | Z41: 1 | AA41: 1 | AB41: 1 | AC41: 1 | AD41: 1 | AE41: 1 | AF41: 1 | AG41: 1 | AH41: 1 | AI41: 1 | AJ41: 1 | AK41: 1 | AL41: 1 | AM41: 1 | AN41: 1 | AO41: 1 | AP41: 1 | AQ41: 1 | AR41: 1 | AS41: 1 | AT41: 1 | AU41: 1 | AV41: 1 | AW41: 1 | AX41: 1 | AY41: 1 | AZ41: 1 | BA41: 1
A42: 233 | B42: 46083 | C42: SPC_1 | D42: INT - SEATS/TRIMS | E42: TH | F42: HALIM | G42: Ins Passe de roue AR | H42: optim design | I42: Ins Passe de roue AR : New | J42: 02/03/2026 LM Meeting CW10 | K42: SFM | P42: o | Q42: CANCELED | S42: 0.5 | U42: =T42*S42 -> 0 | V42: 1 | W42: 1 | X42: 1 | Y42: 1 | Z42: 1 | AA42: 1 | AB42: 1 | AC42: 1 | AD42: 1 | AE42: 1 | AF42: 1 | AG42: 1 | AH42: 1 | AI42: 1 | AJ42: 1 | AK42: 1 | AL42: 1 | AM42: 1 | AN42: 1 | AO42: 1 | AP42: 1 | AQ42: 1 | AR42: 1 | AS42: 1 | AT42: 1 | AU42: 1 | AV42: 1 | AW42: 1 | AX42: 1 | AY42: 1 | AZ42: 1 | BA42: 1
A43: 234 | B43: 18/06/2024 | C43: SP1 | D43: BIW | E43: TH | F43: FRANK BAILLON | G43: Garniture Raidisseur Pavillon | H43: optim design | I43: Dossier RFQ (obj masse) => A verifier dans la BDD | J43: 24/06/2025 à checker en RFQ avec les FNR | K43: SFM | L43: 18/06/2024 Dossier RFQ : Masses sup | P43: o | Q43: CANCELED | S43: 0.5 | T43: 0.3 | U43: =T43*S43 -> 0.15 | V43: 1 | W43: 1 | X43: 1 | Y43: 1 | Z43: 1 | AA43: 1 | AB43: 1 | AC43: 1 | AD43: 1 | AE43: 1 | AF43: 1 | AG43: 1 | AH43: 1 | AI43: 1 | AJ43: 1 | AK43: 1 | AL43: 1 | AM43: 1 | AN43: 1 | AO43: 1 | AP43: 1 | AQ43: 1 | AR43: 1 | AS43: 1 | AT43: 1 | AU43: 1 | AV43: 1 | AW43: 1 | AX43: 1 | AY43: 1 | AZ43: 1 | BA43: 1
A44: 99c | B44: 26/08/2024 | C44: SP1 | D44: PRS | E44: PWT | G44: Ens PWT HR + 11kW | I44: HR Bat / FWD S EDM / IDCM 11kW | L44: 26/08/2024 Status maj > Ptf en Risque => Echéance C-sample : date ? 08/07/2024 Mass updated CW27 / maj en cours | P44: o | Q44: CANCELED | S44: 0.5 | T44: 1.8 | U44: =T44*S44 -> 0.9 | V44: 1 | W44: 1 | X44: 1 | Y44: 1 | Z44: 1 | AA44: 1 | AB44: 1 | AC44: 1 | AD44: 1 | AE44: 1 | AF44: 1 | AG44: 1 | AH44: 1 | AI44: 1 | AJ44: 1 | AK44: 1 | AL44: 1 | AM44: 1 | AN44: 1 | AO44: 1 | AP44: 1 | AQ44: 1 | AR44: 1 | AS44: 1 | AV44: 1 | AW44: 1 | AX44: 1 | AY44: 1 | AZ44: 1 | BA44: 1
A45: 9b | B45: 46058 | C45: SP1 | D45: BCI_BODY | E45: PTF | G45: Optimisation des écrans sous caisse | H45: optim phase 2 | I45: Optimisation de dessin | L45: 17/11/2025 : Config P1H figée. 17/07/2025 : Pas de casse d'écran (ecran ar cassé mais à priori non conforme). Attente retour QAU pour voir si déformation ok. 07/07/2025 : Ecran actuellement trop souple. Besoin d'essai de passage au gué pour etat des lieux (cette semaine). Voir avec JC si masse des ecrans dans la BOM est conforme de la techno Mussel. 20/11/2024 : Consultation en cours. Certains fournisseurs propose la techno Mussel : injecte de l'air dans la matière pour avoir de l'épaisseur sans masse (permet d'avoir de la raideur et de réduire le besoin de nervurage). Choix fournisseur début avril 2025. 23/10/2024 : Design avant essai 23/09/2024 : Piste maximisée | P45: o | Q45: IN PROGRESS | S45: 0.25 | T45: -2 | U45: =T45*S45 -> -0.5 | V45: 1 | W45: 1 | X45: 1 | Y45: 1 | Z45: 1 | AA45: 1 | AB45: 1 | AC45: 1 | AD45: 1 | AE45: 1 | AF45: 1 | AG45: 1 | AH45: 1 | AI45: 1 | AJ45: 1 | AK45: 1 | AL45: 1 | AM45: 1 | AN45: 1 | AO45: 1 | AP45: 1 | AS45: 1 | AW45: 1 | AX45: 1
A46: 283 | B46: 11/02/2025 | C46: SP1 | D46: BCI_CHASSIS | E46: PTF | G46: Actionneur volant direction filaire (SBW uniquement) | H46: Steer-by-wire steering wheel actuator (SBW only) | I46: Optimisation fournisseur | L46: 11/02/2025 : Pb en collapse vu en simu qui risque d'augmenter la masse. Essai physique cette semaine à Turin. Existe une solution en simu qui resout le problème -> à chiffrer S08 + passage en VSM/PTM S07 pour valider ECR chez le fournisseur 7/25/2024 : GT presta S30 : Convergence presque à la cible avec une estimation masse à 7.3 kg ald 8 kg en cible. Il reste des implementation à faire mais probablement pas à la hauteur des +0.7 d'écart. | P46: o | Q46: CANCELED | S46: 0.25 | T46: -0.7 | U46: =T46*S46 -> -0.175 | V46: 1 | W46: 1 | X46: 1 | Y46: 1 | Z46: 1 | AA46: 1 | AB46: 1 | AC46: 1 | AD46: 1 | AE46: 1 | AF46: 1 | AG46: 1 | AH46: 1 | AI46: 1 | AJ46: 1 | AK46: 1 | AL46: 1 | AM46: 1 | AN46: 1 | AO46: 1 | AP46: 1 | AQ46: 1 | AR46: 1 | AS46: 1 | AV46: 1 | AW46: 1 | AX46: 1 | AY46: 1 | AZ46: 1 | BA46: 1
A47: 284 | B47: 11/02/2025 | C47: SP1 | D47: BCI_CHASSIS | E47: PTF | G47: Actionneur volant direction filaire (SBW uniquement) | H47: Steer-by-wire steering wheel actuator (SBW only) | I47: Optimisation reponse en frequence | L47: 11/02/2025 : Solution fer à cheval choisie. Retour cette semaine pour la faisa. 03/10/2024 : Essai prévu S40 mais pb appro pièce. 28/08/2024 : Travail en cours sur la traverse PdB. Simu et essais en cours. Délai a voir avec Philippe Vannier et Olivier en GT Prestation. 7/25/2024 : GT presta S30 : Convergence presque à la cible avec une estimation masse à 7.3 kg ald 8 kg en cible. Il reste des implementation à faire mais probablement pas à la hauteur des +0.7 d'écart. | P47: o | Q47: CANCELED | S47: 1 | T47: 0.3 | U47: =T47*S47 -> 0.3 | V47: 1 | W47: 1 | X47: 1 | Y47: 1 | Z47: 1 | AA47: 1 | AB47: 1 | AC47: 1 | AD47: 1 | AE47: 1 | AF47: 1 | AG47: 1 | AH47: 1 | AI47: 1 | AJ47: 1 | AK47: 1 | AL47: 1 | AM47: 1 | AN47: 1 | AO47: 1 | AP47: 1 | AQ47: 1 | AR47: 1 | AS47: 1 | AV47: 1 | AW47: 1 | AX47: 1 | AY47: 1 | AZ47: 1 | BA47: 1
A48: 287 | B48: 11/02/2025 | C48: SP1 | D48: BCI_BODY | E48: PTF | G48: Zone Brancard | H48: Side rail area | L48: 11/02/2025 : Passage du sujet en VSM/PTM S07 pour décider. 03/12/2024 : GT conception : eval précise après calcul : estimation à +0,7 kg hors tablier (valable TT). Epaisseur tablier à passer en 0,9 ald 0,7 --> +0,9 kg (impact seulement sur P1H, P1X déjà en 0,9). 20/11/2024 : Pb de choc après reception MaJ modèles de choc. Dessin en cours, calcul d'ici 2 ou 3 semaines. | P48: o | Q48: CANCELED | S48: 1 | T48: 0.5 | U48: =T48*S48 -> 0.5 | V48: 1 | W48: 1 | X48: 1 | Y48: 1 | Z48: 1 | AA48: 1 | AB48: 1 | AC48: 1 | AD48: 1 | AE48: 1 | AF48: 1 | AG48: 1 | AH48: 1 | AI48: 1 | AJ48: 1 | AK48: 1 | AL48: 1 | AM48: 1 | AN48: 1 | AO48: 1 | AP48: 1 | AQ48: 1 | AR48: 1 | AS48: 1 | AV48: 1 | AW48: 1 | AX48: 1 | AY48: 1 | AZ48: 1 | BA48: 1
A49: 255 | B49: 46058 | C49: SP1 | D49: PHES | E49: PTF | G49: Damper | H49: TPC | I49: Remove sur Chiller, TMM, Compresseur. | L49: 29/10/2025 : Essais 12/2025 11/09/2024 : Piste TPC. Gains suivant essai NVH à venir. | P49: o | Q49: CANCELED | S49: 0.5 | T49: -0.1 | U49: =T49*S49 -> -0.05 | V49: 1 | W49: 1 | X49: 1 | Y49: 1 | Z49: 1 | AA49: 1 | AB49: 1 | AC49: 1 | AD49: 1 | AE49: 1 | AF49: 1 | AG49: 1 | AH49: 1 | AI49: 1 | AJ49: 1 | AK49: 1 | AL49: 1 | AM49: 1 | AN49: 1 | AO49: 1 | AP49: 1 | AT49: 1 | AU49: 1 | AV49: 1 | AY49: 1 | AZ49: 1 | BA49: 1
B50: 01/09/024 | C50: SPC_1 | D50: BIW | E50: TH | F50: FRANK BAILLON | G50: Montant de baie | H50: Windscreen pillar reinforcer | I50: stratégie embout Mise en panoplie avec Roof Arch reinforcement | J50: 06/10/2025 a reboucler avec l'embout - Mickael Ludovic DASNOIS | K50: DTM PM-CM | L50: 26/06/2025 a reboucler après hypothèse projet | M50: -350K€ | N50: 1.6 | P50: o | Q50: CANCELED | R50: TBD | S50: 0.1 | T50: 1.2 | U50: =T50*S50 -> 0.12 | V50: 1 | W50: 1 | X50: 1 | Y50: 1 | Z50: 1 | AA50: 1 | AB50: 1 | AC50: 1 | AD50: 1 | AE50: 1 | AF50: 1 | AG50: 1 | AH50: 1 | AI50: 1 | AJ50: 1 | AK50: 1 | AL50: 1 | AM50: 1 | AN50: 1 | AO50: 1 | AP50: 1 | AQ50: 1 | AR50: 1 | AS50: 1 | AT50: 1 | AU50: 1 | AV50: 1 | AW50: 1 | AX50: 1 | AY50: 1 | AZ50: 1 | BA50: 1
A51: 294 | B51: 11/02/2025 | C51: SP1 | D51: BCI_BODY | E51: PTF | G51: Longeron | H51: SILL | I51: Reduction feuillure inf longeron | L51: 11/02/2025 : A passer en RD suite accord de toutes les parties. 07/01/2025 : reduction de la hauteur de feuillure de 9mm (6mm sur TH) pour un gain de 0,540 kg (-0,35 kg sur PTF et -0,19 kg sur TH) | P51: o | Q51: CANCELED | S51: 1 | T51: -0.35 | U51: =T51*S51 -> -0.35 | V51: 1 | W51: 1 | X51: 1 | Y51: 1 | Z51: 1 | AA51: 1 | AB51: 1 | AC51: 1 | AD51: 1 | AE51: 1 | AF51: 1 | AG51: 1 | AH51: 1 | AI51: 1 | AJ51: 1 | AK51: 1 | AL51: 1 | AM51: 1 | AN51: 1 | AO51: 1 | AP51: 1 | AQ51: 1 | AR51: 1 | AS51: 1 | AV51: 1 | AW51: 1 | AX51: 1 | AY51: 1 | AZ51: 1 | BA51: 1
A52: 295 | B52: 46058 | C52: SP1 | D52: BCI_BODY | E52: PTF | G52: Demande ajout écran aero sur bras train ML | I52: 27/11/2025 : Présentation en VSM/PTM. Gain important en Aero, mais cout important (+3,5€). Besoin à confirmer après essai, pas en ref en ce moment. Nouvelle estimation à 0,5 kg 03/10/2025 : Aero demande des écrans sur les bras du ML. Demande à confirmer. | L52: 27/11/2025 : Présentation en VSM/PTM. Gain important en Aero, mais cout important (+3,5€). Besoin à confirmer après essai, pas en ref en ce moment. Nouvelle estimation à 0,5 kg 03/10/2025 : Aero demande des écrans sur les bras du ML. Demande à confirmer. | P52: o | Q52: IN PROGRESS | S52: 0.75 | T52: 0.5 | U52: =T52*S52 -> 0.375 | V52: 1 | W52: 1 | X52: 1 | Y52: 1 | Z52: 1 | AA52: 1 | AB52: 1 | AC52: 1 | AD52: 1 | AE52: 1 | AF52: 1 | AG52: 1 | AH52: 1 | AI52: 1 | AJ52: 1 | AK52: 1 | AL52: 1 | AM52: 1 | AN52: 1 | AO52: 1 | AP52: 1 | AW52: 1 | AX52: 1
A53: 296 | B53: 46058 | C53: SP1 | D53: BCI_BODY | E53: PTF | G53: Longeronnet AV | H53: Front sub-frame | I53: Besoin de raideur dyn | L53: 11/02/2025 : Besoin de raideur dyn | P53: o | Q53: CANCELED | S53: 1 | T53: 0.3 | U53: =T53*S53 -> 0.3 | V53: 1 | W53: 1 | X53: 1 | Y53: 1 | Z53: 1 | AA53: 1 | AB53: 1 | AC53: 1 | AD53: 1 | AE53: 1 | AF53: 1 | AG53: 1 | AH53: 1 | AI53: 1 | AJ53: 1 | AK53: 1 | AL53: 1 | AM53: 1 | AN53: 1 | AO53: 1 | AP53: 1 | AQ53: 1 | AR53: 1 | AS53: 1 | AV53: 1 | AW53: 1 | AX53: 1 | AY53: 1 | AZ53: 1 | BA53: 1
A54: 298 | B54: 46058 | C54: SP1 | D54: BCI_BODY | E54: PTF | G54: Optimasse phase 3 P1X | H54: Underbody optimization | L54: 07/11/2025 : hypothèse de reduction de 0,05mm sur les tôles entre 0,7 et 1,6. | P54: o | Q54: IN PROGRESS | S54: 0.25 | T54: -4.9 | U54: =T54*S54 -> -1.225 | V54: 1 | W54: 1 | X54: 1 | Y54: 1 | Z54: 1 | AA54: 1 | AB54: 1 | AC54: 1 | AD54: 1 | AE54: 1 | AF54: 1 | AG54: 1 | AH54: 1 | AI54: 1 | AJ54: 1 | AK54: 1 | AL54: 1 | AM54: 1 | AN54: 1 | AO54: 1 | AP54: 1 | AS54: 1 | AW54: 1 | AX54: 1 | AY54: 1
A55: 305 | B55: 24/04/2025 | C55: SP1 | D55: INT - PDB/CONSOLE | E55: TH | F55: FREDERIC BRUNIER | G55: Traverse planche de bord | H55: risk perfo | I55: Renforcement | J55: CP P1H Sébastien Dupuis 24/06/2025 à confirmer avec Sébastien | L55: 24/04/2025 Tenue NVH / Vibration | P55: o | Q55: CANCELED | S55: 0.25 | T55: 0.4 | U55: =T55*S55 -> 0.1 | V55: 1 | W55: 1 | X55: 1 | Y55: 1 | Z55: 1 | AA55: 1 | AB55: 1 | AC55: 1 | AD55: 1 | AE55: 1 | AF55: 1 | AG55: 1 | AH55: 1 | AI55: 1 | AJ55: 1 | AK55: 1 | AL55: 1 | AM55: 1 | AN55: 1 | AO55: 1 | AP55: 1 | AQ55: 1 | AR55: 1 | AS55: 1 | AV55: 1 | AW55: 1 | AX55: 1 | AY55: 1 | AZ55: 1 | BA55: 1
B56: 45536 | C56: SPC_1 | D56: BIW | E56: TH | F56: FRANK BAILLON | G56: Montant de baie | H56: Inner Windscreen pillar | I56: stratégie embout Mise en panoplie avec Inner Roof Arch | J56: 06/10/2025 a reboucler avec l'embout - Mickael Ludovic DASNOIS | K56: DTM PM-CM | L56: 26/06/2025 a reboucler après hypothèse projet | M56: -250K€ | N56: 0.7 | P56: o | Q56: CANCELED | R56: TBD | S56: 0.1 | T56: 0.5 | U56: =T56*S56 -> 0.05 | V56: 1 | W56: 1 | X56: 1 | Y56: 1 | Z56: 1 | AA56: 1 | AB56: 1 | AC56: 1 | AD56: 1 | AE56: 1 | AF56: 1 | AG56: 1 | AH56: 1 | AI56: 1 | AJ56: 1 | AK56: 1 | AL56: 1 | AM56: 1 | AN56: 1 | AO56: 1 | AP56: 1 | AQ56: 1 | AR56: 1 | AS56: 1 | AT56: 1 | AU56: 1 | AV56: 1 | AW56: 1 | AX56: 1 | AY56: 1 | AZ56: 1 | BA56: 1
B57: 45536 | C57: SPC_1 | D57: BIW | E57: TH | F57: FRANK BAILLON | G57: Pavillon AR | H57: Rear roof reinforcer | I57: stratégie embout Mise en panoplie avec Crossmenber | J57: 06/10/2025 a reboucler avec l'embout - Mickael Ludovic DASNOIS | K57: DTM PM-CM | L57: 26/06/2025 a reboucler après hypothèse projet | M57: -400K€ | N57: 0 | P57: o | Q57: CANCELED | R57: TBD | S57: 0.1 | T57: 0.3 | U57: =T57*S57 -> 0.03 | V57: 1 | W57: 1 | X57: 1 | Y57: 1 | Z57: 1 | AA57: 1 | AB57: 1 | AC57: 1 | AD57: 1 | AE57: 1 | AF57: 1 | AG57: 1 | AH57: 1 | AI57: 1 | AJ57: 1 | AK57: 1 | AL57: 1 | AM57: 1 | AN57: 1 | AO57: 1 | AP57: 1 | AQ57: 1 | AR57: 1 | AS57: 1 | AT57: 1 | AU57: 1 | AV57: 1 | AW57: 1 | AX57: 1 | AY57: 1 | AZ57: 1 | BA57: 1
B58: 45536 | C58: SPC_1 | D58: FRSD | E58: TH | F58: MICHAEL BORE | G58: feu AR T2 | H58: rear central lamp T2 | I58: estimation entre 2 FNR | J58: 13/03/2026 LM | M58: 0 | N58: (-59,31) | P58: x | Q58: IN PROGRESS | R58: TBD | S58: 0.1 | T58: -2 | U58: =T58*S58 -> -0.2 | V58: 1 | AE58: 1 | AN58: 1 | AO58: 1 | AP58: 1 | AQ58: 1 | AR58: 1
A59: 299 | B59: 46058 | C59: SP1 | D59: PHES | E59: PTF | G59: HVAC | H59: HVAC | I59: Augmentation des performances | L59: 07/03/2025 : Décision d'ajout d'aillettes et augmentation du radiateur. Valeur reelle à avoir après convergence archi. | P59: o | Q59: IN PROGRESS | S59: 1 | T59: 0.2 | U59: =T59*S59 -> 0.2 | V59: 1 | W59: 1 | X59: 1 | Y59: 1 | Z59: 1 | AA59: 1 | AB59: 1 | AC59: 1 | AD59: 1 | AE59: 1 | AF59: 1 | AG59: 1 | AH59: 1 | AI59: 1 | AJ59: 1 | AK59: 1 | AL59: 1 | AM59: 1 | AN59: 1 | AO59: 1 | AP59: 1 | AQ59: 1 | AR59: 1 | AS59: 1 | AT59: 1 | AU59: 1 | AV59: 1 | AW59: 1 | AX59: 1 | AY59: 1 | AZ59: 1 | BA59: 1
B60: 45536 | C60: SPC_1 | D60: BCI_BODY | E60: TH | F60: MICHAEL BORE | G60: Renfort Aile AV | H60: Front fender reinforcer | I60: Removal - Wait SYNC1 simulation P1H | J60: 20/03/2026 a reboucler avec Cédric Choffel (DRE) LM 29/09/25 Attente Style mais pas de Renfort à aujourd'hui à reboucler avec Junghee | K60: PM-CM | M60: TBD | N60: -0.23 | P60: o | Q60: IN PROGRESS | R60: TBD | S60: 0 | T60: -1.2 | U60: =T60*S60 -> 0 | V60: 1 | W60: 1 | X60: 1 | Y60: 1 | Z60: 1 | AA60: 1 | AB60: 1 | AC60: 1 | AD60: 1 | AE60: 1 | AF60: 1 | AG60: 1 | AH60: 1 | AI60: 1 | AJ60: 1 | AK60: 1 | AL60: 1 | AM60: 1 | AN60: 1 | AO60: 1 | AP60: 1 | AQ60: 1 | AR60: 1 | AS60: 1 | AT60: 1 | AU60: 1 | AV60: 1 | AW60: 1 | AX60: 1 | AY60: 1 | AZ60: 1 | BA60: 1
A61: 302a | B61: 25/03/2025 | C61: SP1 | D61: BIW | E61: TH | F61: Franck Baillon (SP1)/ Cyrille P1X | G61: Appui cric | H61: new part | I61: Optim Longeron | J61: Si application SP1 ok SPC | L61: 25/03/2025 Transfert PtF Appui cric au TH : Fermeture Av Longeron | P61: o | Q61: DECIDED | S61: 1 | T61: 0.4 | U61: =T61*S61 -> 0.4 | V61: 1 | W61: 1 | X61: 1 | Y61: 1 | Z61: 1 | AA61: 1 | AB61: 1 | AC61: 1 | AD61: 1 | AE61: 1 | AF61: 1 | AG61: 1 | AH61: 1 | AI61: 1 | AJ61: 1 | AK61: 1 | AL61: 1 | AM61: 1 | AN61: 1 | AO61: 1 | AP61: 1 | AQ61: 1 | AR61: 1 | AS61: 1 | AV61: 1 | AW61: 1 | AX61: 1 | AY61: 1 | AZ61: 1 | BA61: 1
A62: 302c | B62: 46058 | C62: SP1 | D62: BIW | E62: PTF | G62: Battery housing HR | H62: Battery housing HR | I62: Renfort vs choc lateral | L62: 04/02/2026 : renforcement du bac batterie pour eviter les contacts avec les busbar en choc latéral. | P62: o | Q62: IN PROGRESS | S62: 0.75 | T62: 5.6 | U62: =T62*S62 -> 4.2 | V62: 1 | W62: 1 | X62: 1 | Y62: 1 | Z62: 1 | AA62: 1 | AB62: 1 | AC62: 1 | AD62: 1 | AE62: 1 | AF62: 1 | AG62: 1 | AH62: 1 | AI62: 1 | AJ62: 1 | AK62: 1 | AL62: 1 | AM62: 1 | AN62: 1 | AO62: 1 | AW62: 1 | AX62: 1
A63: 304 | B63: 08/04/2025 | C63: SP1 | D63: BIW | E63: TH | F63: Franck Baillon (SP1)/ Cyrille P1X | G63: SYNC3+ | H63: risk perfo | I63: Addon ChoC FR | J63: A checker pour SPC | L63: 01/07/2025 2Synthèse différente => CANCELLED 08/04/2025 Périmètre SYNC3+, add-ons au sujet 93B : : raidisseur inf pied avant, +0,341kg | P63: o | Q63: CANCELED | S63: 0.25 | T63: 0.341 | U63: =T63*S63 -> 0.08525 | V63: 1 | W63: 1 | X63: 1 | Y63: 1 | Z63: 1 | AA63: 1 | AB63: 1 | AC63: 1 | AD63: 1 | AE63: 1 | AF63: 1 | AG63: 1 | AH63: 1 | AI63: 1 | AJ63: 1 | AK63: 1 | AL63: 1 | AM63: 1 | AN63: 1 | AO63: 1 | AP63: 1 | AQ63: 1 | AR63: 1 | AS63: 1 | AV63: 1 | AW63: 1 | AX63: 1 | AY63: 1 | AZ63: 1 | BA63: 1
B64: 45536 | C64: SPC_1 | D64: BIW | E64: TH | F64: FRANK BAILLON | G64: Pare-Boue AR | H64: Mudguards | I64: P1H : Pare-Boue AR - version textil au lieu d'injecté. Avec patch NVH | J64: 24/03/2026 LM point CW 15 pour retour | M64: 500K€ | N64: -0.9 | P64: DECISION ? | Q64: IN PROGRESS | R64: TBD | S64: 1 | T64: -0.7 | U64: =T64*S64 -> -0.7 | V64: 1 | W64: 1 | X64: 1 | Y64: 1 | Z64: 1 | AA64: 1 | AB64: 1 | AC64: 1 | AD64: 1 | AE64: 1 | AF64: 1 | AG64: 1 | AH64: 1 | AI64: 1 | AJ64: 1 | AK64: 1 | AL64: 1 | AM64: 1 | AN64: 1 | AO64: 1 | AP64: 1 | AQ64: 1 | AR64: 1 | AS64: 1 | AT64: 1 | AU64: 1 | AV64: 1 | AW64: 1 | AX64: 1 | AY64: 1 | AZ64: 1 | BA64: 1
A65: 222 | B65: 45536 | C65: SPC_1 | D65: BIW | E65: TH | F65: MICHAEL BORE | G65: Aerofin | H65: Aerofin | I65: Impact aerofin sur tolerie de volet suite choix de concept aerofin embarqué sur volet | J65: LM 31/01/2026 A abandonner car toit bi-ton 06/10/2025 P3U Aerofin sur volet plastique J2U pas d'Aerofin sur volet tôle J1X sur volet tôle sujet à reboucler plus tard suvant le style, peu de gain masse | K65: PM | M65: 0 | N65: 0.7 | P65: o | Q65: CANCELED | R65: TBD | S65: 0 | T65: 0.5 | U65: =T65*S65 -> 0 | V65: 1 | W65: 1 | X65: 1 | Y65: 1 | Z65: 1 | AA65: 1 | AB65: 1 | AC65: 1 | AD65: 1 | AE65: 1 | AF65: 1 | AG65: 1 | AH65: 1 | AI65: 1 | AJ65: 1 | AK65: 1 | AL65: 1 | AM65: 1 | AN65: 1 | AO65: 1 | AP65: 1 | AQ65: 1 | AR65: 1 | AS65: 1 | AV65: 1 | AW65: 1 | AX65: 1 | AY65: 1 | AZ65: 1 | BA65: 1
B66: 45536 | C66: SPC_1 | D66: BIW | E66: TH | F66: MICHAEL BORE | G66: enjoliveur noir si feu AR T2 supp | H66: black trim | J66: 06/10/2025 Pas de PORO et T2 tout type, donc ligne à supprimer | K66: CM poro signature | L66: 26/06/2025 a reboucler après hypothèse projet | M66: 0 | N66: (15) | P66: o | Q66: CANCELED | R66: TBD | S66: 0 | T66: 1.7 | U66: =T66*S66 -> 0 | V66: 1 | W66: 1 | X66: 1 | Y66: 1 | Z66: 1 | AA66: 1 | AB66: 1 | AC66: 1 | AD66: 1 | AE66: 1 | AF66: 1 | AG66: 1 | AH66: 1 | AI66: 1 | AJ66: 1 | AK66: 1 | AL66: 1 | AM66: 1 | AN66: 1 | AO66: 1 | AP66: 1 | AQ66: 1 | AR66: 1 | AS66: 1 | AV66: 1 | AW66: 1 | AX66: 1 | AY66: 1 | AZ66: 1 | BA66: 1
B67: 45821 | C67: SPC_1 | D67: BIW | E67: PTF | G67: Compsite rear floor | H67: Raw material Change | I67: Matetrial Change | J67: 10/10/2025 a reboucler avec la base Nicolas Tessier | M67: TBD | N67: TBD | P67: o | Q67: CANCELED | U67: =T67*S67 -> 0 | AN67: 1 | AO67: 1 | AP67: 1 | AQ67: 1 | AR67: 1 | AS67: 1 | AT67: 1 | AU67: 1 | AV67: 1 | AW67: 1 | AX67: 1 | AY67: 1 | AZ67: 1 | BA67: 1
A68: 309 | B68: 03/06/2025 | C68: SP1 | D68: INT - SEATS/TRIMS | E68: TH | F68: Laurent VILLA | G68: Garniture Volet…. | H68: Tailgate trim... | I68: Optim idem P1H | J68: 24/06/2025 Laurent reboucle avec Sébatien Carrier sur SPC volet plastique donc pas de garniture latérale | K68: SFM | L68: 18/07/2025 Suite RD CW29(Volet Plastique) => Annulé 03/06/2025 CHANTIER : Garn inf revue maj à-0,2kg (ald-0,9kg) // Uniqut si volet ACIER ! 28/05/2025 CHANTIER MASSE : Idem P1H (Garn Vole- 0,9kg / Lat -0,64kg / Sup -0,260kg) | P68: o | Q68: CANCELED | S68: 0.25 | T68: -1.1 | U68: =T68*S68 -> -0.275 | V68: 1 | W68: 1 | X68: 1 | Y68: 1 | Z68: 1 | AA68: 1 | AB68: 1 | AC68: 1 | AD68: 1 | AE68: 1 | AF68: 1 | AG68: 1 | AH68: 1 | AI68: 1 | AJ68: 1 | AK68: 1 | AL68: 1 | AM68: 1 | AN68: 1 | AO68: 1 | AP68: 1 | AQ68: 1 | AR68: 1 | AS68: 1 | AV68: 1 | AW68: 1 | AX68: 1 | AY68: 1 | AZ68: 1 | BA68: 1
A69: celui | B69: 45821 | C69: SPC_1 | D69: BCI_BODY | E69: PTF | F69: Herve robert | G69: longeron composite | H69: Composite side member reinforcement | I69: Matetrial Change | L69: 20/06/25 : - 7,2 kg / nouvelle ref => Side crash reinforcement (retour FNR CW25 2025 -7,2kg à -4,6kg) 14/03/2024 : Workshop mass | M69: TOOLING | N69: 106€+60€ | P69: o | Q69: IN PROGRESS | S69: 1 | T69: -7.2 | U69: =T69*S69 -> -7.2 | AN69: 1 | AO69: 1 | AP69: 1 | AS69: 1 | AW69: 1 | AX69: 1
B70: 45821 | C70: SPC_1 | D70: BCI_BODY | E70: TH | F70: MICHAEL BORE | G70: Aile avant Alu | I70: Matetrial Change | J70: 06/03/2026 LM : pas d'aile alu pour P3U - à supprimer 10/10/2025 a reboucler avec la base Benoit Allais | M70: 800k€ | N70: 7.7 | P70: DECISION ? | Q70: CANCELED | S70: 1 | T70: -1.5 | U70: =T70*S70 -> -1.5 | AN70: 1 | AO70: 1 | AP70: 1 | AQ70: 1 | AR70: 1
B71: 45821 | C71: SPC_1 | D71: BCI_BODY | E71: TH | F71: Hervet Lambin | G71: Portes Alu | H71: Door | I71: Matetrial Change | J71: 10/10/2025 refusé par le projet ligne à supprimer | M71: TBD | N71: TBD | P71: o | Q71: CANCELED | S71: 0 | U71: =T71*S71 -> 0
A72: 317a | B72: 03/06/2025 | C72: SP1 | D72: INT - SEATS/TRIMS | E72: TH | F72: HALIM | G72: P2P | H72: P2P | L72: 03/06/2025 CHANTIER MASSE : Revoir la décli | P72: WS | Q72: DECIDED | S72: 0 | T72: -2 | U72: =T72*S72 -> 0 | V72: 1 | W72: 1 | X72: 1 | Y72: 1 | Z72: 1 | AA72: 1 | AB72: 1 | AC72: 1 | AD72: 1 | AE72: 1 | AF72: 1 | AG72: 1 | AH72: 1 | AI72: 1 | AJ72: 1 | AK72: 1 | AL72: 1 | AM72: 1 | AS72: 1 | AT72: 1 | AU72: 1 | AV72: 1 | AW72: 1 | AX72: 1 | AY72: 1 | AZ72: 1 | BA72: 1
A73: 317b | B73: 03/06/2025 | C73: SP1 | D73: INT - SEATS/TRIMS | E73: TH | G73: P2P (supports) | I73: Revoir la diversité | L73: 03/06/2025 CHANTIER MASSE : Supprimer les supports du TT > Impact sur la diversité des GLC | P73: o | Q73: CANCELED | S73: 0.25 | T73: -0.7 | U73: =T73*S73 -> -0.175 | V73: 1 | W73: 1 | X73: 1 | Y73: 1 | Z73: 1 | AA73: 1 | AB73: 1 | AC73: 1 | AD73: 1 | AE73: 1 | AF73: 1 | AG73: 1 | AH73: 1 | AI73: 1 | AJ73: 1 | AK73: 1 | AL73: 1 | AM73: 1 | AN73: 1 | AO73: 1 | AP73: 1 | AQ73: 1 | AR73: 1 | AS73: 1 | AV73: 1 | AW73: 1 | AX73: 1 | AY73: 1 | AZ73: 1 | BA73: 1
B74: 45940 | C74: SPC_1 | D74: DIW | E74: TH | F74: Damien Demougeot/ Hervet Lambin | G74: Module de Porte AV et AR | H74: Door | J74: 13/03/2026 LM en cours d'application 20/02/2026 LM - application non confirmé en CW 08_26 06/02/2026 LM - Réunion pour validation de l'application en CW 07_26 24/10/2025 Après calcul par le métier, pas de gain masse sur cet item - sujet stain by 10/10/2025 à reboucler avec Herve Lambin | M74: TBD | N74: TBD | P74: o | Q74: IN PROGRESS | S74: 1 | T74: -1.5 | U74: =T74*S74 -> -1.5 | AN74: 1 | AO74: 1 | AP74: 1 | AQ74: 1 | AR74: 1 | AS74: 1 | AT74: 1 | AU74: 1 | AV74: 1 | AW74: 1 | AX74: 1 | AY74: 1 | AZ74: 1 | BA74: 1
A75: 202 | B75: 11/06/2025 | C75: SPC_1 | D75: DIW | E75: TH | F75: Hervet Lambin | G75: Rft Choc LAT Porte AV | H75: BIW/ DIW process | I75: Embout à chaud PHS950 YS1500T => PHS1400-Y1800T et réduction épaisseur | J75: 06/02/2026 LM sujet déjà appliqué sur SPC_1 sujet à supprimer 10/10/2025 à reboucler avec Herve Lambin question à revérifier pour SPC-1 | L75: 02/07/2025 CANCELLED : Ep.mini déjà atteinte (chgt de matière possible mais aurait nécessité une dimintution d'épasisseur) 11/06/2025 A ré-évaluer 04/11/2024 Idem post Go-Calcul SYNC3 08/07/2024 Retour calcul SYNC3 (Go calcul Nov => 2025?) Pièce en Embout à chaud | P75: o | Q75: DECIDED | S75: 0 | T75: -0.1 | U75: =T75*S75 -> 0 | V75: 1 | W75: 1 | X75: 1 | Y75: 1 | Z75: 1 | AA75: 1 | AB75: 1 | AC75: 1 | AD75: 1 | AE75: 1 | AF75: 1 | AG75: 1 | AH75: 1 | AI75: 1 | AJ75: 1 | AK75: 1 | AL75: 1 | AM75: 1 | AN75: 1 | AO75: 1 | AP75: 1 | AQ75: 1 | AR75: 1 | AS75: 1 | AV75: 1 | AW75: 1 | AX75: 1 | AY75: 1 | AZ75: 1 | BA75: 1
B76: 45536 | C76: SPC_1 | D76: DIW | E76: TH | F76: Hervet Lambin | G76: Rft Choc LAT Porte D/G AR | H76: Hot Stamping lat reinfor | I76: Embout à chaud | J76: 06/02/2026 LM sujet déjà appliqué sur SPC_1 sujet à supprimer 10/10/2025 à reboucler avec Herve Lambin question à revérifier pour SPC-1 | K76: PM-CM | M76: 104 | N76: -0.8 | P76: o | Q76: DECIDED | R76: TBD | S76: 0 | T76: -0.5 | U76: =T76*S76 -> 0 | Y76: 1 | Z76: 1 | AC76: 1 | AD76: 1 | AH76: 1 | AI76: 1 | AL76: 1 | AM76: 1 | AQ76: 1 | AR76: 1 | AV76: 1 | AZ76: 1 | BA76: 1
A77: 26 | B77: 45758 | C77: SP2 | D77: BCI_CHASSIS | E77: PTF | G77: Pivot alu | H77: Longitudinal member | I77: Changement de matière | L77: 14/03/2024 : Workshop mass | N77: 40 | Q77: CANCELED | R77: TBD | S77: 1 | T77: -1 | U77: =T77*S77 -> -1 | V77: 1 | W77: 1 | X77: 1 | AE77: 1 | AF77: 1 | AG77: 1 | AQ77: 1 | AZ77: 1
A78: 308 | B78: 06/06/2025 | C78: SP1 | D78: INT - SEATS/TRIMS | E78: TH | F78: HALIM | G78: Insono Coffre Rds | H78: Trunk soundproofing (Rds) | I78: TRUNK SOUNDPROOF | J78: 02/03/2026 LM à Supprimer car non appliqué sur P3U 24/06/2025 à checker en RFQ avec les FNR | K78: SFM | L78: 06/06/2025 Que sur le ML ! 23/05/2025 A supprimer TT | P78: o | Q78: CANCELED | S78: 0.25 | T78: -0.15 | U78: =T78*S78 -> -0.0375 | V78: 1 | W78: 1 | X78: 1 | Y78: 1 | Z78: 1 | AA78: 1 | AB78: 1 | AC78: 1 | AD78: 1 | AE78: 1 | AF78: 1 | AG78: 1 | AH78: 1 | AI78: 1 | AJ78: 1 | AK78: 1 | AL78: 1 | AM78: 1 | AN78: 1 | AO78: 1 | AP78: 1 | AQ78: 1 | AR78: 1 | AS78: 1 | AT78: 1 | AU78: 1 | AV78: 1 | AW78: 1 | AX78: 1 | AY78: 1 | AZ78: 1 | BA78: 1
A79: 50 | C79: SP2 | D79: BCI_BODY | E79: PTF | G79: Rear Crashbeam | I79: STEP 2 : Ecart concurrence. -3 kg | L79: 14/03/2024 : Workshop mass | N79: 10 | Q79: CANCELED | R79: TBD | S79: 0.5 | T79: -3 | U79: =T79*S79 -> -1.5 | V79: 1 | W79: 1 | X79: 1 | AE79: 1 | AF79: 1 | AG79: 1 | AQ79: 1 | AZ79: 1
A80: 58 | C80: SP2 | D80: BCI_DOORS | E80: TH | G80: Portes ALU | H80: Aluminum doors | L80: 14/03/2024 : Workshop mass | M80: 0 | N80: 200 | Q80: CANCELED | R80: TBD | S80: 1 | T80: -22 | U80: =T80*S80 -> -22 | V80: 1 | W80: 1 | X80: 1 | AE80: 1 | AF80: 1 | AG80: 1 | AQ80: 1 | AZ80: 1
A81: 59 | C81: SP2 | D81: BCI_BODY | E81: TH | G81: Pavillon ALU | H81: Alloy roof | L81: 14/03/2024 : Workshop mass | N81: 15 | Q81: CANCELED | R81: TBD | S81: 0.25 | T81: -4 | U81: =T81*S81 -> -1 | V81: 1 | W81: 1 | X81: 1 | AE81: 1 | AF81: 1 | AG81: 1 | AQ81: 1 | AZ81: 1
A82: 97a | C82: SP2 | D82: BCI_BODY | E82: PTF | G82: SAC AR | H82: Rear Repair Beam | I82: Optimisation vs Choc_répa => voir classe d'assurance ! | L82: 14/03/2024 : Workshop mass | N82: 10 | Q82: CANCELED | R82: TBD | S82: 1 | T82: -3 | U82: =T82*S82 -> -3 | V82: 1 | W82: 1 | X82: 1 | AE82: 1 | AF82: 1 | AG82: 1 | AQ82: 1 | AZ82: 1
A83: 97b | C83: SP2 | D83: BCI_BODY | E83: PTF | G83: SAC AR | H83: Rear Repair Beam | I83: Alloy => Plastic def | L83: 14/03/2024 : Workshop mass | N83: 10 | Q83: CANCELED | R83: TBD | S83: 1 | T83: -2 | U83: =T83*S83 -> -2 | V83: 1 | W83: 1 | X83: 1 | AE83: 1 | AF83: 1 | AG83: 1 | AQ83: 1 | AZ83: 1
A84: 99 | C84: SP2 | D84: PRS_EDM | E84: PWT | G84: Moteur elec (EDM) | H84: EDM | I84: EDM mass reduction portfolio under investigation for C sample :  -2,5kg potential at EDM side Rotor/stator length reduction : around -2kg (20% confidence). Investigation started. : Go/No Go CW37 Housing optimisation : -0,5 Kg (20% confidence) balance between mass reduction, NVH and stiffness impact to optimize and evaluate :_x000B_Go/No Go CW34 | L84: 14/03/2024 : Workshop mass | Q84: CANCELED | R84: TBD | S84: 1 | T84: -2.5 | U84: =T84*S84 -> -2.5 | V84: 1 | W84: 1 | X84: 1 | AE84: 1 | AF84: 1 | AG84: 1 | AQ84: 1 | AZ84: 1
A85: 103 | C85: SP2 | D85: PRS_BATT | E85: PWT | G85: Battery 80kWhu | I85: 80kWhu chemistry 577->615Wh/L | L85: 14/03/2024 : Workshop mass | Q85: CANCELED | R85: TBD | S85: 1 | T85: -22 | U85: =T85*S85 -> -22 | V85: 1 | W85: 1 | X85: 1 | AE85: 1 | AF85: 1 | AG85: 1 | AQ85: 1 | AZ85: 1
A86: 105 | C86: SP2 | D86: BCI_BODY | E86: PTF | G86: techno BCI | I86: perimeter to be defined | L86: 14/03/2024 : Workshop mass | Q86: CANCELED | R86: TBD | S86: 0.5 | T86: -5 | U86: =T86*S86 -> -2.5 | V86: 1 | W86: 1 | X86: 1 | AE86: 1 | AF86: 1 | AG86: 1 | AQ86: 1 | AZ86: 1
A87: 49 | C87: SP2 | D87: BCI_BODY | E87: PTF | G87: Front & rear Crashbeam | I87: STEP2 : change to alu | L87: 14/03/2024 : Workshop mass | N87: 16 | P87: o | Q87: DECIDED | R87: TBD | S87: 0.65 | T87: -7 | U87: =T87*S87 -> -4.55 | V87: 1 | W87: 1 | X87: 1 | Y87: 1 | AA87: 1 | AB87: 1 | AC87: 1 | AE87: 1 | AF87: 1 | AG87: 1 | AH87: 1 | AJ87: 1 | AK87: 1 | AL87: 1
A88: 109 | C88: SP2 | D88: SWX_EHE | E88: PTF | G88: Batterie 12V | I88: Li-ON / L1 / AGS | L88: 14/03/2024 : Workshop mass | N88: 50 | Q88: CANCELED | R88: TBD | S88: 1 | T88: -8 | U88: =T88*S88 -> -8 | V88: 1 | W88: 1 | X88: 1 | AE88: 1 | AF88: 1 | AG88: 1 | AQ88: 1 | AZ88: 1
A89: 117 | C89: SP2 | D89: BCI_FRSD | E89: TH | G89: Aile ALU | H89: Fr Fender ALLOY | I89: Alloy ald Steel | L89: setp 3 | Q89: CANCELED | R89: TBD | S89: 0.5 | T89: -1.4 | U89: =T89*S89 -> -0.7 | V89: 1 | W89: 1 | X89: 1 | AE89: 1 | AF89: 1 | AG89: 1 | AQ89: 1 | AZ89: 1
A90: 26 | C90: SP2 | D90: BCI_FRSD | E90: TH | G90: Volet | H90: Steel tailgate | I90: Changement de matière | J90: 08/10/2024: BDD à jour plastic | K90: PM CW30 | L90: 14/03/2024 : Workshop mass | N90: 52 | P90: o | Q90: DECIDED | R90: TBD | S90: 1 | T90: 5 | U90: =T90*S90 -> 5 | AQ90: 1 | AZ90: 1
A91: 63 | C91: SP2 | D91: BCI_BODY | E91: TH | G91: techno BCI | I91: emboutissage à chaud, colle, etc .. | L91: 11/04/2024 : Workshop mass | Q91: CANCELED | R91: TBD | S91: 0.5 | T91: -5 | U91: =T91*S91 -> -2.5 | V91: 1 | W91: 1 | X91: 1 | AE91: 1 | AF91: 1 | AG91: 1 | AQ91: 1 | AZ91: 1
A92: 26 | C92: SPC_1 | D92: BCI_CHASSIS | E92: PTF | F92: FREDERIC GUINGAND | G92: Triangle alu | I92: Changement de matière | L92: Doublon | N92: 40 | P92: ? | Q92: CANCELED | R92: Step1 | S92: 1 | T92: -1 | U92: =T92*S92 -> -1 | V92: 1 | W92: 1 | X92: 1 | AE92: 1 | AF92: 1 | AG92: 1 | AQ92: 1 | AZ92: 1
B93: 45536 | C93: SPC_1 | D93: INT - SEATS/TRIMS | E93: TH | F93: HALIM | G93: Insono Tablier Habitacle | H93: Cabin firewall soundproofing | I93: Insono tablier habitacle (Spécifique FNR ADLER "Le MAPLITE", brevet). Masse à communiquée par Laurent. Attente RFQ). (-10% de masse & -10% de TPC) | J93: 02/03/2026 LM à Supprimer car non appliqué sur P3U 24/06/2025 à checker en RFQ avec les FNR | K93: SFM | L93: Check avec le fournisseur | M93: TBD | N93: -1.2 | P93: o | Q93: CANCELED | R93: TBD | S93: 0.1 | T93: -0.42 | U93: =T93*S93 -> -0.042 | V93: 1 | W93: 1 | X93: 1 | Y93: 1 | Z93: 1 | AA93: 1 | AB93: 1 | AC93: 1 | AD93: 1 | AE93: 1 | AF93: 1 | AG93: 1 | AH93: 1 | AI93: 1 | AJ93: 1 | AK93: 1 | AL93: 1 | AM93: 1 | AN93: 1 | AO93: 1 | AP93: 1 | AQ93: 1 | AR93: 1 | AS93: 1 | AT93: 1 | AU93: 1 | AV93: 1 | AW93: 1 | AX93: 1 | AY93: 1 | AZ93: 1 | BA93: 1
A94: 107 | C94: SP2 | D94: SWX_EHE | E94: PTF | G94: Cable mode3 | I94: to be removed to MOPAR | L94: 23/07/24 : Mode 3 (11kW) 14/03/2024 : Workshop mass | N94: -45 | P94: x | Q94: DECIDED | R94: TBD | S94: 1 | T94: -2.6 | U94: =T94*S94 -> -2.6 | V94: 1 | W94: 1 | X94: 1 | AA94: 1 | AB94: 1 | AE94: 1 | AF94: 1 | AG94: 1 | AJ94: 1 | AK94: 1
B95: 45536 | C95: SPC_1 | D95: INT - SEATS/TRIMS | E95: TH | F95: HALIM | G95: Pavillon | H95: Headliner | I95: Pavillon sans interface poignées sur la version SERENITY LONG RANGE. Actuellement, les 4 poignées sont en référence sans diversité | J95: 02/03/2026 LM à Supprimer car non appliqué sur P3U 24/06/2025 à vérifier plus tard Proposition d'enlever 2 poignées selon la déclinaison.* A partager avec le produit si accord | K95: CM | M95: 0 | N95: -0.1 | P95: o | Q95: CANCELED | R95: TBD | S95: 0.25 | T95: -0.24 | U95: =T95*S95 -> -0.06 | V95: 1 | W95: 1 | X95: 1 | Y95: 1 | Z95: 1 | AA95: 1 | AB95: 1 | AC95: 1 | AD95: 1 | AE95: 1 | AF95: 1 | AG95: 1 | AH95: 1 | AI95: 1 | AJ95: 1 | AK95: 1 | AL95: 1 | AM95: 1 | AN95: 1 | AO95: 1 | AP95: 1 | AQ95: 1 | AR95: 1 | AS95: 1 | AT95: 1 | AU95: 1 | AV95: 1 | AW95: 1 | AX95: 1 | AY95: 1 | AZ95: 1 | BA95: 1
B96: 45536 | C96: SP2 | D96: BCI_BODY | E96: TH | G96: Enjoliveur passage de roue | H96: Wheel Cladding | I96: Remove Wheel claddings (like D41) : -0,5kg / part | J96: 24/09/2024 LM - dossier chez le style Préciser les voitures qui embarquent QCDP rocker trim + warning same front mudguard | K96: PM | M96: -1638K€ | N96: (-21.2) | P96: o | Q96: CANCELED | R96: TBD | S96: 0 | T96: -2 | U96: =T96*S96 -> 0 | V96: 1 | W96: 1 | X96: 1 | Y96: 1 | AA96: 1 | AB96: 1 | AC96: 1 | AE96: 1 | AF96: 1 | AG96: 1 | AH96: 1 | AJ96: 1 | AK96: 1 | AL96: 1 | AQ96: 1 | AZ96: 1
B97: 45536 | C97: SP2 | D97: BCI_BODY | E97: TH | G97: Raidisseur | H97: Stiffener | I97: Si Renfort choc lat en EMB à chaud : Suppression raidisseurs --> Attente résultat SYNC1 SP1 pour confirmer si suppression possible sans passer les renfort choc lat en EMBOUT à chaud | J97: 28/04/2025 lm : sujet appliqué BDD OK à passer à decided avec Stéphane QCDP SP1 ok : -1,65kg | K97: PM-CM | L97: preciser le sujet ? | M97: +224 K€ | N97: -2.6 | P97: o | Q97: DECIDED | R97: TBD | S97: 1 | T97: -2 | U97: =T97*S97 -> -2 | V97: 1 | W97: 1 | X97: 1 | Y97: 1 | AA97: 1 | AB97: 1 | AC97: 1 | AE97: 1 | AF97: 1 | AG97: 1 | AH97: 1 | AJ97: 1 | AK97: 1 | AL97: 1 | AQ97: 1 | AZ97: 1
A98: 231 | C98: SP1 | D98: PRS | E98: PWT | G98: IDCM | I98: Pour P1X_HR : Passage en 7kW | N98: +183€ | P98: o | Q98: DECIDED | S98: 1 | T98: -4.4 | U98: =T98*S98 -> -4.4
A99: 19 | C99: SP1 | D99: PRS | E99: PTF | G99: Supports Complémentaires | I99: Provision pour risques d'ajout de support | L99: 19/06/2024 : L'etat actuel de l'architecture permet de dire qu'il n'y aura plus de support complémentaire. 23/10/2023 : Création de la piste | N99: =T99*1 -> 1 | P99: o | Q99: CANCELED | R99: TBD | S99: 0.25 | T99: 1 | U99: =T99*S99 -> 0.25
C100: SP2 | D100: BCI_FRSD | E100: TH | G100: Becquet | H100: remove spolier | I100: Remove spoiler (BDD : 4,23 Kg = masse P24 sans le CHMSL, Becquet C41 : 2,2 Kg masse PLM) | J100: Gain masse quand on passe d’un spoiler type P24 à un spoiler C41 "plus simple" (sans faisceaux….) --> Déjà appliqué et passé en ref BDD le 02/07/2024 | K100: PM CW30 | L100: 24/09/2024 -LM- A passer en decided A presicer : spolier en REF | M100: invest volet plastique | N100: -28 | P100: o | Q100: DECIDED | R100: TBD | S100: 1 | T100: -1.5 | U100: =T100*S100 -> -1.5
...

Sheet Feuil1
B3: Ajouter JEEP
B5: Sujet 1
B6: A mettre dans le PTF | C6: Volet P3U => 8 et 10kg d'impact masse du volet P3U vs. concept P1X remis aux dimensions P3U (Rodolphe).
B7: suppression du risk a voir avec adpatation | C7: Fuel tank => 40 (44, +1) et 45 (47, +0,5) HEV préssurisé / non préssurisé MHEV (TPC ?). Goulotte métal. Voir le réservoir de CMP annoncé à 9,3kg avec une capacité de 44kg
B8: dans le PTF | C8: Door module => -1,5kg, Marc Nespoulos
B9: dans le PTF | C9: Siège rang 2 => 40/20/40 P3U. 40/60. Masse 2,4.
B10: dans le PTF | C10: Magic handle si déclinaison. => 0,8
B11: A mettre dans le PTF | C11: 17'' => 235/60R17 sur les MHEV de J1X (=> J2U ? => P3U ?). => Adrien 4kg à confirmer
B12: A mettre dans le PTF | C12: Headlamp P3U. Proposition de déclinaison entry => -6kg
B13: A mettre dans le PTF | C13: Poutre répa arrière => 6,6kg sur P1X versus 3,7kg sur une Yaris Cross, 3,1 sur P21 pour Hybride
B14: A mettre dans le PTF | C14: Brake disk ald eDrum => 1,5kg ? Avec ajout park lock
B15: A mettre dans le PTF | C15: COI XV = -0,5kg
B16: A mettre dans le PTF | C16: update Nouveau point C Masse ?
B17: A mettre dans le PTF | C17: pivot alu
... B22: A mettre dans le PTF | C22: Volet plastique pour jeep
C23: Coffre entry peugeot ?
B24: A mettre dans le PTF | C24: Rear lamp T2 supp jeep
B25: RISK | C25: P2P pour JEEP = 2kg
B26: A mettre dans le PTF | C26: optim tapis XHEV / BEV =-1kg / BEV
B29: Sujet 2
B30: A mettre dans le PTF | C30: Niv 0 a evoquer
B32: Sujet 3
B33: dans le PTF | C33: process -4%
B35: Sujet 4
B36: recherche d'idée

Sheet TcD SPC
A1: P3U HR FWD | D1: P3U MHEV FWD | G1: P3U HEV FWD
A2: P3U HR 63 FWD€ | B2: 1 | D2: P3U MHEV FWD€ | E2: 1 | G2: P3U HEV FWD€ | H2: 1
A3: COTATION (*) | B3: IN PROGRESS | D3: COTATION (*) | E3: IN PROGRESS | G3: COTATION (*) | H3: IN PROGRESS
A5: Étiquettes de lignes | B5: Somme de Ponderated mass / Ratio (kg*%) | D5: Étiquettes de lignes | E5: Somme de Ponderated mass / Ratio (kg*%) | G5: Étiquettes de lignes | H5: Somme de Ponderated mass / Ratio (kg*%)
A6: PTF | B6: -4.715 | D6: PTF | E6: -16.80275 | G6: PTF | H6: -16.80275
A7: BCI_BODY | B7: -8.55 | D7: BCI_CHASSIS | E7: -1.3 | G7: BCI_CHASSIS | H7: -1.3
A8: BCI_CHASSIS | B8: 0 | D8: BIW | E8: -3.38775 | G8: BIW | H8: -3.38775
A9: BIW | B9: 4.2 | D9: PHES | E9: -9.125 | G9: PHES | H9: -9.125
A10: PHES | B10: 0.075 | D10: SWX/EE | E10: -2.99 | G10: SWX/EE | H10: -2.99
A11: SWX/EE | B11: -0.44 | D11: TH | E11: -33.495 | G11: PWT | H11: 1.7
A12: PWT | B12: -1.15 | D12: All | E12: -17.5 | G12: PRS | H12: 1.7
A13: PRS | B13: -1.15 | D13: BCI_BODY | E13: 0 | G13: TH | H13: -33.495
A14: TH | B14: -29.495 | D14: BCI_CHASSIS | E14: -4 | G14: All | H14: -17.5
A15: All | B15: -17.5 | D15: BIW | E15: -0.87 | G15: BCI_BODY | H15: 0
A16: BCI_BODY | B16: 0 | D16: DIW | E16: -1.5 | G16: BCI_CHASSIS | H16: -4
A17: BIW | B17: -0.87 | D17: FRSD | E17: -7.2 | G17: BIW | H17: -0.87
... A21: INT - SEATS/TRIMS | B21: -1.86 | D21: Total général | E21: -50.29775 | G21: INT - SEATS/TRIMS | H21: -1.86
A22: SWX/EE | B22: -0.4 | G22: SWX/EE | H22: -0.4
A23: Total général | B23: -35.36 | G23: Total général | H23: -48.59775
A33: J1X SR FWD | D33: J1X MHEV FWD | G33: J1X HEV FWD
A34: J1X SR FWD€ | B34: 1 | D34: J1X MHEV FWD€ | E34: 1 | G34: J1X HEV FWD€ | H34: 1
A35: COTATION (*) | B35: IN PROGRESS | D35: COTATION (*) | E35: IN PROGRESS | G35: COTATION (*) | H35: IN PROGRESS
A37: Étiquettes de lignes | B37: Somme de Ponderated mass / Ratio (kg*%) | D37: Étiquettes de lignes | E37: Somme de Ponderated mass / Ratio (kg*%) | G37: Étiquettes de lignes | H37: Somme de Ponderated mass / Ratio (kg*%)
A38: PTF | B38: -9.29 | D38: PTF | E38: -16.115 | G38: PTF | H38: -16.115
A39: BCI_BODY | B39: -8.925 | D39: BCI_CHASSIS | E39: -1.3 | G39: BCI_CHASSIS | H39: -1.3
A40: BCI_CHASSIS | B40: 0 | D40: BIW | E40: -2.7 | G40: BIW | H40: -2.7
A41: BIW | B41: 0 | D41: PHES | E41: -9.125 | G41: PHES | H41: -9.125
A42: PHES | B42: 0.075 | D42: SWX/EE | E42: -2.99 | G42: SWX/EE | H42: -2.99
A43: SWX/EE | B43: -0.44 | D43: TH | E43: -29.095 | G43: PWT | H43: 1.7
A44: PWT | B44: 0.35 | D44: All | E44: -17.5 | G44: PRS | H44: 1.7
A45: PRS | B45: 0.35 | D45: BCI_BODY | E45: 0 | G45: TH | H45: -28.955
A46: TH | B46: -24.955 | D46: BCI_CHASSIS | E46: -4 | G46: All | H46: -17.5
A47: All | B47: -17.5 | D47: BIW | E47: -0.87 | G47: BCI_BODY | H47: 0
A48: BCI_BODY | B48: 0 | D48: DIW | E48: -1.5 | G48: BCI_CHASSIS | H48: -4
A49: BIW | B49: -0.87 | D49: FRSD | E49: -2.7 | G49: BIW | H49: -0.87
... A53: INT - SEATS/TRIMS | B53: -1.86 | D53: Total général | E53: -45.21 | G53: INT - SEATS/TRIMS | H53: -1.86
A54: SWX/EE | B54: -0.4 | G54: SWX/EE | H54: -0.4
A55: Total général | B55: -33.895 | G55: Total général | H55: -43.37
A67: J2U HR FWD | D67: J2U MHEV FWD | G67: J2U HEV FWD
A68: J2U HR 63 FWD€ | B68: 1 | D68: J2U MHEV FWD | E68: 1 | G68: J2U HEV FWD | H68: 1
A69: COTATION (*) | B69: IN PROGRESS | D69: COTATION (*) | E69: IN PROGRESS | G69: COTATION (*) | H69: IN PROGRESS
A71: Étiquettes de lignes | B71: Somme de Ponderated mass / Ratio (kg*%) | D71: Étiquettes de lignes | E71: Somme de Ponderated mass / Ratio (kg*%) | G71: Étiquettes de lignes | H71: Somme de Ponderated mass / Ratio (kg*%)
A72: PTF | B72: -4.715 | D72: PTF | E72: -18.02775 | G72: PTF | H72: -16.80275
A73: BCI_BODY | B73: -8.55 | D73: BCI_BODY | E73: -1.225 | G73: BCI_CHASSIS | H73: -1.3
A74: BCI_CHASSIS | B74: 0 | D74: BCI_CHASSIS | E74: -1.3 | G74: BIW | H74: -3.38775
A75: BIW | B75: 4.2 | D75: BIW | E75: -3.38775 | G75: PHES | H75: -9.125
A76: PHES | B76: 0.075 | D76: PHES | E76: -9.125 | G76: SWX/EE | H76: -2.99
A77: SWX/EE | B77: -0.44 | D77: SWX/EE | E77: -2.99 | G77: PWT | H77: 1.7
A78: PWT | B78: -1.15 | D78: TH | E78: -28.955 | G78: PRS | H78: 1.7
A79: PRS | B79: -1.15 | D79: All | E79: -17.5 | G79: TH | H79: -24.955
A80: TH | B80: -24.955 | D80: BCI_BODY | E80: 0 | G80: All | H80: -17.5
A81: All | B81: -17.5 | D81: BCI_CHASSIS | E81: -4 | G81: BCI_BODY | H81: 0
A82: BCI_BODY | B82: 0 | D82: BIW | E82: -0.87 | G82: BIW | H82: -0.87
A83: BIW | B83: -0.87 | D83: DIW | E83: -1.5 | G83: DIW | H83: -1.5
... A88: SWX/EE | B88: -0.4 | D88: Total général | E88: -46.98275 | G88: Total général | H88: -40.05775
A89: Total général | B89: -30.82

Sheet export SP1 S26
A1: Topic Nr | B1: Creation Date | C1: Responsible | D1: Functions | E1: BVH / PWT / Tophat | F1: Désignation : Ensemble / Piéces FR | G1: Désignation : Ensemble / Piéces ENG | H1: Description | I1: Comments BCI SP2 | J1: Date | K1: Mass comments (changes, dates, …) | L1: Invest impact | M1: TPC Impact (€) | N1: Next steps | O1: Decision expected for ? | P1: COTATION (*) | Q1: Priorization | R1: Confidence % | S1: Mass kg (*) | T1: Ponderated mass / Ratio (kg*%) | U1: O3H HR 63 FWD€ | V1: O3H XR 80 FWD€ | W1: O3H XR 80 AWD perfo € | X1: O3W 63 kWhu LFP FWD€ | Y1: O3W 80 kWhu NMx FWD€ | Z1: O3H MHEV FWD€ | AA1: O3W MHEV FWD€ | AB1: P3S HR 63 FWD€ | AC1: P3S XR 80 FWD€ | AD1: P3S XR 80 AWD perfo € | AE1: P3W 63 kWhu LFP FWD€ | AF1: P3W 80 kWhu NMx FWD€ | AG1: P3S MHEV FWD€ | AH1: P3WMHEV FWD€ | AI1: O1X HR 63 FWD€ | AJ1: O1X XR 80 FWD€ | AK1: O1X XR 80 AWD perfo € | AL1: O1X MHEV FWD€ | AM1: P1H MHEV | AN1: P1X MHEV
A2: 215 | B2: 45758 | C2: SP1 | D2: SWX/EE | E2: PTF | F2: Goulotte faisceaux moteur | G2: Optimisation | K2: 25/09/2024 : Compté dans le périmètre TH. 18/07/2024 : issu GT EE scope du 15/07/2024 | O2: o | P2: IN PROGRESS | Q2: TBD | R2: 0.5 | S2: 0.02 | T2: =S2*R2 -> 0.01 | U2: 1 | V2: 1 | W2: 1 | X2: 1 | Y2: 1 | Z2: 1 | AA2: 1 | AB2: 1 | AC2: 1 | AD2: 1 | AE2: 1 | AF2: 1 | AG2: 1 | AH2: 1 | AI2: 1 | AJ2: 1 | AK2: 1 | AL2: 1
A4: N° du sujet | B4: Date de mise à jour | C4: Métier (*) | D4: Métier (*) | E4: PTF/PRS/TH | F4: FR Désignation : Ensemble / Piéces | G4: Typologie : Raw Mat/Style/Process…. | H4: Description | K4: Commentaires masse tracer les changements apportés, par date | P4: COTATION (*) | R4: % confiance | S4: Masse kg (*)
A5: 54 | B5: 11/06/2025 | C5: SP1 | D5: INT - SEATS/TRIMS | E5: TH | F5: Assise Rg1 - Tissus | G5: optim design | H5: Retour frns | K5: 11/06/2025 Style non gélé , mais orientation en cours avec Tie down donc Potentiel a descendre a 25% [ald50%] 18/11/2024 Maj suite SYNC3 =>-0,8kg*50% (ald 25%*-0,2kg) 05/11/2024 Reporté 2025 25/09/2024 EN attente choirs frns => Fin Sept 11/07/2024 choix frns CW39 | P5: IN PROGRESS | R5: 0.25 | S5: -0.8 | T5: =S5*R5 -> -0.2
A6: 55 | B6: 11/06/2025 | C6: SP1 | D6: INT - SEATS/TRIMS | E6: TH | F6: Assise Rg2 - Tissus | G6: optim design | H6: Retour frns | K6: 11/06/2025 Style non gélé , mais orientation en cours avec Tie down donc Potentiel a descendre a 25% [ald 50%] 18/11/2024 Maj suite SYNC3=-0,6kg*50% (ald-0,65kg*25%) 05/11/2024 Reporté 2025 25/09/2024 EN attente choirs frns => Fin Sept 11/07/2024 choix frns CW39 | P6: IN PROGRESS | R6: 0.25 | S6: -0.6 | T6: =S6*R6 -> -0.15
A7: 92 | B7: 06/06/2025 | C7: SP1 | D7: DIW | E7: TH | F7: Portes | G7: BIW/ DIW process | H7: Impact masse demande DIR pour diminuer la diversité (ép. : dizaine supérieure) | K7: 06/06/2025 Niveau de risk diminué à 25%, Final step : fin de SYNC3 04/11/2024 Décalage planning > Post Go_Calcul 12/07/2024 En attente des résultats SYNC3 21/03/2024 A valoriser suite aux résultats SYNC2 (voir avec RM) 14/03/2024 New / A décider avant engagement SYNC3 | P7: IN PROGRESS | R7: 0.25 | S7: 1.2 | T7: =S7*R7 -> 0.3
A8: 105b | B8: 28/05/2025 | C8: SP1 | D8: BIW | E8: TH | F8: Optimass P1X | G8: optimass process | H8: Calculs : Choc Fr&Lat, R14 Rg2, NVH | K8: 28/05/2025 CHANTIER MASSE : A construire | P8: IN PROGRESS | R8: 0.5 | S8: -1.8 | T8: =S8*R8 -> -0.9
A9: 122 | B9: 27/06/2024 | C9: SP1 | D9: SWX/EE | E9: TH | F9: Faisceaux_LV | H9: Cross section optimization | K9: 27/06/2024 Estim à -0,3kg (-50%) 25/03/2024 A développer à l'aide des prochains plans faisceaux : X0 13/03/2024b New | P9: IN PROGRESS | R9: 0.5 | S9: -0.3 | T9: =S9*R9 -> -0.15
A10: 130 | B10: 15/11/2024 | C10: SP1 | D10: INT - PDB/CONSOLE | E10: TH | F10: PdB | G10: optim design | H10: Retour calcul SYNC2> SYNC3 | K10: 15/11/2024 Tjrs ouvert => calcul avec les SYNC3 05/09/2024 Retour calcul SYNC2 ok => Optim à étudier 06/06/2024 Besoin choix frns Fin Sept / En attente retour calcul SYNC2 14/03/2024 Selon process frn | P10: IN PROGRESS | R10: 0.25 | S10: -0.3 | T10: =S10*R10 -> -0.075
A11: 131 | B11: 01/04/2025 | C11: SP1 | D11: Door panel | E11: TH | F11: Panneau de porte | G11: style/brand | H11: Suppression Textile Fabric | K11: 01/04/2025 FOAM nécessaire pour process/frn. Et Risque d'ajout d'un tissu embossé sur Portes AV - Demande STYLE, TT niveau -(PTM/VSM) 15/11/2024 Suppression FOAM 14/03/2024 Line-up V9 | P11: IN PROGRESS | R11: 0.25 | S11: 0.1 | T11: =S11*R11 -> 0.025
A12: 132 | B12: 01/04/2025 | C12: SP1 | D12: INT - PDB/CONSOLE | E12: TH | F12: Pdb_suppression du foam sur les décors textiles | G12: style/brand | H12: suppression du foam sur les décors textiles | K12: 01/04/2025 Idem Pano Porte 20/09/2024 Passage en PT/VSM CW40 05/09/2024 A revoir avec Guillaume 14/03/2024 Line-up V9 | P12: IN PROGRESS | R12: 0.25 | S12: 0.1 | T12: =S12*R12 -> 0.025
A13: 136 | B13: 11/09/2024 | C13: SP1 | D13: INT - PDB/CONSOLE | E13: TH | F13: Pdb_Eclairage | G13: style/brand | H13: Suppression Ambient lighting - sur Mainstream | K13: 11/09/2024 Supp eclair écran(228g+40g) = Inscrit au plan coût /Supp ALCOVE (200g) : STd bye 05/09/2024 A revoir avec Guillaume 05/09/2024 : Ne concerne que ALCOVE / Sous écran : pas de contrainte / Ss facade aérateur : uniqt Niv3 06/06/2024 Si TT= RAS/ Si MeG besoin de obturateur ! 14/03/2024 dans l'alcove | P13: IN PROGRESS | R13: 0.25 | S13: -0.268 | T13: =S13*R13 -> -0.067
A14: 181 | B14: 11/02/2025 | C14: SP1 | D14: BCI_CHASSIS | E14: PTF | F14: Pedale frein | H14: Optimization apres award BATZ | K14: 11/02/2025 : A suivre lors des offi en juin. Design en cours. Risque de ne pas avoir de gain voire une augmentation de masse. passage de la piste à 0. 27/11/2024 : ECR lancé. impact masse à venir S49. 03/10/2024 : Itérations en cours avec NVH 28/08/2024 : Convergence NVH en cours. Solution a 1,2 kg (vs 1,5 kg) en cours. A voir avec Philippe pour bilan. 28/06/2024 : Bilan prestation à présenter 10/04/2024 : Reste à converger avec ACV 21/03/2024 : LHD seulement | P14: IN PROGRESS | R14: 1 | S14: 0 | T14: =S14*R14 -> 0
A15: 202 | B15: 11/06/2025 | C15: SP1 | D15: DIW | E15: TH | F15: Rft Choc LAT Porte AV | G15: BIW/ DIW process | H15: Embout à chaud PHS950 YS1500T => PHS1400-Y1800T et réduction épaisseur | K15: 11/06/2025 A ré-évaluer 04/11/2024 Idem post Go-Calcul SYNC3 08/07/2024 Retour calcul SYNC3 (Go calcul Nov => 2025?) Pièce en Embout à chaud | P15: IN PROGRESS | R15: 0.5 | S15: -0.1 | T15: =S15*R15 -> -0.05
A16: 203 | B16: 08/04/2025 | C16: SP1 | D16: BIW | E16: TH | F16: BIW Renfort montant baie + renfort pied avant | G16: BIW/ DIW process | H16: Embout à chaud :PHS950 YS1500T => PHS1400-Y1800T et réduction épaisseur | K16: 08/04/2025 Relance SAF 05/11/2024 A revoir avec SAF 03/09/2024 Synthèse Métier en cours 11/07/2024 Uniqt Rf Montant Baie, Maj eval à -0,34kg*100% (vs-0,8*25%) | P16: IN PROGRESS | R16: 1 | S16: -0.34 | T16: =S16*R16 -> -0.34
A17: 215 | B17: 25/09/2024 | C17: SP1 | D17: SWX/EE | E17: PTF | F17: Goulotte faisceaux moteur | H17: Optimisation | K17: 25/09/2024 : Compté dans le périmètre TH. 18/07/2024 : issu GT EE scope du 15/07/2024 | P17: IN PROGRESS | R17: 0.5 | S17: 0.02 | T17: =S17*R17 -> 0.01
A18: 224 | B18: 25/09/2024 | C18: SP1 | D18: ICDV | E18: TH | F18: Pneu | H18: Optim de masse 17" et 18" | K18: 25/09/2024 reporté S40 02/09/2024 besoin anayse VDYN 12/06/2024 New / attente retour frns | P18: IN PROGRESS | R18: 0.5 | S18: -1.2 | T18: =S18*R18 -> -0.6
A19: 233 | B19: 18/06/2024 | C19: SP1 | D19: INT - SEATS/TRIMS | E19: TH | F19: Insono | G19: optim design | H19: Insono Lat AV Console +10/20g Insono AR Console -50g Insono Lat CENT Console -100g Ins Collecteur AUVENT : New Ins. DEFLECTEUR EXTRACTEUR AIR : Supp Ins Passe de roue AR : New CALE PAVILLON : New | K19: 18/06/2024 Dossier RFQ : Masses sup | P19: IN PROGRESS | R19: 0.5 | S19: 0.3 | T19: =S19*R19 -> 0.15
A20: 234 | B20: 18/06/2024 | C20: SP1 | D20: INT - SEATS/TRIMS | E20: TH | F20: Garniture Raidisseur Pavillon | G20: optim design | H20: Dossier RFQ (obj masse) | K20: 18/06/2024 Dossier RFQ : Masses sup | P20: IN PROGRESS | R20: 0.5 | S20: 0.3 | T20: =S20*R20 -> 0.15
A21: 238 | C21: SP1 | D21: SWX/EE | E21: PTF | F21: Batterie 12V | H21: Retour fournisseur en fonction de niv equipement | K21: 25/09/2024 : batterie EFR L2 sur niv1. La masse absolue dépend du fournisseur. 24/06/2024 : Retour fournisseur | P21: IN PROGRESS | R21: 1 | S21: -0.4 | T21: =S21*R21 -> -0.4
A22: 245 | B22: 09/07/2024 | C22: SP1 | D22: PRS | E22: PWT | F22: Batterie RR/SR/HR | H22: 2 topics : Remove Fuse FO -0,3kg + Volume increase +1kg | K22: 09/07/2024 New | P22: IN PROGRESS | R22: 0.5 | S22: 0.7 | T22: =S22*R22 -> 0.35
A23: 248 | B23: 09/07/2024 | C23: SP1 | D23: PRS | E23: PWT | F23: Batterie HR | H23: 2 topics : Bracket reif +1kg / Aluminium busbars -0,6kg | K23: 09/07/2024 New | P23: IN PROGRESS | R23: 1 | S23: 0.68 | T23: =S23*R23 -> 0.68
A24: 254 | B24: 11/06/2025 | C24: SP1 | D24: DIW | E24: TH | F24: Porte AR : Rft | G24: optim design | H24: Remplacement / rft allégé | K24: 11/06/2025 ECR engagé => Publi en cours ; Passe à 100% / -1kg [50% ; -0,8kg] 04/11/2024 Revoir résult Choc Lat 03/09/2024 : GT_Presta CW35 / En attente résultat Side Crash SYNC2 | P24: IN PROGRESS | R24: 1 | S24: -1 | T24: =S24*R24 -> -1
A25: 107b | B25: 08/10/2024 | C25: SP1 | D25: SWX/EE | E25: PTF | F25: Cable mode3 (7kW) | H25: Passage en option/APV | K25: 08/10/2024 : Proposition de mettre le cable en option lors de l'achat (forcée par défaut dans le cnfigurateur avec possibilité de le supprimer). 25/09/2024 : Interdit par la politique tech pour le passage APV (Julien Grand clerc / Alain Lefevre sollicités pour offi). 19/06/2024 : en cours sur SP1 et sur SP2 13/03/2024 ECMP > APV | P25: IN PROGRESS | R25: 0.5 | S25: -2.6 | T25: =S25*R25 -> -1.3
A26: 188a | B26: 28/05/2025 | C26: SP1 | D26: FRSD | E26: TH | F26: Aile/Capot P1X | G26: style/brand | H26: Nvo STYLE | K26: 28/05/2025 CHANTIER MASSE : Nvo Styl, en attente design 25/04/2024 : pas de modif style => A annuler pour P1H. 27/03/2024 New WS S14 | P26: IN PROGRESS | R26: 0.25 | S26: 0.5 | T26: =S26*R26 -> 0.125
A27: 45b | B27: 11/09/2024 | C27: SP1 | D27: PHES | E27: PTF | F27: Optimisation des supports PHES | H27: STEP2 : Optimize thickness | K27: 11/09/2024 : Travaux en cours | P27: IN PROGRESS | R27: 1 | S27: -0.5 | T27: =S27*R27 -> -0.5
A28: 45c | B28: 06/03/2025 | C28: SP1 | D28: SWX/EE | E28: PTF | F28: Optimisation des supports EHE | H28: STEP2 : Optimize thickness valeur initiale : 0,847 kg | K28: 06/03/2025 : Presentation en PTM/VSM d'un modèle en plastique de 0,28 kg --> augmentation du gain à -0,57 kg 25/09/2024 : Fait parti du faisceau moteur | P28: IN PROGRESS | R28: 1 | S28: -0.567 | T28: =S28*R28 -> -0.567
A29: 45c | B29: 03/09/2024 | C29: SP1 | D29: BIW | E29: TH | F29: Panneau AR_P1X : ep.0,85 | H29: status=0,9 | K29: 03/09/2024 Retour Métier sur hypothèse Ref 13/03/2024 NVH constraint (P21:0,65) CW10 ref | P29: IN PROGRESS | R29: 1 | S29: -0.48 | T29: =S29*R29 -> -0.48
A30: 93B | B30: 08/04/2025 | C30: SP1 | D30: BIW | E30: TH | F30: BIW : CHOC | G30: risk perfo | H30: Rft 3é voie | K30: 08/04/2025 Scénario choc tt SP1 : Dbl Aile AV & Rft Abv Cote HAB (+0,888kg) 03/09/2024 En attente travaux Base sur la 3ée voie … Synthèse idem P1H ! (0,5kg à 50%) 25/04/2024 : Suite choc frontal SYNC1 .Risque ajout raidisseu 13/03/2024 maj 01/02/2024 Ptf | P30: IN PROGRESS | R30: 0.5 | S30: 0.888 | T30: =S30*R30 -> 0.444
A31: 95d | B31: 28/05/2025 | C31: SP1 | D31: BIW | E31: TH | F31: Coeff Num/Phys TH | G31: num/phys | H31: -2,5% (BIW=110kg) | K31: 28/05/2025 CHANTIER MASSE : Masse P1X | P31: IN PROGRESS | R31: 1 | S31: -2.75 | T31: =S31*R31 -> -2.75
A32: 95e | B32: 06/06/2025 | C32: SP1 | D32: FRSD | E32: TH | F32: Coeff Num/Phys TH | G32: num/phys | K32: 06/06/2025 A revoir si decision du volet Plastique 28/05/2025 CHANTIER MASSE : Masse P1X | P32: IN PROGRESS | R32: 1 | S32: -0.9 | T32: =S32*R32 -> -0.9
A33: 95f | B33: 28/05/2025 | C33: SP1 | D33: DIW | E33: TH | F33: Coeff Num/Phys TH | G33: num/phys | H33: Ratio RETEX Métier selon pièces | K33: 28/05/2025 CHANTIER MASSE : Masse P1X | P33: IN PROGRESS | R33: 1 | S33: -2.5 | T33: =S33*R33 -> -2.5
A34: 96b | B34: 07/06/2024 | C34: SP1 | D34: All | E34: TH | F34: DFNu -4% | K34: 07/06/2024 Proposition cotation RT RAL -4% 22/03/2024 A définir pour les DFNU | P34: IN PROGRESS | R34: 0.25 | S34: -4 | T34: =S34*R34 -> -1
A35: 99c | B35: 26/08/2024 | C35: SP1 | D35: PRS | E35: PWT | F35: Ens PWT HR + 11kW | H35: HR Bat / FWD S EDM / IDCM 11kW | K35: 26/08/2024 Status maj > Ptf en Risque => Echéance C-sample : date ? 08/07/2024 Mass updated CW27 / maj en cours | P35: IN PROGRESS | R35: 0.5 | S35: 1.8 | T35: =S35*R35 -> 0.9
A36: 9b | B36: 23/10/2024 | C36: SP1 | D36: BCI_BODY | E36: PTF | F36: OPTIMASSE phase 2 : Opti dessin | H36: Optimisation de dessin | K36: 23/10/2024 : idem 9a. 23/07/2024 : Mise à jour suite présentation métier BCI (S.Choppard) 26/03/2024 : Examiner la BOM pour consolider le chiffre. 27/11/2023 : prise en compte PF | P36: IN PROGRESS | R36: 1 | S36: -1 | T36: =S36*R36 -> -1
A37: 283 | B37: 11/02/2025 | C37: SP1 | D37: BCI_CHASSIS | E37: PTF | F37: Actionneur volant direction filaire (SBW uniquement) | H37: Optimisation fournisseur | K37: 11/02/2025 : Pb en collapse vu en simu qui risque d'augmenter la masse. Essai physique cette semaine à Turin. Existe une solution en simu qui resout le problème -> à chiffrer S08 + passage en VSM/PTM S07 pour valider ECR chez le fournisseur 7/25/2024 : GT presta S30 : Convergence presque à la cible avec une estimation masse à 7.3 kg ald 8 kg en cible. Il reste des implementation à faire mais probablement pas à la hauteur des +0.7 d'écart. | P37: IN PROGRESS | R37: 0.25 | S37: -0.7 | T37: =S37*R37 -> -0.175
A38: 284 | B38: 11/02/2025 | C38: SP1 | D38: BCI_CHASSIS | E38: PTF | F38: Actionneur volant direction filaire (SBW uniquement) | H38: Optimisation reponse en frequence | K38: 11/02/2025 : Solution fer à cheval choisie. Retour cette semaine pour la faisa. 03/10/2024 : Essai prévu S40 mais pb appro pièce. 28/08/2024 : Travail en cours sur la traverse PdB. Simu et essais en cours. Délai a voir avec Philippe Vannier et Olivier en GT Prestation. 7/25/2024 : GT presta S30 : Convergence presque à la cible avec une estimation masse à 7.3 kg ald 8 kg en cible. Il reste des implementation à faire mais probablement pas à la hauteur des +0.7 d'écart. | P38: IN PROGRESS | R38: 1 | S38: 0.3 | T38: =S38*R38 -> 0.3
A39: 287 | B39: 11/02/2025 | C39: SP1 | D39: BCI_BODY | E39: PTF | F39: Zone Brancard | K39: 11/02/2025 : Passage du sujet en VSM/PTM S07 pour décider. 03/12/2024 : GT conception : eval précise après calcul : estimation à +0,7 kg hors tablier (valable TT). Epaisseur tablier à passer en 0,9 ald 0,7 --> +0,9 kg (impact seulement sur P1H, P1X déjà en 0,9). 20/11/2024 : Pb de choc après reception MaJ modèles de choc. Dessin en cours, calcul d'ici 2 ou 3 semaines. | P39: IN PROGRESS | R39: 1 | S39: 0.5 | T39: =S39*R39 -> 0.5
A40: 255 | C40: SP1 | D40: PHES | E40: PTF | F40: Damper | G40: TPC | H40: Remove sur Chiller, TMM, Compresseur. | K40: 11/09/2024 : Piste TPC. Gains suivant essai NVH à venir. | P40: IN PROGRESS | R40: 0.5 | S40: -0.1 | T40: =S40*R40 -> -0.05
A41: 294b | B41: 06/06/2025 | C41: SP1 | D41: BIW | E41: TH | F41: Longeron | G41: optim design | H41: Reduction feuillure inf longeron | K41: 06/06/2025 A re-vérifer ! RISK ??? 11/02/2025 : A passer en RD suite accord de toutes les parties. 07/01/2025 : reduction de la hauteur de feuillure de 9mm (6mm sur TH) pour un gain de 0,540 kg (-0,35 kg sur PTF et -0,19 kg sur TH) | P41: IN PROGRESS | R41: 1 | S41: -0.19 | T41: =S41*R41 -> -0.19
A42: 294 | B42: 11/02/2025 | C42: SP1 | D42: BCI_BODY | E42: PTF | F42: Longeron | H42: Reduction feuillure inf longeron | K42: 11/02/2025 : A passer en RD suite accord de toutes les parties. 07/01/2025 : reduction de la hauteur de feuillure de 9mm (6mm sur TH) pour un gain de 0,540 kg (-0,35 kg sur PTF et -0,19 kg sur TH) | P42: IN PROGRESS | R42: 1 | S42: -0.35 | T42: =S42*R42 -> -0.35
A43: 295 | B43: 11/02/2025 | C43: SP1 | D43: BCI_BODY | E43: PTF | F43: Renfort acier av | H43: Pb due care | K43: 11/02/2025 : Pb de tenue sur le fonctionnel S09 | P43: IN PROGRESS | R43: 1 | S43: 0.5 | T43: =S43*R43 -> 0.5
A44: 296 | B44: 11/02/2025 | C44: SP1 | D44: BCI_BODY | E44: PTF | F44: Longeronnet AV | H44: Besoin de raideur dyn | K44: 11/02/2025 : Besoin de raideur dyn | P44: IN PROGRESS | R44: 1 | S44: 0.3 | T44: =S44*R44 -> 0.3
A45: 298 | B45: 20/11/2024 | C45: SP1 | D45: BCI_BODY | E45: PTF | F45: Optimisation des écrans sous caisse | K45: 20/11/2024 : Consultation en cours. Certains fournisseurs propose la techno Mussel : injecte de l'air dans la matière pour avoir de l'épaisseur sans masse (permet d'avoir de la raideur et de réduire le besoin de nervurage). Choix fournisseur début avril 2025. 23/10/2024 : Design avant essai 23/09/2024 : Piste maximisée | P45: IN PROGRESS | R45: 0.5 | S45: -2 | T45: =S45*R45 -> -1
A46: 268 | B46: 05/11/2024 | C46: SP1 | D46: FRSD | E46: TH | F46: Capot(Charniere) | G46: optim design | H46: Optim / Rédution ep. Charnons mobiles | K46: 05/11/2024 Confirmé : passage de 3.5 à 3 mm validé sur le charnon mobile / Gain -0.2 kg /véhicule. ce sera intégré dans les def post SYNC3, lors du restart (100% ald -75%) 07/10/2024 Suite au SYNC3, validation via GDM | P46: IN PROGRESS | R46: 1 | S46: -0.2 | T46: =S46*R46 -> -0.2
A47: 270 | B47: 08/04/2025 | C47: SP1 | D47: INT - SEATS/TRIMS | E47: TH | F47: Isolant Tapis | H47: Insono Tapis pour le ThermalRunaway | K47: 08/04/2025 GT_calcul : Risque levé pour P1H-SR / Reste pour HR et XR 18/03/2025 Coord_STLAS : Pour P1h=7pièces => +1,5kg ; +4€ // Pour P1X +2pièces 19/11/2024 Risque SYNC3 (Estim 1,2*1,9 / 650gr/m²:GlassMAT™HTX isolation thermique et phonique des compartiments moteur) | P47: IN PROGRESS | R47: 0.25 | S47: 1.482 | T47: =S47*R47 -> 0.3705
A48: 271 | B48: 08/04/2025 | C48: SP1 | D48: BIW | E48: TH | F48: Zone Auvent | G48: new part | H48: Ajout pièces | K48: 08/04/2025 Détail : Finition LAT D/G Grille Entrée Air / Grille Entrée Air / Deflect Eau / Etanchéité D/G Grille / Conduit Entrée Air 22/11/2024 Complétude de BOM | P48: IN PROGRESS | R48: 1 | S48: 0.54 | T48: =S48*R48 -> 0.54
A49: 272 | B49: 24/04/2025 | C49: SP1 | D49: INT - SEATS/TRIMS | E49: TH | F49: Assises AV : Airbag Cent | G49: risk perfo | H49: Safety 3* | K49: 24/04/2025 RD S15_DEC032572 18/03/2025 PTM/VSM : 3* > FCAB+1kg / Brin_Boucle+0,06kg / Nappe detec_Ar +0,25kg / Airbag Pass +0,06kg 14/02/2025 : Protocole NCAP, risk to 3* ? | P49: IN PROGRESS | R49: 1 | S49: 1.37 | T49: =S49*R49 -> 1.37
A50: 299 | B50: 07/03/2025 | C50: SP1 | D50: PHES | E50: PTF | F50: HVAC | H50: Augmentation des performances | K50: 07/03/2025 : Décision d'ajout d'aillettes et augmentation du radiateur. Valeur reelle à avoir après convergence archi. | P50: IN PROGRESS | R50: 1 | S50: 0.2 | T50: =S50*R50 -> 0.2
A51: 301a | B51: 20/06/2025 | C51: SP1 | D51: FRSD | E51: TH | F51: PC Av / Proj - MS | G51: style/brand | H51: P1HX : Nouvelle face_Av MS | K51: 20/06/2025 Retour frns : Proj MS+1,2kg / PC MS+1kg 28/05/2025 à 50% suite 1er retour frns du Proj / En attente info du PC 06/05/2025 passe à 75% 22/04/2025 RD _S16 : Choix Concept Proj (3 parts)_01353_25_00247 24/03/2025 Impact nvo Style_Feu déporté | P51: IN PROGRESS | R51: 1 | S51: 2.2 | T51: =S51*R51 -> 2.2
A52: 302a | B52: 25/03/2025 | C52: SP1 | D52: BIW | E52: TH | F52: Appui cric | G52: new part | H52: Optim Longeron | K52: 25/03/2025 Transfert PtF Appui cric au TH : Fermeture Av Longeron | P52: IN PROGRESS | R52: 1 | S52: 0.4 | T52: =S52*R52 -> 0.4
A53: 302c | B53: 07/04/2025 | C53: SP1 | D53: BCI_BODY | E53: PTF | F53: Appui cric et suppression cloisons av | K53: 07/04/2025 : Calcul en cours avec renfort raccourci en cours. A priori ok pour SR mais pas sur en HR. A voir possibilité de réduire le renfort pour SR et ajouter un renfort spécifique HR si nok HR. 25/03/2025_Coord S13 : Transfert Appui cric au TH / Optim du longeron | P53: IN PROGRESS | R53: 0.25 | S53: -3.4 | T53: =S53*R53 -> -0.85
A54: 304 | B54: 08/04/2025 | C54: SP1 | D54: BIW | E54: TH | F54: SYNC3+ | G54: risk perfo | H54: Addon ChoC FR | K54: 08/04/2025 Périmètre SYNC3+, add-ons au sujet 93B : : raidisseur inf pied avant, +0,341kg | P54: IN PROGRESS | R54: 0.25 | S54: 0.341 | T54: =S54*R54 -> 0.08525
A55: 305 | B55: 24/04/2025 | C55: SP1 | D55: INT - PDB/CONSOLE | E55: TH | F55: Traverse planche de bord | G55: risk perfo | H55: Renforcement | K55: 24/04/2025 Tenue NVH / Vibration | P55: IN PROGRESS | R55: 0.25 | S55: 0.4 | T55: =S55*R55 -> 0.1
A56: 306 | B56: 28/05/2025 | C56: SP1 | D56: FRSD | E56: TH | F56: Volet Composite | H56: Chgt de matière | K56: 28/05/2025 CHANTIER MASSE : Eval à -6kg/ 75% 16/05/2025 Volet P1X en Composite (volet + spoiler + aerofin + lighting T2) | P56: IN PROGRESS | R56: 0.75 | S56: -6 | T56: =S56*R56 -> -4.5
A57: 307 | B57: 23/05/2025 | C57: SP1 | D57: INT - SEATS/TRIMS | E57: TH | F57: Extracteur Air | H57: Air Extractor | K57: 23/05/2025 A supprimer de P1X | P57: IN PROGRESS | R57: 0.25 | S57: -0.4 | T57: =S57*R57 -> -0.1
A58: 308 | B58: 06/06/2025 | C58: SP1 | D58: INT - SEATS/TRIMS | E58: TH | F58: Insono Coffre Rds | H58: TRUNK SOUNDPROOF | K58: 06/06/2025 Que sur le SR ! 23/05/2025 A supprimer TT | P58: IN PROGRESS | R58: 0.25 | S58: -0.15 | T58: =S58*R58 -> -0.0375
A59: 309 | B59: 03/06/2025 | C59: SP1 | D59: INT - SEATS/TRIMS | E59: TH | F59: Garniture Volet…. | H59: Optim idem P1H | K59: 03/06/2025 CHANTIER : Garn inf revue maj à-0,2kg (ald-0,9kg) // Uniqut si volet ACIER ! 28/05/2025 CHANTIER MASSE : Idem P1H (Garn Vole- 0,9kg / Lat -0,64kg / Sup -0,260kg) | P59: IN PROGRESS | R59: 0.25 | S59: -1.1 | T59: =S59*R59 -> -0.275
A60: 311 | B60: 28/05/2025 | C60: SP1 | D60: BIW | E60: TH | F60: Piéces communes P1HX | H60: Périmètre Masse : à re-partager | K60: 28/05/2025 CHANTIER MASSE : Périmètre Commune à re-partager avec Franck | P60: IN PROGRESS | R60: 0.5 | S60: -0.4 | T60: =S60*R60 -> -0.2
A61: 312 | B61: 28/05/2025 | C61: SP1 | D61: Door Panel | E61: TH | F61: Garniture Pano AV | H61: Périmètre Masse | K61: 28/05/2025 CHANTIER MASSE : Vérifier cohérence des masses | P61: IN PROGRESS | R61: 0.25 | S61: -0.8 | T61: =S61*R61 -> -0.2
A62: 313 | B62: 28/05/2025 | C62: SP1 | D62: SWX/EE | E62: TH | F62: HP AR | H62: A décliner selon le Lvl | K62: 28/05/2025 CHANTIER MASSE : Créer une MeG | P62: IN PROGRESS | R62: 0.25 | S62: -1 | T62: =S62*R62 -> -0.25
A63: 317a | B63: 03/06/2025 | C63: SP1 | D63: INT - SEATS/TRIMS | E63: TH | F63: P2P | H63: A passer en Option | K63: 03/06/2025 CHANTIER MASSE : Revoir la décli | P63: IN PROGRESS | R63: 0.25 | S63: -2.57 | T63: =S63*R63 -> -0.6425
A64: 317b | B64: 03/06/2025 | C64: SP1 | D64: INT - SEATS/TRIMS | E64: TH | F64: P2P (supports) | H64: Revoir la diversité | K64: 03/06/2025 CHANTIER MASSE : Supprimer les supports du TT > Impact sur la diversité des GLC | P64: IN PROGRESS | R64: 0.25 | S64: -0.7 | T64: =S64*R64 -> -0.175
A65: 322 | B65: 45813 | C65: SP1 | D65: INT - PDB/CONSOLE | E65: TH | F65: PdB/Console UPPER | H65: Chgt de matière (passage du TD 12 vierge au TD12 recyclé / passage du MD20 au TD28 green) | K65: 05/06/2025  Planche de Bord : +0.280 kg / Console UPPER : +0.147 kg et +0.260 kg | P65: IN PROGRESS | R65: 0.25 | S65: 0.687 | T65: =S65*R65 -> 0.17175
A66: 323 | B66: 06/06/2025 | C66: SP1 | D66: FRSD | E66: TH | F66: PC Av/Ar | H66: P1X | K66: 06/06/2025 PC P1X avec Air-Curtain | P66: IN PROGRESS | R66: 0.25 | S66: 2 | T66: =S66*R66 -> 0.5
A67: 324 | B67: 10/06/2025 | C67: SP1 | D67: All | E67: TH | F67: Pièces Communes P1HX | H67: P1HX | K67: 10/06/2025 Effort d'allégement sur les pièces communes P1HX (-2%) | P67: IN PROGRESS | R67: 0.25 | S67: -3.5 | T67: =S67*R67 -> -0.875

Sheet GLOBAL PORTFOLIO
A1: COMMON PART | BM1: FREE COLUMN To be used from PPEs
AJ2: PROGRAM deployement
A3: UPDATE | B3: PROPOSAL | L3: Mass (kg) | O3: Costs | T3: IMPLEMENTATION CONFIDENCE | AF3: TIMING | AJ3: SPC
A4: LAST UPDATE | B4: Cluster (Idea origin) | C4: Num | D4: PTF/TH/PS | E4: System Description | F4: Subsystems Description | G4: SFS/eBOM/DECOUPAGE | H4: Metafunction OWNER/ LEADER (SSTM - métier) | I4: PFDI VSM | J4: PART | K4: LIGHTWEIGHT ACTION | L4: Mass (kg) | M4: STARTING abs Weight (kg) | N4: STARTING Material | O4: w/o Costs | P4: INV (k€) | Q4: R&D (k€) | R4: TPC (€) | S4: €/kg | T4: Process STATUS | U4: Implementation milestone (from forecast to status) | V4: CONFIDENCE LEVEL (SSTM & VSM ASSESSMENT) | W4: FEASIBILITY (SSTM) | X4: COMPLEXITY | Y4: PERFORMANCES | Z4: PACKAGING | AA4: COSTS | AB4: TIMING | AC4: ODM | AD4: CAD RELEASE | AE4: Action/ Notes | AF4: OPENING DATE | AG4: REVIEW for DECISION DATE | AH4: Day to review | AI4: LAST CALL MILESTONE | AJ4: ='Portefeuille SP2'!V14 -> O3H HR 63 FWD€ | AK4: ='Portefeuille SP2'!W14 -> O3H XR 80 FWD€ | AL4: ='Portefeuille SP2'!X14 -> O3H XR 80 AWD perfo € | AM4: ='Portefeuille SP2'!Y14 -> O3H MHEV FWD€ | AN4: ='Portefeuille SP2'!Z14 -> O3H HEV FWD€ | AO4: ='Portefeuille SP2'!AA14 -> O3W 63 kWhu LFP FWD€ | AP4: ='Portefeuille SP2'!AB14 -> O3W 80 kWhu NMx FWD€ | AQ4: ='Portefeuille SP2'!AC14 -> O3W MHEV FWD€ | ... BF4: ='Portefeuille SP2'!AR14 -> P3U HEV FWD€ | BG4: ='Portefeuille SP2'!#REF! -> #REF! | BH4: ='Portefeuille SP2'!#REF! -> #REF! | BI4: ='Portefeuille SP2'!#REF! -> #REF! | BJ4: ='Portefeuille SP2'!#REF! -> #REF! | BK4: ='Portefeuille SP2'!#REF! -> #REF!
A5: 43918 | B5: Workshop | C5: A01 | D5: TH | E5: Body | F5: Underbody | G5: 5SCC/ | H5: NAME XXX | I5: NAME XXX | J5: Mid Floor | K5: Thickness reductions 0,8mm -->0,7mm | L5: -3.4 | M5: 24 | N5: Steel | O5: X | T5: New Proposal | U5: SHRM | V5: HIGH | W5: V | X5: V | Y5: G | Z5: V | AA5: G | AB5: G | AC5: =IF(COUNTIF(W5,"OK")>0,"OK",(IF(COUNTIF(W5:AB5,"K")>0,"KO",(IF(COUNTIF(W5:AB5,"R")>0,"R",(IF(COUNTIF(W5:AB5,"G")>0,"G",(IF(COUNTIF(W5:AB5,"V")>0,"V","-"))))))))) -> G | AF5: 45483 | AG5: 45514 | AH5: =IFERROR(DAYS360(TODAY(),AG5),"TBD") -> -626 | AI5: CM | AL5: 1 | AV5: 1 | BF5: 1
A6: 43918 | B6: Workshop | D6: PTF | G6: Multi | H6: A.SALESSE | I6: L.Perrugia | J6: Underbody | L6: -7 | N6: Steel | S6: -1.5 | T6: Under investigation (IN BEST P) | AF6: 45257 | AI6: S37
A7: 43918
A8: ='Portefeuille SP2'!B15 -> 45632 | B8: ='Portefeuille SP2'!Q15 -> CANCELED | D8: ='Portefeuille SP2'!E15 -> TH | E8: =LEFT(J8,3) -> BIW | F8: =MID(J8, 4, 20) | G8: ='Portefeuille SP2'!C15 -> SPC_1 | H8: ='Portefeuille SP2'!F15 -> MICHAEL BORE | J8: ='Portefeuille SP2'!D15 -> BIW | K8: ='Portefeuille SP2'!H15 -> activ spoiler | L8: ='Portefeuille SP2'!U15 -> 3.2 | P8: ='Portefeuille SP2'!M15 -> 0 | R8: ='Portefeuille SP2'!N15 -> 0 | T8: ='Portefeuille SP2'!R15 -> TBD | U8: ='Portefeuille SP2'!K15 -> 0 | V8: ='Portefeuille SP2'!S15 -> 0.8 | AE8: ='Portefeuille SP2'!J15 -> 06/10/2025 sujet à supprimer car pas d'active Spoiler sur le projet SPC_1 | AJ8: ='Portefeuille SP2'!V15 -> 1 | AK8: ='Portefeuille SP2'!W15 -> 1 | AL8: ='Portefeuille SP2'!X15 -> 1 | AM8: ='Portefeuille SP2'!Y15 -> 1 | AN8: ='Portefeuille SP2'!Z15 -> 1 | AO8: ='Portefeuille SP2'!AA15 -> 1 | AP8: ='Portefeuille SP2'!AB15 -> 1 | AQ8: ='Portefeuille SP2'!AC15 -> 1 | ... BF8: ='Portefeuille SP2'!AR15 -> 1 | BG8: ='Portefeuille SP2'!#REF! -> #REF! | BH8: ='Portefeuille SP2'!#REF! -> #REF! | BI8: ='Portefeuille SP2'!#REF! -> #REF! | BJ8: ='Portefeuille SP2'!#REF! -> #REF! | BK8: ='Portefeuille SP2'!#REF! -> #REF! | BM8: ='Portefeuille SP2'!L15 -> 0
A9: ='Portefeuille SP2'!B16 -> 20/06/2025 | B9: ='Portefeuille SP2'!Q16 -> CANCELED | D9: ='Portefeuille SP2'!E16 -> TH | E9: =LEFT(J9,3) -> FRS | F9: =MID(J9, 4, 20) -> D | G9: ='Portefeuille SP2'!C16 -> SP1 | H9: ='Portefeuille SP2'!F16 -> Sébastien Bonnefoi (P1H)/ Jean Michel Gabus P1X | J9: ='Portefeuille SP2'!D16 -> FRSD | K9: ='Portefeuille SP2'!H16 -> style/brand | L9: ='Portefeuille SP2'!U16 -> 2.2 | P9: ='Portefeuille SP2'!M16 -> 0 | R9: ='Portefeuille SP2'!N16 -> 0 | T9: ='Portefeuille SP2'!R16 -> 0 | U9: ='Portefeuille SP2'!K16 -> 0 | V9: ='Portefeuille SP2'!S16 -> 1 | AE9: ='Portefeuille SP2'!J16 -> Stratégie projet | AJ9: ='Portefeuille SP2'!V16 -> 1 | AK9: ='Portefeuille SP2'!W16 -> 1 | AL9: ='Portefeuille SP2'!X16 -> 1 | AM9: ='Portefeuille SP2'!Y16 -> 1 | AN9: ='Portefeuille SP2'!Z16 -> 1 | AO9: ='Portefeuille SP2'!AA16 -> 1 | AP9: ='Portefeuille SP2'!AB16 -> 1 | AQ9: ='Portefeuille SP2'!AC16 -> 1 | ... BF9: ='Portefeuille SP2'!AR16 -> 1 | BG9: ='Portefeuille SP2'!#REF! -> #REF! | BH9: ='Portefeuille SP2'!#REF! -> #REF! | BI9: ='Portefeuille SP2'!#REF! -> #REF! | BJ9: ='Portefeuille SP2'!#REF! -> #REF! | BK9: ='Portefeuille SP2'!#REF! -> #REF! | BM9: ='Portefeuille SP2'!L16 -> 20/06/2025 Retour frns : Proj MS+1,2kg / PC MS+1kg 28/05/2025 à 50% suite 1er retour frns du Proj / En attente info du PC 06/05/2025 passe à 75% 22/04/2025 RD _S16 : Choix Concept Proj (3 parts)_01353_25_00247 24/03/2025 Impact nvo Style_Feu déporté
A10: ='Portefeuille SP2'!#REF! -> #REF! | B10: ='Portefeuille SP2'!#REF! -> #REF! | D10: ='Portefeuille SP2'!#REF! -> #REF! | E10: =LEFT(J10,3) -> #REF! | F10: =MID(J10, 4, 20) -> #REF! | G10: ='Portefeuille SP2'!#REF! -> #REF! | H10: ='Portefeuille SP2'!#REF! -> #REF! | J10: ='Portefeuille SP2'!#REF! -> #REF! | K10: ='Portefeuille SP2'!#REF! -> #REF! | L10: ='Portefeuille SP2'!#REF! -> #REF! | P10: ='Portefeuille SP2'!#REF! -> #REF! | R10: ='Portefeuille SP2'!#REF! -> #REF! | T10: ='Portefeuille SP2'!#REF! -> #REF! | U10: ='Portefeuille SP2'!#REF! -> #REF! | V10: ='Portefeuille SP2'!#REF! -> #REF! | AE10: ='Portefeuille SP2'!#REF! -> #REF! | AJ10: ='Portefeuille SP2'!#REF! -> #REF! | AK10: ='Portefeuille SP2'!#REF! -> #REF! | AL10: ='Portefeuille SP2'!#REF! -> #REF! | AM10: ='Portefeuille SP2'!#REF! -> #REF! | AN10: ='Portefeuille SP2'!#REF! -> #REF! | AO10: ='Portefeuille SP2'!#REF! -> #REF! | AP10: ='Portefeuille SP2'!#REF! -> #REF! | AQ10: ='Portefeuille SP2'!#REF! -> #REF! | ... BK10: ='Portefeuille SP2'!#REF! -> #REF! | BM10: ='Portefeuille SP2'!#REF! -> #REF!
A11: ='Portefeuille SP2'!B17 -> 45536 | B11: ='Portefeuille SP2'!Q17 -> DECIDED | D11: ='Portefeuille SP2'!E17 -> TH | E11: =LEFT(J11,3) -> BIW | F11: =MID(J11, 4, 20) | G11: ='Portefeuille SP2'!C17 -> SPC_1 | H11: ='Portefeuille SP2'!F17 -> MICHAEL BORE | J11: ='Portefeuille SP2'!D17 -> BIW | K11: ='Portefeuille SP2'!H17 -> hood Pantographe | L11: ='Portefeuille SP2'!U17 -> 1 | P11: ='Portefeuille SP2'!M17 -> 350 | R11: ='Portefeuille SP2'!N17 -> 8.5 | T11: ='Portefeuille SP2'!R17 -> TBD | U11: ='Portefeuille SP2'!K17 -> PM | V11: ='Portefeuille SP2'!S17 -> 1 | AE11: ='Portefeuille SP2'!J17 -> 10/10/2025 référence projet col de cygne, mais demande PEDPRO de Pantographe 11/10/2024 QCTP Pantograh hood hinge =>https://docinfogroupe.stellantis.com/ead/doc/ref.21007_24_00151/v.vc/fiche | AJ11: ='Portefeuille SP2'!V17 -> 1 | AK11: ='Portefeuille SP2'!W17 -> 1 | AL11: ='Portefeuille SP2'!X17 -> 1 | AM11: ='Portefeuille SP2'!Y17 -> 1 | AN11: ='Portefeuille SP2'!Z17 -> 1 | AO11: ='Portefeuille SP2'!AA17 -> 1 | AP11: ='Portefeuille SP2'!AB17 -> 1 | AQ11: ='Portefeuille SP2'!AC17 -> 1 | ... BF11: ='Portefeuille SP2'!AR17 -> 1 | BG11: ='Portefeuille SP2'!#REF! -> #REF! | BH11: ='Portefeuille SP2'!#REF! -> #REF! | BI11: ='Portefeuille SP2'!#REF! -> #REF! | BJ11: ='Portefeuille SP2'!#REF! -> #REF! | BK11: ='Portefeuille SP2'!#REF! -> #REF! | BM11: ='Portefeuille SP2'!L17 -> 0
A12: ='Portefeuille SP2'!B18 -> 45536 | B12: ='Portefeuille SP2'!Q18 -> DECIDED | D12: ='Portefeuille SP2'!E18 -> TH | E12: =LEFT(J12,3) -> BIW | F12: =MID(J12, 4, 20) | G12: ='Portefeuille SP2'!C18 -> SPC_1 | H12: ='Portefeuille SP2'!F18 -> MICHAEL BORE | J12: ='Portefeuille SP2'!D18 -> BIW | K12: ='Portefeuille SP2'!H18 -> front & rear bumper | L12: ='Portefeuille SP2'!U18 -> 0.82 | P12: ='Portefeuille SP2'!M18 -> 0 | R12: ='Portefeuille SP2'!N18 -> (-6) | T12: ='Portefeuille SP2'!R18 -> TBD | U12: ='Portefeuille SP2'!K18 -> 0 | V12: ='Portefeuille SP2'!S18 -> 1 | AE12: ='Portefeuille SP2'!J18 -> 06/10/2025 Pas de PORO | AJ12: ='Portefeuille SP2'!V18 -> 1 | AK12: ='Portefeuille SP2'!W18 -> 1 | AL12: ='Portefeuille SP2'!X18 -> 1 | AM12: ='Portefeuille SP2'!Y18 -> 1 | AN12: ='Portefeuille SP2'!Z18 -> 1 | AO12: ='Portefeuille SP2'!AA18 -> 1 | AP12: ='Portefeuille SP2'!AB18 -> 1 | AQ12: ='Portefeuille SP2'!AC18 -> 1 | ... BF12: ='Portefeuille SP2'!AR18 -> 1 | BG12: ='Portefeuille SP2'!#REF! -> #REF! | BH12: ='Portefeuille SP2'!#REF! -> #REF! | BI12: ='Portefeuille SP2'!#REF! -> #REF! | BJ12: ='Portefeuille SP2'!#REF! -> #REF! | BK12: ='Portefeuille SP2'!#REF! -> #REF! | BM12: ='Portefeuille SP2'!L18 -> 0
A13: ='Portefeuille SP2'!B19 -> 45813 | B13: ='Portefeuille SP2'!Q19 -> CANCELED | D13: ='Portefeuille SP2'!E19 -> TH | E13: =LEFT(J13,3) -> INT | F13: =MID(J13, 4, 20) -> - PDB/CONSOLE | G13: ='Portefeuille SP2'!C19 -> SP1 | H13: ='Portefeuille SP2'!F19 -> FREDERIC BRUNIER | J13: ='Portefeuille SP2'!D19 -> INT - PDB/CONSOLE | K13: ='Portefeuille SP2'!H19 -> Dashboard/Upper console | L13: ='Portefeuille SP2'!U19 -> 0.75 | P13: ='Portefeuille SP2'!M19 -> 0 | R13: ='Portefeuille SP2'!N19 -> 0 | T13: ='Portefeuille SP2'!R19 -> 0 | U13: ='Portefeuille SP2'!K19 -> 0 | V13: ='Portefeuille SP2'!S19 -> 0.75 | AE13: ='Portefeuille SP2'!J19 -> CP P1H Sébastien Dupuis 24/06/2025 à confirmer avec Sébastien car attente panneau SYNC5 et MAJ de la masse | AJ13: ='Portefeuille SP2'!V19 -> 1 | AK13: ='Portefeuille SP2'!W19 -> 1 | AL13: ='Portefeuille SP2'!X19 -> 1 | AM13: ='Portefeuille SP2'!Y19 -> 1 | AN13: ='Portefeuille SP2'!Z19 -> 1 | AO13: ='Portefeuille SP2'!AA19 -> 1 | AP13: ='Portefeuille SP2'!AB19 -> 1 | AQ13: ='Portefeuille SP2'!AC19 -> 1 | ... BF13: ='Portefeuille SP2'!AR19 -> 1 | BG13: ='Portefeuille SP2'!#REF! -> #REF! | BH13: ='Portefeuille SP2'!#REF! -> #REF! | BI13: ='Portefeuille SP2'!#REF! -> #REF! | BJ13: ='Portefeuille SP2'!#REF! -> #REF! | BK13: ='Portefeuille SP2'!#REF! -> #REF! | BM13: ='Portefeuille SP2'!L19 -> 05/06/2025  Planche de Bord : +0.280 kg / Console UPPER : +0.147 kg et +0.260 kg
A14: ='Portefeuille SP2'!B20 -> 01/04/2025 | B14: ='Portefeuille SP2'!Q20 -> CANCELED | D14: ='Portefeuille SP2'!E20 -> TH | E14: =LEFT(J14,3) -> Doo | F14: =MID(J14, 4, 20) -> r panel | G14: ='Portefeuille SP2'!C20 -> SP1 | H14: ='Portefeuille SP2'!F20 -> FREDERIC BRUNIER | J14: ='Portefeuille SP2'!D20 -> Door panel | K14: ='Portefeuille SP2'!H20 -> style/brand | L14: ='Portefeuille SP2'!U20 -> 0.025 | P14: ='Portefeuille SP2'!M20 -> 0 | R14: ='Portefeuille SP2'!N20 -> 0 | T14: ='Portefeuille SP2'!R20 -> 0 | U14: ='Portefeuille SP2'!K20 -> 0 | V14: ='Portefeuille SP2'!S20 -> 0.25 | AE14: ='Portefeuille SP2'!J20 -> CP P1H Sébastien Dupuis 23/06/25 LM : Vu avec Frédéric refusé par SP1 - A confirmer pour SPC | AJ14: ='Portefeuille SP2'!V20 -> 1 | AK14: ='Portefeuille SP2'!W20 -> 1 | AL14: ='Portefeuille SP2'!X20 -> 1 | AM14: ='Portefeuille SP2'!Y20 -> 1 | AN14: ='Portefeuille SP2'!Z20 -> 1 | AO14: ='Portefeuille SP2'!AA20 -> 1 | AP14: ='Portefeuille SP2'!AB20 -> 1 | AQ14: ='Portefeuille SP2'!AC20 -> 1 | ... BF14: ='Portefeuille SP2'!AR20 -> 1 | BG14: ='Portefeuille SP2'!#REF! -> #REF! | BH14: ='Portefeuille SP2'!#REF! -> #REF! | BI14: ='Portefeuille SP2'!#REF! -> #REF! | BJ14: ='Portefeuille SP2'!#REF! -> #REF! | BK14: ='Portefeuille SP2'!#REF! -> #REF! | BM14: ='Portefeuille SP2'!L20 -> 01/04/2025 FOAM nécessaire pour process/frn. Et Risque d'ajout d'un tissu embossé sur Portes AV - Demande STYLE, TT niveau -(PTM/VSM) 15/11/2024 Suppression FOAM 14/03/2024 Line-up V9
A15: ='Portefeuille SP2'!B21 -> 01/04/2025 | B15: ='Portefeuille SP2'!Q21 -> CANCELED | D15: ='Portefeuille SP2'!E21 -> TH | E15: =LEFT(J15,3) -> INT | F15: =MID(J15, 4, 20) -> - PDB/CONSOLE | G15: ='Portefeuille SP2'!C21 -> SP1 | H15: ='Portefeuille SP2'!F21 -> FREDERIC BRUNIER | J15: ='Portefeuille SP2'!D21 -> INT - PDB/CONSOLE | K15: ='Portefeuille SP2'!H21 -> style/brand | L15: ='Portefeuille SP2'!U21 -> 0.025 | P15: ='Portefeuille SP2'!M21 -> 0 | R15: ='Portefeuille SP2'!N21 -> 0 | T15: ='Portefeuille SP2'!R21 -> 0 | U15: ='Portefeuille SP2'!K21 -> 0 | V15: ='Portefeuille SP2'!S21 -> 0.25 | AE15: ='Portefeuille SP2'!J21 -> CP P1H Sébastien Dupuis 23/06/25 LM : Vu avec Frédéric refusé par SP1 - A confirmer pour SPC | AJ15: ='Portefeuille SP2'!V21 -> 1 | AK15: ='Portefeuille SP2'!W21 -> 1 | AL15: ='Portefeuille SP2'!X21 -> 1 | AM15: ='Portefeuille SP2'!Y21 -> 1 | AN15: ='Portefeuille SP2'!Z21 -> 1 | AO15: ='Portefeuille SP2'!AA21 -> 1 | AP15: ='Portefeuille SP2'!AB21 -> 1 | AQ15: ='Portefeuille SP2'!AC21 -> 1 | ... BF15: ='Portefeuille SP2'!AR21 -> 1 | BG15: ='Portefeuille SP2'!#REF! -> #REF! | BH15: ='Portefeuille SP2'!#REF! -> #REF! | BI15: ='Portefeuille SP2'!#REF! -> #REF! | BJ15: ='Portefeuille SP2'!#REF! -> #REF! | BK15: ='Portefeuille SP2'!#REF! -> #REF! | BM15: ='Portefeuille SP2'!L21 -> 01/04/2025 Idem Pano Porte 20/09/2024 Passage en PT/VSM CW40 05/09/2024 A revoir avec Guillaume 14/03/2024 Line-up V9
A16: ='Portefeuille SP2'!B22 -> 45546 | B16: ='Portefeuille SP2'!Q22 -> DECIDED | D16: ='Portefeuille SP2'!E22 -> TH | E16: =LEFT(J16,3) -> BIW | F16: =MID(J16, 4, 20) | G16: ='Portefeuille SP2'!C22 -> SPC_1 | H16: ='Portefeuille SP2'!F22 -> FRANK BAILLON | J16: ='Portefeuille SP2'!D22 -> BIW | K16: ='Portefeuille SP2'!H22 -> B pillar inner | L16: ='Portefeuille SP2'!U22 -> 0.75 | P16: ='Portefeuille SP2'!M22 -> -350K€ | R16: ='Portefeuille SP2'!N22 -> 2 | T16: ='Portefeuille SP2'!R22 -> TBD | U16: ='Portefeuille SP2'!K22 -> DTM PM-CM | V16: ='Portefeuille SP2'!S22 -> 0.5 | AE16: ='Portefeuille SP2'!J22 -> 06/10/2025 a reboucler avec l'embout - Mickael Ludovic DASNOIS | AJ16: ='Portefeuille SP2'!V22 -> 1 | AK16: ='Portefeuille SP2'!W22 -> 1 | AL16: ='Portefeuille SP2'!X22 -> 1 | AM16: ='Portefeuille SP2'!Y22 -> 1 | AN16: ='Portefeuille SP2'!Z22 -> 1 | AO16: ='Portefeuille SP2'!AA22 -> 1 | AP16: ='Portefeuille SP2'!AB22 -> 1 | AQ16: ='Portefeuille SP2'!AC22 -> 1 | ... BF16: ='Portefeuille SP2'!AR22 -> 1 | BG16: ='Portefeuille SP2'!#REF! -> #REF! | BH16: ='Portefeuille SP2'!#REF! -> #REF! | BI16: ='Portefeuille SP2'!#REF! -> #REF! | BJ16: ='Portefeuille SP2'!#REF! -> #REF! | BK16: ='Portefeuille SP2'!#REF! -> #REF! | BM16: ='Portefeuille SP2'!L22 -> 26/06/2025 a reboucler après hypothèse projet
A17: ='Portefeuille SP2'!B23 -> 46058 | B17: ='Portefeuille SP2'!Q23 -> IN PROGRESS | D17: ='Portefeuille SP2'!E23 -> PTF | E17: =LEFT(J17,3) -> BCI | F17: =MID(J17, 4, 20) -> _CHASSIS | G17: ='Portefeuille SP2'!C23 -> SP1 | H17: ='Portefeuille SP2'!F23 -> 0 | J17: ='Portefeuille SP2'!D23 -> BCI_CHASSIS | K17: ='Portefeuille SP2'!H23 -> Rr axle ML | L17: ='Portefeuille SP2'!U23 -> 0 | P17: ='Portefeuille SP2'!M23 -> 0 | R17: ='Portefeuille SP2'!N23 -> 0 | T17: ='Portefeuille SP2'!R23 -> 0 | U17: ='Portefeuille SP2'!K23 -> 0 | V17: ='Portefeuille SP2'!S23 -> 0.75 | AE17: ='Portefeuille SP2'!J23 -> 0 | AJ17: ='Portefeuille SP2'!V23 -> 1 | AK17: ='Portefeuille SP2'!W23 -> 1 | AL17: ='Portefeuille SP2'!X23 -> 1 | AM17: ='Portefeuille SP2'!Y23 -> 1 | AN17: ='Portefeuille SP2'!Z23 -> 1 | AO17: ='Portefeuille SP2'!AA23 -> 1 | AP17: ='Portefeuille SP2'!AB23 -> 1 | AQ17: ='Portefeuille SP2'!AC23 -> 1 | ... BF17: ='Portefeuille SP2'!AR23 -> 1 | BG17: ='Portefeuille SP2'!#REF! -> #REF! | BH17: ='Portefeuille SP2'!#REF! -> #REF! | BI17: ='Portefeuille SP2'!#REF! -> #REF! | BJ17: ='Portefeuille SP2'!#REF! -> #REF! | BK17: ='Portefeuille SP2'!#REF! -> #REF! | BM17: ='Portefeuille SP2'!L23 -> 27/11/2025 : Présentation en VSM/PTM. Gain important en Aero, mais cout important (+3,5€). Besoin à confirmer après essai, pas en ref en ce moment. Nouvelle estimation à 0,5 kg 03/10/2025 : Aero demande des écrans sur les bras du ML. Demande à confirmer.
A18: ='Portefeuille SP2'!B24 -> 11/06/2025 | B18: ='Portefeuille SP2'!Q24 -> CANCELED | D18: ='Portefeuille SP2'!E24 -> TH | E18: =LEFT(J18,3) -> DIW | F18: =MID(J18, 4, 20) | G18: ='Portefeuille SP2'!C24 -> SP1 | H18: ='Portefeuille SP2'!F24 -> Filipe Goncalves (P1H)/ Cyrille P1X | J18: ='Portefeuille SP2'!D24 -> DIW | K18: ='Portefeuille SP2'!H24 -> BIW/ DIW process | L18: ='Portefeuille SP2'!U24 -> -0.05 | P18: ='Portefeuille SP2'!M24 -> 0 | R18: ='Portefeuille SP2'!N24 -> 0 | T18: ='Portefeuille SP2'!R24 -> 0 | U18: ='Portefeuille SP2'!K24 -> 0 | V18: ='Portefeuille SP2'!S24 -> 0.5 | AE18: ='Portefeuille SP2'!J24 -> déjà intégré dans la BDD SP2 - ligne à supprimer | AJ18: ='Portefeuille SP2'!V24 -> 1 | AK18: ='Portefeuille SP2'!W24 -> 1 | AL18: ='Portefeuille SP2'!X24 -> 1 | AM18: ='Portefeuille SP2'!Y24 -> 1 | AN18: ='Portefeuille SP2'!Z24 -> 1 | AO18: ='Portefeuille SP2'!AA24 -> 1 | AP18: ='Portefeuille SP2'!AB24 -> 1 | AQ18: ='Portefeuille SP2'!AC24 -> 1 | ... BF18: ='Portefeuille SP2'!AR24 -> 1 | BG18: ='Portefeuille SP2'!#REF! -> #REF! | BH18: ='Portefeuille SP2'!#REF! -> #REF! | BI18: ='Portefeuille SP2'!#REF! -> #REF! | BJ18: ='Portefeuille SP2'!#REF! -> #REF! | BK18: ='Portefeuille SP2'!#REF! -> #REF! | BM18: ='Portefeuille SP2'!L24 -> 02/07/2025 CANCELLED : Ep.mini déjà atteinte (chgt de matière possible mais aurait nécessité une dimintution d'épasisseur) 11/06/2025 A ré-évaluer 04/11/2024 Idem post Go-Calcul SYNC3 08/07/2024 Retour calcul SYNC3 (Go calcul Nov => 2025?) Pièce en Embout à chaud
A19: ='Portefeuille SP2'!B25 -> 45536 | B19: ='Portefeuille SP2'!Q25 -> DECIDED | D19: ='Portefeuille SP2'!E25 -> TH | E19: =LEFT(J19,3) -> BIW | F19: =MID(J19, 4, 20) | G19: ='Portefeuille SP2'!C25 -> SPC_1 | H19: ='Portefeuille SP2'!F25 -> MICHAEL BORE | J19: ='Portefeuille SP2'!D25 -> BIW | K19: ='Portefeuille SP2'!H25 -> Rear quarter GLASS | L19: ='Portefeuille SP2'!U25 -> 0.75 | P19: ='Portefeuille SP2'!M25 -> 690K€ | R19: ='Portefeuille SP2'!N25 -> 27.1 | T19: ='Portefeuille SP2'!R25 -> TBD | U19: ='Portefeuille SP2'!K25 -> PM-CM | V19: ='Portefeuille SP2'!S25 -> 0.75 | AE19: ='Portefeuille SP2'!J25 -> 06/10/2025 OK pour P3U et J2U | AJ19: ='Portefeuille SP2'!V25 -> 1 | AK19: ='Portefeuille SP2'!W25 -> 1 | AL19: ='Portefeuille SP2'!X25 -> 1 | AM19: ='Portefeuille SP2'!Y25 -> 1 | AN19: ='Portefeuille SP2'!Z25 -> 1 | AO19: ='Portefeuille SP2'!AA25 -> 1 | AP19: ='Portefeuille SP2'!AB25 -> 1 | AQ19: ='Portefeuille SP2'!AC25 -> 1 | ... BF19: ='Portefeuille SP2'!AR25 -> 1 | BG19: ='Portefeuille SP2'!#REF! -> #REF! | BH19: ='Portefeuille SP2'!#REF! -> #REF! | BI19: ='Portefeuille SP2'!#REF! -> #REF! | BJ19: ='Portefeuille SP2'!#REF! -> #REF! | BK19: ='Portefeuille SP2'!#REF! -> #REF! | BM19: ='Portefeuille SP2'!L25 -> 26/06/2025 a reboucler après hypothèse projet
A20: ='Portefeuille SP2'!B26 -> 46058 | B20: ='Portefeuille SP2'!Q26 -> IN PROGRESS | D20: ='Portefeuille SP2'!E26 -> PTF | E20: =LEFT(J20,3) -> SWX | F20: =MID(J20, 4, 20) -> /EE | G20: ='Portefeuille SP2'!C26 -> SP1 | H20: ='Portefeuille SP2'!F26 -> 0 | J20: ='Portefeuille SP2'!D26 -> SWX/EE | K20: ='Portefeuille SP2'!H26 -> ENGINE CABLE DUCT | L20: ='Portefeuille SP2'!U26 -> 0.01 | P20: ='Portefeuille SP2'!M26 -> 0 | R20: ='Portefeuille SP2'!N26 -> 0 | T20: ='Portefeuille SP2'!R26 -> 0 | U20: ='Portefeuille SP2'!K26 -> 0 | V20: ='Portefeuille SP2'!S26 -> 0.5 | AE20: ='Portefeuille SP2'!J26 -> 0 | AJ20: ='Portefeuille SP2'!V26 -> 1 | AK20: ='Portefeuille SP2'!W26 -> 1 | AL20: ='Portefeuille SP2'!X26 -> 1 | AM20: ='Portefeuille SP2'!Y26 -> 1 | AN20: ='Portefeuille SP2'!Z26 -> 1 | AO20: ='Portefeuille SP2'!AA26 -> 1 | AP20: ='Portefeuille SP2'!AB26 -> 1 | AQ20: ='Portefeuille SP2'!AC26 -> 1 | ... BF20: ='Portefeuille SP2'!AR26 -> 1 | BG20: ='Portefeuille SP2'!#REF! -> #REF! | BH20: ='Portefeuille SP2'!#REF! -> #REF! | BI20: ='Portefeuille SP2'!#REF! -> #REF! | BJ20: ='Portefeuille SP2'!#REF! -> #REF! | BK20: ='Portefeuille SP2'!#REF! -> #REF! | BM20: ='Portefeuille SP2'!L26 -> 25/09/2024 : Compté dans le périmètre TH. 18/07/2024 : issu GT EE scope du 15/07/2024
A21: ='Portefeuille SP2'!B27 -> 25/09/2024 | B21: ='Portefeuille SP2'!Q27 -> CANCELED | D21: ='Portefeuille SP2'!E27 -> TH | E21: =LEFT(J21,3) -> ICD | F21: =MID(J21, 6, 20) | G21: ='Portefeuille SP2'!C27 -> SP1 | H21: ='Portefeuille SP2'!F27 -> 0 | J21: ='Portefeuille SP2'!D27 -> ICDV | K21: ='Portefeuille SP2'!H27 -> 0 | L21: ='Portefeuille SP2'!U27 -> -0.6 | P21: ='Portefeuille SP2'!M27 -> 0 | R21: ='Portefeuille SP2'!N27 -> 0 | T21: ='Portefeuille SP2'!R27 -> 0 | U21: ='Portefeuille SP2'!K27 -> 0 | V21: ='Portefeuille SP2'!S27 -> 0.5 | AE21: ='Portefeuille SP2'!J27 -> 0 | AJ21: ='Portefeuille SP2'!V27 -> 1 | AK21: ='Portefeuille SP2'!W27 -> 1 | AL21: ='Portefeuille SP2'!X27 -> 1 | AM21: ='Portefeuille SP2'!Y27 -> 1 | AN21: ='Portefeuille SP2'!Z27 -> 1 | AO21: ='Portefeuille SP2'!AA27 -> 1 | AP21: ='Portefeuille SP2'!AB27 -> 1 | AQ21: ='Portefeuille SP2'!AC27 -> 1 | ... BF21: ='Portefeuille SP2'!AR27 -> 1 | BG21: ='Portefeuille SP2'!#REF! -> #REF! | BH21: ='Portefeuille SP2'!#REF! -> #REF! | BI21: ='Portefeuille SP2'!#REF! -> #REF! | BJ21: ='Portefeuille SP2'!#REF! -> #REF! | BK21: ='Portefeuille SP2'!#REF! -> #REF! | BM21: ='Portefeuille SP2'!L27 -> 25/09/2024 reporté S40 02/09/2024 besoin anayse VDYN 12/06/2024 New / attente retour frns
A22: ='Portefeuille SP2'!B28 -> 08/04/2025 | B22: ='Portefeuille SP2'!Q28 -> DECIDED | D22: ='Portefeuille SP2'!E28 -> TH | E22: =LEFT(J22,3) -> BIW | F22: =MID(J22, 4, 20) | G22: ='Portefeuille SP2'!C28 -> SP1 | H22: ='Portefeuille SP2'!F28 -> Franck Baillon (SP1)/ Cyrille P1X | J22: ='Portefeuille SP2'!D28 -> BIW | K22: ='Portefeuille SP2'!H28 -> new part | L22: ='Portefeuille SP2'!U28 -> 0.54 | P22: ='Portefeuille SP2'!M28 -> 0 | R22: ='Portefeuille SP2'!N28 -> 0 | T22: ='Portefeuille SP2'!R28 -> 0 | U22: ='Portefeuille SP2'!K28 -> 0 | V22: ='Portefeuille SP2'!S28 -> 1 | AE22: ='Portefeuille SP2'!J28 -> ???? Déjà sur SP2 | AJ22: ='Portefeuille SP2'!V28 -> 1 | AK22: ='Portefeuille SP2'!W28 -> 1 | AL22: ='Portefeuille SP2'!X28 -> 1 | AM22: ='Portefeuille SP2'!Y28 -> 1 | AN22: ='Portefeuille SP2'!Z28 -> 1 | AO22: ='Portefeuille SP2'!AA28 -> 1 | AP22: ='Portefeuille SP2'!AB28 -> 1 | AQ22: ='Portefeuille SP2'!AC28 -> 1 | ... BF22: ='Portefeuille SP2'!AR28 -> 1 | BG22: ='Portefeuille SP2'!#REF! -> #REF! | BH22: ='Portefeuille SP2'!#REF! -> #REF! | BI22: ='Portefeuille SP2'!#REF! -> #REF! | BJ22: ='Portefeuille SP2'!#REF! -> #REF! | BK22: ='Portefeuille SP2'!#REF! -> #REF! | BM22: ='Portefeuille SP2'!L28 -> 08/04/2025 Détail : Finition LAT D/G Grille Entrée Air / Grille Entrée Air / Deflect Eau / Etanchéité D/G Grille / Conduit Entrée Air 22/11/2024 Complétude de BOM
A23: ='Portefeuille SP2'!B29 -> 06/06/2025 | B23: ='Portefeuille SP2'!Q29 -> CANCELED | D23: ='Portefeuille SP2'!E29 -> TH | E23: =LEFT(J23,3) -> FRS | F23: =MID(J23, 4, 20) -> D | G23: ='Portefeuille SP2'!C29 -> SP1 | H23: ='Portefeuille SP2'!F29 -> Sébastien Bonnefoi (P1H)/ Jean Michel Gabus P1X | J23: ='Portefeuille SP2'!D29 -> FRSD | K23: ='Portefeuille SP2'!H29 -> Front/Rear bumper | L23: ='Portefeuille SP2'!U29 -> 0.5 | P23: ='Portefeuille SP2'!M29 -> 0 | R23: ='Portefeuille SP2'!N29 -> 0 | T23: ='Portefeuille SP2'!R29 -> 0 | U23: ='Portefeuille SP2'!K29 -> 0 | V23: ='Portefeuille SP2'!S29 -> 0.25 | AE23: ='Portefeuille SP2'!J29 -> traité en PORO dépend du style | AJ23: ='Portefeuille SP2'!V29 -> 1 | AK23: ='Portefeuille SP2'!W29 -> 1 | AL23: ='Portefeuille SP2'!X29 -> 1 | AM23: ='Portefeuille SP2'!Y29 -> 1 | AN23: ='Portefeuille SP2'!Z29 -> 1 | AO23: ='Portefeuille SP2'!AA29 -> 1 | AP23: ='Portefeuille SP2'!AB29 -> 1 | AQ23: ='Portefeuille SP2'!AC29 -> 1 | ... BF23: ='Portefeuille SP2'!AR29 -> 1 | BG23: ='Portefeuille SP2'!#REF! -> #REF! | BH23: ='Portefeuille SP2'!#REF! -> #REF! | BI23: ='Portefeuille SP2'!#REF! -> #REF! | BJ23: ='Portefeuille SP2'!#REF! -> #REF! | BK23: ='Portefeuille SP2'!#REF! -> #REF! | BM23: ='Portefeuille SP2'!L29 -> 06/06/2025 PC P1X avec Air-Curtain
A24: ='Portefeuille SP2'!B30 -> 46058 | B24: ='Portefeuille SP2'!Q30 -> CANCELED | D24: ='Portefeuille SP2'!E30 -> PTF | E24: =LEFT(J24,3) -> SWX | F24: =MID(J24, 4, 20) -> /EE | G24: ='Portefeuille SP2'!C30 -> SP1 | H24: ='Portefeuille SP2'!F30 -> 0 | J24: ='Portefeuille SP2'!D30 -> SWX/EE | K24: ='Portefeuille SP2'!H30 -> 12V battery | L24: ='Portefeuille SP2'!U30 -> -0.4 | P24: ='Portefeuille SP2'!M30 -> 0 | R24: ='Portefeuille SP2'!N30 -> 0 | T24: ='Portefeuille SP2'!R30 -> 0 | U24: ='Portefeuille SP2'!K30 -> 0 | V24: ='Portefeuille SP2'!S30 -> 1 | AE24: ='Portefeuille SP2'!J30 -> 0 | AJ24: ='Portefeuille SP2'!V30 -> 1 | AK24: ='Portefeuille SP2'!W30 -> 1 | AL24: ='Portefeuille SP2'!X30 -> 1 | AM24: ='Portefeuille SP2'!Y30 -> 1 | AN24: ='Portefeuille SP2'!Z30 -> 1 | AO24: ='Portefeuille SP2'!AA30 -> 1 | AP24: ='Portefeuille SP2'!AB30 -> 1 | AQ24: ='Portefeuille SP2'!AC30 -> 1 | ... BF24: ='Portefeuille SP2'!AR30 -> 0 | BG24: ='Portefeuille SP2'!#REF! -> #REF! | BH24: ='Portefeuille SP2'!#REF! -> #REF! | BI24: ='Portefeuille SP2'!#REF! -> #REF! | BJ24: ='Portefeuille SP2'!#REF! -> #REF! | BK24: ='Portefeuille SP2'!#REF! -> #REF! | BM24: ='Portefeuille SP2'!L30 -> 25/09/2024 : batterie EFR L2 sur niv1. La masse absolue dépend du fournisseur. 24/06/2024 : Retour fournisseur
A25: ='Portefeuille SP2'!B31 -> 09/07/2024 | B25: ='Portefeuille SP2'!Q31 -> IN PROGRESS | D25: ='Portefeuille SP2'!E31 -> PWT | E25: =LEFT(J25,3) -> PRS | F25: =MID(J25, 4, 20) | G25: ='Portefeuille SP2'!C31 -> SP1 | H25: ='Portefeuille SP2'!F31 -> ANTOINE SAINT MARCOUX | J25: ='Portefeuille SP2'!D31 -> PRS | K25: ='Portefeuille SP2'!H31 -> HR battery | L25: ='Portefeuille SP2'!U31 -> 0.35 | P25: ='Portefeuille SP2'!M31 -> 0 | R25: ='Portefeuille SP2'!N31 -> 0 | T25: ='Portefeuille SP2'!R31 -> 0 | U25: ='Portefeuille SP2'!K31 -> 0 | V25: ='Portefeuille SP2'!S31 -> 0.5 | AE25: ='Portefeuille SP2'!J31 -> 0 | AJ25: ='Portefeuille SP2'!V31 -> 1 | AK25: ='Portefeuille SP2'!W31 -> 1 | AL25: ='Portefeuille SP2'!X31 -> 1 | AM25: ='Portefeuille SP2'!Y31 -> 1 | AN25: ='Portefeuille SP2'!Z31 -> 1 | AO25: ='Portefeuille SP2'!AA31 -> 1 | AP25: ='Portefeuille SP2'!AB31 -> 1 | AQ25: ='Portefeuille SP2'!AC31 -> 1 | ... BF25: ='Portefeuille SP2'!AR31 -> 0 | BG25: ='Portefeuille SP2'!#REF! -> #REF! | BH25: ='Portefeuille SP2'!#REF! -> #REF! | BI25: ='Portefeuille SP2'!#REF! -> #REF! | BJ25: ='Portefeuille SP2'!#REF! -> #REF! | BK25: ='Portefeuille SP2'!#REF! -> #REF! | BM25: ='Portefeuille SP2'!L31 -> 09/07/2024 New
A26: ='Portefeuille SP2'!B32 -> 09/07/2024 | B26: ='Portefeuille SP2'!Q32 -> IN PROGRESS | D26: ='Portefeuille SP2'!E32 -> PWT | E26: =LEFT(J26,3) -> PRS | F26: =MID(J26, 4, 20) | G26: ='Portefeuille SP2'!C32 -> SP1 | H26: ='Portefeuille SP2'!F32 -> ANTOINE SAINT MARCOUX | J26: ='Portefeuille SP2'!D32 -> PRS | K26: ='Portefeuille SP2'!H32 -> HR battery | L26: ='Portefeuille SP2'!U32 -> -1.5 | P26: ='Portefeuille SP2'!M32 -> 0 | R26: ='Portefeuille SP2'!N32 -> 0 | T26: ='Portefeuille SP2'!R32 -> 0 | U26: ='Portefeuille SP2'!K32 -> 0 | V26: ='Portefeuille SP2'!S32 -> 0.5 | AE26: ='Portefeuille SP2'!J32 -> 0 | AJ26: ='Portefeuille SP2'!V32 -> 1 | AK26: ='Portefeuille SP2'!W32 -> 1 | AL26: ='Portefeuille SP2'!X32 -> 1 | AM26: ='Portefeuille SP2'!Y32 -> 1 | AN26: ='Portefeuille SP2'!Z32 -> 1 | AO26: ='Portefeuille SP2'!AA32 -> 1 | AP26: ='Portefeuille SP2'!AB32 -> 1 | AQ26: ='Portefeuille SP2'!AC32 -> 1 | ... BF26: ='Portefeuille SP2'!AR32 -> 0 | BG26: ='Portefeuille SP2'!#REF! -> #REF! | BH26: ='Portefeuille SP2'!#REF! -> #REF! | BI26: ='Portefeuille SP2'!#REF! -> #REF! | BJ26: ='Portefeuille SP2'!#REF! -> #REF! | BK26: ='Portefeuille SP2'!#REF! -> #REF! | BM26: ='Portefeuille SP2'!L32 -> 26/09/2025 Brackets : inc ds le STATUS 24/07/2025 2 sujets new : Bracket reinforct -2kg / Alu Busbar-3 (50%) 09/07/2024 New
A27: ='Portefeuille SP2'!B33 -> 08/04/2025 | B27: ='Portefeuille SP2'!Q33 -> CANCELED | D27: ='Portefeuille SP2'!E33 -> TH | E27: =LEFT(J27,3) -> INT | F27: =MID(J27, 4, 20) -> - SEATS/TRIMS | G27: ='Portefeuille SP2'!C33 -> SP1 | H27: ='Portefeuille SP2'!F33 -> HALIM | J27: ='Portefeuille SP2'!D33 -> INT - SEATS/TRIMS | K27: ='Portefeuille SP2'!H33 -> Carpet insulation | L27: ='Portefeuille SP2'!U33 -> 0.3705 | P27: ='Portefeuille SP2'!M33 -> 0 | R27: ='Portefeuille SP2'!N33 -> 0 | T27: ='Portefeuille SP2'!R33 -> 0 | U27: ='Portefeuille SP2'!K33 -> SFM | V27: ='Portefeuille SP2'!S33 -> 0.25 | AE27: ='Portefeuille SP2'!J33 -> 24/06/2025 à vérifier plus tard | AJ27: ='Portefeuille SP2'!V33 -> 1 | AK27: ='Portefeuille SP2'!W33 -> 1 | AL27: ='Portefeuille SP2'!X33 -> 1 | AM27: ='Portefeuille SP2'!Y33 -> 1 | AN27: ='Portefeuille SP2'!Z33 -> 1 | AO27: ='Portefeuille SP2'!AA33 -> 1 | AP27: ='Portefeuille SP2'!AB33 -> 1 | AQ27: ='Portefeuille SP2'!AC33 -> 1 | ... BF27: ='Portefeuille SP2'!AR33 -> 1 | BG27: ='Portefeuille SP2'!#REF! -> #REF! | BH27: ='Portefeuille SP2'!#REF! -> #REF! | BI27: ='Portefeuille SP2'!#REF! -> #REF! | BJ27: ='Portefeuille SP2'!#REF! -> #REF! | BK27: ='Portefeuille SP2'!#REF! -> #REF! | BM27: ='Portefeuille SP2'!L33 -> 08/04/2025 GT_calcul : Risque levé pour P1H-SR / Reste pour HR et XR 18/03/2025 Coord_STLAS : Pour P1h=7pièces => +1,5kg ; +4€ // Pour P1X +2pièces 19/11/2024 Risque SYNC3 (Estim 1,2*1,9 / 650gr/m²:GlassMAT™HTX isolation thermique et phonique des compartiments moteur)
A28: ='Portefeuille SP2'!B34 -> 08/10/2024 | B28: ='Portefeuille SP2'!Q34 -> CANCELED | D28: ='Portefeuille SP2'!E34 -> PTF | E28: =LEFT(J28,3) -> SWX | F28: =MID(J28, 6, 20) -> E | G28: ='Portefeuille SP2'!C34 -> SP1 | H28: ='Portefeuille SP2'!F34 -> 0 | J28: ='Portefeuille SP2'!D34 -> SWX/EE | K28: ='Portefeuille SP2'!H34 -> 0 | L28: ='Portefeuille SP2'!U34 -> -1.3 | P28: ='Portefeuille SP2'!M34 -> 0 | R28: ='Portefeuille SP2'!N34 -> 0 | T28: ='Portefeuille SP2'!R34 -> 0 | U28: ='Portefeuille SP2'!K34 -> 0 | V28: ='Portefeuille SP2'!S34 -> 0.5 | AE28: ='Portefeuille SP2'!J34 -> 0 | AJ28: ='Portefeuille SP2'!V34 -> 1 | AK28: ='Portefeuille SP2'!W34 -> 1 | AL28: ='Portefeuille SP2'!X34 -> 1 | AM28: ='Portefeuille SP2'!Y34 -> 1 | AN28: ='Portefeuille SP2'!Z34 -> 1 | AO28: ='Portefeuille SP2'!AA34 -> 1 | AP28: ='Portefeuille SP2'!AB34 -> 1 | AQ28: ='Portefeuille SP2'!AC34 -> 1 | ... BF28: ='Portefeuille SP2'!AR34 -> 1 | BG28: ='Portefeuille SP2'!#REF! -> #REF! | BH28: ='Portefeuille SP2'!#REF! -> #REF! | BI28: ='Portefeuille SP2'!#REF! -> #REF! | BJ28: ='Portefeuille SP2'!#REF! -> #REF! | BK28: ='Portefeuille SP2'!#REF! -> #REF! | BM28: ='Portefeuille SP2'!L34 -> 08/10/2024 : Proposition de mettre le cable en option lors de l'achat (forcée par défaut dans le cnfigurateur avec possibilité de le supprimer). 25/09/2024 : Interdit par la politique tech pour le passage APV (Julien Grand clerc / Alain Lefevre sollicités pour offi). 19/06/2024 : en cours sur SP1 et sur SP2 13/03/2024 ECMP > APV
A29: ='Portefeuille SP2'!B35 -> 28/05/2025 | B29: ='Portefeuille SP2'!Q35 -> CANCELED | D29: ='Portefeuille SP2'!E35 -> TH | E29: =LEFT(J29,3) -> FRS | F29: =MID(J29, 6, 20) | G29: ='Portefeuille SP2'!C35 -> SP1 | H29: ='Portefeuille SP2'!F35 -> Sébastien Bonnefoi (P1H)/ Jean Michel Gabus P1X | J29: ='Portefeuille SP2'!D35 -> FRSD | K29: ='Portefeuille SP2'!H35 -> style/brand | L29: ='Portefeuille SP2'!U35 -> 0.125 | P29: ='Portefeuille SP2'!M35 -> 0 | R29: ='Portefeuille SP2'!N35 -> 0 | T29: ='Portefeuille SP2'!R35 -> 0 | U29: ='Portefeuille SP2'!K35 -> 0 | V29: ='Portefeuille SP2'!S35 -> 0.25 | AE29: ='Portefeuille SP2'!J35 -> 0 | AJ29: ='Portefeuille SP2'!V35 -> 1 | AK29: ='Portefeuille SP2'!W35 -> 1 | AL29: ='Portefeuille SP2'!X35 -> 1 | AM29: ='Portefeuille SP2'!Y35 -> 1 | AN29: ='Portefeuille SP2'!Z35 -> 1 | AO29: ='Portefeuille SP2'!AA35 -> 1 | AP29: ='Portefeuille SP2'!AB35 -> 1 | AQ29: ='Portefeuille SP2'!AC35 -> 1 | ... BF29: ='Portefeuille SP2'!AR35 -> 1 | BG29: ='Portefeuille SP2'!#REF! -> #REF! | BH29: ='Portefeuille SP2'!#REF! -> #REF! | BI29: ='Portefeuille SP2'!#REF! -> #REF! | BJ29: ='Portefeuille SP2'!#REF! -> #REF! | BK29: ='Portefeuille SP2'!#REF! -> #REF! | BM29: ='Portefeuille SP2'!L35 -> 28/05/2025 CHANTIER MASSE : Nvo Styl, en attente design 25/04/2024 : pas de modif style => A annuler pour P1H. 27/03/2024 New WS S14
A30: ='Portefeuille SP2'!B36 -> 46058 | B30: ='Portefeuille SP2'!Q36 -> IN PROGRESS | D30: ='Portefeuille SP2'!E36 -> PTF | E30: =LEFT(J30,3) -> PHE | F30: =MID(J30, 4, 20) -> S | G30: ='Portefeuille SP2'!C36 -> SP1 | H30: ='Portefeuille SP2'!F36 -> 0 | J30: ='Portefeuille SP2'!D36 -> PHES | K30: ='Portefeuille SP2'!H36 -> support optim | L30: ='Portefeuille SP2'!U36 -> -0.125 | P30: ='Portefeuille SP2'!M36 -> 0 | R30: ='Portefeuille SP2'!N36 -> 0 | T30: ='Portefeuille SP2'!R36 -> 0 | U30: ='Portefeuille SP2'!K36 -> 0 | V30: ='Portefeuille SP2'!S36 -> 0.25 | AE30: ='Portefeuille SP2'!J36 -> 0 | AJ30: ='Portefeuille SP2'!V36 -> 1 | AK30: ='Portefeuille SP2'!W36 -> 1 | AL30: ='Portefeuille SP2'!X36 -> 1 | AM30: ='Portefeuille SP2'!Y36 -> 1 | AN30: ='Portefeuille SP2'!Z36 -> 1 | AO30: ='Portefeuille SP2'!AA36 -> 1 | AP30: ='Portefeuille SP2'!AB36 -> 1 | AQ30: ='Portefeuille SP2'!AC36 -> 1 | ... BF30: ='Portefeuille SP2'!AR36 -> 1 | BG30: ='Portefeuille SP2'!#REF! -> #REF! | BH30: ='Portefeuille SP2'!#REF! -> #REF! | BI30: ='Portefeuille SP2'!#REF! -> #REF! | BJ30: ='Portefeuille SP2'!#REF! -> #REF! | BK30: ='Portefeuille SP2'!#REF! -> #REF! | BM30: ='Portefeuille SP2'!L36 -> 11/09/2024 : Travaux en cours
A31: ='Portefeuille SP2'!B37 -> 46058 | B31: ='Portefeuille SP2'!Q37 -> IN PROGRESS | D31: ='Portefeuille SP2'!E37 -> PTF | E31: =LEFT(J31,3) -> SWX | F31: =MID(J31, 4, 20) -> /EE | G31: ='Portefeuille SP2'!C37 -> SP1 | H31: ='Portefeuille SP2'!F37 -> 0 | J31: ='Portefeuille SP2'!D37 -> SWX/EE | K31: ='Portefeuille SP2'!H37 -> support optim | L31: ='Portefeuille SP2'!U37 -> -0.45 | P31: ='Portefeuille SP2'!M37 -> 0 | R31: ='Portefeuille SP2'!N37 -> 0 | T31: ='Portefeuille SP2'!R37 -> 0 | U31: ='Portefeuille SP2'!K37 -> 0 | V31: ='Portefeuille SP2'!S37 -> 1 | AE31: ='Portefeuille SP2'!J37 -> 0 | AJ31: ='Portefeuille SP2'!V37 -> 1 | AK31: ='Portefeuille SP2'!W37 -> 1 | AL31: ='Portefeuille SP2'!X37 -> 1 | AM31: ='Portefeuille SP2'!Y37 -> 1 | AN31: ='Portefeuille SP2'!Z37 -> 1 | AO31: ='Portefeuille SP2'!AA37 -> 1 | AP31: ='Portefeuille SP2'!AB37 -> 1 | AQ31: ='Portefeuille SP2'!AC37 -> 1 | ... BF31: ='Portefeuille SP2'!AR37 -> 0 | BG31: ='Portefeuille SP2'!#REF! -> #REF! | BH31: ='Portefeuille SP2'!#REF! -> #REF! | BI31: ='Portefeuille SP2'!#REF! -> #REF! | BJ31: ='Portefeuille SP2'!#REF! -> #REF! | BK31: ='Portefeuille SP2'!#REF! -> #REF! | BM31: ='Portefeuille SP2'!L37 -> 09/12/2025 : Proposition de créer une diversité entre les versions AWD et FWD pour tous les HR
A32: ='Portefeuille SP2'!B38 -> 06/06/2025 | B32: ='Portefeuille SP2'!Q38 -> CANCELED | D32: ='Portefeuille SP2'!E38 -> TH | E32: =LEFT(J32,3) -> DIW | F32: =MID(J32, 4, 20) | G32: ='Portefeuille SP2'!C38 -> SP1 | H32: ='Portefeuille SP2'!F38 -> Filipe Goncalves (P1H)/ Cyrille P1X | J32: ='Portefeuille SP2'!D38 -> DIW | K32: ='Portefeuille SP2'!H38 -> BIW/ DIW process | L32: ='Portefeuille SP2'!U38 -> 0.3 | P32: ='Portefeuille SP2'!M38 -> 0 | R32: ='Portefeuille SP2'!N38 -> 0 | T32: ='Portefeuille SP2'!R38 -> 0 | U32: ='Portefeuille SP2'!K38 -> 0 | V32: ='Portefeuille SP2'!S38 -> 0.25 | AE32: ='Portefeuille SP2'!J38 -> 06/02/2026LM Pas concerné | AJ32: ='Portefeuille SP2'!V38 -> 1 | AK32: ='Portefeuille SP2'!W38 -> 1 | AL32: ='Portefeuille SP2'!X38 -> 1 | AM32: ='Portefeuille SP2'!Y38 -> 1 | AN32: ='Portefeuille SP2'!Z38 -> 1 | AO32: ='Portefeuille SP2'!AA38 -> 1 | AP32: ='Portefeuille SP2'!AB38 -> 1 | AQ32: ='Portefeuille SP2'!AC38 -> 1 | ... BF32: ='Portefeuille SP2'!AR38 -> 1 | BG32: ='Portefeuille SP2'!#REF! -> #REF! | BH32: ='Portefeuille SP2'!#REF! -> #REF! | BI32: ='Portefeuille SP2'!#REF! -> #REF! | BJ32: ='Portefeuille SP2'!#REF! -> #REF! | BK32: ='Portefeuille SP2'!#REF! -> #REF! | BM32: ='Portefeuille SP2'!L38 -> 06/06/2025 Niveau de risk diminué à 25%, Final step : fin de SYNC3 04/11/2024 Décalage planning > Post Go_Calcul 12/07/2024 En attente des résultats SYNC3 21/03/2024 A valoriser suite aux résultats SYNC2 (voir avec RM) 14/03/2024 New / A décider avant engagement SYNC3
A33: ='Portefeuille SP2'!B39 -> 08/04/2025 | B33: ='Portefeuille SP2'!Q39 -> DECIDED | D33: ='Portefeuille SP2'!E39 -> TH | E33: =LEFT(J33,3) -> BIW | F33: =MID(J33, 4, 20) | G33: ='Portefeuille SP2'!C39 -> SP1 | H33: ='Portefeuille SP2'!F39 -> Franck Baillon (SP1)/ Cyrille P1X | J33: ='Portefeuille SP2'!D39 -> BIW | K33: ='Portefeuille SP2'!H39 -> risk perfo | L33: ='Portefeuille SP2'!U39 -> 0.444 | P33: ='Portefeuille SP2'!M39 -> 0 | R33: ='Portefeuille SP2'!N39 -> 0 | T33: ='Portefeuille SP2'!R39 -> 0 | U33: ='Portefeuille SP2'!K39 -> 0 | V33: ='Portefeuille SP2'!S39 -> 0.5 | AE33: ='Portefeuille SP2'!J39 -> Bilan Choc dira si on peut appliquer aussi | AJ33: ='Portefeuille SP2'!V39 -> 1 | AK33: ='Portefeuille SP2'!W39 -> 1 | AL33: ='Portefeuille SP2'!X39 -> 1 | AM33: ='Portefeuille SP2'!Y39 -> 1 | AN33: ='Portefeuille SP2'!Z39 -> 1 | AO33: ='Portefeuille SP2'!AA39 -> 1 | AP33: ='Portefeuille SP2'!AB39 -> 1 | AQ33: ='Portefeuille SP2'!AC39 -> 1 | ... BF33: ='Portefeuille SP2'!AR39 -> 1 | BG33: ='Portefeuille SP2'!#REF! -> #REF! | BH33: ='Portefeuille SP2'!#REF! -> #REF! | BI33: ='Portefeuille SP2'!#REF! -> #REF! | BJ33: ='Portefeuille SP2'!#REF! -> #REF! | BK33: ='Portefeuille SP2'!#REF! -> #REF! | BM33: ='Portefeuille SP2'!L39 -> 08/04/2025 Scénario choc tt SP1 : Dbl Aile AV & Rft Abv Cote HAB (+0,888kg) 03/09/2024 En attente travaux Base sur la 3ée voie … Synthèse idem P1H ! (0,5kg à 50%) 25/04/2024 : Suite choc frontal SYNC1 .Risque ajout raidisseu 13/03/2024 maj 01/02/2024 Ptf
A34: ='Portefeuille SP2'!B40 -> 45536 | B34: ='Portefeuille SP2'!Q40 -> CANCELED | D34: ='Portefeuille SP2'!E40 -> TH | E34: =LEFT(J34,3) -> BIW | F34: =MID(J34, 4, 20) | G34: ='Portefeuille SP2'!C40 -> SPC_1 | H34: ='Portefeuille SP2'!F40 -> FRANK BAILLON | J34: ='Portefeuille SP2'!D40 -> BIW | K34: ='Portefeuille SP2'!H40 -> Lower quarter inner | L34: ='Portefeuille SP2'!U40 -> 0.215 | P34: ='Portefeuille SP2'!M40 -> -400K€ | R34: ='Portefeuille SP2'!N40 -> 0.7 | T34: ='Portefeuille SP2'!R40 -> TBD | U34: ='Portefeuille SP2'!K40 -> DTM PM-CM | V34: ='Portefeuille SP2'!S40 -> 0.5 | AE34: ='Portefeuille SP2'!J40 -> 06/10/2025 a reboucler avec l'embout - Mickael Ludovic DASNOIS | AJ34: ='Portefeuille SP2'!V40 -> 1 | AK34: ='Portefeuille SP2'!W40 -> 1 | AL34: ='Portefeuille SP2'!X40 -> 1 | AM34: ='Portefeuille SP2'!Y40 -> 1 | AN34: ='Portefeuille SP2'!Z40 -> 1 | AO34: ='Portefeuille SP2'!AA40 -> 1 | AP34: ='Portefeuille SP2'!AB40 -> 1 | AQ34: ='Portefeuille SP2'!AC40 -> 1 | ... BF34: ='Portefeuille SP2'!AR40 -> 1 | BG34: ='Portefeuille SP2'!#REF! -> #REF! | BH34: ='Portefeuille SP2'!#REF! -> #REF! | BI34: ='Portefeuille SP2'!#REF! -> #REF! | BJ34: ='Portefeuille SP2'!#REF! -> #REF! | BK34: ='Portefeuille SP2'!#REF! -> #REF! | BM34: ='Portefeuille SP2'!L40 -> 26/06/2025 a reboucler après hypothèse projet
A35: ='Portefeuille SP2'!B41 -> 45536 | B35: ='Portefeuille SP2'!Q41 -> CANCELED | D35: ='Portefeuille SP2'!E41 -> TH | E35: =LEFT(J35,3) -> BIW | F35: =MID(J35, 4, 20) | G35: ='Portefeuille SP2'!C41 -> SPC_1 | H35: ='Portefeuille SP2'!F41 -> FRANK BAILLON | J35: ='Portefeuille SP2'!D41 -> BIW | K35: ='Portefeuille SP2'!H41 -> Rear Inner pannel | L35: ='Portefeuille SP2'!U41 -> 0.2 | P35: ='Portefeuille SP2'!M41 -> -500K€ | R35: ='Portefeuille SP2'!N41 -> 0.6 | T35: ='Portefeuille SP2'!R41 -> TBD | U35: ='Portefeuille SP2'!K41 -> DTM PM-CM | V35: ='Portefeuille SP2'!S41 -> 0.5 | AE35: ='Portefeuille SP2'!J41 -> 06/10/2025 a reboucler avec l'embout - Mickael Ludovic DASNOIS | AJ35: ='Portefeuille SP2'!V41 -> 1 | AK35: ='Portefeuille SP2'!W41 -> 1 | AL35: ='Portefeuille SP2'!X41 -> 1 | AM35: ='Portefeuille SP2'!Y41 -> 1 | AN35: ='Portefeuille SP2'!Z41 -> 1 | AO35: ='Portefeuille SP2'!AA41 -> 1 | AP35: ='Portefeuille SP2'!AB41 -> 1 | AQ35: ='Portefeuille SP2'!AC41 -> 1 | ... BF35: ='Portefeuille SP2'!AR41 -> 1 | BG35: ='Portefeuille SP2'!#REF! -> #REF! | BH35: ='Portefeuille SP2'!#REF! -> #REF! | BI35: ='Portefeuille SP2'!#REF! -> #REF! | BJ35: ='Portefeuille SP2'!#REF! -> #REF! | BK35: ='Portefeuille SP2'!#REF! -> #REF! | BM35: ='Portefeuille SP2'!L41 -> 26/06/2025 a reboucler après hypothèse projet
A36: ='Portefeuille SP2'!B42 -> 46083 | B36: ='Portefeuille SP2'!Q42 -> CANCELED | D36: ='Portefeuille SP2'!E42 -> TH | E36: =LEFT(J36,3) -> INT | F36: =MID(J36, 4, 20) -> - SEATS/TRIMS | G36: ='Portefeuille SP2'!C42 -> SPC_1 | H36: ='Portefeuille SP2'!F42 -> HALIM | J36: ='Portefeuille SP2'!D42 -> INT - SEATS/TRIMS | K36: ='Portefeuille SP2'!H42 -> optim design | L36: ='Portefeuille SP2'!U42 -> 0 | P36: ='Portefeuille SP2'!M42 -> 0 | R36: ='Portefeuille SP2'!N42 -> 0 | T36: ='Portefeuille SP2'!R42 -> 0 | U36: ='Portefeuille SP2'!K42 -> SFM | V36: ='Portefeuille SP2'!S42 -> 0.5 | AE36: ='Portefeuille SP2'!J42 -> 02/03/2026 LM Meeting CW10 | AJ36: ='Portefeuille SP2'!V42 -> 1 | AK36: ='Portefeuille SP2'!W42 -> 1 | AL36: ='Portefeuille SP2'!X42 -> 1 | AM36: ='Portefeuille SP2'!Y42 -> 1 | AN36: ='Portefeuille SP2'!Z42 -> 1 | AO36: ='Portefeuille SP2'!AA42 -> 1 | AP36: ='Portefeuille SP2'!AB42 -> 1 | AQ36: ='Portefeuille SP2'!AC42 -> 1 | ... BF36: ='Portefeuille SP2'!AR42 -> 1 | BG36: ='Portefeuille SP2'!#REF! -> #REF! | BH36: ='Portefeuille SP2'!#REF! -> #REF! | BI36: ='Portefeuille SP2'!#REF! -> #REF! | BJ36: ='Portefeuille SP2'!#REF! -> #REF! | BK36: ='Portefeuille SP2'!#REF! -> #REF! | BM36: ='Portefeuille SP2'!L42 -> 0
A37: ='Portefeuille SP2'!B43 -> 18/06/2024 | B37: ='Portefeuille SP2'!Q43 -> CANCELED | D37: ='Portefeuille SP2'!E43 -> TH | E37: =LEFT(J37,3) -> BIW | F37: =MID(J37, 4, 20) | G37: ='Portefeuille SP2'!C43 -> SP1 | H37: ='Portefeuille SP2'!F43 -> FRANK BAILLON | J37: ='Portefeuille SP2'!D43 -> BIW | K37: ='Portefeuille SP2'!H43 -> optim design | L37: ='Portefeuille SP2'!U43 -> 0.15 | P37: ='Portefeuille SP2'!M43 -> 0 | R37: ='Portefeuille SP2'!N43 -> 0 | T37: ='Portefeuille SP2'!R43 -> 0 | U37: ='Portefeuille SP2'!K43 -> SFM | V37: ='Portefeuille SP2'!S43 -> 0.5 | AE37: ='Portefeuille SP2'!J43 -> 24/06/2025 à checker en RFQ avec les FNR | AJ37: ='Portefeuille SP2'!V43 -> 1 | AK37: ='Portefeuille SP2'!W43 -> 1 | AL37: ='Portefeuille SP2'!X43 -> 1 | AM37: ='Portefeuille SP2'!Y43 -> 1 | AN37: ='Portefeuille SP2'!Z43 -> 1 | AO37: ='Portefeuille SP2'!AA43 -> 1 | AP37: ='Portefeuille SP2'!AB43 -> 1 | AQ37: ='Portefeuille SP2'!AC43 -> 1 | ... BF37: ='Portefeuille SP2'!AR43 -> 1 | BG37: ='Portefeuille SP2'!#REF! -> #REF! | BH37: ='Portefeuille SP2'!#REF! -> #REF! | BI37: ='Portefeuille SP2'!#REF! -> #REF! | BJ37: ='Portefeuille SP2'!#REF! -> #REF! | BK37: ='Portefeuille SP2'!#REF! -> #REF! | BM37: ='Portefeuille SP2'!L43 -> 18/06/2024 Dossier RFQ : Masses sup
A38: ='Portefeuille SP2'!B44 -> 26/08/2024 | B38: ='Portefeuille SP2'!Q44 -> CANCELED | D38: ='Portefeuille SP2'!E44 -> PWT | E38: =LEFT(J38,3) -> PRS | F38: =MID(J38, 6, 20) | G38: ='Portefeuille SP2'!C44 -> SP1 | H38: ='Portefeuille SP2'!F44 -> 0 | J38: ='Portefeuille SP2'!D44 -> PRS | K38: ='Portefeuille SP2'!H44 -> 0 | L38: ='Portefeuille SP2'!U44 -> 0.9 | P38: ='Portefeuille SP2'!M44 -> 0 | R38: ='Portefeuille SP2'!N44 -> 0 | T38: ='Portefeuille SP2'!R44 -> 0 | U38: ='Portefeuille SP2'!K44 -> 0 | V38: ='Portefeuille SP2'!S44 -> 0.5 | AE38: ='Portefeuille SP2'!J44 -> 0 | AJ38: ='Portefeuille SP2'!V44 -> 1 | AK38: ='Portefeuille SP2'!W44 -> 1 | AL38: ='Portefeuille SP2'!X44 -> 1 | AM38: ='Portefeuille SP2'!Y44 -> 1 | AN38: ='Portefeuille SP2'!Z44 -> 1 | AO38: ='Portefeuille SP2'!AA44 -> 1 | AP38: ='Portefeuille SP2'!AB44 -> 1 | AQ38: ='Portefeuille SP2'!AC44 -> 1 | ... BF38: ='Portefeuille SP2'!AR44 -> 1 | BG38: ='Portefeuille SP2'!#REF! -> #REF! | BH38: ='Portefeuille SP2'!#REF! -> #REF! | BI38: ='Portefeuille SP2'!#REF! -> #REF! | BJ38: ='Portefeuille SP2'!#REF! -> #REF! | BK38: ='Portefeuille SP2'!#REF! -> #REF! | BM38: ='Portefeuille SP2'!L44 -> 26/08/2024 Status maj > Ptf en Risque => Echéance C-sample : date ? 08/07/2024 Mass updated CW27 / maj en cours
A39: ='Portefeuille SP2'!B45 -> 46058 | B39: ='Portefeuille SP2'!Q45 -> IN PROGRESS | D39: ='Portefeuille SP2'!E45 -> PTF | E39: =LEFT(J39,3) -> BCI | F39: =MID(J39, 4, 20) -> _BODY | G39: ='Portefeuille SP2'!C45 -> SP1 | H39: ='Portefeuille SP2'!F45 -> 0 | J39: ='Portefeuille SP2'!D45 -> BCI_BODY | K39: ='Portefeuille SP2'!H45 -> optim phase 2 | L39: ='Portefeuille SP2'!U45 -> -0.5 | P39: ='Portefeuille SP2'!M45 -> 0 | R39: ='Portefeuille SP2'!N45 -> 0 | T39: ='Portefeuille SP2'!R45 -> 0 | U39: ='Portefeuille SP2'!K45 -> 0 | V39: ='Portefeuille SP2'!S45 -> 0.25 | AE39: ='Portefeuille SP2'!J45 -> 0 | AJ39: ='Portefeuille SP2'!V45 -> 1 | AK39: ='Portefeuille SP2'!W45 -> 1 | AL39: ='Portefeuille SP2'!X45 -> 1 | AM39: ='Portefeuille SP2'!Y45 -> 1 | AN39: ='Portefeuille SP2'!Z45 -> 1 | AO39: ='Portefeuille SP2'!AA45 -> 1 | AP39: ='Portefeuille SP2'!AB45 -> 1 | AQ39: ='Portefeuille SP2'!AC45 -> 1 | ... BF39: ='Portefeuille SP2'!AR45 -> 0 | BG39: ='Portefeuille SP2'!#REF! -> #REF! | BH39: ='Portefeuille SP2'!#REF! -> #REF! | BI39: ='Portefeuille SP2'!#REF! -> #REF! | BJ39: ='Portefeuille SP2'!#REF! -> #REF! | BK39: ='Portefeuille SP2'!#REF! -> #REF! | BM39: ='Portefeuille SP2'!L45 -> 17/11/2025 : Config P1H figée. 17/07/2025 : Pas de casse d'écran (ecran ar cassé mais à priori non conforme). Attente retour QAU pour voir si déformation ok. 07/07/2025 : Ecran actuellement trop souple. Besoin d'essai de passage au gué pour etat des lieux (cette semaine). Voir avec JC si masse des ecrans dans la BOM est conforme de la techno Mussel. 20/11/2024 : Consultation en cours. Certains fournisseurs propose la techno Mussel : injecte de l'air dans la matière pour avoir de l'épaisseur sans masse (permet d'avoir de la raideur et de réduire le besoin de nervurage). Choix fournisseur début avril 2025. 23/10/2024 : Design avant essai 23/09/2024 : Piste maximisée
A40: ='Portefeuille SP2'!B46 -> 11/02/2025 | B40: ='Portefeuille SP2'!Q46 -> CANCELED | D40: ='Portefeuille SP2'!E46 -> PTF | E40: =LEFT(J40,3) -> BCI | F40: =MID(J40, 4, 20) -> _CHASSIS | G40: ='Portefeuille SP2'!C46 -> SP1 | H40: ='Portefeuille SP2'!F46 -> 0 | J40: ='Portefeuille SP2'!D46 -> BCI_CHASSIS | K40: ='Portefeuille SP2'!H46 -> Steer-by-wire steering wheel actuator (SBW only) | L40: ='Portefeuille SP2'!U46 -> -0.175 | P40: ='Portefeuille SP2'!M46 -> 0 | R40: ='Portefeuille SP2'!N46 -> 0 | T40: ='Portefeuille SP2'!R46 -> 0 | U40: ='Portefeuille SP2'!K46 -> 0 | V40: ='Portefeuille SP2'!S46 -> 0.25 | AE40: ='Portefeuille SP2'!J46 -> 0 | AJ40: ='Portefeuille SP2'!V46 -> 1 | AK40: ='Portefeuille SP2'!W46 -> 1 | AL40: ='Portefeuille SP2'!X46 -> 1 | AM40: ='Portefeuille SP2'!Y46 -> 1 | AN40: ='Portefeuille SP2'!Z46 -> 1 | AO40: ='Portefeuille SP2'!AA46 -> 1 | AP40: ='Portefeuille SP2'!AB46 -> 1 | AQ40: ='Portefeuille SP2'!AC46 -> 1 | ... BF40: ='Portefeuille SP2'!AR46 -> 1 | BG40: ='Portefeuille SP2'!#REF! -> #REF! | BH40: ='Portefeuille SP2'!#REF! -> #REF! | BI40: ='Portefeuille SP2'!#REF! -> #REF! | BJ40: ='Portefeuille SP2'!#REF! -> #REF! | BK40: ='Portefeuille SP2'!#REF! -> #REF! | BM40: ='Portefeuille SP2'!L46 -> 11/02/2025 : Pb en collapse vu en simu qui risque d'augmenter la masse. Essai physique cette semaine à Turin. Existe une solution en simu qui resout le problème -> à chiffrer S08 + passage en VSM/PTM S07 pour valider ECR chez le fournisseur 7/25/2024 : GT presta S30 : Convergence presque à la cible avec une estimation masse à 7.3 kg ald 8 kg en cible. Il reste des implementation à faire mais probablement pas à la hauteur des +0.7 d'écart.
A41: ='Portefeuille SP2'!B47 -> 11/02/2025 | B41: ='Portefeuille SP2'!Q47 -> CANCELED | D41: ='Portefeuille SP2'!E47 -> PTF | E41: =LEFT(J41,3) -> BCI | F41: =MID(J41, 4, 20) -> _CHASSIS | G41: ='Portefeuille SP2'!C47 -> SP1 | H41: ='Portefeuille SP2'!F47 -> 0 | J41: ='Portefeuille SP2'!D47 -> BCI_CHASSIS | K41: ='Portefeuille SP2'!H47 -> Steer-by-wire steering wheel actuator (SBW only) | L41: ='Portefeuille SP2'!U47 -> 0.3 | P41: ='Portefeuille SP2'!M47 -> 0 | R41: ='Portefeuille SP2'!N47 -> 0 | T41: ='Portefeuille SP2'!R47 -> 0 | U41: ='Portefeuille SP2'!K47 -> 0 | V41: ='Portefeuille SP2'!S47 -> 1 | AE41: ='Portefeuille SP2'!J47 -> 0 | AJ41: ='Portefeuille SP2'!V47 -> 1 | AK41: ='Portefeuille SP2'!W47 -> 1 | AL41: ='Portefeuille SP2'!X47 -> 1 | AM41: ='Portefeuille SP2'!Y47 -> 1 | AN41: ='Portefeuille SP2'!Z47 -> 1 | AO41: ='Portefeuille SP2'!AA47 -> 1 | AP41: ='Portefeuille SP2'!AB47 -> 1 | AQ41: ='Portefeuille SP2'!AC47 -> 1 | ... BF41: ='Portefeuille SP2'!AR47 -> 1 | BG41: ='Portefeuille SP2'!#REF! -> #REF! | BH41: ='Portefeuille SP2'!#REF! -> #REF! | BI41: ='Portefeuille SP2'!#REF! -> #REF! | BJ41: ='Portefeuille SP2'!#REF! -> #REF! | BK41: ='Portefeuille SP2'!#REF! -> #REF! | BM41: ='Portefeuille SP2'!L47 -> 11/02/2025 : Solution fer à cheval choisie. Retour cette semaine pour la faisa. 03/10/2024 : Essai prévu S40 mais pb appro pièce. 28/08/2024 : Travail en cours sur la traverse PdB. Simu et essais en cours. Délai a voir avec Philippe Vannier et Olivier en GT Prestation. 7/25/2024 : GT presta S30 : Convergence presque à la cible avec une estimation masse à 7.3 kg ald 8 kg en cible. Il reste des implementation à faire mais probablement pas à la hauteur des +0.7 d'écart.
A42: ='Portefeuille SP2'!B48 -> 11/02/2025 | B42: ='Portefeuille SP2'!Q48 -> CANCELED | D42: ='Portefeuille SP2'!E48 -> PTF | E42: =LEFT(J42,3) -> BCI | F42: =MID(J42, 4, 20) -> _BODY | G42: ='Portefeuille SP2'!C48 -> SP1 | H42: ='Portefeuille SP2'!F48 -> 0 | J42: ='Portefeuille SP2'!D48 -> BCI_BODY | K42: ='Portefeuille SP2'!H48 -> Side rail area | L42: ='Portefeuille SP2'!U48 -> 0.5 | P42: ='Portefeuille SP2'!M48 -> 0 | R42: ='Portefeuille SP2'!N48 -> 0 | T42: ='Portefeuille SP2'!R48 -> 0 | U42: ='Portefeuille SP2'!K48 -> 0 | V42: ='Portefeuille SP2'!S48 -> 1 | AE42: ='Portefeuille SP2'!J48 -> 0 | AJ42: ='Portefeuille SP2'!V48 -> 1 | AK42: ='Portefeuille SP2'!W48 -> 1 | AL42: ='Portefeuille SP2'!X48 -> 1 | AM42: ='Portefeuille SP2'!Y48 -> 1 | AN42: ='Portefeuille SP2'!Z48 -> 1 | AO42: ='Portefeuille SP2'!AA48 -> 1 | AP42: ='Portefeuille SP2'!AB48 -> 1 | AQ42: ='Portefeuille SP2'!AC48 -> 1 | ... BF42: ='Portefeuille SP2'!AR48 -> 1 | BG42: ='Portefeuille SP2'!#REF! -> #REF! | BH42: ='Portefeuille SP2'!#REF! -> #REF! | BI42: ='Portefeuille SP2'!#REF! -> #REF! | BJ42: ='Portefeuille SP2'!#REF! -> #REF! | BK42: ='Portefeuille SP2'!#REF! -> #REF! | BM42: ='Portefeuille SP2'!L48 -> 11/02/2025 : Passage du sujet en VSM/PTM S07 pour décider. 03/12/2024 : GT conception : eval précise après calcul : estimation à +0,7 kg hors tablier (valable TT). Epaisseur tablier à passer en 0,9 ald 0,7 --> +0,9 kg (impact seulement sur P1H, P1X déjà en 0,9). 20/11/2024 : Pb de choc après reception MaJ modèles de choc. Dessin en cours, calcul d'ici 2 ou 3 semaines.
A43: ='Portefeuille SP2'!B49 -> 46058 | B43: ='Portefeuille SP2'!Q49 -> CANCELED | D43: ='Portefeuille SP2'!E49 -> PTF | E43: =LEFT(J43,3) -> PHE | F43: =MID(J43, 4, 20) -> S | G43: ='Portefeuille SP2'!C49 -> SP1 | H43: ='Portefeuille SP2'!F49 -> 0 | J43: ='Portefeuille SP2'!D49 -> PHES | K43: ='Portefeuille SP2'!H49 -> TPC | L43: ='Portefeuille SP2'!U49 -> -0.05 | P43: ='Portefeuille SP2'!M49 -> 0 | R43: ='Portefeuille SP2'!N49 -> 0 | T43: ='Portefeuille SP2'!R49 -> 0 | U43: ='Portefeuille SP2'!K49 -> 0 | V43: ='Portefeuille SP2'!S49 -> 0.5 | AE43: ='Portefeuille SP2'!J49 -> 0 | AJ43: ='Portefeuille SP2'!V49 -> 1 | AK43: ='Portefeuille SP2'!W49 -> 1 | AL43: ='Portefeuille SP2'!X49 -> 1 | AM43: ='Portefeuille SP2'!Y49 -> 1 | AN43: ='Portefeuille SP2'!Z49 -> 1 | AO43: ='Portefeuille SP2'!AA49 -> 1 | AP43: ='Portefeuille SP2'!AB49 -> 1 | AQ43: ='Portefeuille SP2'!AC49 -> 1 | ... BF43: ='Portefeuille SP2'!AR49 -> 0 | BG43: ='Portefeuille SP2'!#REF! -> #REF! | BH43: ='Portefeuille SP2'!#REF! -> #REF! | BI43: ='Portefeuille SP2'!#REF! -> #REF! | BJ43: ='Portefeuille SP2'!#REF! -> #REF! | BK43: ='Portefeuille SP2'!#REF! -> #REF! | BM43: ='Portefeuille SP2'!L49 -> 29/10/2025 : Essais 12/2025 11/09/2024 : Piste TPC. Gains suivant essai NVH à venir.
A44: ='Portefeuille SP2'!B50 -> 01/09/024 | B44: ='Portefeuille SP2'!Q50 -> CANCELED | D44: ='Portefeuille SP2'!E50 -> TH | E44: =LEFT(J44,3) -> BIW | F44: =MID(J44, 4, 20) | G44: ='Portefeuille SP2'!C50 -> SPC_1 | H44: ='Portefeuille SP2'!F50 -> FRANK BAILLON | J44: ='Portefeuille SP2'!D50 -> BIW | K44: ='Portefeuille SP2'!H50 -> Windscreen pillar reinforcer | L44: ='Portefeuille SP2'!U50 -> 0.12 | P44: ='Portefeuille SP2'!M50 -> -350K€ | R44: ='Portefeuille SP2'!N50 -> 1.6 | T44: ='Portefeuille SP2'!R50 -> TBD | U44: ='Portefeuille SP2'!K50 -> DTM PM-CM | V44: ='Portefeuille SP2'!S50 -> 0.1 | AE44: ='Portefeuille SP2'!J50 -> 06/10/2025 a reboucler avec l'embout - Mickael Ludovic DASNOIS | AJ44: ='Portefeuille SP2'!V50 -> 1 | AK44: ='Portefeuille SP2'!W50 -> 1 | AL44: ='Portefeuille SP2'!X50 -> 1 | AM44: ='Portefeuille SP2'!Y50 -> 1 | AN44: ='Portefeuille SP2'!Z50 -> 1 | AO44: ='Portefeuille SP2'!AA50 -> 1 | AP44: ='Portefeuille SP2'!AB50 -> 1 | AQ44: ='Portefeuille SP2'!AC50 -> 1 | ... BF44: ='Portefeuille SP2'!AR50 -> 1 | BG44: ='Portefeuille SP2'!#REF! -> #REF! | BH44: ='Portefeuille SP2'!#REF! -> #REF! | BI44: ='Portefeuille SP2'!#REF! -> #REF! | BJ44: ='Portefeuille SP2'!#REF! -> #REF! | BK44: ='Portefeuille SP2'!#REF! -> #REF! | BM44: ='Portefeuille SP2'!L50 -> 26/06/2025 a reboucler après hypothèse projet
A45: ='Portefeuille SP2'!B51 -> 11/02/2025 | B45: ='Portefeuille SP2'!Q51 -> CANCELED | D45: ='Portefeuille SP2'!E51 -> PTF | E45: =LEFT(J45,3) -> BCI | F45: =MID(J45, 4, 20) -> _BODY | G45: ='Portefeuille SP2'!C51 -> SP1 | H45: ='Portefeuille SP2'!F51 -> 0 | J45: ='Portefeuille SP2'!D51 -> BCI_BODY | K45: ='Portefeuille SP2'!H51 -> SILL | L45: ='Portefeuille SP2'!U51 -> -0.35 | P45: ='Portefeuille SP2'!M51 -> 0 | R45: ='Portefeuille SP2'!N51 -> 0 | T45: ='Portefeuille SP2'!R51 -> 0 | U45: ='Portefeuille SP2'!K51 -> 0 | V45: ='Portefeuille SP2'!S51 -> 1 | AE45: ='Portefeuille SP2'!J51 -> 0 | AJ45: ='Portefeuille SP2'!V51 -> 1 | AK45: ='Portefeuille SP2'!W51 -> 1 | AL45: ='Portefeuille SP2'!X51 -> 1 | AM45: ='Portefeuille SP2'!Y51 -> 1 | AN45: ='Portefeuille SP2'!Z51 -> 1 | AO45: ='Portefeuille SP2'!AA51 -> 1 | AP45: ='Portefeuille SP2'!AB51 -> 1 | AQ45: ='Portefeuille SP2'!AC51 -> 1 | ... BF45: ='Portefeuille SP2'!AR51 -> 1 | BG45: ='Portefeuille SP2'!#REF! -> #REF! | BH45: ='Portefeuille SP2'!#REF! -> #REF! | BI45: ='Portefeuille SP2'!#REF! -> #REF! | BJ45: ='Portefeuille SP2'!#REF! -> #REF! | BK45: ='Portefeuille SP2'!#REF! -> #REF! | BM45: ='Portefeuille SP2'!L51 -> 11/02/2025 : A passer en RD suite accord de toutes les parties. 07/01/2025 : reduction de la hauteur de feuillure de 9mm (6mm sur TH) pour un gain de 0,540 kg (-0,35 kg sur PTF et -0,19 kg sur TH)
A46: ='Portefeuille SP2'!B52 -> 46058 | B46: ='Portefeuille SP2'!Q52 -> IN PROGRESS | D46: ='Portefeuille SP2'!E52 -> PTF | E46: =LEFT(J46,3) -> BCI | F46: =MID(J46, 4, 20) -> _BODY | G46: ='Portefeuille SP2'!C52 -> SP1 | H46: ='Portefeuille SP2'!F52 -> 0 | J46: ='Portefeuille SP2'!D52 -> BCI_BODY | K46: ='Portefeuille SP2'!H52 -> 0 | L46: ='Portefeuille SP2'!U52 -> 0.375 | P46: ='Portefeuille SP2'!M52 -> 0 | R46: ='Portefeuille SP2'!N52 -> 0 | T46: ='Portefeuille SP2'!R52 -> 0 | U46: ='Portefeuille SP2'!K52 -> 0 | V46: ='Portefeuille SP2'!S52 -> 0.75 | AE46: ='Portefeuille SP2'!J52 -> 0 | AJ46: ='Portefeuille SP2'!V52 -> 1 | AK46: ='Portefeuille SP2'!W52 -> 1 | AL46: ='Portefeuille SP2'!X52 -> 1 | AM46: ='Portefeuille SP2'!Y52 -> 1 | AN46: ='Portefeuille SP2'!Z52 -> 1 | AO46: ='Portefeuille SP2'!AA52 -> 1 | AP46: ='Portefeuille SP2'!AB52 -> 1 | AQ46: ='Portefeuille SP2'!AC52 -> 1 | ... BF46: ='Portefeuille SP2'!AR52 -> 0 | BG46: ='Portefeuille SP2'!#REF! -> #REF! | BH46: ='Portefeuille SP2'!#REF! -> #REF! | BI46: ='Portefeuille SP2'!#REF! -> #REF! | BJ46: ='Portefeuille SP2'!#REF! -> #REF! | BK46: ='Portefeuille SP2'!#REF! -> #REF! | BM46: ='Portefeuille SP2'!L52 -> 27/11/2025 : Présentation en VSM/PTM. Gain important en Aero, mais cout important (+3,5€). Besoin à confirmer après essai, pas en ref en ce moment. Nouvelle estimation à 0,5 kg 03/10/2025 : Aero demande des écrans sur les bras du ML. Demande à confirmer.
A47: ='Portefeuille SP2'!B53 -> 46058 | B47: ='Portefeuille SP2'!Q53 -> CANCELED | D47: ='Portefeuille SP2'!E53 -> PTF | E47: =LEFT(J47,3) -> BCI | F47: =MID(J47, 4, 20) -> _BODY | G47: ='Portefeuille SP2'!C53 -> SP1 | H47: ='Portefeuille SP2'!F53 -> 0 | J47: ='Portefeuille SP2'!D53 -> BCI_BODY | K47: ='Portefeuille SP2'!H53 -> Front sub-frame | L47: ='Portefeuille SP2'!U53 -> 0.3 | P47: ='Portefeuille SP2'!M53 -> 0 | R47: ='Portefeuille SP2'!N53 -> 0 | T47: ='Portefeuille SP2'!R53 -> 0 | U47: ='Portefeuille SP2'!K53 -> 0 | V47: ='Portefeuille SP2'!S53 -> 1 | AE47: ='Portefeuille SP2'!J53 -> 0 | AJ47: ='Portefeuille SP2'!V53 -> 1 | AK47: ='Portefeuille SP2'!W53 -> 1 | AL47: ='Portefeuille SP2'!X53 -> 1 | AM47: ='Portefeuille SP2'!Y53 -> 1 | AN47: ='Portefeuille SP2'!Z53 -> 1 | AO47: ='Portefeuille SP2'!AA53 -> 1 | AP47: ='Portefeuille SP2'!AB53 -> 1 | AQ47: ='Portefeuille SP2'!AC53 -> 1 | ... BF47: ='Portefeuille SP2'!AR53 -> 1 | BG47: ='Portefeuille SP2'!#REF! -> #REF! | BH47: ='Portefeuille SP2'!#REF! -> #REF! | BI47: ='Portefeuille SP2'!#REF! -> #REF! | BJ47: ='Portefeuille SP2'!#REF! -> #REF! | BK47: ='Portefeuille SP2'!#REF! -> #REF! | BM47: ='Portefeuille SP2'!L53 -> 11/02/2025 : Besoin de raideur dyn
A48: ='Portefeuille SP2'!B54 -> 46058 | B48: ='Portefeuille SP2'!Q54 -> IN PROGRESS | D48: ='Portefeuille SP2'!E54 -> PTF | E48: =LEFT(J48,3) -> BCI | F48: =MID(J48, 4, 20) -> _BODY | G48: ='Portefeuille SP2'!C54 -> SP1 | H48: ='Portefeuille SP2'!F54 -> 0 | J48: ='Portefeuille SP2'!D54 -> BCI_BODY | K48: ='Portefeuille SP2'!H54 -> Underbody optimization | L48: ='Portefeuille SP2'!U54 -> -1.225 | P48: ='Portefeuille SP2'!M54 -> 0 | R48: ='Portefeuille SP2'!N54 -> 0 | T48: ='Portefeuille SP2'!R54 -> 0 | U48: ='Portefeuille SP2'!K54 -> 0 | V48: ='Portefeuille SP2'!S54 -> 0.25 | AE48: ='Portefeuille SP2'!J54 -> 0 | AJ48: ='Portefeuille SP2'!V54 -> 1 | AK48: ='Portefeuille SP2'!W54 -> 1 | AL48: ='Portefeuille SP2'!X54 -> 1 | AM48: ='Portefeuille SP2'!Y54 -> 1 | AN48: ='Portefeuille SP2'!Z54 -> 1 | AO48: ='Portefeuille SP2'!AA54 -> 1 | AP48: ='Portefeuille SP2'!AB54 -> 1 | AQ48: ='Portefeuille SP2'!AC54 -> 1 | ... BF48: ='Portefeuille SP2'!AR54 -> 0 | BG48: ='Portefeuille SP2'!#REF! -> #REF! | BH48: ='Portefeuille SP2'!#REF! -> #REF! | BI48: ='Portefeuille SP2'!#REF! -> #REF! | BJ48: ='Portefeuille SP2'!#REF! -> #REF! | BK48: ='Portefeuille SP2'!#REF! -> #REF! | BM48: ='Portefeuille SP2'!L54 -> 07/11/2025 : hypothèse de reduction de 0,05mm sur les tôles entre 0,7 et 1,6.
A49: ='Portefeuille SP2'!B55 -> 24/04/2025 | B49: ='Portefeuille SP2'!Q55 -> CANCELED | D49: ='Portefeuille SP2'!E55 -> TH | E49: =LEFT(J49,3) -> INT | F49: =MID(J49, 4, 20) -> - PDB/CONSOLE | G49: ='Portefeuille SP2'!C55 -> SP1 | H49: ='Portefeuille SP2'!F55 -> FREDERIC BRUNIER | J49: ='Portefeuille SP2'!D55 -> INT - PDB/CONSOLE | K49: ='Portefeuille SP2'!H55 -> risk perfo | L49: ='Portefeuille SP2'!U55 -> 0.1 | P49: ='Portefeuille SP2'!M55 -> 0 | R49: ='Portefeuille SP2'!N55 -> 0 | T49: ='Portefeuille SP2'!R55 -> 0 | U49: ='Portefeuille SP2'!K55 -> 0 | V49: ='Portefeuille SP2'!S55 -> 0.25 | AE49: ='Portefeuille SP2'!J55 -> CP P1H Sébastien Dupuis 24/06/2025 à confirmer avec Sébastien | AJ49: ='Portefeuille SP2'!V55 -> 1 | AK49: ='Portefeuille SP2'!W55 -> 1 | AL49: ='Portefeuille SP2'!X55 -> 1 | AM49: ='Portefeuille SP2'!Y55 -> 1 | AN49: ='Portefeuille SP2'!Z55 -> 1 | AO49: ='Portefeuille SP2'!AA55 -> 1 | AP49: ='Portefeuille SP2'!AB55 -> 1 | AQ49: ='Portefeuille SP2'!AC55 -> 1 | ... BF49: ='Portefeuille SP2'!AR55 -> 1 | BG49: ='Portefeuille SP2'!#REF! -> #REF! | BH49: ='Portefeuille SP2'!#REF! -> #REF! | BI49: ='Portefeuille SP2'!#REF! -> #REF! | BJ49: ='Portefeuille SP2'!#REF! -> #REF! | BK49: ='Portefeuille SP2'!#REF! -> #REF! | BM49: ='Portefeuille SP2'!L55 -> 24/04/2025 Tenue NVH / Vibration
A50: ='Portefeuille SP2'!B56 -> 45536 | B50: ='Portefeuille SP2'!Q56 -> CANCELED | D50: ='Portefeuille SP2'!E56 -> TH | E50: =LEFT(J50,3) -> BIW | F50: =MID(J50, 4, 20) | G50: ='Portefeuille SP2'!C56 -> SPC_1 | H50: ='Portefeuille SP2'!F56 -> FRANK BAILLON | J50: ='Portefeuille SP2'!D56 -> BIW | K50: ='Portefeuille SP2'!H56 -> Inner Windscreen pillar | L50: ='Portefeuille SP2'!U56 -> 0.05 | P50: ='Portefeuille SP2'!M56 -> -250K€ | R50: ='Portefeuille SP2'!N56 -> 0.7 | T50: ='Portefeuille SP2'!R56 -> TBD | U50: ='Portefeuille SP2'!K56 -> DTM PM-CM | V50: ='Portefeuille SP2'!S56 -> 0.1 | AE50: ='Portefeuille SP2'!J56 -> 06/10/2025 a reboucler avec l'embout - Mickael Ludovic DASNOIS | AJ50: ='Portefeuille SP2'!V56 -> 1 | AK50: ='Portefeuille SP2'!W56 -> 1 | AL50: ='Portefeuille SP2'!X56 -> 1 | AM50: ='Portefeuille SP2'!Y56 -> 1 | AN50: ='Portefeuille SP2'!Z56 -> 1 | AO50: ='Portefeuille SP2'!AA56 -> 1 | AP50: ='Portefeuille SP2'!AB56 -> 1 | AQ50: ='Portefeuille SP2'!AC56 -> 1 | ... BF50: ='Portefeuille SP2'!AR56 -> 1 | BG50: ='Portefeuille SP2'!#REF! -> #REF! | BH50: ='Portefeuille SP2'!#REF! -> #REF! | BI50: ='Portefeuille SP2'!#REF! -> #REF! | BJ50: ='Portefeuille SP2'!#REF! -> #REF! | BK50: ='Portefeuille SP2'!#REF! -> #REF! | BM50: ='Portefeuille SP2'!L56 -> 26/06/2025 a reboucler après hypothèse projet
... A65: ='Portefeuille SP2'!B71 -> 45821 | B65: ='Portefeuille SP2'!Q71 -> CANCELED | D65: ='Portefeuille SP2'!E71 -> TH | E65: =LEFT(J65,3) -> BCI | F65: =MID(J65, 4, 20) -> _BODY | G65: ='Portefeuille SP2'!C71 -> SPC_1 | H65: ='Portefeuille SP2'!F71 -> Hervet Lambin | J65: ='Portefeuille SP2'!D71 -> BCI_BODY | K65: ='Portefeuille SP2'!H71 -> Door | L65: ='Portefeuille SP2'!U71 -> 0 | P65: ='Portefeuille SP2'!M71 -> TBD | R65: ='Portefeuille SP2'!N71 -> TBD | T65: ='Portefeuille SP2'!R71 -> 0 | U65: ='Portefeuille SP2'!K71 -> 0 | V65: ='Portefeuille SP2'!S71 -> 0 | AE65: ='Portefeuille SP2'!J71 -> 10/10/2025 refusé par le projet ligne à supprimer | AJ65: ='Portefeuille SP2'!V71 -> 0 | AK65: ='Portefeuille SP2'!W71 -> 0 | AL65: ='Portefeuille SP2'!X71 -> 0 | AM65: ='Portefeuille SP2'!Y71 -> 0 | AN65: ='Portefeuille SP2'!Z71 -> 0 | AO65: ='Portefeuille SP2'!AA71 -> 0 | AP65: ='Portefeuille SP2'!AB71 -> 0 | AQ65: ='Portefeuille SP2'!AC71 -> 0 | ... BF65: ='Portefeuille SP2'!AR71 -> 0 | BG65: ='Portefeuille SP2'!#REF! -> #REF! | BH65: ='Portefeuille SP2'!#REF! -> #REF! | BI65: ='Portefeuille SP2'!#REF! -> #REF! | BJ65: ='Portefeuille SP2'!#REF! -> #REF! | BK65: ='Portefeuille SP2'!#REF! -> #REF! | BM65: ='Portefeuille SP2'!L71 -> 0
A66: ='Portefeuille SP2'!B72 -> 03/06/2025 | B66: ='Portefeuille SP2'!Q72 -> DECIDED | D66: ='Portefeuille SP2'!E72 -> TH | E66: =LEFT(J66,3) -> INT | F66: =MID(J66, 6, 20) -> SEATS/TRIMS | G66: ='Portefeuille SP2'!C72 -> SP1 | H66: ='Portefeuille SP2'!F72 -> HALIM | J66: ='Portefeuille SP2'!D72 -> INT - SEATS/TRIMS | K66: ='Portefeuille SP2'!H72 -> P2P | L66: ='Portefeuille SP2'!U72 -> 0 | P66: ='Portefeuille SP2'!M72 -> 0 | R66: ='Portefeuille SP2'!N72 -> 0 | T66: ='Portefeuille SP2'!R72 -> 0 | U66: ='Portefeuille SP2'!K72 -> 0 | V66: ='Portefeuille SP2'!S72 -> 0 | AE66: ='Portefeuille SP2'!J72 -> 0 | AJ66: ='Portefeuille SP2'!V72 -> 1 | AK66: ='Portefeuille SP2'!W72 -> 1 | AL66: ='Portefeuille SP2'!X72 -> 1 | AM66: ='Portefeuille SP2'!Y72 -> 1 | AN66: ='Portefeuille SP2'!Z72 -> 1 | AO66: ='Portefeuille SP2'!AA72 -> 1 | AP66: ='Portefeuille SP2'!AB72 -> 1 | AQ66: ='Portefeuille SP2'!AC72 -> 1 | ... BF66: ='Portefeuille SP2'!AR72 -> 0 | BG66: ='Portefeuille SP2'!#REF! -> #REF! | BH66: ='Portefeuille SP2'!#REF! -> #REF! | BI66: ='Portefeuille SP2'!#REF! -> #REF! | BJ66: ='Portefeuille SP2'!#REF! -> #REF! | BK66: ='Portefeuille SP2'!#REF! -> #REF! | BM66: ='Portefeuille SP2'!L72 -> 03/06/2025 CHANTIER MASSE : Revoir la décli
A67: ='Portefeuille SP2'!B73 -> 03/06/2025 | B67: ='Portefeuille SP2'!Q73 -> CANCELED | D67: ='Portefeuille SP2'!E73 -> TH | E67: =LEFT(J67,3) -> INT | F67: =MID(J67, 6, 20) -> SEATS/TRIMS | G67: ='Portefeuille SP2'!C73 -> SP1 | H67: ='Portefeuille SP2'!F73 -> 0 | J67: ='Portefeuille SP2'!D73 -> INT - SEATS/TRIMS | K67: ='Portefeuille SP2'!H73 -> 0 | L67: ='Portefeuille SP2'!U73 -> -0.175 | P67: ='Portefeuille SP2'!M73 -> 0 | R67: ='Portefeuille SP2'!N73 -> 0 | T67: ='Portefeuille SP2'!R73 -> 0 | U67: ='Portefeuille SP2'!K73 -> 0 | V67: ='Portefeuille SP2'!S73 -> 0.25 | AE67: ='Portefeuille SP2'!J73 -> 0 | AJ67: ='Portefeuille SP2'!V73 -> 1 | AK67: ='Portefeuille SP2'!W73 -> 1 | AL67: ='Portefeuille SP2'!X73 -> 1 | AM67: ='Portefeuille SP2'!Y73 -> 1 | AN67: ='Portefeuille SP2'!Z73 -> 1 | AO67: ='Portefeuille SP2'!AA73 -> 1 | AP67: ='Portefeuille SP2'!AB73 -> 1 | AQ67: ='Portefeuille SP2'!AC73 -> 1 | ... BF67: ='Portefeuille SP2'!AR73 -> 1 | BG67: ='Portefeuille SP2'!#REF! -> #REF! | BH67: ='Portefeuille SP2'!#REF! -> #REF! | BI67: ='Portefeuille SP2'!#REF! -> #REF! | BJ67: ='Portefeuille SP2'!#REF! -> #REF! | BK67: ='Portefeuille SP2'!#REF! -> #REF! | BM67: ='Portefeuille SP2'!L73 -> 03/06/2025 CHANTIER MASSE : Supprimer les supports du TT > Impact sur la diversité des GLC
A68: ='Portefeuille SP2'!B74 -> 45940 | B68: ='Portefeuille SP2'!Q74 -> IN PROGRESS | D68: ='Portefeuille SP2'!E74 -> TH | E68: =LEFT(J68,3) -> DIW | F68: =MID(J68, 4, 20) | G68: ='Portefeuille SP2'!C74 -> SPC_1 | H68: ='Portefeuille SP2'!F74 -> Damien Demougeot/ Hervet Lambin | J68: ='Portefeuille SP2'!D74 -> DIW | K68: ='Portefeuille SP2'!H74 -> Door | L68: ='Portefeuille SP2'!U74 -> -1.5 | P68: ='Portefeuille SP2'!M74 -> TBD | R68: ='Portefeuille SP2'!N74 -> TBD | T68: ='Portefeuille SP2'!R74 -> 0 | U68: ='Portefeuille SP2'!K74 -> 0 | V68: ='Portefeuille SP2'!S74 -> 1 | AE68: ='Portefeuille SP2'!J74 -> 13/03/2026 LM en cours d'application 20/02/2026 LM - application non confirmé en CW 08_26 06/02/2026 LM - Réunion pour validation de l'application en CW 07_26 24/10/2025 Après calcul par le métier, pas de gain masse sur cet item - sujet stain by 10/10/2025 à reboucler avec Herve Lambin | AJ68: ='Portefeuille SP2'!V74 -> 0 | AK68: ='Portefeuille SP2'!W74 -> 0 | AL68: ='Portefeuille SP2'!X74 -> 0 | AM68: ='Portefeuille SP2'!Y74 -> 0 | AN68: ='Portefeuille SP2'!Z74 -> 0 | AO68: ='Portefeuille SP2'!AA74 -> 0 | AP68: ='Portefeuille SP2'!AB74 -> 0 | AQ68: ='Portefeuille SP2'!AC74 -> 0 | ... BF68: ='Portefeuille SP2'!AR74 -> 1 | BG68: ='Portefeuille SP2'!#REF! -> #REF! | BH68: ='Portefeuille SP2'!#REF! -> #REF! | BI68: ='Portefeuille SP2'!#REF! -> #REF! | BJ68: ='Portefeuille SP2'!#REF! -> #REF! | BK68: ='Portefeuille SP2'!#REF! -> #REF! | BM68: ='Portefeuille SP2'!L74 -> 0
A69: ='Portefeuille SP2'!B75 -> 11/06/2025 | B69: ='Portefeuille SP2'!Q75 -> DECIDED | D69: ='Portefeuille SP2'!E75 -> TH | E69: =LEFT(J69,3) -> DIW | F69: =MID(J69, 4, 20) | G69: ='Portefeuille SP2'!C75 -> SPC_1 | H69: ='Portefeuille SP2'!F75 -> Hervet Lambin | J69: ='Portefeuille SP2'!D75 -> DIW | K69: ='Portefeuille SP2'!H75 -> BIW/ DIW process | L69: ='Portefeuille SP2'!U75 -> 0 | P69: ='Portefeuille SP2'!M75 -> 0 | R69: ='Portefeuille SP2'!N75 -> 0 | T69: ='Portefeuille SP2'!R75 -> 0 | U69: ='Portefeuille SP2'!K75 -> 0 | V69: ='Portefeuille SP2'!S75 -> 0 | AE69: ='Portefeuille SP2'!J75 -> 06/02/2026 LM sujet déjà appliqué sur SPC_1 sujet à supprimer 10/10/2025 à reboucler avec Herve Lambin question à revérifier pour SPC-1 | AJ69: ='Portefeuille SP2'!V75 -> 1 | AK69: ='Portefeuille SP2'!W75 -> 1 | AL69: ='Portefeuille SP2'!X75 -> 1 | AM69: ='Portefeuille SP2'!Y75 -> 1 | AN69: ='Portefeuille SP2'!Z75 -> 1 | AO69: ='Portefeuille SP2'!AA75 -> 1 | AP69: ='Portefeuille SP2'!AB75 -> 1 | AQ69: ='Portefeuille SP2'!AC75 -> 1 | ... BF69: ='Portefeuille SP2'!AR75 -> 1 | BG69: ='Portefeuille SP2'!#REF! -> #REF! | BH69: ='Portefeuille SP2'!#REF! -> #REF! | BI69: ='Portefeuille SP2'!#REF! -> #REF! | BJ69: ='Portefeuille SP2'!#REF! -> #REF! | BK69: ='Portefeuille SP2'!#REF! -> #REF! | BM69: ='Portefeuille SP2'!L75 -> 02/07/2025 CANCELLED : Ep.mini déjà atteinte (chgt de matière possible mais aurait nécessité une dimintution d'épasisseur) 11/06/2025 A ré-évaluer 04/11/2024 Idem post Go-Calcul SYNC3 08/07/2024 Retour calcul SYNC3 (Go calcul Nov => 2025?) Pièce en Embout à chaud
A70: ='Portefeuille SP2'!B76 -> 45536 | B70: ='Portefeuille SP2'!Q76 -> DECIDED | D70: ='Portefeuille SP2'!E76 -> TH | E70: =LEFT(J70,3) -> DIW | F70: =MID(J70, 4, 20) | G70: ='Portefeuille SP2'!C76 -> SPC_1 | H70: ='Portefeuille SP2'!F76 -> Hervet Lambin | J70: ='Portefeuille SP2'!D76 -> DIW | K70: ='Portefeuille SP2'!H76 -> Hot Stamping lat reinfor | L70: ='Portefeuille SP2'!U76 -> 0 | P70: ='Portefeuille SP2'!M76 -> 104 | R70: ='Portefeuille SP2'!N76 -> -0.8 | T70: ='Portefeuille SP2'!R76 -> TBD | U70: ='Portefeuille SP2'!K76 -> PM-CM | V70: ='Portefeuille SP2'!S76 -> 0 | AE70: ='Portefeuille SP2'!J76 -> 06/02/2026 LM sujet déjà appliqué sur SPC_1 sujet à supprimer 10/10/2025 à reboucler avec Herve Lambin question à revérifier pour SPC-1 | AJ70: ='Portefeuille SP2'!V76 -> 0 | AK70: ='Portefeuille SP2'!W76 -> 0 | AL70: ='Portefeuille SP2'!X76 -> 0 | AM70: ='Portefeuille SP2'!Y76 -> 1 | AN70: ='Portefeuille SP2'!Z76 -> 1 | AO70: ='Portefeuille SP2'!AA76 -> 0 | AP70: ='Portefeuille SP2'!AB76 -> 0 | AQ70: ='Portefeuille SP2'!AC76 -> 1 | ... BF70: ='Portefeuille SP2'!AR76 -> 1 | BG70: ='Portefeuille SP2'!#REF! -> #REF! | BH70: ='Portefeuille SP2'!#REF! -> #REF! | BI70: ='Portefeuille SP2'!#REF! -> #REF! | BJ70: ='Portefeuille SP2'!#REF! -> #REF! | BK70: ='Portefeuille SP2'!#REF! -> #REF! | BM70: ='Portefeuille SP2'!L76 -> 0
A71: ='Portefeuille SP2'!B77 -> 45758 | B71: ='Portefeuille SP2'!Q77 -> CANCELED | D71: ='Portefeuille SP2'!E77 -> PTF | E71: =LEFT(J71,3) -> BCI | F71: =MID(J71, 6, 20) -> HASSIS | G71: ='Portefeuille SP2'!C77 -> SP2 | H71: ='Portefeuille SP2'!F77 -> 0 | J71: ='Portefeuille SP2'!D77 -> BCI_CHASSIS | K71: ='Portefeuille SP2'!H77 -> Longitudinal member | L71: ='Portefeuille SP2'!U77 -> -1 | P71: ='Portefeuille SP2'!M77 -> 0 | R71: ='Portefeuille SP2'!N77 -> 40 | T71: ='Portefeuille SP2'!R77 -> TBD | U71: ='Portefeuille SP2'!K77 -> 0 | V71: ='Portefeuille SP2'!S77 -> 1 | AE71: ='Portefeuille SP2'!J77 -> 0 | AJ71: ='Portefeuille SP2'!V77 -> 1 | AK71: ='Portefeuille SP2'!W77 -> 1 | AL71: ='Portefeuille SP2'!X77 -> 1 | AM71: ='Portefeuille SP2'!Y77 -> 0 | AN71: ='Portefeuille SP2'!Z77 -> 0 | AO71: ='Portefeuille SP2'!AA77 -> 0 | AP71: ='Portefeuille SP2'!AB77 -> 0 | AQ71: ='Portefeuille SP2'!AC77 -> 0 | ... BF71: ='Portefeuille SP2'!AR77 -> 0 | BG71: ='Portefeuille SP2'!#REF! -> #REF! | BH71: ='Portefeuille SP2'!#REF! -> #REF! | BI71: ='Portefeuille SP2'!#REF! -> #REF! | BJ71: ='Portefeuille SP2'!#REF! -> #REF! | BK71: ='Portefeuille SP2'!#REF! -> #REF! | BM71: ='Portefeuille SP2'!L77 -> 14/03/2024 : Workshop mass
A72: ='Portefeuille SP2'!B78 -> 06/06/2025 | B72: ='Portefeuille SP2'!Q78 -> CANCELED | D72: ='Portefeuille SP2'!E78 -> TH | E72: =LEFT(J72,3) -> INT | F72: =MID(J72, 4, 20) -> - SEATS/TRIMS | G72: ='Portefeuille SP2'!C78 -> SP1 | H72: ='Portefeuille SP2'!F78 -> HALIM | I72: CHARLES HENRI BONFILS | J72: ='Portefeuille SP2'!D78 -> INT - SEATS/TRIMS | K72: ='Portefeuille SP2'!H78 -> Trunk soundproofing (Rds) | L72: ='Portefeuille SP2'!U78 -> -0.0375 | P72: ='Portefeuille SP2'!M78 -> 0 | R72: ='Portefeuille SP2'!N78 -> 0 | T72: ='Portefeuille SP2'!R78 -> 0 | U72: ='Portefeuille SP2'!K78 -> SFM | V72: ='Portefeuille SP2'!S78 -> 0.25 | AE72: ='Portefeuille SP2'!J78 -> 02/03/2026 LM à Supprimer car non appliqué sur P3U 24/06/2025 à checker en RFQ avec les FNR | AJ72: ='Portefeuille SP2'!V78 -> 1 | AK72: ='Portefeuille SP2'!W78 -> 1 | AL72: ='Portefeuille SP2'!X78 -> 1 | AM72: ='Portefeuille SP2'!Y78 -> 1 | AN72: ='Portefeuille SP2'!Z78 -> 1 | AO72: ='Portefeuille SP2'!AA78 -> 1 | AP72: ='Portefeuille SP2'!AB78 -> 1 | AQ72: ='Portefeuille SP2'!AC78 -> 1 | ... BF72: ='Portefeuille SP2'!AR78 -> 1 | BG72: ='Portefeuille SP2'!#REF! -> #REF! | BH72: ='Portefeuille SP2'!#REF! -> #REF! | BI72: ='Portefeuille SP2'!#REF! -> #REF! | BJ72: ='Portefeuille SP2'!#REF! -> #REF! | BK72: ='Portefeuille SP2'!#REF! -> #REF! | BM72: ='Portefeuille SP2'!L78 -> 06/06/2025 Que sur le ML ! 23/05/2025 A supprimer TT
A73: ='Portefeuille SP2'!B79 -> 0 | B73: ='Portefeuille SP2'!Q79 -> CANCELED | D73: ='Portefeuille SP2'!E79 -> PTF | E73: =LEFT(J73,3) -> BCI | F73: =MID(J73, 6, 20) -> ODY | G73: ='Portefeuille SP2'!C79 -> SP2 | H73: ='Portefeuille SP2'!F79 -> 0 | J73: ='Portefeuille SP2'!D79 -> BCI_BODY | K73: ='Portefeuille SP2'!H79 -> 0 | L73: ='Portefeuille SP2'!U79 -> -1.5 | P73: ='Portefeuille SP2'!M79 -> 0 | R73: ='Portefeuille SP2'!N79 -> 10 | T73: ='Portefeuille SP2'!R79 -> TBD | U73: ='Portefeuille SP2'!K79 -> 0 | V73: ='Portefeuille SP2'!S79 -> 0.5 | AE73: ='Portefeuille SP2'!J79 -> 0 | AJ73: ='Portefeuille SP2'!V79 -> 1 | AK73: ='Portefeuille SP2'!W79 -> 1 | AL73: ='Portefeuille SP2'!X79 -> 1 | AM73: ='Portefeuille SP2'!Y79 -> 0 | AN73: ='Portefeuille SP2'!Z79 -> 0 | AO73: ='Portefeuille SP2'!AA79 -> 0 | AP73: ='Portefeuille SP2'!AB79 -> 0 | AQ73: ='Portefeuille SP2'!AC79 -> 0 | ... BF73: ='Portefeuille SP2'!AR79 -> 0 | BG73: ='Portefeuille SP2'!#REF! -> #REF! | BH73: ='Portefeuille SP2'!#REF! -> #REF! | BI73: ='Portefeuille SP2'!#REF! -> #REF! | BJ73: ='Portefeuille SP2'!#REF! -> #REF! | BK73: ='Portefeuille SP2'!#REF! -> #REF! | BM73: ='Portefeuille SP2'!L79 -> 14/03/2024 : Workshop mass
A74: ='Portefeuille SP2'!B80 -> 0 | B74: ='Portefeuille SP2'!Q80 -> CANCELED | D74: ='Portefeuille SP2'!E80 -> TH | E74: =LEFT(J74,3) -> BCI | F74: =MID(J74, 6, 20) -> OORS | G74: ='Portefeuille SP2'!C80 -> SP2 | H74: ='Portefeuille SP2'!F80 -> 0 | J74: ='Portefeuille SP2'!D80 -> BCI_DOORS | K74: ='Portefeuille SP2'!H80 -> Aluminum doors | L74: ='Portefeuille SP2'!U80 -> -22 | P74: ='Portefeuille SP2'!M80 -> 0 | R74: ='Portefeuille SP2'!N80 -> 200 | T74: ='Portefeuille SP2'!R80 -> TBD | U74: ='Portefeuille SP2'!K80 -> 0 | V74: ='Portefeuille SP2'!S80 -> 1 | AE74: ='Portefeuille SP2'!J80 -> 0 | AJ74: ='Portefeuille SP2'!V80 -> 1 | AK74: ='Portefeuille SP2'!W80 -> 1 | AL74: ='Portefeuille SP2'!X80 -> 1 | AM74: ='Portefeuille SP2'!Y80 -> 0 | AN74: ='Portefeuille SP2'!Z80 -> 0 | AO74: ='Portefeuille SP2'!AA80 -> 0 | AP74: ='Portefeuille SP2'!AB80 -> 0 | AQ74: ='Portefeuille SP2'!AC80 -> 0 | ... BF74: ='Portefeuille SP2'!AR80 -> 0 | BG74: ='Portefeuille SP2'!#REF! -> #REF! | BH74: ='Portefeuille SP2'!#REF! -> #REF! | BI74: ='Portefeuille SP2'!#REF! -> #REF! | BJ74: ='Portefeuille SP2'!#REF! -> #REF! | BK74: ='Portefeuille SP2'!#REF! -> #REF! | BM74: ='Portefeuille SP2'!L80 -> 14/03/2024 : Workshop mass
A75: ='Portefeuille SP2'!B81 -> 0 | B75: ='Portefeuille SP2'!Q81 -> CANCELED | D75: ='Portefeuille SP2'!E81 -> TH | E75: =LEFT(J75,3) -> BCI | F75: =MID(J75, 6, 20) -> ODY | G75: ='Portefeuille SP2'!C81 -> SP2 | H75: ='Portefeuille SP2'!F81 -> 0 | J75: ='Portefeuille SP2'!D81 -> BCI_BODY | K75: ='Portefeuille SP2'!H81 -> Alloy roof | L75: ='Portefeuille SP2'!U81 -> -1 | P75: ='Portefeuille SP2'!M81 -> 0 | R75: ='Portefeuille SP2'!N81 -> 15 | T75: ='Portefeuille SP2'!R81 -> TBD | U75: ='Portefeuille SP2'!K81 -> 0 | V75: ='Portefeuille SP2'!S81 -> 0.25 | AE75: ='Portefeuille SP2'!J81 -> 0 | AJ75: ='Portefeuille SP2'!V81 -> 1 | AK75: ='Portefeuille SP2'!W81 -> 1 | AL75: ='Portefeuille SP2'!X81 -> 1 | AM75: ='Portefeuille SP2'!Y81 -> 0 | AN75: ='Portefeuille SP2'!Z81 -> 0 | AO75: ='Portefeuille SP2'!AA81 -> 0 | AP75: ='Portefeuille SP2'!AB81 -> 0 | AQ75: ='Portefeuille SP2'!AC81 -> 0 | ... BF75: ='Portefeuille SP2'!AR81 -> 0 | BG75: ='Portefeuille SP2'!#REF! -> #REF! | BH75: ='Portefeuille SP2'!#REF! -> #REF! | BI75: ='Portefeuille SP2'!#REF! -> #REF! | BJ75: ='Portefeuille SP2'!#REF! -> #REF! | BK75: ='Portefeuille SP2'!#REF! -> #REF! | BM75: ='Portefeuille SP2'!L81 -> 14/03/2024 : Workshop mass
A76: ='Portefeuille SP2'!#REF! -> #REF! | B76: ='Portefeuille SP2'!#REF! -> #REF! | D76: ='Portefeuille SP2'!#REF! -> #REF! | E76: =LEFT(J76,3) -> #REF! | F76: =MID(J76, 4, 20) -> #REF! | G76: ='Portefeuille SP2'!#REF! -> #REF! | H76: ='Portefeuille SP2'!#REF! -> #REF! | I76: CHARLES HENRI BONFILS | J76: ='Portefeuille SP2'!#REF! -> #REF! | K76: ='Portefeuille SP2'!#REF! -> #REF! | L76: ='Portefeuille SP2'!#REF! -> #REF! | P76: ='Portefeuille SP2'!#REF! -> #REF! | R76: ='Portefeuille SP2'!#REF! -> #REF! | T76: ='Portefeuille SP2'!#REF! -> #REF! | U76: ='Portefeuille SP2'!#REF! -> #REF! | V76: ='Portefeuille SP2'!#REF! -> #REF! | AE76: ='Portefeuille SP2'!#REF! -> #REF! | AJ76: ='Portefeuille SP2'!#REF! -> #REF! | AK76: ='Portefeuille SP2'!#REF! -> #REF! | AL76: ='Portefeuille SP2'!#REF! -> #REF! | AM76: ='Portefeuille SP2'!#REF! -> #REF! | AN76: ='Portefeuille SP2'!#REF! -> #REF! | AO76: ='Portefeuille SP2'!#REF! -> #REF! | AP76: ='Portefeuille SP2'!#REF! -> #REF! | AQ76: ='Portefeuille SP2'!#REF! -> #REF! | ... BK76: ='Portefeuille SP2'!#REF! -> #REF! | BM76: ='Portefeuille SP2'!#REF! -> #REF!
A77: ='Portefeuille SP2'!B82 -> 0 | B77: ='Portefeuille SP2'!Q82 -> CANCELED | D77: ='Portefeuille SP2'!E82 -> PTF | E77: =LEFT(J77,3) -> BCI | F77: =MID(J77, 6, 20) -> ODY | G77: ='Portefeuille SP2'!C82 -> SP2 | H77: ='Portefeuille SP2'!F82 -> 0 | J77: ='Portefeuille SP2'!D82 -> BCI_BODY | K77: ='Portefeuille SP2'!H82 -> Rear Repair Beam | L77: ='Portefeuille SP2'!U82 -> -3 | P77: ='Portefeuille SP2'!M82 -> 0 | R77: ='Portefeuille SP2'!N82 -> 10 | T77: ='Portefeuille SP2'!R82 -> TBD | U77: ='Portefeuille SP2'!K82 -> 0 | V77: ='Portefeuille SP2'!S82 -> 1 | AE77: ='Portefeuille SP2'!J82 -> 0 | AJ77: ='Portefeuille SP2'!V82 -> 1 | AK77: ='Portefeuille SP2'!W82 -> 1 | AL77: ='Portefeuille SP2'!X82 -> 1 | AM77: ='Portefeuille SP2'!Y82 -> 0 | AN77: ='Portefeuille SP2'!Z82 -> 0 | AO77: ='Portefeuille SP2'!AA82 -> 0 | AP77: ='Portefeuille SP2'!AB82 -> 0 | AQ77: ='Portefeuille SP2'!AC82 -> 0 | ... BF77: ='Portefeuille SP2'!AR82 -> 0 | BG77: ='Portefeuille SP2'!#REF! -> #REF! | BH77: ='Portefeuille SP2'!#REF! -> #REF! | BI77: ='Portefeuille SP2'!#REF! -> #REF! | BJ77: ='Portefeuille SP2'!#REF! -> #REF! | BK77: ='Portefeuille SP2'!#REF! -> #REF! | BM77: ='Portefeuille SP2'!L82 -> 14/03/2024 : Workshop mass
A78: ='Portefeuille SP2'!B83 -> 0 | B78: ='Portefeuille SP2'!Q83 -> CANCELED | D78: ='Portefeuille SP2'!E83 -> PTF | E78: =LEFT(J78,3) -> BCI | F78: =MID(J78, 6, 20) -> ODY | G78: ='Portefeuille SP2'!C83 -> SP2 | H78: ='Portefeuille SP2'!F83 -> 0 | J78: ='Portefeuille SP2'!D83 -> BCI_BODY | K78: ='Portefeuille SP2'!H83 -> Rear Repair Beam | L78: ='Portefeuille SP2'!U83 -> -2 | P78: ='Portefeuille SP2'!M83 -> 0 | R78: ='Portefeuille SP2'!N83 -> 10 | T78: ='Portefeuille SP2'!R83 -> TBD | U78: ='Portefeuille SP2'!K83 -> 0 | V78: ='Portefeuille SP2'!S83 -> 1 | AE78: ='Portefeuille SP2'!J83 -> 0 | AJ78: ='Portefeuille SP2'!V83 -> 1 | AK78: ='Portefeuille SP2'!W83 -> 1 | AL78: ='Portefeuille SP2'!X83 -> 1 | AM78: ='Portefeuille SP2'!Y83 -> 0 | AN78: ='Portefeuille SP2'!Z83 -> 0 | AO78: ='Portefeuille SP2'!AA83 -> 0 | AP78: ='Portefeuille SP2'!AB83 -> 0 | AQ78: ='Portefeuille SP2'!AC83 -> 0 | ... BF78: ='Portefeuille SP2'!AR83 -> 0 | BG78: ='Portefeuille SP2'!#REF! -> #REF! | BH78: ='Portefeuille SP2'!#REF! -> #REF! | BI78: ='Portefeuille SP2'!#REF! -> #REF! | BJ78: ='Portefeuille SP2'!#REF! -> #REF! | BK78: ='Portefeuille SP2'!#REF! -> #REF! | BM78: ='Portefeuille SP2'!L83 -> 14/03/2024 : Workshop mass
A79: ='Portefeuille SP2'!B84 -> 0 | B79: ='Portefeuille SP2'!Q84 -> CANCELED | D79: ='Portefeuille SP2'!E84 -> PWT | E79: =LEFT(J79,3) -> PRS | F79: =MID(J79, 6, 20) -> DM | G79: ='Portefeuille SP2'!C84 -> SP2 | H79: ='Portefeuille SP2'!F84 -> 0 | J79: ='Portefeuille SP2'!D84 -> PRS_EDM | K79: ='Portefeuille SP2'!H84 -> EDM | L79: ='Portefeuille SP2'!U84 -> -2.5 | P79: ='Portefeuille SP2'!M84 -> 0 | R79: ='Portefeuille SP2'!N84 -> 0 | T79: ='Portefeuille SP2'!R84 -> TBD | U79: ='Portefeuille SP2'!K84 -> 0 | V79: ='Portefeuille SP2'!S84 -> 1 | AE79: ='Portefeuille SP2'!J84 -> 0 | AJ79: ='Portefeuille SP2'!V84 -> 1 | AK79: ='Portefeuille SP2'!W84 -> 1 | AL79: ='Portefeuille SP2'!X84 -> 1 | AM79: ='Portefeuille SP2'!Y84 -> 0 | AN79: ='Portefeuille SP2'!Z84 -> 0 | AO79: ='Portefeuille SP2'!AA84 -> 0 | AP79: ='Portefeuille SP2'!AB84 -> 0 | AQ79: ='Portefeuille SP2'!AC84 -> 0 | ... BF79: ='Portefeuille SP2'!AR84 -> 0 | BG79: ='Portefeuille SP2'!#REF! -> #REF! | BH79: ='Portefeuille SP2'!#REF! -> #REF! | BI79: ='Portefeuille SP2'!#REF! -> #REF! | BJ79: ='Portefeuille SP2'!#REF! -> #REF! | BK79: ='Portefeuille SP2'!#REF! -> #REF! | BM79: ='Portefeuille SP2'!L84 -> 14/03/2024 : Workshop mass
A80: ='Portefeuille SP2'!B85 -> 0 | B80: ='Portefeuille SP2'!Q85 -> CANCELED | D80: ='Portefeuille SP2'!E85 -> PWT | E80: =LEFT(J80,3) -> PRS | F80: =MID(J80, 6, 20) -> ATT | G80: ='Portefeuille SP2'!C85 -> SP2 | H80: ='Portefeuille SP2'!F85 -> 0 | J80: ='Portefeuille SP2'!D85 -> PRS_BATT | K80: ='Portefeuille SP2'!H85 -> 0 | L80: ='Portefeuille SP2'!U85 -> -22 | P80: ='Portefeuille SP2'!M85 -> 0 | R80: ='Portefeuille SP2'!N85 -> 0 | T80: ='Portefeuille SP2'!R85 -> TBD | U80: ='Portefeuille SP2'!K85 -> 0 | V80: ='Portefeuille SP2'!S85 -> 1 | AE80: ='Portefeuille SP2'!J85 -> 0 | AJ80: ='Portefeuille SP2'!V85 -> 1 | AK80: ='Portefeuille SP2'!W85 -> 1 | AL80: ='Portefeuille SP2'!X85 -> 1 | AM80: ='Portefeuille SP2'!Y85 -> 0 | AN80: ='Portefeuille SP2'!Z85 -> 0 | AO80: ='Portefeuille SP2'!AA85 -> 0 | AP80: ='Portefeuille SP2'!AB85 -> 0 | AQ80: ='Portefeuille SP2'!AC85 -> 0 | ... BF80: ='Portefeuille SP2'!AR85 -> 0 | BG80: ='Portefeuille SP2'!#REF! -> #REF! | BH80: ='Portefeuille SP2'!#REF! -> #REF! | BI80: ='Portefeuille SP2'!#REF! -> #REF! | BJ80: ='Portefeuille SP2'!#REF! -> #REF! | BK80: ='Portefeuille SP2'!#REF! -> #REF! | BM80: ='Portefeuille SP2'!L85 -> 14/03/2024 : Workshop mass
A81: ='Portefeuille SP2'!B86 -> 0 | B81: ='Portefeuille SP2'!Q86 -> CANCELED | D81: ='Portefeuille SP2'!E86 -> PTF | E81: =LEFT(J81,3) -> BCI | F81: =MID(J81, 6, 20) -> ODY | G81: ='Portefeuille SP2'!C86 -> SP2 | H81: ='Portefeuille SP2'!F86 -> 0 | J81: ='Portefeuille SP2'!D86 -> BCI_BODY | K81: ='Portefeuille SP2'!H86 -> 0 | L81: ='Portefeuille SP2'!U86 -> -2.5 | P81: ='Portefeuille SP2'!M86 -> 0 | R81: ='Portefeuille SP2'!N86 -> 0 | T81: ='Portefeuille SP2'!R86 -> TBD | U81: ='Portefeuille SP2'!K86 -> 0 | V81: ='Portefeuille SP2'!S86 -> 0.5 | AE81: ='Portefeuille SP2'!J86 -> 0 | AJ81: ='Portefeuille SP2'!V86 -> 1 | AK81: ='Portefeuille SP2'!W86 -> 1 | AL81: ='Portefeuille SP2'!X86 -> 1 | AM81: ='Portefeuille SP2'!Y86 -> 0 | AN81: ='Portefeuille SP2'!Z86 -> 0 | AO81: ='Portefeuille SP2'!AA86 -> 0 | AP81: ='Portefeuille SP2'!AB86 -> 0 | AQ81: ='Portefeuille SP2'!AC86 -> 0 | ... BF81: ='Portefeuille SP2'!AR86 -> 0 | BG81: ='Portefeuille SP2'!#REF! -> #REF! | BH81: ='Portefeuille SP2'!#REF! -> #REF! | BI81: ='Portefeuille SP2'!#REF! -> #REF! | BJ81: ='Portefeuille SP2'!#REF! -> #REF! | BK81: ='Portefeuille SP2'!#REF! -> #REF! | BM81: ='Portefeuille SP2'!L86 -> 14/03/2024 : Workshop mass
A82: ='Portefeuille SP2'!B87 -> 0 | B82: ='Portefeuille SP2'!Q87 -> DECIDED | D82: ='Portefeuille SP2'!E87 -> PTF | E82: =LEFT(J82,3) -> BCI | F82: =MID(J82, 6, 20) -> ODY | G82: ='Portefeuille SP2'!C87 -> SP2 | H82: ='Portefeuille SP2'!F87 -> 0 | J82: ='Portefeuille SP2'!D87 -> BCI_BODY | K82: ='Portefeuille SP2'!H87 -> 0 | L82: ='Portefeuille SP2'!U87 -> -4.55 | P82: ='Portefeuille SP2'!M87 -> 0 | R82: ='Portefeuille SP2'!N87 -> 16 | T82: ='Portefeuille SP2'!R87 -> TBD | U82: ='Portefeuille SP2'!K87 -> 0 | V82: ='Portefeuille SP2'!S87 -> 0.65 | AE82: ='Portefeuille SP2'!J87 -> 0 | AJ82: ='Portefeuille SP2'!V87 -> 1 | AK82: ='Portefeuille SP2'!W87 -> 1 | AL82: ='Portefeuille SP2'!X87 -> 1 | AM82: ='Portefeuille SP2'!Y87 -> 1 | AN82: ='Portefeuille SP2'!Z87 -> 0 | AO82: ='Portefeuille SP2'!AA87 -> 1 | AP82: ='Portefeuille SP2'!AB87 -> 1 | AQ82: ='Portefeuille SP2'!AC87 -> 1 | ... BF82: ='Portefeuille SP2'!AR87 -> 0 | BG82: ='Portefeuille SP2'!#REF! -> #REF! | BH82: ='Portefeuille SP2'!#REF! -> #REF! | BI82: ='Portefeuille SP2'!#REF! -> #REF! | BJ82: ='Portefeuille SP2'!#REF! -> #REF! | BK82: ='Portefeuille SP2'!#REF! -> #REF! | BM82: ='Portefeuille SP2'!L87 -> 14/03/2024 : Workshop mass
A83: ='Portefeuille SP2'!B88 -> 0 | B83: ='Portefeuille SP2'!Q88 -> CANCELED | D83: ='Portefeuille SP2'!E88 -> PTF | E83: =LEFT(J83,3) -> SWX | F83: =MID(J83, 6, 20) -> HE | G83: ='Portefeuille SP2'!C88 -> SP2 | H83: ='Portefeuille SP2'!F88 -> 0 | J83: ='Portefeuille SP2'!D88 -> SWX_EHE | K83: ='Portefeuille SP2'!H88 -> 0 | L83: ='Portefeuille SP2'!U88 -> -8 | P83: ='Portefeuille SP2'!M88 -> 0 | R83: ='Portefeuille SP2'!N88 -> 50 | T83: ='Portefeuille SP2'!R88 -> TBD | U83: ='Portefeuille SP2'!K88 -> 0 | V83: ='Portefeuille SP2'!S88 -> 1 | AE83: ='Portefeuille SP2'!J88 -> 0 | AJ83: ='Portefeuille SP2'!V88 -> 1 | AK83: ='Portefeuille SP2'!W88 -> 1 | AL83: ='Portefeuille SP2'!X88 -> 1 | AM83: ='Portefeuille SP2'!Y88 -> 0 | AN83: ='Portefeuille SP2'!Z88 -> 0 | AO83: ='Portefeuille SP2'!AA88 -> 0 | AP83: ='Portefeuille SP2'!AB88 -> 0 | AQ83: ='Portefeuille SP2'!AC88 -> 0 | ... BF83: ='Portefeuille SP2'!AR88 -> 0 | BG83: ='Portefeuille SP2'!#REF! -> #REF! | BH83: ='Portefeuille SP2'!#REF! -> #REF! | BI83: ='Portefeuille SP2'!#REF! -> #REF! | BJ83: ='Portefeuille SP2'!#REF! -> #REF! | BK83: ='Portefeuille SP2'!#REF! -> #REF! | BM83: ='Portefeuille SP2'!L88 -> 14/03/2024 : Workshop mass
A84: ='Portefeuille SP2'!B89 -> 0 | B84: ='Portefeuille SP2'!Q89 -> CANCELED | D84: ='Portefeuille SP2'!E89 -> TH | E84: =LEFT(J84,3) -> BCI | F84: =MID(J84, 6, 20) -> RSD | G84: ='Portefeuille SP2'!C89 -> SP2 | H84: ='Portefeuille SP2'!F89 -> 0 | J84: ='Portefeuille SP2'!D89 -> BCI_FRSD | K84: ='Portefeuille SP2'!H89 -> Fr Fender ALLOY | L84: ='Portefeuille SP2'!U89 -> -0.7 | P84: ='Portefeuille SP2'!M89 -> 0 | R84: ='Portefeuille SP2'!N89 -> 0 | T84: ='Portefeuille SP2'!R89 -> TBD | U84: ='Portefeuille SP2'!K89 -> 0 | V84: ='Portefeuille SP2'!S89 -> 0.5 | AE84: ='Portefeuille SP2'!J89 -> 0 | AJ84: ='Portefeuille SP2'!V89 -> 1 | AK84: ='Portefeuille SP2'!W89 -> 1 | AL84: ='Portefeuille SP2'!X89 -> 1 | AM84: ='Portefeuille SP2'!Y89 -> 0 | AN84: ='Portefeuille SP2'!Z89 -> 0 | AO84: ='Portefeuille SP2'!AA89 -> 0 | AP84: ='Portefeuille SP2'!AB89 -> 0 | AQ84: ='Portefeuille SP2'!AC89 -> 0 | ... BF84: ='Portefeuille SP2'!AR89 -> 0 | BG84: ='Portefeuille SP2'!#REF! -> #REF! | BH84: ='Portefeuille SP2'!#REF! -> #REF! | BI84: ='Portefeuille SP2'!#REF! -> #REF! | BJ84: ='Portefeuille SP2'!#REF! -> #REF! | BK84: ='Portefeuille SP2'!#REF! -> #REF! | BM84: ='Portefeuille SP2'!L89 -> setp 3
A85: ='Portefeuille SP2'!B90 -> 0 | B85: ='Portefeuille SP2'!Q90 -> DECIDED | D85: ='Portefeuille SP2'!E90 -> TH | E85: =LEFT(J85,3) -> BCI | F85: =MID(J85, 6, 20) -> RSD | G85: ='Portefeuille SP2'!C90 -> SP2 | H85: ='Portefeuille SP2'!F90 -> 0 | J85: ='Portefeuille SP2'!D90 -> BCI_FRSD | K85: ='Portefeuille SP2'!H90 -> Steel tailgate | L85: ='Portefeuille SP2'!U90 -> 5 | P85: ='Portefeuille SP2'!M90 -> 0 | R85: ='Portefeuille SP2'!N90 -> 52 | T85: ='Portefeuille SP2'!R90 -> TBD | U85: ='Portefeuille SP2'!K90 -> PM CW30 | V85: ='Portefeuille SP2'!S90 -> 1 | AE85: ='Portefeuille SP2'!J90 -> 08/10/2024: BDD à jour plastic | AJ85: ='Portefeuille SP2'!V90 -> 0 | AK85: ='Portefeuille SP2'!W90 -> 0 | AL85: ='Portefeuille SP2'!X90 -> 0 | AM85: ='Portefeuille SP2'!Y90 -> 0 | AN85: ='Portefeuille SP2'!Z90 -> 0 | AO85: ='Portefeuille SP2'!AA90 -> 0 | AP85: ='Portefeuille SP2'!AB90 -> 0 | AQ85: ='Portefeuille SP2'!AC90 -> 0 | ... BF85: ='Portefeuille SP2'!AR90 -> 0 | BG85: ='Portefeuille SP2'!#REF! -> #REF! | BH85: ='Portefeuille SP2'!#REF! -> #REF! | BI85: ='Portefeuille SP2'!#REF! -> #REF! | BJ85: ='Portefeuille SP2'!#REF! -> #REF! | BK85: ='Portefeuille SP2'!#REF! -> #REF! | BM85: ='Portefeuille SP2'!L90 -> 14/03/2024 : Workshop mass
A86: ='Portefeuille SP2'!B91 -> 0 | B86: ='Portefeuille SP2'!Q91 -> CANCELED | D86: ='Portefeuille SP2'!E91 -> TH | E86: =LEFT(J86,3) -> BCI | F86: =MID(J86, 6, 20) -> ODY | G86: ='Portefeuille SP2'!C91 -> SP2 | H86: ='Portefeuille SP2'!F91 -> 0 | J86: ='Portefeuille SP2'!D91 -> BCI_BODY | K86: ='Portefeuille SP2'!H91 -> 0 | L86: ='Portefeuille SP2'!U91 -> -2.5 | P86: ='Portefeuille SP2'!M91 -> 0 | R86: ='Portefeuille SP2'!N91 -> 0 | T86: ='Portefeuille SP2'!R91 -> TBD | U86: ='Portefeuille SP2'!K91 -> 0 | V86: ='Portefeuille SP2'!S91 -> 0.5 | AE86: ='Portefeuille SP2'!J91 -> 0 | AJ86: ='Portefeuille SP2'!V91 -> 1 | AK86: ='Portefeuille SP2'!W91 -> 1 | AL86: ='Portefeuille SP2'!X91 -> 1 | AM86: ='Portefeuille SP2'!Y91 -> 0 | AN86: ='Portefeuille SP2'!Z91 -> 0 | AO86: ='Portefeuille SP2'!AA91 -> 0 | AP86: ='Portefeuille SP2'!AB91 -> 0 | AQ86: ='Portefeuille SP2'!AC91 -> 0 | ... BF86: ='Portefeuille SP2'!AR91 -> 0 | BG86: ='Portefeuille SP2'!#REF! -> #REF! | BH86: ='Portefeuille SP2'!#REF! -> #REF! | BI86: ='Portefeuille SP2'!#REF! -> #REF! | BJ86: ='Portefeuille SP2'!#REF! -> #REF! | BK86: ='Portefeuille SP2'!#REF! -> #REF! | BM86: ='Portefeuille SP2'!L91 -> 11/04/2024 : Workshop mass
A87: ='Portefeuille SP2'!B92 -> 0 | B87: ='Portefeuille SP2'!Q92 -> CANCELED | D87: ='Portefeuille SP2'!E92 -> PTF | E87: =LEFT(J87,3) -> BCI | F87: =MID(J87, 6, 20) -> HASSIS | G87: ='Portefeuille SP2'!C92 -> SPC_1 | H87: ='Portefeuille SP2'!F92 -> FREDERIC GUINGAND | J87: ='Portefeuille SP2'!D92 -> BCI_CHASSIS | K87: ='Portefeuille SP2'!H92 -> 0 | L87: ='Portefeuille SP2'!U92 -> -1 | P87: ='Portefeuille SP2'!M92 -> 0 | R87: ='Portefeuille SP2'!N92 -> 40 | T87: ='Portefeuille SP2'!R92 -> Step1 | U87: ='Portefeuille SP2'!K92 -> 0 | V87: ='Portefeuille SP2'!S92 -> 1 | AE87: ='Portefeuille SP2'!J92 -> 0 | AJ87: ='Portefeuille SP2'!V92 -> 1 | AK87: ='Portefeuille SP2'!W92 -> 1 | AL87: ='Portefeuille SP2'!X92 -> 1 | AM87: ='Portefeuille SP2'!Y92 -> 0 | AN87: ='Portefeuille SP2'!Z92 -> 0 | AO87: ='Portefeuille SP2'!AA92 -> 0 | AP87: ='Portefeuille SP2'!AB92 -> 0 | AQ87: ='Portefeuille SP2'!AC92 -> 0 | ... BF87: ='Portefeuille SP2'!AR92 -> 0 | BG87: ='Portefeuille SP2'!#REF! -> #REF! | BH87: ='Portefeuille SP2'!#REF! -> #REF! | BI87: ='Portefeuille SP2'!#REF! -> #REF! | BJ87: ='Portefeuille SP2'!#REF! -> #REF! | BK87: ='Portefeuille SP2'!#REF! -> #REF! | BM87: ='Portefeuille SP2'!L92 -> Doublon
A88: ='Portefeuille SP2'!B93 -> 45536 | B88: ='Portefeuille SP2'!Q93 -> CANCELED | D88: ='Portefeuille SP2'!E93 -> TH | E88: =LEFT(J88,3) -> INT | F88: =MID(J88, 4, 20) -> - SEATS/TRIMS | G88: ='Portefeuille SP2'!C93 -> SPC_1 | H88: ='Portefeuille SP2'!F93 -> HALIM | I88: CHARLES HENRI BONFILS | J88: ='Portefeuille SP2'!D93 -> INT - SEATS/TRIMS | K88: ='Portefeuille SP2'!H93 -> Cabin firewall soundproofing | L88: ='Portefeuille SP2'!U93 -> -0.042 | P88: ='Portefeuille SP2'!M93 -> TBD | R88: ='Portefeuille SP2'!N93 -> -1.2 | T88: ='Portefeuille SP2'!R93 -> TBD | U88: ='Portefeuille SP2'!K93 -> SFM | V88: ='Portefeuille SP2'!S93 -> 0.1 | AE88: ='Portefeuille SP2'!J93 -> 02/03/2026 LM à Supprimer car non appliqué sur P3U 24/06/2025 à checker en RFQ avec les FNR | AJ88: ='Portefeuille SP2'!V93 -> 1 | AK88: ='Portefeuille SP2'!W93 -> 1 | AL88: ='Portefeuille SP2'!X93 -> 1 | AM88: ='Portefeuille SP2'!Y93 -> 1 | AN88: ='Portefeuille SP2'!Z93 -> 1 | AO88: ='Portefeuille SP2'!AA93 -> 1 | AP88: ='Portefeuille SP2'!AB93 -> 1 | AQ88: ='Portefeuille SP2'!AC93 -> 1 | ... BF88: ='Portefeuille SP2'!AR93 -> 1 | BG88: ='Portefeuille SP2'!#REF! -> #REF! | BH88: ='Portefeuille SP2'!#REF! -> #REF! | BI88: ='Portefeuille SP2'!#REF! -> #REF! | BJ88: ='Portefeuille SP2'!#REF! -> #REF! | BK88: ='Portefeuille SP2'!#REF! -> #REF! | BM88: ='Portefeuille SP2'!L93 -> Check avec le fournisseur
A89: ='Portefeuille SP2'!B94 -> 0 | B89: ='Portefeuille SP2'!Q94 -> DECIDED | D89: ='Portefeuille SP2'!E94 -> PTF | E89: =LEFT(J89,3) -> SWX | F89: =MID(J89, 6, 20) -> HE | G89: ='Portefeuille SP2'!C94 -> SP2 | H89: ='Portefeuille SP2'!F94 -> 0 | J89: ='Portefeuille SP2'!D94 -> SWX_EHE | K89: ='Portefeuille SP2'!H94 -> 0 | L89: ='Portefeuille SP2'!U94 -> -2.6 | P89: ='Portefeuille SP2'!M94 -> 0 | R89: ='Portefeuille SP2'!N94 -> -45 | T89: ='Portefeuille SP2'!R94 -> TBD | U89: ='Portefeuille SP2'!K94 -> 0 | V89: ='Portefeuille SP2'!S94 -> 1 | AE89: ='Portefeuille SP2'!J94 -> 0 | AJ89: ='Portefeuille SP2'!V94 -> 1 | AK89: ='Portefeuille SP2'!W94 -> 1 | AL89: ='Portefeuille SP2'!X94 -> 1 | AM89: ='Portefeuille SP2'!Y94 -> 0 | AN89: ='Portefeuille SP2'!Z94 -> 0 | AO89: ='Portefeuille SP2'!AA94 -> 1 | AP89: ='Portefeuille SP2'!AB94 -> 1 | AQ89: ='Portefeuille SP2'!AC94 -> 0 | ... BF89: ='Portefeuille SP2'!AR94 -> 0 | BG89: ='Portefeuille SP2'!#REF! -> #REF! | BH89: ='Portefeuille SP2'!#REF! -> #REF! | BI89: ='Portefeuille SP2'!#REF! -> #REF! | BJ89: ='Portefeuille SP2'!#REF! -> #REF! | BK89: ='Portefeuille SP2'!#REF! -> #REF! | BM89: ='Portefeuille SP2'!L94 -> 23/07/24 : Mode 3 (11kW) 14/03/2024 : Workshop mass
A90: ='Portefeuille SP2'!B95 -> 45536 | B90: ='Portefeuille SP2'!Q95 -> CANCELED | D90: ='Portefeuille SP2'!E95 -> TH | E90: =LEFT(J90,3) -> INT | F90: =MID(J90, 4, 20) -> - SEATS/TRIMS | G90: ='Portefeuille SP2'!C95 -> SPC_1 | H90: ='Portefeuille SP2'!F95 -> HALIM | I90: CHARLES HENRI BONFILS | J90: ='Portefeuille SP2'!D95 -> INT - SEATS/TRIMS | K90: ='Portefeuille SP2'!H95 -> Headliner | L90: ='Portefeuille SP2'!U95 -> -0.06 | P90: ='Portefeuille SP2'!M95 -> 0 | R90: ='Portefeuille SP2'!N95 -> -0.1 | T90: ='Portefeuille SP2'!R95 -> TBD | U90: ='Portefeuille SP2'!K95 -> CM | V90: ='Portefeuille SP2'!S95 -> 0.25 | AE90: ='Portefeuille SP2'!J95 -> 02/03/2026 LM à Supprimer car non appliqué sur P3U 24/06/2025 à vérifier plus tard Proposition d'enlever 2 poignées selon la déclinaison.* A partager avec le produit si accord | AJ90: ='Portefeuille SP2'!V95 -> 1 | AK90: ='Portefeuille SP2'!W95 -> 1 | AL90: ='Portefeuille SP2'!X95 -> 1 | AM90: ='Portefeuille SP2'!Y95 -> 1 | AN90: ='Portefeuille SP2'!Z95 -> 1 | AO90: ='Portefeuille SP2'!AA95 -> 1 | AP90: ='Portefeuille SP2'!AB95 -> 1 | AQ90: ='Portefeuille SP2'!AC95 -> 1 | ... BF90: ='Portefeuille SP2'!AR95 -> 1 | BG90: ='Portefeuille SP2'!#REF! -> #REF! | BH90: ='Portefeuille SP2'!#REF! -> #REF! | BI90: ='Portefeuille SP2'!#REF! -> #REF! | BJ90: ='Portefeuille SP2'!#REF! -> #REF! | BK90: ='Portefeuille SP2'!#REF! -> #REF! | BM90: ='Portefeuille SP2'!L95 -> 0
A91: ='Portefeuille SP2'!B96 -> 45536 | B91: ='Portefeuille SP2'!Q96 -> CANCELED | D91: ='Portefeuille SP2'!E96 -> TH | E91: =LEFT(J91,3) -> BCI | F91: =MID(J91, 6, 20) -> ODY | G91: ='Portefeuille SP2'!C96 -> SP2 | H91: ='Portefeuille SP2'!F96 -> 0 | J91: ='Portefeuille SP2'!D96 -> BCI_BODY | K91: ='Portefeuille SP2'!H96 -> Wheel Cladding | L91: ='Portefeuille SP2'!U96 -> 0 | P91: ='Portefeuille SP2'!M96 -> -1638K€ | R91: ='Portefeuille SP2'!N96 -> (-21.2) | T91: ='Portefeuille SP2'!R96 -> TBD | U91: ='Portefeuille SP2'!K96 -> PM | V91: ='Portefeuille SP2'!S96 -> 0 | AE91: ='Portefeuille SP2'!J96 -> 24/09/2024 LM - dossier chez le style Préciser les voitures qui embarquent QCDP rocker trim + warning same front mudguard | AJ91: ='Portefeuille SP2'!V96 -> 1 | AK91: ='Portefeuille SP2'!W96 -> 1 | AL91: ='Portefeuille SP2'!X96 -> 1 | AM91: ='Portefeuille SP2'!Y96 -> 1 | AN91: ='Portefeuille SP2'!Z96 -> 0 | AO91: ='Portefeuille SP2'!AA96 -> 1 | AP91: ='Portefeuille SP2'!AB96 -> 1 | AQ91: ='Portefeuille SP2'!AC96 -> 1 | ... BF91: ='Portefeuille SP2'!AR96 -> 0 | BG91: ='Portefeuille SP2'!#REF! -> #REF! | BH91: ='Portefeuille SP2'!#REF! -> #REF! | BI91: ='Portefeuille SP2'!#REF! -> #REF! | BJ91: ='Portefeuille SP2'!#REF! -> #REF! | BK91: ='Portefeuille SP2'!#REF! -> #REF! | BM91: ='Portefeuille SP2'!L96 -> 0
A92: ='Portefeuille SP2'!B97 -> 45536 | B92: ='Portefeuille SP2'!Q97 -> DECIDED | D92: ='Portefeuille SP2'!E97 -> TH | E92: =LEFT(J92,3) -> BCI | F92: =MID(J92, 6, 20) -> ODY | G92: ='Portefeuille SP2'!C97 -> SP2 | H92: ='Portefeuille SP2'!F97 -> 0 | J92: ='Portefeuille SP2'!D97 -> BCI_BODY | K92: ='Portefeuille SP2'!H97 -> Stiffener | L92: ='Portefeuille SP2'!U97 -> -2 | P92: ='Portefeuille SP2'!M97 -> +224 K€ | R92: ='Portefeuille SP2'!N97 -> -2.6 | T92: ='Portefeuille SP2'!R97 -> TBD | U92: ='Portefeuille SP2'!K97 -> PM-CM | V92: ='Portefeuille SP2'!S97 -> 1 | AE92: ='Portefeuille SP2'!J97 -> 28/04/2025 lm : sujet appliqué BDD OK à passer à decided avec Stéphane QCDP SP1 ok : -1,65kg | AJ92: ='Portefeuille SP2'!V97 -> 1 | AK92: ='Portefeuille SP2'!W97 -> 1 | AL92: ='Portefeuille SP2'!X97 -> 1 | AM92: ='Portefeuille SP2'!Y97 -> 1 | AN92: ='Portefeuille SP2'!Z97 -> 0 | AO92: ='Portefeuille SP2'!AA97 -> 1 | AP92: ='Portefeuille SP2'!AB97 -> 1 | AQ92: ='Portefeuille SP2'!AC97 -> 1 | ... BF92: ='Portefeuille SP2'!AR97 -> 0 | BG92: ='Portefeuille SP2'!#REF! -> #REF! | BH92: ='Portefeuille SP2'!#REF! -> #REF! | BI92: ='Portefeuille SP2'!#REF! -> #REF! | BJ92: ='Portefeuille SP2'!#REF! -> #REF! | BK92: ='Portefeuille SP2'!#REF! -> #REF! | BM92: ='Portefeuille SP2'!L97 -> preciser le sujet ?
A93: ='Portefeuille SP2'!B98 -> 0 | B93: ='Portefeuille SP2'!Q98 -> DECIDED | D93: ='Portefeuille SP2'!E98 -> PWT | E93: =LEFT(J93,3) -> PRS | F93: =MID(J93, 6, 20) | G93: ='Portefeuille SP2'!C98 -> SP1 | H93: ='Portefeuille SP2'!F98 -> 0 | J93: ='Portefeuille SP2'!D98 -> PRS | K93: ='Portefeuille SP2'!H98 -> 0 | L93: ='Portefeuille SP2'!U98 -> -4.4 | P93: ='Portefeuille SP2'!M98 -> 0 | R93: ='Portefeuille SP2'!N98 -> +183€ | T93: ='Portefeuille SP2'!R98 -> 0 | U93: ='Portefeuille SP2'!K98 -> 0 | V93: ='Portefeuille SP2'!S98 -> 1 | AE93: ='Portefeuille SP2'!J98 -> 0 | AJ93: ='Portefeuille SP2'!V98 -> 0 | AK93: ='Portefeuille SP2'!W98 -> 0 | AL93: ='Portefeuille SP2'!X98 -> 0 | AM93: ='Portefeuille SP2'!Y98 -> 0 | AN93: ='Portefeuille SP2'!Z98 -> 0 | AO93: ='Portefeuille SP2'!AA98 -> 0 | AP93: ='Portefeuille SP2'!AB98 -> 0 | AQ93: ='Portefeuille SP2'!AC98 -> 0 | ... BF93: ='Portefeuille SP2'!AR98 -> 0 | BG93: ='Portefeuille SP2'!#REF! -> #REF! | BH93: ='Portefeuille SP2'!#REF! -> #REF! | BI93: ='Portefeuille SP2'!#REF! -> #REF! | BJ93: ='Portefeuille SP2'!#REF! -> #REF! | BK93: ='Portefeuille SP2'!#REF! -> #REF! | BM93: ='Portefeuille SP2'!L98 -> 0
A94: ='Portefeuille SP2'!B99 -> 0 | B94: ='Portefeuille SP2'!Q99 -> CANCELED | D94: ='Portefeuille SP2'!E99 -> PTF | E94: =LEFT(J94,3) -> PRS | F94: =MID(J94, 6, 20) | G94: ='Portefeuille SP2'!C99 -> SP1 | H94: ='Portefeuille SP2'!F99 -> 0 | J94: ='Portefeuille SP2'!D99 -> PRS | K94: ='Portefeuille SP2'!H99 -> 0 | L94: ='Portefeuille SP2'!U99 -> 0.25 | P94: ='Portefeuille SP2'!M99 -> 0 | R94: ='Portefeuille SP2'!N99 -> 1 | T94: ='Portefeuille SP2'!R99 -> TBD | U94: ='Portefeuille SP2'!K99 -> 0 | V94: ='Portefeuille SP2'!S99 -> 0.25 | AE94: ='Portefeuille SP2'!J99 -> 0 | AJ94: ='Portefeuille SP2'!V99 -> 0 | AK94: ='Portefeuille SP2'!W99 -> 0 | AL94: ='Portefeuille SP2'!X99 -> 0 | AM94: ='Portefeuille SP2'!Y99 -> 0 | AN94: ='Portefeuille SP2'!Z99 -> 0 | AO94: ='Portefeuille SP2'!AA99 -> 0 | AP94: ='Portefeuille SP2'!AB99 -> 0 | AQ94: ='Portefeuille SP2'!AC99 -> 0 | ... BF94: ='Portefeuille SP2'!AR99 -> 0 | BG94: ='Portefeuille SP2'!#REF! -> #REF! | BH94: ='Portefeuille SP2'!#REF! -> #REF! | BI94: ='Portefeuille SP2'!#REF! -> #REF! | BJ94: ='Portefeuille SP2'!#REF! -> #REF! | BK94: ='Portefeuille SP2'!#REF! -> #REF! | BM94: ='Portefeuille SP2'!L99 -> 19/06/2024 : L'etat actuel de l'architecture permet de dire qu'il n'y aura plus de support complémentaire. 23/10/2023 : Création de la piste
A95: ='Portefeuille SP2'!B100 -> 0 | B95: ='Portefeuille SP2'!Q100 -> DECIDED | D95: ='Portefeuille SP2'!E100 -> TH | E95: =LEFT(J95,3) -> BCI | F95: =MID(J95, 6, 20) -> RSD | G95: ='Portefeuille SP2'!C100 -> SP2 | H95: ='Portefeuille SP2'!F100 -> 0 | J95: ='Portefeuille SP2'!D100 -> BCI_FRSD | K95: ='Portefeuille SP2'!H100 -> remove spolier | L95: ='Portefeuille SP2'!U100 -> -1.5 | P95: ='Portefeuille SP2'!M100 -> invest volet plastique | R95: ='Portefeuille SP2'!N100 -> -28 | T95: ='Portefeuille SP2'!R100 -> TBD | U95: ='Portefeuille SP2'!K100 -> PM CW30 | V95: ='Portefeuille SP2'!S100 -> 1 | AE95: ='Portefeuille SP2'!J100 -> Gain masse quand on passe d’un spoiler type P24 à un spoiler C41 "plus simple" (sans faisceaux….) --> Déjà appliqué et passé en ref BDD le 02/07/2024 | AJ95: ='Portefeuille SP2'!V100 -> 0 | AK95: ='Portefeuille SP2'!W100 -> 0 | AL95: ='Portefeuille SP2'!X100 -> 0 | AM95: ='Portefeuille SP2'!Y100 -> 0 | AN95: ='Portefeuille SP2'!Z100 -> 0 | AO95: ='Portefeuille SP2'!AA100 -> 0 | AP95: ='Portefeuille SP2'!AB100 -> 0 | AQ95: ='Portefeuille SP2'!AC100 -> 0 | ... BF95: ='Portefeuille SP2'!AR100 -> 0 | BG95: ='Portefeuille SP2'!#REF! -> #REF! | BH95: ='Portefeuille SP2'!#REF! -> #REF! | BI95: ='Portefeuille SP2'!#REF! -> #REF! | BJ95: ='Portefeuille SP2'!#REF! -> #REF! | BK95: ='Portefeuille SP2'!#REF! -> #REF! | BM95: ='Portefeuille SP2'!L100 -> 24/09/2024 -LM- A passer en decided A presicer : spolier en REF
A96: ='Portefeuille SP2'!B101 -> 0 | B96: ='Portefeuille SP2'!Q101 -> DECIDED | D96: ='Portefeuille SP2'!E101 -> PTF | E96: =LEFT(J96,3) -> PRS | F96: =MID(J96, 6, 20) | G96: ='Portefeuille SP2'!C101 -> SP1 | H96: ='Portefeuille SP2'!F101 -> 0 | J96: ='Portefeuille SP2'!D101 -> PRS | K96: ='Portefeuille SP2'!H101 -> 0 | L96: ='Portefeuille SP2'!U101 -> -0.2 | P96: ='Portefeuille SP2'!M101 -> 0 | R96: ='Portefeuille SP2'!N101 -> 0 | T96: ='Portefeuille SP2'!R101 -> TBD | U96: ='Portefeuille SP2'!K101 -> 0 | V96: ='Portefeuille SP2'!S101 -> 1 | AE96: ='Portefeuille SP2'!J101 -> 0 | AJ96: ='Portefeuille SP2'!V101 -> 0 | AK96: ='Portefeuille SP2'!W101 -> 0 | AL96: ='Portefeuille SP2'!X101 -> 0 | AM96: ='Portefeuille SP2'!Y101 -> 0 | AN96: ='Portefeuille SP2'!Z101 -> 0 | AO96: ='Portefeuille SP2'!AA101 -> 0 | AP96: ='Portefeuille SP2'!AB101 -> 0 | AQ96: ='Portefeuille SP2'!AC101 -> 0 | ... BF96: ='Portefeuille SP2'!AR101 -> 0 | BG96: ='Portefeuille SP2'!#REF! -> #REF! | BH96: ='Portefeuille SP2'!#REF! -> #REF! | BI96: ='Portefeuille SP2'!#REF! -> #REF! | BJ96: ='Portefeuille SP2'!#REF! -> #REF! | BK96: ='Portefeuille SP2'!#REF! -> #REF! | BM96: ='Portefeuille SP2'!L101 -> 10/04/2024 : Fournisseur choisi. Bilan à faire. 14/02/2024 : Toujours pas choisi. Demande d'avoir 2 fournisseurs différents dont un typé plastique/caoutchouc pour gagner de la masse si opportunité de passer en plastique. 13/12/2023 : début des retours fournisseurs. Pb de choix des fournisseurs dans des pays qui ne maitrisent pas forcement les dernières tech moins lourdes. 23/10/2023 : Création de la piste
A97: ='Portefeuille SP2'!B102 -> 0 | B97: ='Portefeuille SP2'!Q102 -> DECIDED | D97: ='Portefeuille SP2'!E102 -> TH | E97: =LEFT(J97,3) -> INT | F97: =MID(J97, 6, 20) -> PDB/CONSOLE | G97: ='Portefeuille SP2'!C102 -> SP2 | H97: ='Portefeuille SP2'!F102 -> 0 | J97: ='Portefeuille SP2'!D102 -> INT - PDB/CONSOLE | K97: ='Portefeuille SP2'!H102 -> Glove boxe | L97: ='Portefeuille SP2'!U102 -> 1.5 | P97: ='Portefeuille SP2'!M102 -> 230K€*4 | R97: ='Portefeuille SP2'!N102 -> 13 | T97: ='Portefeuille SP2'!R102 -> TBD | U97: ='Portefeuille SP2'!K102 -> 0 | V97: ='Portefeuille SP2'!S102 -> 1 | AE97: ='Portefeuille SP2'!J102 -> 29 juillet 2024 : intergé dans la BDD O3H Changement de la pondération de 75% à 100% | AJ97: ='Portefeuille SP2'!V102 -> 0 | AK97: ='Portefeuille SP2'!W102 -> 0 | AL97: ='Portefeuille SP2'!X102 -> 0 | AM97: ='Portefeuille SP2'!Y102 -> 0 | AN97: ='Portefeuille SP2'!Z102 -> 0 | AO97: ='Portefeuille SP2'!AA102 -> 0 | AP97: ='Portefeuille SP2'!AB102 -> 0 | AQ97: ='Portefeuille SP2'!AC102 -> 0 | ... BF97: ='Portefeuille SP2'!AR102 -> 0 | BG97: ='Portefeuille SP2'!#REF! -> #REF! | BH97: ='Portefeuille SP2'!#REF! -> #REF! | BI97: ='Portefeuille SP2'!#REF! -> #REF! | BJ97: ='Portefeuille SP2'!#REF! -> #REF! | BK97: ='Portefeuille SP2'!#REF! -> #REF! | BM97: ='Portefeuille SP2'!L102 -> RHD/LHD-FABRIC/PLASTIC
A98: ='Portefeuille SP2'!B103 -> 0 | B98: ='Portefeuille SP2'!Q103 -> DECIDED | D98: ='Portefeuille SP2'!E103 -> PTF | E98: =LEFT(J98,3) -> PRS | F98: =MID(J98, 6, 20) | G98: ='Portefeuille SP2'!C103 -> SP1 | H98: ='Portefeuille SP2'!F103 -> 0 | J98: ='Portefeuille SP2'!D103 -> PRS | K98: ='Portefeuille SP2'!H103 -> 0 | L98: ='Portefeuille SP2'!U103 -> 2 | P98: ='Portefeuille SP2'!M103 -> 0 | R98: ='Portefeuille SP2'!N103 -> 0 | T98: ='Portefeuille SP2'!R103 -> TBD | U98: ='Portefeuille SP2'!K103 -> 0 | V98: ='Portefeuille SP2'!S103 -> 1 | AE98: ='Portefeuille SP2'!J103 -> 0 | AJ98: ='Portefeuille SP2'!V103 -> 0 | AK98: ='Portefeuille SP2'!W103 -> 0 | AL98: ='Portefeuille SP2'!X103 -> 0 | AM98: ='Portefeuille SP2'!Y103 -> 0 | AN98: ='Portefeuille SP2'!Z103 -> 0 | AO98: ='Portefeuille SP2'!AA103 -> 0 | AP98: ='Portefeuille SP2'!AB103 -> 0 | AQ98: ='Portefeuille SP2'!AC103 -> 0 | ... BF98: ='Portefeuille SP2'!AR103 -> 0 | BG98: ='Portefeuille SP2'!#REF! -> #REF! | BH98: ='Portefeuille SP2'!#REF! -> #REF! | BI98: ='Portefeuille SP2'!#REF! -> #REF! | BJ98: ='Portefeuille SP2'!#REF! -> #REF! | BK98: ='Portefeuille SP2'!#REF! -> #REF! | BM98: ='Portefeuille SP2'!L103 -> 30/04/2024 : Choix repossé en mai. VMAX : 2,7 kg (seul fournisseur valable, le moins lourd mais irrecevable techniquement est à 1,65kg) 10/04/2024 : Choix repoussé à mi avril 13/12/2023 : Plage de retour fournisseur allant jusqu'à 1,4 kg. Fin choix fournisseur fin fevrier. 22/11/2023 : RFQ très tardive. Il existe actuellement un fournisseur avec un objet sur étagère -> voir les retours fournisseurs.
A99: ='Portefeuille SP2'!B104 -> 0 | B99: ='Portefeuille SP2'!Q104 -> DECIDED | D99: ='Portefeuille SP2'!E104 -> PTF | E99: =LEFT(J99,3) -> BCI | F99: =MID(J99, 6, 20) -> HASSIS | G99: ='Portefeuille SP2'!C104 -> SP2 | H99: ='Portefeuille SP2'!F104 -> 0 | J99: ='Portefeuille SP2'!D104 -> BCI_CHASSIS | K99: ='Portefeuille SP2'!H104 -> 0 | L99: ='Portefeuille SP2'!U104 -> -3.5 | P99: ='Portefeuille SP2'!M104 -> 0 | R99: ='Portefeuille SP2'!N104 -> 0 | T99: ='Portefeuille SP2'!R104 -> TBD | U99: ='Portefeuille SP2'!K104 -> 0 | V99: ='Portefeuille SP2'!S104 -> 0.5 | AE99: ='Portefeuille SP2'!J104 -> 0 | AJ99: ='Portefeuille SP2'!V104 -> 1 | AK99: ='Portefeuille SP2'!W104 -> 1 | AL99: ='Portefeuille SP2'!X104 -> 1 | AM99: ='Portefeuille SP2'!Y104 -> 0 | AN99: ='Portefeuille SP2'!Z104 -> 0 | AO99: ='Portefeuille SP2'!AA104 -> 0 | AP99: ='Portefeuille SP2'!AB104 -> 0 | AQ99: ='Portefeuille SP2'!AC104 -> 0 | ... BF99: ='Portefeuille SP2'!AR104 -> 0 | BG99: ='Portefeuille SP2'!#REF! -> #REF! | BH99: ='Portefeuille SP2'!#REF! -> #REF! | BI99: ='Portefeuille SP2'!#REF! -> #REF! | BJ99: ='Portefeuille SP2'!#REF! -> #REF! | BK99: ='Portefeuille SP2'!#REF! -> #REF! | BM99: ='Portefeuille SP2'!L104 -> 14/03/2024 : Workshop mass
A100: ='Portefeuille SP2'!B105 -> 0 | B100: ='Portefeuille SP2'!Q105 -> CANCELED | D100: ='Portefeuille SP2'!E105 -> PTF | E100: =LEFT(J100,3) -> BCI | F100: =MID(J100, 6, 20) -> HASSIS | G100: ='Portefeuille SP2'!C105 -> SP1 | H100: ='Portefeuille SP2'!F105 -> 0 | J100: ='Portefeuille SP2'!D105 -> BCI_CHASSIS | K100: ='Portefeuille SP2'!H105 -> 0 | L100: ='Portefeuille SP2'!U105 -> -0.25 | P100: ='Portefeuille SP2'!M105 -> 0 | R100: ='Portefeuille SP2'!N105 -> -3 | T100: ='Portefeuille SP2'!R105 -> TBD | U100: ='Portefeuille SP2'!K105 -> 0 | V100: ='Portefeuille SP2'!S105 -> 0.25 | AE100: ='Portefeuille SP2'!J105 -> 0 | AJ100: ='Portefeuille SP2'!V105 -> 0 | AK100: ='Portefeuille SP2'!W105 -> 0 | AL100: ='Portefeuille SP2'!X105 -> 0 | AM100: ='Portefeuille SP2'!Y105 -> 0 | AN100: ='Portefeuille SP2'!Z105 -> 0 | AO100: ='Portefeuille SP2'!AA105 -> 0 | AP100: ='Portefeuille SP2'!AB105 -> 0 | AQ100: ='Portefeuille SP2'!AC105 -> 0 | ... BF100: ='Portefeuille SP2'!AR105 -> 0 | BG100: ='Portefeuille SP2'!#REF! -> #REF! | BH100: ='Portefeuille SP2'!#REF! -> #REF! | BI100: ='Portefeuille SP2'!#REF! -> #REF! | BJ100: ='Portefeuille SP2'!#REF! -> #REF! | BK100: ='Portefeuille SP2'!#REF! -> #REF! | BM100: ='Portefeuille SP2'!L105 -> 10/06/2024 : RD S23 : décision d'annulation pour cause d'impossibilité de trouver un scénario de choc satisfaisant. 29/05/2024 : Pas de convergence sur le choc, contrainte planning. Retour sur BaD sur traverse très probable. Annulation à passer en décision. 10/04/2024 : Pas encore de solution pour conserver la BaD sur caisse. 3/13/2024 : risque de retour en arriere car nok choc. 06/02/2024 : à banquer
A101: ='Portefeuille SP2'!B106 -> 45536 | B101: ='Portefeuille SP2'!Q106 -> CANCELED | D101: ='Portefeuille SP2'!E106 -> TH | E101: =LEFT(J101,3) -> BCI | F101: =MID(J101, 6, 20) -> RSD | G101: ='Portefeuille SP2'!C106 -> SPC_1 | H101: ='Portefeuille SP2'!F106 -> 0 | J101: ='Portefeuille SP2'!D106 -> BCI_FRSD | K101: ='Portefeuille SP2'!H106 -> Aluminum Fender | L101: ='Portefeuille SP2'!U106 -> 0 | P101: ='Portefeuille SP2'!M106 -> 750 | R101: ='Portefeuille SP2'!N106 -> 5.6 | T101: ='Portefeuille SP2'!R106 -> Step4 | U101: ='Portefeuille SP2'!K106 -> PM-CM | V101: ='Portefeuille SP2'!S106 -> 0 | AE101: ='Portefeuille SP2'!J106 -> 28/04/2025 LM : Annulé 24/09/2024 - LM - ne sera pas appliqué à reboucler avec le projet http://docinfogroupe.inetpsa.com/ead/doc/ref.01364_22_00699/v.vc/fiche | AJ101: ='Portefeuille SP2'!V106 -> 0 | AK101: ='Portefeuille SP2'!W106 -> 0 | AL101: ='Portefeuille SP2'!X106 -> 0 | AM101: ='Portefeuille SP2'!Y106 -> 1 | AN101: ='Portefeuille SP2'!Z106 -> 0 | AO101: ='Portefeuille SP2'!AA106 -> 0 | AP101: ='Portefeuille SP2'!AB106 -> 0 | AQ101: ='Portefeuille SP2'!AC106 -> 1 | ... BF101: ='Portefeuille SP2'!AR106 -> 0 | BG101: ='Portefeuille SP2'!#REF! -> #REF! | BH101: ='Portefeuille SP2'!#REF! -> #REF! | BI101: ='Portefeuille SP2'!#REF! -> #REF! | BJ101: ='Portefeuille SP2'!#REF! -> #REF! | BK101: ='Portefeuille SP2'!#REF! -> #REF! | BM101: ='Portefeuille SP2'!L106 -> MAJ 12/04 : +5,81kg/ 4,3€/kg/SFT:+500 KE (by tophat)
A102: ='Portefeuille SP2'!B107 -> 11/09/2024 | B102: ='Portefeuille SP2'!Q107 -> DECIDED | D102: ='Portefeuille SP2'!E107 -> TH | E102: =LEFT(J102,3) -> INT | F102: =MID(J102, 4, 20) -> - PDB/CONSOLE | G102: ='Portefeuille SP2'!C107 -> SP1 | H102: ='Portefeuille SP2'!F107 -> FREDERIC BRUNIER | I102: CHARLES HENRI BONFILS | J102: ='Portefeuille SP2'!D107 -> INT - PDB/CONSOLE | K102: ='Portefeuille SP2'!H107 -> style/brand | L102: ='Portefeuille SP2'!U107 -> -0.268 | P102: ='Portefeuille SP2'!M107 -> 0 | R102: ='Portefeuille SP2'!N107 -> 0 | T102: ='Portefeuille SP2'!R107 -> 0 | U102: ='Portefeuille SP2'!K107 -> 0 | V102: ='Portefeuille SP2'!S107 -> 1 | AE102: ='Portefeuille SP2'!J107 -> 16/02/2026 LM SUJET SUPPRIMER | AJ102: ='Portefeuille SP2'!V107 -> 1 | AK102: ='Portefeuille SP2'!W107 -> 1 | AL102: ='Portefeuille SP2'!X107 -> 1 | AM102: ='Portefeuille SP2'!Y107 -> 1 | AN102: ='Portefeuille SP2'!Z107 -> 1 | AO102: ='Portefeuille SP2'!AA107 -> 1 | AP102: ='Portefeuille SP2'!AB107 -> 1 | AQ102: ='Portefeuille SP2'!AC107 -> 1 | ... BF102: ='Portefeuille SP2'!AR107 -> 1 | BG102: ='Portefeuille SP2'!#REF! -> #REF! | BH102: ='Portefeuille SP2'!#REF! -> #REF! | BI102: ='Portefeuille SP2'!#REF! -> #REF! | BJ102: ='Portefeuille SP2'!#REF! -> #REF! | BK102: ='Portefeuille SP2'!#REF! -> #REF! | BM102: ='Portefeuille SP2'!L107 -> 11/09/2024 Supp eclair écran(228g+40g) = Inscrit au plan coût /Supp ALCOVE (200g) : STd bye 05/09/2024 A revoir avec Guillaume 05/09/2024 : Ne concerne que ALCOVE / Sous écran : pas de contrainte / Ss facade aérateur : uniqt Niv3 06/06/2024 Si TT= RAS/ Si MeG besoin de obturateur ! 14/03/2024 dans l'alcove
A103: ='Portefeuille SP2'!B108 -> 0 | B103: ='Portefeuille SP2'!Q108 -> CANCELED | D103: ='Portefeuille SP2'!E108 -> PTF | E103: =LEFT(J103,3) -> SWX | F103: =MID(J103, 6, 20) -> E | G103: ='Portefeuille SP2'!C108 -> SP1 | H103: ='Portefeuille SP2'!F108 -> 0 | J103: ='Portefeuille SP2'!D108 -> SWX/EE | K103: ='Portefeuille SP2'!H108 -> 0 | L103: ='Portefeuille SP2'!U108 -> -2 | P103: ='Portefeuille SP2'!M108 -> 0 | R103: ='Portefeuille SP2'!N108 -> L2 AGM --> L1 AGM (n'existe pas dans le groupe) :entre -10 et -15 (L2 EEF /EFR) = -0,7 kg / -20 vs L2AGM | T103: ='Portefeuille SP2'!R108 -> TBD | U103: ='Portefeuille SP2'!K108 -> 0 | V103: ='Portefeuille SP2'!S108 -> 0.5 | AE103: ='Portefeuille SP2'!J108 -> 0 | AJ103: ='Portefeuille SP2'!V108 -> 0 | AK103: ='Portefeuille SP2'!W108 -> 0 | AL103: ='Portefeuille SP2'!X108 -> 0 | AM103: ='Portefeuille SP2'!Y108 -> 0 | AN103: ='Portefeuille SP2'!Z108 -> 0 | AO103: ='Portefeuille SP2'!AA108 -> 0 | AP103: ='Portefeuille SP2'!AB108 -> 0 | AQ103: ='Portefeuille SP2'!AC108 -> 0 | ... BF103: ='Portefeuille SP2'!AR108 -> 0 | BG103: ='Portefeuille SP2'!#REF! -> #REF! | BH103: ='Portefeuille SP2'!#REF! -> #REF! | BI103: ='Portefeuille SP2'!#REF! -> #REF! | BJ103: ='Portefeuille SP2'!#REF! -> #REF! | BK103: ='Portefeuille SP2'!#REF! -> #REF! | BM103: ='Portefeuille SP2'!L108 -> 25/03/2024 : Revision du protocole Safety. Sans SBW 19/02/2024 : prise en compte STEP2
A104: ='Portefeuille SP2'!B109 -> 0 | B104: ='Portefeuille SP2'!Q109 -> CANCELED | D104: ='Portefeuille SP2'!E109 -> PTF | E104: =LEFT(J104,3) -> SWX | F104: =MID(J104, 6, 20) -> E | G104: ='Portefeuille SP2'!C109 -> SP1 | H104: ='Portefeuille SP2'!F109 -> 0 | J104: ='Portefeuille SP2'!D109 -> SWX/EE | K104: ='Portefeuille SP2'!H109 -> 0 | L104: ='Portefeuille SP2'!U109 -> 0 | P104: ='Portefeuille SP2'!M109 -> 0 | R104: ='Portefeuille SP2'!N109 | T104: ='Portefeuille SP2'!R109 -> 0 | U104: ='Portefeuille SP2'!K109 -> 0 | V104: ='Portefeuille SP2'!S109 -> 0 | AE104: ='Portefeuille SP2'!J109 -> 0 | AJ104: ='Portefeuille SP2'!V109 -> 0 | AK104: ='Portefeuille SP2'!W109 -> 0 | AL104: ='Portefeuille SP2'!X109 -> 0 | AM104: ='Portefeuille SP2'!Y109 -> 0 | AN104: ='Portefeuille SP2'!Z109 -> 0 | AO104: ='Portefeuille SP2'!AA109 -> 0 | AP104: ='Portefeuille SP2'!AB109 -> 0 | AQ104: ='Portefeuille SP2'!AC109 -> 0 | ... BF104: ='Portefeuille SP2'!AR109 -> 0 | BG104: ='Portefeuille SP2'!#REF! -> #REF! | BH104: ='Portefeuille SP2'!#REF! -> #REF! | BI104: ='Portefeuille SP2'!#REF! -> #REF! | BJ104: ='Portefeuille SP2'!#REF! -> #REF! | BK104: ='Portefeuille SP2'!#REF! -> #REF! | BM104: ='Portefeuille SP2'!L109 -> 25/03/2024 : Revision du protocole Safety. Sans SBW 19/02/2024 : prise en compte STEP2
